{
  "author": {
    "id": "70-10",
    "display_name": "70_10",
    "avatar_url": "https://avatars.githubusercontent.com/u/5960697?v=4"
  },
  "marketplaces": [
    {
      "name": "70-10-plugins",
      "version": null,
      "description": "70-10's Claude Code plugins",
      "repo_full_name": "70-10/claude-code-plugins",
      "repo_url": "https://github.com/70-10/claude-code-plugins",
      "repo_description": null,
      "signals": {
        "stars": 0,
        "forks": 0,
        "pushed_at": "2026-01-28T13:30:03Z"
      },
      "files": {
        ".claude-plugin/marketplace.json": "{\n  \"name\": \"70-10-plugins\",\n  \"owner\": {\n    \"name\": \"70-10\"\n  },\n  \"metadata\": {\n    \"description\": \"70-10's Claude Code plugins\",\n    \"version\": \"1.0.0\",\n    \"pluginRoot\": \"./plugins\"\n  },\n  \"plugins\": [\n    {\n      \"name\": \"dr\",\n      \"source\": \"./plugins/dr\",\n      \"description\": \"Auto-generate Decision Records (DR) from conversation and save as Markdown files\",\n      \"version\": \"1.0.0\",\n      \"author\": {\n        \"name\": \"70-10\"\n      },\n      \"keywords\": [\"decision-record\", \"documentation\", \"adr\"],\n      \"category\": \"productivity\"\n    },\n    {\n      \"name\": \"elaborate\",\n      \"source\": \"./plugins/elaborate\",\n      \"description\": \"Elaborate on specifications through detailed, structured interviews\",\n      \"version\": \"1.0.0\",\n      \"author\": {\n        \"name\": \"70-10\"\n      },\n      \"keywords\": [\"specification\", \"interview\", \"requirements\", \"elaboration\"],\n      \"category\": \"productivity\"\n    }\n  ]\n}\n",
        "README.md": "# claude-code-plugins\n\nA collection of Claude Code plugins.\n\n## Plugins\n\n| Plugin | Description |\n|--------|-------------|\n| [dr](./plugins/dr) | Auto-generate Decision Records (DR) from conversation and save as Markdown files |\n| [elaborate](./plugins/elaborate) | Elaborate on specifications through detailed, structured interviews |\n\n## Installation\n\nAdd marketplace:\n\n```bash\n/plugin marketplace add 70-10/claude-code-plugins\n```\n\nInstall plugin:\n\n```bash\n/plugin install dr@70-10-plugins\n/plugin install elaborate@70-10-plugins\n```\n\n## Usage\n\n### dr - Decision Record Generator\n\nAutomatically generates a Decision Record from your conversation and saves it as a Markdown file.\n\n#### Trigger Phrases\n\n- \"Record this decision\"\n- \"Create a DR\"\n- \"Generate Decision Record\"\n- \"Document this decision\"\n\n#### Explicit Invocation\n\n```\n/dr\n```\n\n#### Output\n\nDecision Records are saved to `decision-records/` directory in the current working directory.\n\n### elaborate - Specification Interview Tool\n\nHelps you elaborate on specifications through detailed, structured interviews.\n\n#### Arguments\n\n- `@path/to/spec.md` - Use an existing spec file as the base for the interview\n- `description` - Create a new spec file from text requirements\n- No arguments - Interactively decide where to save and what to write\n\n#### Explicit Invocation\n\n```\n/elaborate\n/elaborate @path/to/spec.md\n/elaborate new feature description\n```\n\n## License\n\nMIT\n"
      },
      "plugins": [
        {
          "name": "dr",
          "source": "./plugins/dr",
          "description": "Auto-generate Decision Records (DR) from conversation and save as Markdown files",
          "version": "1.0.0",
          "author": {
            "name": "70-10"
          },
          "keywords": [
            "decision-record",
            "documentation",
            "adr"
          ],
          "category": "productivity",
          "categories": [
            "adr",
            "decision-record",
            "documentation",
            "productivity"
          ],
          "install_commands": [
            "/plugin marketplace add 70-10/claude-code-plugins",
            "/plugin install dr@70-10-plugins"
          ]
        },
        {
          "name": "elaborate",
          "source": "./plugins/elaborate",
          "description": "Elaborate on specifications through detailed, structured interviews",
          "version": "1.0.0",
          "author": {
            "name": "70-10"
          },
          "keywords": [
            "specification",
            "interview",
            "requirements",
            "elaboration"
          ],
          "category": "productivity",
          "categories": [
            "elaboration",
            "interview",
            "productivity",
            "requirements",
            "specification"
          ],
          "install_commands": [
            "/plugin marketplace add 70-10/claude-code-plugins",
            "/plugin install elaborate@70-10-plugins"
          ]
        }
      ]
    }
  ]
}