{
  "author": {
    "id": "chouzz",
    "display_name": "Chouzz",
    "avatar_url": "https://avatars.githubusercontent.com/u/18023066?u=d292338e7849372ff05a11164ffe9679fa59d32e&v=4"
  },
  "marketplaces": [
    {
      "name": "chouzz-plugins",
      "version": null,
      "description": "Personal Claude Code plugins by chouzz",
      "repo_full_name": "chouzz/minecraft-mod-dev",
      "repo_url": "https://github.com/chouzz/minecraft-mod-dev",
      "repo_description": "Claude Code skill for Minecraft mod development with NeoForge/Fabric support and inter-mod integration (JEI/AE2/Create)",
      "signals": {
        "stars": 1,
        "forks": 0,
        "pushed_at": "2026-01-15T14:44:44Z"
      },
      "files": {
        ".claude-plugin/marketplace.json": "{\n  \"name\": \"chouzz-plugins\",\n  \"owner\": {\n    \"name\": \"chouzz\"\n  },\n  \"metadata\": {\n    \"description\": \"Personal Claude Code plugins by chouzz\"\n  },\n  \"plugins\": [\n    {\n      \"name\": \"minecraft-mod-dev\",\n      \"source\": \".\",\n      \"description\": \"A Claude Code plugin for Minecraft mod development with modern loaders (NeoForge/Fabric) and ecosystem interoperability.\",\n      \"version\": \"1.0.0\",\n      \"author\": {\n        \"name\": \"chouzz\"\n      },\n      \"license\": \"MIT\",\n      \"keywords\": [\"minecraft\", \"mod\", \"neoforge\", \"fabric\", \"game-dev\"],\n      \"category\": \"development\"\n    }\n  ]\n}\n",
        ".claude-plugin/plugin.json": "{\n  \"name\": \"minecraft-mod-dev\",\n  \"version\": \"1.0.0\",\n  \"description\": \"A Claude Code plugin for Minecraft mod development with modern loaders (NeoForge/Fabric) and ecosystem interoperability.\",\n  \"author\": \"chouzz\",\n  \"license\": \"MIT\",\n  \"homepage\": \"https://github.com/chouzz/minecraft-mod-dev\"\n}\n",
        "README.md": "# Minecraft Mod Development Plugin\n\nA Claude Code plugin for Minecraft mod development with modern loaders (NeoForge/Fabric) and ecosystem interoperability.\n\n## Features\n\n- **Dynamic Documentation Fetching** - Automatically fetches latest docs for NeoForge/Fabric\n- **Inter-mod Integration** - Guides for JEI, AE2, Create, and other popular mods\n- **Modern Standards** - Data Components, Data Generation, Convention Tags\n- **Environment Detection** - Auto-detects project configuration\n\n## Installation\n\nAdd the marketplace and install the plugin:\n\n```bash\n/plugin marketplace add chouzz/minecraft-mod-dev\n/plugin install minecraft-mod-dev@chouzz-plugins\n```\n\nOr run `/plugin` and go to the **Marketplaces** tab to add, then **Discover** to install.\n\n## Usage Triggers\n\nThis skill activates when you:\n- Create new blocks, items, or entities\n- Integrate with JEI/AE2/Create\n- Set up modding environment\n- Migrate code to 1.21+\n- Work with NeoForge or Fabric loaders\n\n## Example\n\n```\n> \"Help me create a machine block that works with AE2 storage and shows recipes in JEI\"\n```\n\nThe skill will guide you through:\n1. Fetching latest API docs\n2. Implementing AE2 Grid integration\n3. Registering JEI recipe types\n4. Using Data Components for item data\n\n## Resources\n\n- [NeoForge Docs](https://docs.neoforged.net/)\n- [Fabric Wiki](https://fabricmc.net/wiki/)\n- See `references/mod-links.md` for more API documentation\n\n## Development\n\nTo test the plugin locally during development:\n\n```bash\nclaude --plugin-dir /path/to/minecraft-mod-dev\n```\n"
      },
      "plugins": [
        {
          "name": "minecraft-mod-dev",
          "source": ".",
          "description": "A Claude Code plugin for Minecraft mod development with modern loaders (NeoForge/Fabric) and ecosystem interoperability.",
          "version": "1.0.0",
          "author": {
            "name": "chouzz"
          },
          "license": "MIT",
          "keywords": [
            "minecraft",
            "mod",
            "neoforge",
            "fabric",
            "game-dev"
          ],
          "category": "development",
          "categories": [
            "development",
            "fabric",
            "game-dev",
            "minecraft",
            "mod",
            "neoforge"
          ],
          "install_commands": [
            "/plugin marketplace add chouzz/minecraft-mod-dev",
            "/plugin install minecraft-mod-dev@chouzz-plugins"
          ]
        }
      ]
    }
  ]
}