{
  "author": {
    "id": "coinpaprika",
    "display_name": "Coinpaprika",
    "avatar_url": "https://avatars.githubusercontent.com/u/38780303?v=4"
  },
  "marketplaces": [
    {
      "name": "coinpaprika-plugins",
      "version": null,
      "description": "Official Claude plugins from CoinPaprika and DexPaprika: crypto market data, DEX analytics, liquidity pools, tokens, OHLCV, and more.",
      "repo_full_name": "coinpaprika/claude-marketplace",
      "repo_url": "https://github.com/coinpaprika/claude-marketplace",
      "repo_description": null,
      "signals": {
        "stars": 3,
        "forks": 1,
        "pushed_at": "2025-10-31T13:56:17Z"
      },
      "files": {
        ".claude-plugin/marketplace.json": "{\n  \"$schema\": \"https://anthropic.com/claude-code/marketplace.schema.json\",\n  \"name\": \"coinpaprika-plugins\",\n  \"owner\": {\n    \"name\": \"CoinPaprika & DexPaprika\"\n  },\n  \"metadata\": {\n    \"description\": \"Official Claude plugins from CoinPaprika and DexPaprika: crypto market data, DEX analytics, liquidity pools, tokens, OHLCV, and more.\",\n    \"version\": \"1.0.0\",\n    \"pluginRoot\": \"plugins\"\n  },\n  \"plugins\": [\n    {\n      \"name\": \"dexpaprika\",\n      \"source\": \"./plugins/dexpaprika-claude-plugin\",\n      \"description\": \"Access comprehensive DeFi data from DexPaprika including DEXes, liquidity pools, tokens, and trading information across 26+ blockchains\",\n      \"version\": \"1.0.0\",\n      \"author\": {\n        \"name\": \"CoinPaprika & DexPaprika\"\n      },\n      \"homepage\": \"https://dexpaprika.com\",\n      \"repository\": \"https://github.com/CoinPaprika/claude-marketplace\",\n      \"license\": \"MIT\",\n      \"keywords\": [\n        \"defi\",\n        \"dex\",\n        \"liquidity\",\n        \"pools\",\n        \"tokens\",\n        \"blockchain\",\n        \"cryptocurrency\",\n        \"trading\",\n        \"analytics\"\n      ],\n      \"category\": \"defi\"\n    },\n    {\n      \"name\": \"coinpaprika\",\n      \"source\": \"./plugins/coinpaprika-claude-plugin\",\n      \"description\": \"Access comprehensive cryptocurrency market data from CoinPaprika including real-time prices, market metrics, historical data, and on-chain analytics for 8000+ cryptocurrencies\",\n      \"version\": \"1.0.0\",\n      \"author\": {\n        \"name\": \"CoinPaprika\"\n      },\n      \"homepage\": \"https://coinpaprika.com\",\n      \"repository\": \"https://github.com/CoinPaprika/claude-marketplace\",\n      \"license\": \"MIT\",\n      \"keywords\": [\n        \"cryptocurrency\",\n        \"crypto\",\n        \"market-data\",\n        \"prices\",\n        \"coins\",\n        \"tokens\",\n        \"blockchain\",\n        \"bitcoin\",\n        \"ethereum\",\n        \"analytics\",\n        \"trading\"\n      ],\n      \"category\": \"cryptocurrency\"\n    }\n  ]\n}",
        "README.md": "# CoinPaprika Claude Marketplace\n\nOfficial Claude Code marketplace providing **two powerful crypto data plugins**:\n- **CoinPaprika** - Market data for 8000+ cryptocurrencies\n- **DexPaprika** - DeFi analytics across 26+ blockchain networks\n\n**üöÄ Complete Bundle**: 2 MCP Servers + 2 Specialized Agents + 14 Slash Commands - all configured automatically!\n\n## Quick Start (2 Options)\n\n### Option 1: Auto-Install (Recommended) ‚≠ê\n```bash\ngit clone https://github.com/coinpaprika/claude-marketplace.git\ncd claude-marketplace\n# Open in Claude Code and Trust the workspace\n```\n**That's it!** Everything installs automatically via `.claude/settings.json`\n\n### Option 2: Manual Install\n```bash\n# In Claude Code\n/plugin marketplace add coinpaprika/claude-marketplace\n\n# Install both plugins:\n/plugin install coinpaprika@coinpaprika-plugins\n/plugin install dexpaprika@coinpaprika-plugins\n\n# Restart Claude Code\n```\n\n**No manual MCP setup needed** - both plugins bundle everything!\n\n## What You Get\n\n### ü™ô CoinPaprika Plugin\n‚úÖ **MCP Server** - Hosted at `https://mcp.coinpaprika.com/sse` (auto-configured)\n‚úÖ **Crypto Analyst Agent** - Market analysis, price tracking, coin research\n‚úÖ **33 MCP Tools** - getCoins, getTickers, getCoinById, getExchanges, search, and more\n‚úÖ **8000+ Coins** - Comprehensive cryptocurrency market coverage\n‚úÖ **7 Slash Commands** - `/coinpaprika:intro`, `/coinpaprika:help`, `/coinpaprika:top`, `/coinpaprika:info`, `/coinpaprika:overview`, `/coinpaprika:search`, `/coinpaprika:health`\n\n### üîÑ DexPaprika Plugin\n‚úÖ **MCP Server** - Hosted at `https://mcp.dexpaprika.com/sse` (auto-configured)\n‚úÖ **DeFi Analyst Agent** - Scam detection, honeypot analysis, security assessment\n‚úÖ **2 Autonomous Skills** - Token Security Analyzer, Technical Pattern Recognition\n‚úÖ **14 MCP Tools** - getNetworks, getTokenDetails, getPoolOHLCV, getTokenPools, and more\n‚úÖ **26+ Networks** - Ethereum, BSC, Base, Solana, Polygon, Arbitrum, and more\n‚úÖ **7 Slash Commands** - `/dexpaprika:intro`, `/dexpaprika:help`, `/dexpaprika:networks`, `/dexpaprika:trending`, `/dexpaprika:prices`, `/dexpaprika:analyze`, `/dexpaprika:health`\n\n## Quick Test\n\n### Test CoinPaprika\n```\n/coinpaprika:intro\n# Shows quick start guide\n\n/coinpaprika:top\n# Shows top cryptocurrencies by market cap\n\n# Or natural language:\nUsing CoinPaprika, show me Bitcoin price and market cap\n```\n\n### Test DexPaprika\n\n**Explicit Commands:**\n```\n/dexpaprika:intro\n# Shows quick start guide\n\n/dexpaprika:trending\n# Shows top DEX pools (specify network like \"Base\")\n```\n\n**Autonomous Skills (no command needed):**\n```\n# Token Security Analysis (auto-activates)\nIs this token safe? 0x1234567890abcdef on Ethereum\n\n# Technical Analysis (auto-activates)\nWhat's happening with the price of this pool? Looks like a double top...\n```\n\n**Natural Language:**\n```\nUsing DexPaprika, show top 10 pools on Base by 24h volume\n```\n\n## Features\n\n### ü™ô CoinPaprika - Cryptocurrency Market Data\n\n#### üìä Market Intelligence\n- **8000+ Cryptocurrencies**: Complete market coverage with real-time data\n- **Price Tracking**: Live prices, market caps, volumes, rankings\n- **Historical Data**: OHLCV candlestick data (latest, today, historical)\n- **Exchange Data**: Track coins across multiple exchanges and markets\n- **Global Metrics**: Total market cap, 24h volume, BTC dominance\n\n#### üîç Research & Discovery\n- **Powerful Search**: Find coins by name, symbol, or ID\n- **Coin Profiles**: Detailed information including teams, events, social links\n- **Contract Addresses**: Multi-platform contract tracking\n- **Price Converter**: Convert between any cryptocurrency pairs\n- **Tags & Categories**: Browse coins by sector or category\n\n#### ü§ñ Crypto Analyst Agent\n- `@crypto-analyst` - Market analysis, price tracking, research\n\n#### üìù Slash Commands\n- `/coinpaprika:intro` - Quick start guide\n- `/coinpaprika:help` - Complete command reference\n- `/coinpaprika:top` - Top cryptocurrencies by market cap\n- `/coinpaprika:info` - Detailed coin information\n- `/coinpaprika:overview` - Global market statistics\n- `/coinpaprika:search` - Search for cryptocurrencies\n- `/coinpaprika:health` - System diagnostics\n\n---\n\n### üîÑ DexPaprika - DeFi & DEX Analytics\n\n#### üîí Security Analysis\n- **Scam Detection**: Identifies pump & dumps, rug pulls, clone tokens\n- **Honeypot Analysis**: Detects buy/sell asymmetry and liquidity traps\n- **Market Manipulation**: Spots wash trading and spoofing\n- **Risk Assessment**: LOW/MEDIUM/HIGH/CRITICAL ratings\n\n#### üìä DeFi Data\n- **26+ Networks**: Ethereum, BSC, Base, Solana, Polygon, Arbitrum, and more\n- **Real-time Pools**: Liquidity pool data across all major DEXes\n- **Token Metrics**: Prices, liquidity, volume, holder counts\n- **Historical Charts**: OHLCV candlestick data for pools\n- **Transaction Analysis**: Track swaps, adds, removes across pools\n\n#### ü§ñ DeFi Analyst Agent\n- `@defi-data-analyst` - DeFi analytics and security assessment\n\n#### üìù Slash Commands\n- `/dexpaprika:intro` - Quick start guide\n- `/dexpaprika:help` - Complete command reference\n- `/dexpaprika:networks` - List all 26+ supported networks\n- `/dexpaprika:trending` - Top pools by 24h volume\n- `/dexpaprika:prices` - Batch token prices (max 10)\n- `/dexpaprika:analyze` - Security and honeypot analysis\n- `/dexpaprika:health` - System diagnostics\n\n#### ü§ñ Autonomous Skills\nDexPaprika includes AI Skills that activate automatically when relevant:\n\n- **Token Security Analyzer** - Automatically analyzes token addresses for honeypots, rug pulls, and scam indicators when users share 0x addresses\n- **Technical Analyzer** - Automatically scans OHLCV data across multiple timeframes to identify candlestick patterns, support/resistance levels, and trend formations when users ask about price patterns\n\n**Key Difference from Commands:**\n- **Commands** (`/dexpaprika:analyze`) - Explicit: User types command\n- **Skills** - Autonomous: Claude automatically activates when patterns in your message match the skill's purpose\n\n## Additional Resources\n\nFor detailed implementation information, see:\n- **[CHANGELOG.md](CHANGELOG.md)** - Version history and recent updates\n\n## API Rate Limits\n\n**Free Tier**: ~10,000 requests/day (no auth required)\n\n**Best Practices**:\n- Use batching for multiple tokens\n- Filter stablecoins early\n- Cache results during session\n\n## Repository Structure\n\n```\nclaude-marketplace/\n‚îú‚îÄ‚îÄ .claude/\n‚îÇ   ‚îî‚îÄ‚îÄ settings.json                      # Auto-install configuration\n‚îú‚îÄ‚îÄ .claude-plugin/\n‚îÇ   ‚îî‚îÄ‚îÄ marketplace.json                   # Marketplace definition\n‚îú‚îÄ‚îÄ plugins/\n‚îÇ   ‚îú‚îÄ‚îÄ coinpaprika-claude-plugin/\n‚îÇ   ‚îÇ   ‚îú‚îÄ‚îÄ .claude-plugin/\n‚îÇ   ‚îÇ   ‚îÇ   ‚îî‚îÄ‚îÄ plugin.json                # Plugin config (MCP + agents + commands)\n‚îÇ   ‚îÇ   ‚îú‚îÄ‚îÄ .mcp-hosted.json              # MCP server connection\n‚îÇ   ‚îÇ   ‚îú‚îÄ‚îÄ agents/\n‚îÇ   ‚îÇ   ‚îÇ   ‚îî‚îÄ‚îÄ crypto-analyst.md          # Crypto market analyst agent\n‚îÇ   ‚îÇ   ‚îú‚îÄ‚îÄ commands/\n‚îÇ   ‚îÇ   ‚îÇ   ‚îú‚îÄ‚îÄ intro.md\n‚îÇ   ‚îÇ   ‚îÇ   ‚îú‚îÄ‚îÄ help.md\n‚îÇ   ‚îÇ   ‚îÇ   ‚îú‚îÄ‚îÄ health.md\n‚îÇ   ‚îÇ   ‚îÇ   ‚îú‚îÄ‚îÄ top-coins.md\n‚îÇ   ‚îÇ   ‚îÇ   ‚îú‚îÄ‚îÄ coin-info.md\n‚îÇ   ‚îÇ   ‚îÇ   ‚îú‚îÄ‚îÄ market-overview.md\n‚îÇ   ‚îÇ   ‚îÇ   ‚îî‚îÄ‚îÄ search.md\n‚îÇ   ‚îÇ   ‚îî‚îÄ‚îÄ README.md\n‚îÇ   ‚îî‚îÄ‚îÄ dexpaprika-claude-plugin/\n‚îÇ       ‚îú‚îÄ‚îÄ .claude-plugin/\n‚îÇ       ‚îÇ   ‚îî‚îÄ‚îÄ plugin.json                # Plugin config (MCP + agents + commands)\n‚îÇ       ‚îú‚îÄ‚îÄ .mcp-hosted.json              # MCP server connection\n‚îÇ       ‚îú‚îÄ‚îÄ agents/\n‚îÇ       ‚îÇ   ‚îî‚îÄ‚îÄ defi-data-analyst.md       # DeFi analyst agent\n‚îÇ       ‚îú‚îÄ‚îÄ commands/\n‚îÇ       ‚îÇ   ‚îú‚îÄ‚îÄ intro.md\n‚îÇ       ‚îÇ   ‚îú‚îÄ‚îÄ help.md\n‚îÇ       ‚îÇ   ‚îú‚îÄ‚îÄ health.md\n‚îÇ       ‚îÇ   ‚îú‚îÄ‚îÄ networks.md\n‚îÇ       ‚îÇ   ‚îú‚îÄ‚îÄ trending.md\n‚îÇ       ‚îÇ   ‚îú‚îÄ‚îÄ prices.md\n‚îÇ       ‚îÇ   ‚îî‚îÄ‚îÄ analyze.md\n‚îÇ       ‚îî‚îÄ‚îÄ README.md\n‚îú‚îÄ‚îÄ INSTALLATION.md                        # Complete installation guide\n‚îú‚îÄ‚îÄ MCP_IMPLEMENTATION_GUIDE.md            # Backend implementation guide\n‚îú‚îÄ‚îÄ MCP_TEST_RESULTS.md                    # Test results and verification\n‚îú‚îÄ‚îÄ CHANGELOG.md                           # Change history\n‚îî‚îÄ‚îÄ README.md                              # This file\n```\n\n## Verification\n\nCheck everything is working:\n```bash\n# 1. Check MCP servers\nclaude mcp list\n# Should show:\n# - plugin:coinpaprika:coinpaprika: https://mcp.coinpaprika.com/sse (SSE) - ‚úì\n# - plugin:dexpaprika:dexpaprika: https://mcp.dexpaprika.com/sse (SSE) - ‚úì\n\n# 2. Check agents\n/agents\n# Should show: crypto-analyst, defi-data-analyst\n\n# 3. Check CoinPaprika commands\n/coinpaprika:intro\n# Should show: CoinPaprika quick start guide\n\n# 4. Check DexPaprika commands\n/dexpaprika:intro\n# Should show: DexPaprika quick start guide\n\n# 5. Run health checks\n/coinpaprika:health\n/dexpaprika:health\n# Both should show: All systems operational\n```\n\n## Example Workflows\n\n### CoinPaprika Workflows\n\n**Market Overview**:\n```\n/coinpaprika:overview\n# Shows global crypto market statistics\n```\n\n**Research a Coin**:\n```\n/coinpaprika:info\n# Get detailed information about any cryptocurrency\n```\n\n**Search for Coins**:\n```\n/coinpaprika:search\n# Find cryptocurrencies by name or symbol\n```\n\n**Natural Language Queries**:\n```\nUsing CoinPaprika:\n- Show me Bitcoin price and 24h volume\n- What are the top 10 cryptocurrencies by market cap?\n- Get historical OHLCV data for Ethereum\n- Compare prices of BTC, ETH, and SOL\n```\n\n### DexPaprika Workflows\n\n**List Supported Networks**:\n```\n/dexpaprika:networks\n# Shows all 26+ blockchain networks available\n```\n\n**Show Trending Pools**:\n```\n/dexpaprika:trending\n# Shows top pools by 24h volume on specified network\n```\n\n**Analyze Token Security**:\n```\n/dexpaprika:analyze\n# Comprehensive security check for honeypots, rug pulls, manipulation\n```\n\n**Natural Language Queries**:\n```\nUsing DexPaprika:\n- Show top 10 pools on Base by 24h volume\n- Get token details for 0x... on ethereum\n- Show 24h OHLCV for pool 0x... on base\n- Analyze this token for security risks\n```\n\n## Support\n\n- **Issues**: [GitHub Issues](https://github.com/coinpaprika/claude-marketplace/issues)\n- **CoinPaprika Docs**: https://docs.coinpaprika.com\n- **DexPaprika Docs**: https://docs.dexpaprika.com\n- **CoinPaprika API**: https://mcp.coinpaprika.com/openapi\n- **DexPaprika API**: https://mcp.dexpaprika.com/openapi\n- **CoinPaprika Website**: https://coinpaprika.com\n- **DexPaprika Website**: https://dexpaprika.com\n\n## License\n\nMIT - see [LICENSE](LICENSE)\n\n---\n\n**Made with ‚ù§Ô∏è by CoinPaprika & DexPaprika Team**\n",
        "plugins/dexpaprika-claude-plugin/README.md": "# DexPaprika Claude Plugin\n\nA Claude Code plugin that provides access to comprehensive DeFi data from DexPaprika, including DEXes, liquidity pools, tokens, and trading information across 26+ blockchain networks.\n\n## Features\n\n- **26+ Blockchain Networks**: Access data from Ethereum, Solana, Polygon, Arbitrum, Optimism, Base, and many more\n- **DEX Discovery**: Find and analyze DEXes across different networks\n- **Pool Analytics**: Get detailed information about liquidity pools, including volume, transactions, and price data\n- **Token Information**: Access comprehensive token data including prices, liquidity, and trading metrics\n- **Historical Data**: Retrieve OHLCV data for technical analysis\n- **Real-time Transactions**: Monitor recent trading activity\n- **Batched Price Queries**: Efficiently fetch prices for up to 10 tokens in a single request\n- **Smart Network Normalization**: User-friendly network names automatically converted to API format\n- **Optimized Payloads**: Field projection support for compact, efficient responses\n\n## Installation\n\n### Prerequisites\n\n- Claude Code CLI installed\n- Internet connection for accessing the hosted MCP server\n\n### Step-by-Step Installation\n\n#### Step 1: Add the CoinPaprika Marketplace\n\n```bash\nclaude plugin marketplace add coinpaprika/claude-marketplace\n```\n\nThis command clones the marketplace repository and makes the DexPaprika plugin available.\n\n#### Step 2: Add the DexPaprika MCP Server\n\n**IMPORTANT:** You must specify the `--transport sse` flag for the SSE (Server-Sent Events) server:\n\n```bash\nclaude mcp add --transport sse dexpaprika https://mcp.dexpaprika.com/sse\n```\n\n‚ö†Ô∏è **Common Mistake:** Do NOT forget the `--transport sse` flag! Without it, the server will be configured incorrectly and won't connect.\n\n#### Step 3: Verify Installation\n\n```bash\nclaude mcp list\n```\n\nExpected output:\n```\ndexpaprika: https://mcp.dexpaprika.com/sse (SSE) - ‚úì Connected\n```\n\nIf you see \"‚úì Connected\", the installation was successful!\n\n## Quick Start\n\n### Skills (Automatic Analysis)\n\nDexPaprika provides **4 automatic skills** that Claude uses without needing slash commands:\n\n1. **Token Security Analyzer** - Automatically analyzes tokens for honeypots, scams, and security risks\n2. **Technical Analyzer** - Analyzes OHLCV data for candlestick patterns and technical indicators\n3. **Batch Token Price Lookup** - Fetches current prices for multiple tokens\n4. **Trending Pools Analyzer** - Shows top pools ranked by 24-hour trading volume\n\nJust ask Claude naturally and it will use the appropriate skill:\n- \"Is this token safe?\" ‚Üí Uses Token Security Analyzer\n- \"Analyze the 4h chart\" ‚Üí Uses Technical Analyzer\n- \"What's the price of USDC and ETH?\" ‚Üí Uses Batch Token Price Lookup\n- \"What's trending on Solana?\" ‚Üí Uses Trending Pools Analyzer\n\n### Using the Agent\n\nFor comprehensive DeFi analysis, use the DeFi data analyst agent:\n\n```\n@defi-data-analyst\n```\n\nThe agent specializes in:\n- Honeypot detection and scam identification\n- Risk assessment and rug pull analysis\n- Market manipulation detection\n- Token security evaluation\n\n## Usage\n\nOnce installed, you can access DexPaprika data through Claude using natural language queries:\n\n### Basic Queries\n\n- \"Show me the top pools on Ethereum by volume\"\n- \"What tokens have the highest liquidity on Polygon?\"\n- \"Get historical price data for USDC on Solana\"\n- \"Find DEXes available on Arbitrum\"\n- \"Show recent transactions for this pool address\"\n\n### Advanced Queries\n\n- \"Get prices for these 5 tokens on Base: [addresses]\" (batched pricing)\n- \"Find trending pools on binance smart chain\" (auto-normalizes to 'bsc')\n- \"Show compact pool data with only volume and price fields\"\n- \"Search for Jupiter token across all networks\"\n\n## Best Practices\n\n### 1. Always Start with getCapabilities\n\nCall `getCapabilities` at the beginning of your session to:\n- Learn available workflow patterns\n- Get network synonyms for normalization\n- Understand common pitfalls\n- See API version and features\n\n### 2. Batched Price Queries\n\nWhen fetching multiple token prices:\n- **Maximum 10 tokens** per request\n- **Format**: Comma-separated string: `\"0xabc...,0xdef...,0x123...\"`\n- Pre-validate array length on client-side\n- Handle missing tokens gracefully (unpriced tokens are omitted)\n\nExample:\n```\n\"Get batched prices for USDC, USDT, DAI, WETH, and WBTC on Ethereum\"\n```\n\n### 3. Network Normalization\n\nUser-friendly network names are automatically converted:\n- \"Binance Smart Chain\" / \"BNB Chain\" ‚Üí `bsc`\n- \"Polygon\" ‚Üí `polygon`\n- \"Base\" ‚Üí `base`\n\nThe plugin handles this automatically using synonyms from `getCapabilities`.\n\n### 4. Optimized Responses\n\nFor large datasets, request specific fields:\n- Use field projection: `fields=pools,page_info`\n- Reduces bandwidth and improves performance\n- Particularly useful for pool listings and token searches\n\n### 5. Error Handling\n\nThe plugin provides intelligent error handling:\n- **Structured 400 errors** with `code`, `message`, `hint`, and `corrected_example`\n- Automatic retry suggestions for correctable errors\n- Client-side validation to prevent common mistakes\n\n## Recommended Workflows\n\n### Workflow 1: Trending Snapshot\n```\n1. List all networks\n2. Get top 10 pools by volume on desired network\n3. Optional: Use field projection for compact view\n```\n\n### Workflow 2: Token Deep Dive\n```\n1. Search for token by name or address\n2. Get token details (price, FDV, metrics)\n3. Find all pools containing the token\n4. Analyze pool transactions and history\n```\n\n### Workflow 3: Batched Price Monitoring\n```\n1. Collect up to 10 token addresses\n2. Request batched prices in single call\n3. Monitor price changes over time\n4. Handle missing/unpriced tokens gracefully\n```\n\n### Workflow 4: Pool Performance Analysis\n```\n1. Get current pool details (state, volume, transactions)\n2. Fetch historical OHLCV data for trends\n3. Review recent transactions for activity patterns\n4. Compare across different time intervals\n```\n\n## Supported Networks\n\nThe plugin provides access to data from 26+ blockchain networks including:\n\n- Ethereum\n- Solana\n- Polygon\n- Arbitrum\n- Optimism\n- Base\n- Avalanche\n- Binance Smart Chain\n- Fantom\n- And many more...\n\n## Development\n\n### Plugin Structure\n\n```\ndexpaprika-claude-plugin/\n‚îú‚îÄ‚îÄ .claude-plugin/\n‚îÇ   ‚îî‚îÄ‚îÄ plugin.json          # Plugin manifest\n‚îú‚îÄ‚îÄ .mcp.json                # MCP server configuration\n‚îî‚îÄ‚îÄ README.md               # This file\n```\n\n### Local Testing\n\nTo test the plugin locally:\n\n1. Create a development marketplace\n2. Add the plugin to your marketplace\n3. Install and test the plugin\n\nSee the Claude plugin documentation for detailed setup instructions.\n\n## API Tools Reference\n\n### Core Functions\n\n- **getCapabilities**: Load workflows, synonyms, and best practices (always call first!)\n- **getNetworks**: List all 26+ supported blockchain networks\n- **getStats**: High-level ecosystem statistics\n\n### DEX & Pool Tools\n\n- **getNetworkDexes**: Find DEXes on a specific network\n- **getNetworkPools**: Get top liquidity pools (PRIMARY pool function)\n- **getDexPools**: Filter pools by specific DEX\n- **getPoolDetails**: Comprehensive pool data\n- **getPoolOHLCV**: Historical price data (OHLCV)\n- **getPoolTransactions**: Recent trading activity\n\n### Token Tools\n\n- **getTokenDetails**: Token metadata, price, FDV, metrics\n- **getTokenPools**: Find all pools containing a token\n- **getTokenMultiPrices**: Batched prices (up to 10 tokens)\n\n### Search Tools\n\n- **search**: Global search across ALL networks for tokens, pools, DEXes\n\n## Configuration\n\nThe plugin can be configured through the `.mcp.json` file to:\n- Use different MCP server endpoints (hosted at `https://mcp.dexpaprika.com/sse`)\n- Set custom environment variables\n- Configure connection parameters\n\n### Hosted MCP Server\n\nThe plugin uses the hosted DexPaprika MCP server at:\n```\nhttps://mcp.dexpaprika.com/sse\n```\n\nAdditional endpoints:\n- **OpenAPI Spec**: `https://mcp.dexpaprika.com/openapi`\n- **Capabilities**: `https://mcp.dexpaprika.com/api/capabilities`\n\n## Troubleshooting\n\n### Installation Issues\n\n**MCP Server Not Connecting?**\n\nIf you see \"No MCP servers configured\" or the server shows as disconnected:\n\n1. **Verify you used the correct command with `--transport sse`:**\n   ```bash\n   claude mcp list\n   ```\n\n2. **If missing the SSE transport, remove and re-add:**\n   ```bash\n   claude mcp remove dexpaprika\n   claude mcp add --transport sse dexpaprika https://mcp.dexpaprika.com/sse\n   ```\n\n3. **Verify the connection:**\n   ```bash\n   claude mcp list\n   ```\n   Should show: `dexpaprika: https://mcp.dexpaprika.com/sse (SSE) - ‚úì Connected`\n\n### Common Runtime Issues\n\nIf you encounter issues during use:\n\n1. **Network Issues**: Verify connectivity to `mcp.dexpaprika.com`\n2. **Invalid Network Names**: Use `getCapabilities` to get valid network IDs and synonyms\n3. **Too Many Tokens**: Batched price requests limited to 10 tokens maximum\n4. **Missing Data**: Some tokens may not have price data (they're omitted from results)\n5. **Debug Output**: Check Claude's debug output for detailed error messages\n\n### Common Error Codes\n\n- **DP400_TOO_MANY_TOKENS**: Exceeded 10 token limit in batched price request\n- **DP400_INVALID_NETWORK**: Network ID not recognized (use synonyms from `getCapabilities`)\n- **DP400_MISSING_TOKENS**: No tokens provided in batched price request\n\nWhen you receive a 400 error, check for `error.corrected_example` which shows the correct format.\n\n## Performance Tips\n\n1. **Use Field Projection**: Request only needed fields with `?fields=pools,page_info`\n2. **Batch Price Requests**: Fetch up to 10 token prices in one call instead of multiple requests\n3. **Cache getCapabilities**: No need to call it repeatedly in the same session\n4. **Parallel Requests**: When fetching data from multiple networks, make parallel calls\n\n## License\n\nMIT License - See plugin.json for details.\n\n## Resources\n\n- **Plugin Homepage**: <https://mcp.dexpaprika.com>\n- **API Documentation**: <https://mcp.dexpaprika.com/openapi>\n- **Capabilities Endpoint**: <https://mcp.dexpaprika.com/api/capabilities>\n- **GitHub Repository**: <https://github.com/coinpaprika/claude-marketplace>\n\n## Support\n\nFor issues related to:\n- **Plugin functionality**: Check Claude Code documentation\n- **DexPaprika data**: Contact CoinPaprika support\n- **MCP server issues**: Verify server configuration and connectivity at `mcp.dexpaprika.com`\n- **Feature requests**: Submit to the GitHub repository\n",
        "plugins/coinpaprika-claude-plugin/README.md": "# CoinPaprika Plugin for Claude Code\n\nAccess comprehensive cryptocurrency market data for 8000+ cryptocurrencies directly from Claude Code using the CoinPaprika API.\n\n## üöÄ Features\n\n- **Real-time Market Data**: Live prices, market caps, and trading volumes for all cryptocurrencies\n- **Historical Analysis**: Access historical price data (OHLCV) for technical analysis\n- **Global Market Overview**: Track total market cap, Bitcoin dominance, and market trends\n- **Comprehensive Coin Data**: Detailed information including supply metrics, social stats, and events\n- **Exchange Information**: Data on 300+ exchanges and their trading pairs\n- **Search & Discovery**: Find coins by name, symbol, or category\n- **Price Conversion**: Convert between cryptocurrencies and fiat currencies\n\n## üì¶ Installation\n\nThe plugin is part of the coinpaprika-plugins marketplace.\n\n```bash\n# Add the marketplace (if not already added)\nclaude plugin marketplace add coinpaprika/claude-marketplace\n\n# Install the plugin\nclaude plugin install coinpaprika-market-data\n```\n\n## üéØ Quick Start\n\n### Skills (Automatic Analysis)\n\nCoinPaprika provides **1 automatic skill** that Claude uses without needing slash commands:\n\n- **Cryptocurrency Market Search** - Automatically searches for cryptocurrencies, provides market overviews, shows top cryptocurrencies by market cap, and delivers detailed project information\n\nJust ask Claude naturally and it will use the skill:\n- \"Tell me about Bitcoin\" ‚Üí Uses Market Search skill\n- \"What are the top 10 cryptocurrencies?\" ‚Üí Uses Market Search skill\n- \"Search for DeFi tokens\" ‚Üí Uses Market Search skill\n- \"Give me a market overview\" ‚Üí Uses Market Search skill\n\n### Example Usage\n\nJust ask Claude naturally:\n\n- \"Show me the global cryptocurrency market overview\"\n- \"What's the current price of Bitcoin?\"\n- \"Search for Ethereum alternatives\"\n- \"Show me the top 20 cryptocurrencies by market cap\"\n- \"Find all DeFi related coins\"\n- \"What's Bitcoin's market dominance?\"\n\n## ü§ñ Crypto Analyst Agent\n\nThe plugin includes a specialized crypto analyst agent for deep market analysis:\n\nSimply reference the agent in your conversation:\n\n```\n@crypto-analyst\n```\n\nThe agent provides:\n- Cryptocurrency research and fundamentals\n- Market cap rankings and positioning\n- Supply metrics and tokenomics\n- Project overview and use cases\n- Price history and trends\n- Comparative cryptocurrency analysis\n\n## üîß Available MCP Tools\n\n### Market Data\n- `getGlobalMarketOverview` - Global market statistics\n- `getTickers` - Market data for all active coins\n- `getTicker` - Market data for specific coin\n\n### Coin Information\n- `getCoins` - List all available cryptocurrencies\n- `getCoinById` - Detailed cryptocurrency information\n- `getCoinEvents` - Important events for a cryptocurrency\n- `getCoinTwitter` - Social media metrics\n\n### Historical Data\n- `getHistoricalTicks` - Historical price data (OHLCV)\n\n### Search & Discovery\n- `searchCoins` - Find coins by name, symbol, or keyword\n- `getTags` - Browse coins by categories\n\n### Exchanges\n- `getExchanges` - List all cryptocurrency exchanges\n- `getExchangeById` - Detailed exchange information\n- `getExchangeMarkets` - Trading pairs on specific exchanges\n\n### Utilities\n- `getPriceConverter` - Convert between cryptocurrencies and fiat\n\n## üìä Use Cases\n\n### Portfolio Tracking\n```\n\"What's the current price of BTC, ETH, and SOL?\"\n\"Show me the 24h price change for my watchlist\"\n```\n\n### Market Research\n```\n\"Find the top DeFi tokens by market cap\"\n\"What are the top gainers in the last 24 hours?\"\n\"Show me upcoming events for Polkadot\"\n```\n\n### Technical Analysis\n```\n\"Show me Bitcoin's price history for the last 7 days\"\n\"What are the support and resistance levels for Ethereum?\"\n\"Analyze the volume trends for BNB\"\n```\n\n### Fundamental Analysis\n```\n\"What is the circulating supply of XRP?\"\n\"How many exchanges is Chainlink listed on?\"\n\"What's the all-time high for Dogecoin?\"\n```\n\n## ‚öôÔ∏è Configuration\n\nThe plugin connects to CoinPaprika's hosted MCP server:\n- **URL**: `https://mcp.coinpaprika.com/sse`\n- **Type**: Server-Sent Events (SSE)\n- **Authentication**: None required\n\n## üìù Important Notes\n\n### Coin ID Format\nCoinPaprika uses specific coin IDs (not just symbols):\n- ‚úÖ Correct: `btc-bitcoin`, `eth-ethereum`\n- ‚ùå Incorrect: `bitcoin`, `BTC`, `ethereum`\n\n**Always use `searchCoins` first if you're unsure about the coin ID.**\n\n### Rate Limiting\nThe CoinPaprika API has rate limits:\n- Free tier: ~10,000 requests/day\n- Response caching recommended for frequently accessed data\n- Use batch endpoints (like `getTickers`) when possible\n\n### Data Freshness\n- Ticker data: Updated every 5 minutes\n- Historical data: Available in various intervals (1h, 24h, 7d, 30d, 1y)\n- Events and social data: Updated periodically\n\n## üêõ Troubleshooting\n\n### Common Issues\n\n**\"Coin not found\" error**\n- Use `searchCoins` to find the correct coin ID\n- Verify spelling and format (lowercase-with-dashes)\n\n**Rate limit exceeded**\n- Wait a few minutes before retrying\n- Reduce number of API calls\n- Cache frequently accessed data\n\n**No data returned**\n- Coin might be inactive or delisted\n- Check if coin ID is correct\n- Some newer coins might have limited data\n\n### Getting Help\n\n1. Use `/coinpaprika-market-data:intro` for quick reference\n2. Check the [CoinPaprika API documentation](https://api.coinpaprika.com)\n3. Report issues on the [GitHub repository](https://github.com/coinpaprika/claude-marketplace)\n\n## üîó Resources\n\n- **Website**: [coinpaprika.com](https://coinpaprika.com)\n- **API Documentation**: [api.coinpaprika.com](https://api.coinpaprika.com)\n- **GitHub**: [github.com/coinpaprika](https://github.com/coinpaprika)\n- **Support**: Contact CoinPaprika team for data-related questions\n\n## üìÑ License\n\nMIT License - See LICENSE file for details\n\n## ü§ù Contributing\n\nContributions are welcome! Please feel free to submit issues or pull requests to improve the plugin.\n\n---\n\n**Disclaimer**: This plugin provides market data for informational purposes only. It is not financial advice. Always do your own research before making investment decisions. Cryptocurrency investments carry significant risk.\n"
      },
      "plugins": [
        {
          "name": "dexpaprika",
          "source": "./plugins/dexpaprika-claude-plugin",
          "description": "Access comprehensive DeFi data from DexPaprika including DEXes, liquidity pools, tokens, and trading information across 26+ blockchains",
          "version": "1.0.0",
          "author": {
            "name": "CoinPaprika & DexPaprika"
          },
          "homepage": "https://dexpaprika.com",
          "repository": "https://github.com/CoinPaprika/claude-marketplace",
          "license": "MIT",
          "keywords": [
            "defi",
            "dex",
            "liquidity",
            "pools",
            "tokens",
            "blockchain",
            "cryptocurrency",
            "trading",
            "analytics"
          ],
          "category": "defi",
          "categories": [
            "analytics",
            "blockchain",
            "cryptocurrency",
            "defi",
            "dex",
            "liquidity",
            "pools",
            "tokens",
            "trading"
          ],
          "install_commands": [
            "/plugin marketplace add coinpaprika/claude-marketplace",
            "/plugin install dexpaprika@coinpaprika-plugins"
          ]
        },
        {
          "name": "coinpaprika",
          "source": "./plugins/coinpaprika-claude-plugin",
          "description": "Access comprehensive cryptocurrency market data from CoinPaprika including real-time prices, market metrics, historical data, and on-chain analytics for 8000+ cryptocurrencies",
          "version": "1.0.0",
          "author": {
            "name": "CoinPaprika"
          },
          "homepage": "https://coinpaprika.com",
          "repository": "https://github.com/CoinPaprika/claude-marketplace",
          "license": "MIT",
          "keywords": [
            "cryptocurrency",
            "crypto",
            "market-data",
            "prices",
            "coins",
            "tokens",
            "blockchain",
            "bitcoin",
            "ethereum",
            "analytics",
            "trading"
          ],
          "category": "cryptocurrency",
          "categories": [
            "analytics",
            "bitcoin",
            "blockchain",
            "coins",
            "crypto",
            "cryptocurrency",
            "ethereum",
            "market-data",
            "prices",
            "tokens",
            "trading"
          ],
          "install_commands": [
            "/plugin marketplace add coinpaprika/claude-marketplace",
            "/plugin install coinpaprika@coinpaprika-plugins"
          ]
        }
      ]
    }
  ]
}