{
  "author": {
    "id": "Data-Wise",
    "display_name": "Davood Tofighi",
    "avatar_url": "https://avatars.githubusercontent.com/u/1749560?u=61d1cd6a5f1dd187802eab60fb4070aa5e51e9df&v=4"
  },
  "marketplaces": [
    {
      "name": "data-wise-craft",
      "version": null,
      "description": "Full-stack developer toolkit for Claude Code with 108 commands, 8 agents, and 25 skills",
      "repo_full_name": "Data-Wise/craft",
      "repo_url": "https://github.com/Data-Wise/craft",
      "repo_description": "Full-stack developer toolkit - 86 commands, 8 agents, 21 skills for code, git, docs, testing, architecture, CI/CD, and ADHD-friendly workflows. Claude Code plugin.",
      "signals": {
        "stars": 0,
        "forks": 0,
        "pushed_at": "2026-02-20T03:28:16Z"
      },
      "files": {
        ".claude-plugin/marketplace.json": "{\n  \"name\": \"data-wise-craft\",\n  \"owner\": {\n    \"name\": \"Data-Wise\",\n    \"email\": \"dt@stat-wise.com\"\n  },\n  \"metadata\": {\n    \"description\": \"Full-stack developer toolkit for Claude Code with 108 commands, 8 agents, and 25 skills\",\n    \"version\": \"2.23.0\"\n  },\n  \"plugins\": [\n    {\n      \"name\": \"craft\",\n      \"source\": {\n        \"source\": \"github\",\n        \"repo\": \"Data-Wise/craft\"\n      },\n      \"description\": \"Full-stack developer toolkit for Claude Code with 108 commands, 8 agents, and 25 skills\",\n      \"version\": \"2.23.0\",\n      \"author\": {\n        \"name\": \"Data-Wise\",\n        \"email\": \"dt@stat-wise.com\"\n      },\n      \"homepage\": \"https://data-wise.github.io/craft/\",\n      \"repository\": \"https://github.com/Data-Wise/craft\",\n      \"license\": \"MIT\",\n      \"category\": \"development\",\n      \"keywords\": [\n        \"workflow\",\n        \"automation\",\n        \"git\",\n        \"testing\",\n        \"documentation\",\n        \"ci-cd\",\n        \"release\",\n        \"architecture\"\n      ]\n    }\n  ]\n}\n",
        ".claude-plugin/plugin.json": "{\n  \"name\": \"craft\",\n  \"version\": \"2.23.0\",\n  \"description\": \"Full-stack developer toolkit with integrated workflow automation - 108 commands (94 craft + 13 workflow), 8 agents, 25 skills with standardized dry-run preview mode (29 with --dry-run support). Code, git, site, docs, testing, architecture, CI, distribution, teaching workflows, planning, release pipeline, and ADHD-friendly features including brainstorming, task management, and spec capture\",\n  \"author\": {\n    \"name\": \"Data-Wise\",\n    \"email\": \"dt@stat-wise.com\"\n  }\n}\n",
        "README.md": "# Craft - Full Stack Developer Toolkit Plugin\n\n[![Craft CI](https://github.com/Data-Wise/craft/actions/workflows/ci.yml/badge.svg?branch=dev)](https://github.com/Data-Wise/craft/actions/workflows/ci.yml)\n[![Documentation Quality](https://github.com/Data-Wise/craft/actions/workflows/docs-quality.yml/badge.svg?branch=dev)](https://github.com/Data-Wise/craft/actions/workflows/docs-quality.yml)\n[![Version](https://img.shields.io/badge/version-2.23.0-blue.svg)](https://github.com/Data-Wise/craft)\n[![Documentation](https://img.shields.io/badge/docs-99%25%20complete-brightgreen.svg)](https://data-wise.github.io/craft/)\n\n> **v2.22.2 - Bump-Version Feature & Documentation Overhaul** üöÄ\n> **108 commands** | **25 skills** | **8 agents** | **~1496 tests passing**\n> Test consolidation (7‚Üí3 commands), layered instruction system, friction-driven prevention.\n\nA comprehensive production-ready toolkit for Claude Code featuring smart orchestration, ADHD-friendly workflows, multi-agent coordination, and complete documentation coverage.\n\n## Installation\n\nCraft works in both Claude Code CLI and Claude Desktop app. No MCP server dependencies required.\n\n### Option 1: Marketplace (Recommended)\n\n```bash\n# Install from the Claude Code plugin marketplace\nclaude plugin add github:Data-Wise/craft\n```\n\nWorks on **all platforms** (macOS, Linux, Windows). No additional tools required.\n\n### Option 2: Homebrew (macOS)\n\n```bash\n# Add the Data-Wise tap\nbrew tap data-wise/tap\n\n# Install craft plugin\nbrew install craft\n```\n\nThe Homebrew formula automatically:\n\n- Installs the plugin to `~/.claude/plugins/craft`\n- Makes it available in Claude Code CLI and Claude Desktop\n- No additional configuration needed\n\n### Option 3: Quick Install (curl)\n\n```bash\n# One-command installation\ncurl -fsSL https://raw.githubusercontent.com/Data-Wise/craft/main/install.sh | bash\n```\n\n**Then restart Claude Code to load the plugin.**\n\n### Option 4: npm (When published)\n\n```bash\n# Install from npm (after publishing)\nnpm install -g @data-wise/claude-craft-plugin\n\n# Plugin will auto-install to ~/.claude/plugins/craft\n```\n\n### Option 5: Manual Installation (Local Development)\n\n**For Claude Code CLI and Claude Desktop:**\n\n```bash\n# Clone the repository\ngit clone https://github.com/Data-Wise/craft.git\ncd craft\n\n# Install in development mode (symlink - changes reflected immediately)\nln -s $(pwd) ~/.claude/plugins/craft\n\n# Or install in production mode (copy - stable)\ncp -r . ~/.claude/plugins/craft\n```\n\n**Installation locations:**\n\n- Plugin directory: `~/.claude/plugins/craft`\n- Commands: `~/.claude/plugins/craft/commands/`\n- Skills: `~/.claude/plugins/craft/skills/`\n- Agents: `~/.claude/plugins/craft/agents/`\n\n### Verify Installation\n\n```bash\n# Check plugin directory exists\nls -la ~/.claude/plugins/craft\n\n# Verify plugin.json\ncat ~/.claude/plugins/craft/.claude-plugin/plugin.json\n\n# Test a command\nclaude\n/craft:help\n```\n\n**Expected output:**\n\n```\nCraft v1.17.0 loaded\n86 commands available\n```\n\n### Using in Claude Code CLI\n\nAfter installation, commands are immediately available:\n\n```bash\n# Start Claude Code in any directory\nclaude\n\n# Use craft commands\n/craft:do \"add user authentication\"\n/craft:check\n/craft:test unit\n```\n\n### Using in Claude Desktop App\n\nCraft automatically loads when you open Claude Desktop. Commands work the same way:\n\n1. Open Claude Desktop app\n2. Start a new conversation\n3. Use slash commands: `/craft:do`, `/brainstorm`, etc.\n\n### MCP Server Setup\n\n**Craft does NOT require any MCP server configuration.**\n\nCraft is a pure plugin that uses built-in Claude Code capabilities. No external servers needed.\n\n**Benefits:**\n\n- ‚úÖ Instant startup (no server overhead)\n- ‚úÖ Simple installation (no server config)\n- ‚úÖ Works offline\n- ‚úÖ Self-contained\n\n## üìö Documentation\n\n**Full documentation:** <https://data-wise.github.io/craft/> (99% complete)\n\n- [Quick Start](https://data-wise.github.io/craft/QUICK-START/) (30 seconds)\n- [ADHD Guide](https://data-wise.github.io/craft/ADHD-QUICK-START/) (neurodivergent-friendly)\n- [Visual Workflows](https://data-wise.github.io/craft/workflows/) (10 GIF demonstrations)\n\n> Full-stack developer toolkit for Claude Code ‚Äî 108 commands, 8 agents, 25 skills with smart orchestration and ADHD-friendly workflows\n\n- [Claude Code 2.1 Integration](https://data-wise.github.io/craft/guide/claude-code-2.1-integration/) (comprehensive guide with 9 diagrams)\n- [Complexity Scoring Algorithm](https://data-wise.github.io/craft/guide/complexity-scoring-algorithm/) (complete technical documentation with 8 diagrams)\n- [Version History](https://data-wise.github.io/craft/VERSION-HISTORY/) (v1.0.0 ‚Üí v1.24.0 timeline)\n- [Dependency Management](https://data-wise.github.io/craft/DEPENDENCY-MANAGEMENT/) (API, Architecture, Developer Guide)\n\n## Quick Start - Smart Commands\n\n```bash\n# Universal command - AI routes to best workflow\n/craft:do \"add user authentication\"\n\n# Pre-flight checks\n/craft:check                    # Quick validation\n/craft:check --for release      # Full release audit\n\n# Context-aware help\n/craft:help                     # Suggestions for your project\n/craft:help testing             # Deep dive into testing\n\n# Discover all commands\n/craft:hub\n```\n\n## Mode System\n\nCommands support execution modes for different use cases:\n\n| Mode         | Time   | Use Case               |\n| ------------ | ------ | ---------------------- |\n| **default**  | < 10s  | Quick checks           |\n| **debug**    | < 120s | Verbose output, traces |\n| **optimize** | < 180s | Parallel, performance  |\n| **release**  | < 300s | Comprehensive audit    |\n\n```bash\n/craft:code:lint                # Quick check\n/craft:code:lint debug          # Verbose with suggestions\n/craft:test release             # Full suite with coverage\n/craft:arch:analyze optimize    # Performance analysis\n```\n\n## Teaching Mode\n\nSpecialized workflows for teaching projects with automated validation, semester tracking, and safe publishing.\n\n**Key Features:**\n\n- Auto-detection via `.flow/teach-config.yml` configuration\n- Content validation (syllabus sections, schedule completeness, assignment files)\n- Preview-before-publish workflow (draft ‚Üí production branches)\n- Semester progress tracking with automatic week calculation\n- ADHD-friendly dashboards and output\n\n![Teaching Workflow Demo](docs/demos/teaching-workflow.gif)\n\n**Quick Start:**\n\n1. Create `.flow/teach-config.yml` with course info and semester dates\n2. Run `/craft:site:validate` to check content completeness\n3. Publish with confidence using `/craft:site:publish`\n\n**Example workflow:**\n\n```bash\n# Check semester progress\n/craft:site:progress\n\n# Validate content before publishing\n/craft:site:validate\n\n# Publish draft ‚Üí production (with preview)\n/craft:site:publish\n```\n\n**[Full Tutorial](https://data-wise.github.io/craft/tutorials/teaching-mode-setup/)** ‚Ä¢ **[Config Schema](https://data-wise.github.io/craft/teaching-config-schema/)**\n\n## Commands (86 total)\n\n### Workflow Commands (12)\n\n| Command                                | Description                                                                                   |\n| -------------------------------------- | --------------------------------------------------------------------------------------------- |\n| `/brainstorm [depth] [focus] [action]` | Enhanced brainstorming with smart detection, design modes, time budgets, and agent delegation |\n| `/spec-review <file>`                  | Interactive spec review with validation, status updates, and archival                         |\n| `/focus [task]`                        | Enter focus mode for deep work on a specific task                                             |\n| `/next`                                | Get next task recommendation                                                                  |\n| `/done [message]`                      | Mark current task as complete                                                                 |\n| `/recap`                               | Generate session summary and progress report                                                  |\n| `/stuck [description]`                 | Get help when blocked on a task                                                               |\n| `/refine <spec-file>`                  | Refine and improve existing spec documents                                                    |\n| `/task-status [task-id]`               | Check status of background tasks                                                              |\n| `/task-output <task-id>`               | Get output from completed task                                                                |\n| `/task-cancel <task-id>`               | Cancel running background task                                                                |\n| `/adhd-guide`                          | ADHD-friendly workflow guide and best practices                                               |\n\n**Brainstorming Modes:**\n\n```bash\n/brainstorm q feat        # Quick feature brainstorm\n/brainstorm d arch        # Deep architecture analysis\n/brainstorm max ux save   # Max depth UX design with spec capture\n```\n\n### Smart Commands (4) - ENHANCED\n\n| Command                            | Description                                                                                      |\n| ---------------------------------- | ------------------------------------------------------------------------------------------------ |\n| `/craft:do <task>`                 | Universal command - routes to appropriate workflow                                               |\n| `/craft:orchestrate <task> [mode]` | **ENHANCED v2.1** Launch orchestrator with mode-aware execution, context tracking, timeline view |\n| `/craft:check`                     | Pre-flight checks (commit/pr/release)                                                            |\n| `/craft:help`                      | Context-aware help and suggestions                                                               |\n\n#### Orchestrator Modes\n\n```bash\n/craft:orchestrate \"add auth\" optimize    # Fast parallel (4 agents)\n/craft:orchestrate \"prep release\" release # Thorough audit\n/craft:orchestrate status                 # Agent dashboard\n/craft:orchestrate timeline               # Execution timeline\n/craft:orchestrate budget                 # Context tracking\n/craft:orchestrate continue               # Resume session\n```\n\n### Code Commands (12)\n\n| Command                  | Description           | Modes |\n| ------------------------ | --------------------- | ----- |\n| `/craft:code:debug`      | Systematic debugging  | ----- |\n| `/craft:code:demo`       | Create demonstrations | ----- |\n| `/craft:code:docs-check` | Pre-flight doc check  | ----- |\n| `/craft:code:refactor`   | Refactoring guidance  | ----- |\n| `/craft:code:release`    | Release workflow      | ----- |\n| `/craft:code:test-gen`   | Generate test files   | ----- |\n| `/craft:code:lint`       | Code style checks     | ‚úì    |\n| `/craft:code:coverage`   | Coverage report       | ‚úì    |\n| `/craft:code:deps-check` | Dependency health     | ----- |\n| `/craft:code:deps-audit` | Security scan         | ----- |\n| `/craft:code:ci-local`   | CI checks locally     | ----- |\n| `/craft:code:ci-fix`     | Fix CI failures       | ----- |\n\n### Test Commands (3)\n\n| Command                  | Description                | Modes |\n| ------------------------ | -------------------------- | ----- |\n| `/craft:test`            | Unified test runner        | ‚úì    |\n| `/craft:test:gen`        | Generate test suites       | ----- |\n| `/craft:test:template`   | Manage test templates      | ----- |\n\n### Architecture Commands (4)\n\n| Command               | Description           | Modes |\n| --------------------- | --------------------- | ----- |\n| `/craft:arch:analyze` | Architecture analysis | ‚úì    |\n| `/craft:arch:plan`    | Design architecture   | ----- |\n| `/craft:arch:review`  | Review changes        | ----- |\n| `/craft:arch:diagram` | Generate diagrams     | ----- |\n\n### Planning Commands (3)\n\n| Command               | Description              |\n| --------------------- | ------------------------ |\n| `/craft:plan:feature` | Plan features with tasks |\n| `/craft:plan:sprint`  | Sprint planning          |\n| `/craft:plan:roadmap` | Generate roadmaps        |\n\n### Documentation Commands (13) - CONSOLIDATED in v1.11.0\n\n#### Super Commands (3) - Smart defaults, do everything useful\n\n| Command              | Description                                                                 |\n| -------------------- | --------------------------------------------------------------------------- |\n| `/craft:docs:update` | **Smart-Full**: Detect ‚Üí Generate all needed ‚Üí Check ‚Üí Changelog            |\n| `/craft:docs:sync`   | **Detection**: Classify changes, report stale docs, recommend actions       |\n| `/craft:docs:check`  | **Validation**: Links + stale + nav + auto-fix (Version C: full-by-default) |\n\n```bash\n# Just run it - figures out what's needed\n/craft:docs:update                    # Smart detection ‚Üí full execution\n/craft:docs:update \"sessions\"         # Feature-specific full cycle\n/craft:docs:sync                      # Quick: \"3 stale, guide recommended\"\n/craft:docs:check                     # Full check cycle, auto-fixes issues\n/craft:docs:check --report-only       # CI-safe mode (no modifications)\n\n# ADHD-friendly website enhancement (NEW v1.15.0)\n/craft:docs:website                   # Full enhancement (all 3 phases)\n/craft:docs:website --analyze         # Show ADHD score only\n/craft:docs:website --phase 1         # Quick wins: TL;DR, mermaid fixes, time estimates\n/craft:docs:website --phase 2         # Structure: Visual workflows, navigation\n/craft:docs:website --phase 3         # Polish: Mobile responsive, interactions\n/craft:docs:website --dry-run         # Preview changes without writing\n```\n\n#### Specialized Commands (9)\n\n| Command                  | Description                                                                       |\n| ------------------------ | --------------------------------------------------------------------------------- |\n| `/craft:docs:api`        | OpenAPI/Swagger documentation                                                     |\n| `/craft:docs:changelog`  | Auto-update CHANGELOG                                                             |\n| `/craft:docs:site`       | Website-focused updates with optional deploy                                      |\n| `/craft:docs:website`    | **NEW v1.15.0** ADHD-friendly website enhancement (scoring, TL;DR, mermaid fixes) |\n| `/craft:docs:mermaid`    | Mermaid diagram templates (6 types)                                               |\n| `/craft:docs:nav-update` | Update mkdocs.yml navigation                                                      |\n| `/craft:docs:prompt`     | Generate reusable maintenance prompts                                             |\n| `/craft:docs:demo`       | Terminal recorder for GIF demos (asciinema/VHS)                                   |\n| `/craft:docs:guide`      | **NEW** Feature guide + demo + refcard generator                                  |\n\n#### Internal (1)\n\n| Command                 | Description                                 |\n| ----------------------- | ------------------------------------------- |\n| `/craft:docs:claude-md` | Update CLAUDE.md (called by other commands) |\n\n### Site Commands (12) - ENHANCED in v1.9.0\n\n| Command                   | Description                                                              |\n| ------------------------- | ------------------------------------------------------------------------ |\n| `/craft:site:create`      | Full documentation site wizard with 8 design presets                     |\n| `/craft:site:nav`         | **NEW v1.9.0** Navigation reorganization (ADHD-friendly, max 7 sections) |\n| `/craft:site:audit`       | **NEW v1.9.0** Content inventory & audit (outdated, duplicates, gaps)    |\n| `/craft:site:consolidate` | **NEW v1.9.0** Merge duplicate/overlapping documentation files           |\n| `/craft:site:update`      | Update site content from code changes                                    |\n| `/craft:site:status`      | Dashboard and health check                                               |\n| `/craft:site:theme`       | Quick theme changes (colors, presets, fonts)                             |\n| `/craft:site:add`         | Add new documentation pages                                              |\n| `/craft:site:build`       | Build site                                                               |\n| `/craft:site:preview`     | Preview locally                                                          |\n| `/craft:site:deploy`      | Deploy to GitHub Pages                                                   |\n| `/craft:site:init`        | Basic initialization (use `create` for full wizard)                      |\n\n### Git Commands (5 + 4 guides)\n\n| Command               | Description                                            |\n| --------------------- | ------------------------------------------------------ |\n| `/craft:git:branch`   | Branch management                                      |\n| `/craft:git:sync`     | Smart git sync                                         |\n| `/craft:git:clean`    | Clean merged branches                                  |\n| `/craft:git:recap`    | Activity summary                                       |\n| `/craft:git:worktree` | **NEW v1.8.0** Parallel development with git worktrees |\n\n**Git Guides:** refcard, undo-guide, safety-rails, learning-guide\n\n### CI Commands (3)\n\n| Command              | Description                                                       |\n| -------------------- | ----------------------------------------------------------------- |\n| `/craft:ci:detect`   | Smart detection of project type, build tools, and CI requirements |\n| `/craft:ci:generate` | Generate GitHub Actions workflow from detection                   |\n| `/craft:ci:validate` | Validate existing CI workflow against project configuration       |\n\n### Distribution Commands (2)\n\n| Command                    | Description                       |\n| -------------------------- | --------------------------------- |\n| `/craft:dist:homebrew`     | Generate/update Homebrew formula  |\n| `/craft:dist:curl-install` | Create curl-based install scripts |\n\n### Discovery\n\n| Command      | Description           |\n| ------------ | --------------------- |\n| `/craft:hub` | Command discovery hub |\n\n## Skills (17)\n\n| Skill                           | Category      | Triggers                                     |\n| ------------------------------- | ------------- | -------------------------------------------- |\n| `backend-designer`              | Design        | API, database, auth                          |\n| `frontend-designer`             | Design        | UI/UX, components                            |\n| `devops-helper`                 | Design        | CI/CD, deployment                            |\n| `test-strategist`               | Testing       | Test strategy                                |\n| `cli-test-strategist`           | Testing       | CLI testing                                  |\n| `system-architect`              | Architecture  | System design                                |\n| `project-planner`               | Planning      | Feature planning                             |\n| `mode-controller`               | Modes         | Mode behavior                                |\n| `task-analyzer`                 | Orchestration | Task routing                                 |\n| `changelog-automation`          | Documentation | Changelog patterns                           |\n| `architecture-decision-records` | Documentation | ADR generation                               |\n| `openapi-spec-generation`       | Documentation | OpenAPI specs                                |\n| `mermaid-linter`                | Documentation | Mermaid diagram validation                   |\n| `project-detector`              | CI            | **NEW v1.10.0** Smart project type detection |\n| `distribution-strategist`       | Distribution  | Release channels                             |\n| `homebrew-formula-expert`       | Distribution  | Homebrew formulas                            |\n| `worktree-expert`               | Git           | Git worktree workflows                       |\n\n## Agents (7)\n\n| Agent               | Purpose                                                            |\n| ------------------- | ------------------------------------------------------------------ |\n| `orchestrator`      | Smart delegation to skills                                         |\n| `orchestrator-v2`   | **ENHANCED** Mode-aware execution, context tracking, timeline view |\n| `docs-architect`    | Long-form technical documentation                                  |\n| `tutorial-engineer` | Step-by-step tutorials                                             |\n| `api-documenter`    | OpenAPI/Swagger documentation                                      |\n| `reference-builder` | Technical reference guides                                         |\n| `mermaid-expert`    | Mermaid diagram generation                                         |\n\n## Workflows\n\n### Daily Development\n\n```\n/craft:check ‚Üí /craft:test unit ‚Üí /craft:git:sync\n```\n\n### Release Preparation\n\n```\n/craft:check --for release\n# OR\n/craft:code:deps-audit ‚Üí /craft:test release ‚Üí /craft:code:release\n```\n\n### Feature Development\n\n```\n/craft:do \"add feature name\"\n# Routes to: arch:plan ‚Üí code:test-gen ‚Üí git:branch\n```\n\n### Documentation Workflow (v1.11.0 - Consolidated)\n\n```bash\n# THE ONE COMMAND - detects what's needed, does it all\n/craft:docs:update                    # Smart detection ‚Üí full execution\n\n# Feature-specific documentation\n/craft:docs:update \"auth\"             # Full cycle for auth feature\n\n# Check documentation health\n/craft:docs:check                     # Full: links + stale + nav + auto-fix\n/craft:docs:check --report-only       # CI mode (no changes)\n\n# Quick status check\n/craft:docs:sync                      # \"3 stale, guide recommended (score: 7)\"\n\n# Deploy website\n/craft:docs:site --deploy\n```\n\n### Site Workflow\n\n```\n# Create new documentation site with design preset\n/craft:site:create --preset adhd-focus\n\n# Change theme quickly\n/craft:site:theme --preset adhd-calm\n/craft:site:theme --primary \"#1a73e8\"\n\n# Add new pages\n/craft:site:add guide \"Getting Started\"\n\n# Update content from code changes\n/craft:site:update\n\n# Check site health\n/craft:site:status\n\n# Build and deploy\n/craft:site:build ‚Üí /craft:site:deploy\n```\n\n## Version\n\n- **Version:** 2.14.0\n- **Author:** DT (Data-Wise)\n- **License:** MIT\n\n## Development\n\n**For plugin development and contributions:**\n\n- üìñ **[Architecture Guide](docs/architecture.md)** - How Craft works internally\n- üìñ **[Commands Reference](docs/commands.md)** - All 86 commands documented\n- üìñ **[Skills & Agents](docs/guide/skills-agents.md)** - 25 skills, 8 agents\n- Development commands (testing, validation, documentation)\n- Architecture patterns and plugin structure\n- CI/CD workflows and quality standards\n\nSee the [documentation site](https://data-wise.github.io/craft/) for comprehensive guides.\n\n## Changelog\n\n### [1.11.0] - 2025-12-30\n\n#### Changed\n\n- **Documentation Commands Consolidation** (16‚Üí12 commands):\n  - **Super Commands (3)**: `update`, `sync`, `check` - smart defaults, do everything useful\n  - **Specialized Commands (8)**: `api`, `changelog`, `site`, `mermaid`, `nav-update`, `prompt`, `demo`, `guide`\n  - **Internal (1)**: `claude-md`\n- **`update`**: Smart-Full default - detect ‚Üí generate all needed ‚Üí check ‚Üí changelog\n- **`sync`**: Merged `analyze` logic - detection + classification + stale report\n- **`check`**: Renamed from `validate`, Version C full-by-default (links + stale + nav + auto-fix)\n\n#### Added\n\n- `/craft:docs:demo` - Terminal recorder for GIF demos (asciinema default, VHS optional)\n- `/craft:docs:guide` - Feature guide + demo + refcard generator\n\n#### Removed\n\n- `/craft:docs:validate` ‚Üí renamed to `/craft:docs:check`\n- `/craft:docs:done` ‚Üí merged into `sync` (default is quick)\n- `/craft:docs:generate` ‚Üí merged into `update`\n- `/craft:docs:feature` ‚Üí use `update \"name\"` instead\n- `/craft:docs:analyze` ‚Üí merged into `sync`\n\n#### Philosophy\n\n> \"Just run the command. It figures out what's needed, then does it.\"\n\n- Total: 68 commands, 17 skills, 7 agents\n\n### [1.10.0] - 2025-12-28\n\n#### Added\n\n- **CI Toolkit** (3 commands):\n  - `/craft:ci:detect` - Smart detection of project type, build tools, and CI requirements\n  - `/craft:ci:generate` - Generate GitHub Actions workflow from detection (Python, Node, R, Rust, Go templates)\n  - `/craft:ci:validate` - Validate existing CI workflow against project configuration\n- **Project Detector Skill**:\n  - Core detection logic for Python (uv/poetry/pip), Node (npm/pnpm/yarn), R, Rust, Go, Claude plugins\n  - Detects test frameworks (pytest, jest, vitest, testthat, cargo test)\n  - Identifies linting configs (ruff, eslint, lintr, clippy)\n  - Recommends appropriate CI templates based on project type\n- Total: 67 commands, 17 skills, 7 agents\n\n### [1.9.0] - 2025-12-28\n\n#### Added\n\n- **Site Navigation Command**:\n  - `/craft:site:nav` - ADHD-friendly navigation reorganization\n  - Interactive mode selection menu (analyze, adhd, apply, preview)\n  - Enforces max 7 top-level sections\n  - Generates reorganization proposals\n- **Site Audit Command**:\n  - `/craft:site:audit` - Content inventory & quality audit\n  - Modes: full, outdated, duplicates, gaps\n  - Generates AUDIT-CONTENT-INVENTORY.md\n  - Detects version mismatches, duplicate files, missing docs\n- **Site Consolidate Command**:\n  - `/craft:site:consolidate` - Merge duplicate documentation files\n  - Auto-detect duplicates or merge specific files\n  - Preview mode, safety backups, link updates\n  - Archive option instead of delete\n- **Docs Prompt Command**:\n  - `/craft:docs:prompt` - Generate reusable maintenance prompts\n  - Types: full, reorganize, audit, edit\n  - Pre-filled with project context\n  - ADHD-friendly design principles included\n- **Sub-command UX Pattern**:\n  - Standard menu pattern for commands with modes\n  - Argument bypass for power users\n  - Keyboard: ‚Üë‚Üì Navigate, ‚èé Select, \"cancel\" to exit\n  - Consistent footer with tips and related commands\n- Total: 63 commands, 16 skills, 7 agents\n\n### [1.8.0] - 2025-12-28\n\n#### Added\n\n- **Git Worktrees**: `/craft:git:worktree` for parallel development\n- **Mermaid Diagrams**: `/craft:docs:mermaid` with 6 diagram templates\n- **New Skills**: `mermaid-linter`, `worktree-expert`\n- Total: 60 commands, 16 skills, 7 agents\n\n### [1.7.0] - 2025-12-27\n\n#### Added\n\n- **Site Commands Redesign** (5 new commands):\n  - `/craft:site:create` - Full documentation site wizard with design presets\n  - `/craft:site:update` - Smart content sync from code changes\n  - `/craft:site:status` - Site dashboard and health check\n  - `/craft:site:theme` - Quick theme changes (colors, presets, fonts)\n  - `/craft:site:add` - Add new documentation pages with templates\n- **8 Design Presets**:\n  - Standard: `data-wise`, `minimal`, `open-source`, `corporate`\n  - ADHD-Friendly: `adhd-focus`, `adhd-calm`, `adhd-dark`, `adhd-light`\n- **ADHD-Friendly Features**:\n  - Reduced animations, larger click targets\n  - Calm color palettes, clear hierarchy\n  - Warm backgrounds (no harsh white/black)\n- **Design System**: Templates, presets, color palettes\n- **Preset Gallery**: Visual reference for all 8 presets\n- Total: 61 commands, 15 skills, 7 agents\n\n### [1.6.0] - 2025-12-27\n\n#### Added\n\n- **Docs Workflow Commands** (4 new commands):\n  - `/craft:docs:update [full]` - Smart universal documentation updater\n  - `/craft:docs:feature [name]` - Comprehensive feature documentation\n  - `/craft:docs:done [summary]` - End-of-session doc updates\n  - `/craft:docs:site [--deploy]` - Website-focused updates with deploy\n- **Documentation Workflow Section** in README\n- Total: 58 commands, 15 skills, 7 agents\n\n### [1.5.0] - 2025-12-27\n\n#### Added\n\n- **Distribution Commands** (2 new commands):\n  - `/craft:dist:homebrew` - Generate/update Homebrew formulas\n  - `/craft:dist:curl-install` - Create curl-based installation scripts\n- **Distribution Skills** (2 new skills):\n  - `distribution-strategist` - Recommend optimal distribution channels\n  - `homebrew-formula-expert` - Homebrew formula best practices\n- Total: 54 commands, 15 skills, 7 agents\n\n### [1.4.0] - 2025-12-27\n\n#### Enhanced\n\n- **Orchestrator v2.1** with major improvements:\n  - Mode-aware execution (default, debug, optimize, release)\n  - Improved context tracking with token estimation heuristics\n  - Timeline view for visual execution progress\n  - Session persistence with auto-save and resume\n  - Per-agent context budgets (~15% each)\n  - Smart summarization for large agent responses\n  - New commands: `timeline`, `budget`, `mode`, `continue`, `save`, `history`, `new`\n- Total: 51 commands, 12 skills, 7 agents\n\n### [1.3.0] - 2025-12-26\n\n#### Added\n\n- 5 documentation agents (ported from documentation-generation plugin)\n  - `docs-architect` - Long-form technical documentation\n  - `tutorial-engineer` - Step-by-step tutorials\n  - `api-documenter` - OpenAPI/Swagger documentation\n  - `reference-builder` - Technical reference guides\n  - `mermaid-expert` - Mermaid diagram generation\n- 3 documentation skills\n  - `changelog-automation` - Changelog patterns\n  - `architecture-decision-records` - ADR generation\n  - `openapi-spec-generation` - OpenAPI specs\n- 4 new commands\n  - `/craft:docs:generate` - Full documentation generation\n  - `/craft:docs:api` - OpenAPI/Swagger documentation\n  - `/craft:test:cli-gen` - Generate CLI test suites\n  - `/craft:test:cli-run` - Run CLI test suites\n- Total: 50 commands, 11 skills, 6 agents\n\n### [1.2.0] - 2025-12-26\n\n#### Added\n\n- Mode system (default, debug, optimize, release)\n- 3 smart commands (do, check, help)\n- 2 new skills (mode-controller, task-analyzer)\n- Mode support for lint, test:run, arch:analyze, coverage\n- Total: 46 commands, 8 skills, 1 agent\n\n### [1.1.0] - 2025-12-26\n\n#### Added\n\n- 6 new code commands (lint, coverage, deps-check, deps-audit, ci-local, ci-fix)\n- 4 new test commands (run, watch, coverage, debug)\n- 4 new architecture commands (analyze, plan, review, diagram)\n- 3 new planning commands (feature, sprint, roadmap)\n- 3 new skills (test-strategist, system-architect, project-planner)\n- Total: 42 commands, 6 skills, 1 agent\n\n### [1.0.0] - 2025-12-26\n\n#### Added\n\n- Initial release with 26 commands\n- 6 code, 6 site, 8 git, 5 docs commands\n- 3 skills (backend, frontend, devops)\n- 1 orchestrator agent\n- Hub command for discovery\n"
      },
      "plugins": [
        {
          "name": "craft",
          "source": {
            "source": "github",
            "repo": "Data-Wise/craft"
          },
          "description": "Full-stack developer toolkit for Claude Code with 108 commands, 8 agents, and 25 skills",
          "version": "2.23.0",
          "author": {
            "name": "Data-Wise",
            "email": "dt@stat-wise.com"
          },
          "homepage": "https://data-wise.github.io/craft/",
          "repository": "https://github.com/Data-Wise/craft",
          "license": "MIT",
          "category": "development",
          "keywords": [
            "workflow",
            "automation",
            "git",
            "testing",
            "documentation",
            "ci-cd",
            "release",
            "architecture"
          ],
          "categories": [
            "architecture",
            "automation",
            "ci-cd",
            "development",
            "documentation",
            "git",
            "release",
            "testing",
            "workflow"
          ],
          "install_commands": [
            "/plugin marketplace add Data-Wise/craft",
            "/plugin install craft@data-wise-craft"
          ]
        }
      ]
    },
    {
      "name": "himalaya-mcp",
      "version": null,
      "description": "Privacy-first email MCP server and Claude Code plugin wrapping himalaya CLI",
      "repo_full_name": "Data-Wise/himalaya-mcp",
      "repo_url": "https://github.com/Data-Wise/himalaya-mcp",
      "repo_description": "Privacy-first email MCP server + Claude Code plugin wrapping himalaya CLI",
      "signals": {
        "stars": 0,
        "forks": 0,
        "pushed_at": "2026-02-17T18:32:08Z"
      },
      "files": {
        ".claude-plugin/marketplace.json": "{\n  \"name\": \"himalaya-mcp\",\n  \"owner\": {\n    \"name\": \"Data-Wise\"\n  },\n  \"metadata\": {\n    \"description\": \"Privacy-first email MCP server and Claude Code plugin wrapping himalaya CLI\",\n    \"version\": \"1.3.0\"\n  },\n  \"plugins\": [{\n    \"name\": \"email\",\n    \"source\": \"./himalaya-mcp-plugin\",\n    \"description\": \"Privacy-first email MCP server wrapping himalaya CLI\",\n    \"category\": \"productivity\",\n    \"tags\": [\"email\", \"mcp\", \"himalaya\", \"privacy\"]\n  }]\n}\n",
        "README.md": "# himalaya-mcp\n\nPrivacy-first email for Claude -- MCP server and Claude Code plugin (`email`) wrapping the [himalaya](https://github.com/pimalaya/himalaya) CLI.\n\n## Features\n\n- **19 MCP tools**: list, search, read, flag, move, compose, draft reply, send (with safety gate), export, action items, clipboard, folders, attachments, calendar\n- **4 MCP prompts**: triage inbox, summarize email, daily digest, draft reply\n- **3 MCP resources**: inbox, message by ID, folders\n- **7 plugin skills**: `/email:inbox`, `/email:triage`, `/email:digest`, `/email:reply`, `/email:compose`, `/email:attachments`, `/email:help`\n- **Multi-account**: per-call account switching via `--account`\n- **Safe subprocess**: uses `execFile` (no shell injection)\n- **Two-phase send**: `send_email` returns preview first, requires explicit `confirm=true`\n- **Env-based config**: `HIMALAYA_BINARY`, `HIMALAYA_ACCOUNT`, `HIMALAYA_FOLDER`, `HIMALAYA_TIMEOUT`\n\n## Install\n\n### Homebrew (recommended)\n\n```bash\nbrew tap data-wise/tap\nbrew install himalaya-mcp\n```\n\nInstalls himalaya CLI + Node.js as dependencies, auto-symlinks plugin to `~/.claude/plugins/`.\n\n### Claude Code Plugin (from GitHub)\n\n```bash\nclaude plugin marketplace add Data-Wise/himalaya-mcp\nclaude plugin install email\n```\n\n### Claude Desktop (.mcpb -- one-click install)\n\nDownload `himalaya-mcp-v{version}.mcpb` from [GitHub Releases](https://github.com/Data-Wise/himalaya-mcp/releases) and open it in Claude Desktop. Requires `brew install himalaya` separately.\n\n### Claude Desktop (CLI setup)\n\n```bash\nhimalaya-mcp setup\n```\n\n### Development (from source)\n\n```bash\nnpm install\nnpm run build\nln -s ~/projects/dev-tools/himalaya-mcp ~/.claude/plugins/himalaya-mcp\n```\n\n## Prerequisites\n\n- [himalaya CLI](https://github.com/pimalaya/himalaya) configured with at least one email account in `~/.config/himalaya/config.toml`\n- Node.js 22+ (installed automatically by Homebrew)\n\n## Testing\n\n```bash\nnpm test              # 314 tests across 15 test files (vitest)\n```\n\n| Category | Tests | Coverage |\n|----------|-------|----------|\n| Unit (parser, config, clipboard) | 35 | Core parsing, config, template variable guards |\n| Integration (tools, prompts) | 80 | All 19 tools + 4 prompts |\n| Dogfooding | 122 | Realistic Claude usage + .mcpb packaging validation |\n| E2E | 34 | Full MCP server pipeline + .mcpb build pipeline |\n| Setup CLI | 36 | Setup, install/upgrade E2E, doctor command, plugin structure |\n\n## Documentation\n\nFull documentation at **[data-wise.github.io/himalaya-mcp](https://data-wise.github.io/himalaya-mcp/)**\n\n- [Installation](https://data-wise.github.io/himalaya-mcp/getting-started/installation/)\n- [Quick Start](https://data-wise.github.io/himalaya-mcp/getting-started/quickstart/)\n- [Tutorials](https://data-wise.github.io/himalaya-mcp/tutorials/)\n- [User Guide](https://data-wise.github.io/himalaya-mcp/guide/guide/)\n- [Command Reference](https://data-wise.github.io/himalaya-mcp/reference/commands/)\n- [Quick Reference Card](https://data-wise.github.io/himalaya-mcp/reference/refcard/)\n- [Architecture](https://data-wise.github.io/himalaya-mcp/reference/architecture/)\n\n## License\n\nMIT\n"
      },
      "plugins": [
        {
          "name": "email",
          "source": "./himalaya-mcp-plugin",
          "description": "Privacy-first email MCP server wrapping himalaya CLI",
          "category": "productivity",
          "tags": [
            "email",
            "mcp",
            "himalaya",
            "privacy"
          ],
          "categories": [
            "email",
            "himalaya",
            "mcp",
            "privacy",
            "productivity"
          ],
          "install_commands": [
            "/plugin marketplace add Data-Wise/himalaya-mcp",
            "/plugin install email@himalaya-mcp"
          ]
        }
      ]
    }
  ]
}