{
  "author": {
    "id": "ehartye",
    "display_name": "Eric Hartye",
    "avatar_url": "https://avatars.githubusercontent.com/u/1032978?u=883a29b612ddb198149f6a9452deb7b6fb02319f&v=4"
  },
  "marketplaces": [
    {
      "name": "hartye-plugins",
      "version": null,
      "description": "Salesforce browser automation via SF CLI - 45+ tools for session management, Lightning navigation, form filling, record operations, and Setup automation",
      "repo_full_name": "ehartye/hartye-claude-plugins",
      "repo_url": "https://github.com/ehartye/hartye-claude-plugins",
      "repo_description": "Claude Code plugin marketplace - Salesforce development and automation tools",
      "signals": {
        "stars": 0,
        "forks": 0,
        "pushed_at": "2026-02-17T05:08:39Z"
      },
      "files": {
        ".claude-plugin/marketplace.json": "{\n  \"name\": \"hartye-plugins\",\n  \"owner\": {\n    \"name\": \"ehartye\",\n    \"email\": \"eric@hartye.com\"\n  },\n  \"plugins\": [\n    {\n      \"name\": \"sf-browser-control\",\n      \"source\": {\n        \"source\": \"github\",\n        \"repo\": \"ehartye/sf-browser-control\"\n      },\n      \"description\": \"Salesforce browser automation via SF CLI - 45+ tools for session management, Lightning navigation, form filling, record operations, and Setup automation\",\n      \"version\": \"1.0.0\",\n      \"author\": {\n        \"name\": \"ehartye\"\n      },\n      \"repository\": \"https://github.com/ehartye/sf-browser-control\",\n      \"license\": \"MIT\"\n    },\n    {\n      \"name\": \"hartye-superpowers\",\n      \"source\": {\n        \"source\": \"github\",\n        \"repo\": \"ehartye/hartye-superpowers\"\n      },\n      \"description\": \"An agentic skills framework for AI coding assistants - composable workflows for planning, TDD, debugging, and code review\",\n      \"version\": \"1.0.0\",\n      \"author\": {\n        \"name\": \"ehartye\"\n      },\n      \"repository\": \"https://github.com/ehartye/hartye-superpowers\",\n      \"license\": \"MIT\"\n    }\n  ]\n}\n",
        "README.md": "# Hartye Claude Plugins\n\nA collection of Claude Code plugins for Salesforce development and automation.\n\n## Installation\n\n```bash\n# Add the marketplace\n/plugin marketplace add ehartye/hartye-claude-plugins\n\n# Install plugins\n/plugin install sf-browser-control@hartye-plugins\n/plugin install hartye-superpowers@hartye-plugins\n```\n\n## Available Plugins\n\n| Plugin | Description |\n|--------|-------------|\n| [sf-browser-control](https://github.com/ehartye/sf-browser-control) | Salesforce browser automation via SF CLI - 45+ tools for session management, Lightning navigation, form filling, and Setup automation |\n| [hartye-superpowers](https://github.com/ehartye/hartye-superpowers) | An agentic skills framework for AI coding assistants - composable workflows for planning, TDD, debugging, and code review |\n\n## License\n\nMIT\n"
      },
      "plugins": [
        {
          "name": "sf-browser-control",
          "source": {
            "source": "github",
            "repo": "ehartye/sf-browser-control"
          },
          "description": "Salesforce browser automation via SF CLI - 45+ tools for session management, Lightning navigation, form filling, record operations, and Setup automation",
          "version": "1.0.0",
          "author": {
            "name": "ehartye"
          },
          "repository": "https://github.com/ehartye/sf-browser-control",
          "license": "MIT",
          "categories": [],
          "install_commands": [
            "/plugin marketplace add ehartye/hartye-claude-plugins",
            "/plugin install sf-browser-control@hartye-plugins"
          ]
        },
        {
          "name": "hartye-superpowers",
          "source": {
            "source": "github",
            "repo": "ehartye/hartye-superpowers"
          },
          "description": "An agentic skills framework for AI coding assistants - composable workflows for planning, TDD, debugging, and code review",
          "version": "1.0.0",
          "author": {
            "name": "ehartye"
          },
          "repository": "https://github.com/ehartye/hartye-superpowers",
          "license": "MIT",
          "categories": [],
          "install_commands": [
            "/plugin marketplace add ehartye/hartye-claude-plugins",
            "/plugin install hartye-superpowers@hartye-plugins"
          ]
        }
      ]
    }
  ]
}