{
  "author": {
    "id": "eumemic",
    "display_name": "eumemic",
    "avatar_url": "https://avatars.githubusercontent.com/u/94939491?u=1f95365680d7ca7f62ae07485ead72c4e22049c5&v=4"
  },
  "marketplaces": [
    {
      "name": "eumemic",
      "version": null,
      "description": "Claude Code plugins by eumemic",
      "repo_full_name": "eumemic/claude-plugins",
      "repo_url": "https://github.com/eumemic/claude-plugins",
      "repo_description": "Claude Code plugins by eumemic",
      "signals": {
        "stars": 0,
        "forks": 0,
        "pushed_at": "2026-01-13T22:33:29Z"
      },
      "files": {
        ".claude-plugin/marketplace.json": "{\n  \"$schema\": \"https://anthropic.com/claude-code/marketplace.schema.json\",\n  \"name\": \"eumemic\",\n  \"owner\": {\n    \"name\": \"eumemic\"\n  },\n  \"metadata\": {\n    \"description\": \"Claude Code plugins by eumemic\"\n  },\n  \"plugins\": [\n    {\n      \"name\": \"ralph\",\n      \"source\": {\n        \"source\": \"github\",\n        \"repo\": \"eumemic/ralph\"\n      },\n      \"description\": \"Autonomous AI-assisted development methodology that keeps specs and code in sync through intelligent iteration loops\",\n      \"version\": \"1.0.10\",\n      \"license\": \"MIT\",\n      \"keywords\": [\"specs\", \"autonomous\", \"planning\", \"implementation\", \"sync\"],\n      \"category\": \"development\"\n    },\n    {\n      \"name\": \"website-cloner\",\n      \"source\": {\n        \"source\": \"github\",\n        \"repo\": \"eumemic/website-cloner\"\n      },\n      \"description\": \"Clone websites by reverse-engineering them into specs using AI-powered browser exploration\",\n      \"version\": \"1.0.0\",\n      \"license\": \"MIT\",\n      \"keywords\": [\"clone\", \"reverse-engineer\", \"specs\", \"browser\", \"discovery\"],\n      \"category\": \"development\"\n    }\n  ]\n}\n",
        "README.md": "# eumemic Claude Code Plugins\n\nA curated collection of Claude Code plugins by eumemic.\n\n## Installation\n\nAdd this marketplace to Claude Code:\n\n```\n/plugin marketplace add eumemic/claude-plugins\n```\n\nThen install plugins:\n\n```\n/plugin install ralph@eumemic\n/plugin install website-cloner@eumemic\n```\n\n## Available Plugins\n\n| Plugin | Description |\n|--------|-------------|\n| [ralph](https://github.com/eumemic/ralph) | Autonomous AI-assisted development methodology that keeps specs and code in sync through intelligent iteration loops |\n| [website-cloner](https://github.com/eumemic/website-cloner) | Clone websites by reverse-engineering them into specs using AI-powered browser exploration |\n\n## License\n\nMIT\n"
      },
      "plugins": [
        {
          "name": "ralph",
          "source": {
            "source": "github",
            "repo": "eumemic/ralph"
          },
          "description": "Autonomous AI-assisted development methodology that keeps specs and code in sync through intelligent iteration loops",
          "version": "1.0.10",
          "license": "MIT",
          "keywords": [
            "specs",
            "autonomous",
            "planning",
            "implementation",
            "sync"
          ],
          "category": "development",
          "categories": [
            "autonomous",
            "development",
            "implementation",
            "planning",
            "specs",
            "sync"
          ],
          "install_commands": [
            "/plugin marketplace add eumemic/claude-plugins",
            "/plugin install ralph@eumemic"
          ]
        },
        {
          "name": "website-cloner",
          "source": {
            "source": "github",
            "repo": "eumemic/website-cloner"
          },
          "description": "Clone websites by reverse-engineering them into specs using AI-powered browser exploration",
          "version": "1.0.0",
          "license": "MIT",
          "keywords": [
            "clone",
            "reverse-engineer",
            "specs",
            "browser",
            "discovery"
          ],
          "category": "development",
          "categories": [
            "browser",
            "clone",
            "development",
            "discovery",
            "reverse-engineer",
            "specs"
          ],
          "install_commands": [
            "/plugin marketplace add eumemic/claude-plugins",
            "/plugin install website-cloner@eumemic"
          ]
        }
      ]
    }
  ]
}