{
  "author": {
    "id": "hanzei",
    "display_name": "Ben Schumacher",
    "avatar_url": "https://avatars.githubusercontent.com/u/16541325?v=4"
  },
  "marketplaces": [
    {
      "name": "mattermost-plugin-development",
      "version": null,
      "description": "Claude Code plugins for developing Mattermost plugins",
      "repo_full_name": "hanzei/mattermost-plugin-development",
      "repo_url": "https://github.com/hanzei/mattermost-plugin-development",
      "repo_description": "A Claude Code plugin to help with Plugin development at Mattermost",
      "signals": {
        "stars": 0,
        "forks": 0,
        "pushed_at": "2026-01-21T11:32:44Z"
      },
      "files": {
        ".claude-plugin/marketplace.json": "{\n  \"name\": \"mattermost-plugin-development\",\n  \"owner\": {\n    \"name\": \"hanzei\"\n  },\n  \"metadata\": {\n    \"description\": \"Claude Code plugins for developing Mattermost plugins\",\n    \"version\": \"0.1.0\"\n  },\n  \"plugins\": [\n    {\n      \"name\": \"mattermost-plugin-development\",\n      \"source\": \"./\",\n      \"description\": \"Claude Code plugins for developing Mattermost plugins\",\n      \"version\": \"0.1.0\",\n      \"author\": {\n        \"name\": \"hanzei\"\n      },\n      \"repository\": \"https://github.com/hanzei/mattermost-plugin-development\",\n      \"license\": \"MIT\",\n      \"keywords\": [\"mattermost\", \"plugin\", \"development\"],\n      \"category\": \"development\"\n    }\n  ]\n}\n",
        ".claude-plugin/plugin.json": "{\n  \"name\": \"mattermost-plugin-development\",\n  \"version\": \"0.1.0\",\n  \"description\": \"Claude Code plugins for developing Mattermost plugins\",\n  \"author\": {\n    \"name\": \"hanzei\"\n  }\n}\n",
        "README.md": "# mattermost-plugin-development\n\nA Claude Code plugin for developing Mattermost plugins.\n\n## Installation\n\nAdd the marketplace and install the plugin:\n\n```\n/plugin marketplace add hanzei/mattermost-plugin-development\n/plugin install mattermost-plugin-development@mattermost-plugin-development\n```\n\nOr clone and use directly:\n\n```\ngit clone https://github.com/hanzei/mattermost-plugin-development.git\nclaude --plugin-dir ./mattermost-plugin-development\n```\n\n## Skills\n\n### update-from-starter-template\n\nSyncs a Mattermost plugin repository with common files from [mattermost-plugin-starter-template](https://github.com/mattermost/mattermost-plugin-starter-template) and fixes all linter issues.\n\n**Usage:**\n\n```\n/mattermost-plugin-development:update-from-starter-template\n```\n\nThis skill will:\n\n1. Prepare the repository by creating a new branch\n2. Update common build and config files from the starter template while preserving plugin-specific customizations\n3. Fix linter issues using `gofumpt` and manual fixes\n4. Verify tests pass and create a commit with PR\n"
      },
      "plugins": [
        {
          "name": "mattermost-plugin-development",
          "source": "./",
          "description": "Claude Code plugins for developing Mattermost plugins",
          "version": "0.1.0",
          "author": {
            "name": "hanzei"
          },
          "repository": "https://github.com/hanzei/mattermost-plugin-development",
          "license": "MIT",
          "keywords": [
            "mattermost",
            "plugin",
            "development"
          ],
          "category": "development",
          "categories": [
            "development",
            "mattermost",
            "plugin"
          ],
          "install_commands": [
            "/plugin marketplace add hanzei/mattermost-plugin-development",
            "/plugin install mattermost-plugin-development@mattermost-plugin-development"
          ]
        }
      ]
    }
  ]
}