{
  "author": {
    "id": "juanre",
    "display_name": "Juan Reyero",
    "avatar_url": "https://avatars.githubusercontent.com/u/132608?v=4"
  },
  "marketplaces": [
    {
      "name": "juanre-ai-tools",
      "version": null,
      "description": "Professional Python tools for AI development: database management, LLM integration, document search, and scientific computing",
      "repo_full_name": "juanre/ai-tools",
      "repo_url": "https://github.com/juanre/ai-tools",
      "repo_description": "Claude code skills marketplace for my open source AI-related packages (pgdbm, llmring, llmemory).",
      "signals": {
        "stars": 1,
        "forks": 1,
        "pushed_at": "2026-01-10T12:52:05Z"
      },
      "files": {
        ".claude-plugin/marketplace.json": "{\n  \"name\": \"juanre-ai-tools\",\n  \"owner\": {\n    \"name\": \"Juan Reyero\",\n    \"email\": \"[email protected]\",\n    \"url\": \"https://github.com/juanre\"\n  },\n  \"metadata\": {\n    \"description\": \"Professional Python tools for AI development: database management, LLM integration, document search, and scientific computing\"\n  },\n  \"plugins\": [\n    {\n      \"name\": \"pgdbm\",\n      \"source\": {\n        \"source\": \"github\",\n        \"repo\": \"juanre/pgdbm\"\n      },\n      \"description\": \"Complete pgdbm skill set: PostgreSQL database management with async operations, migrations, and connection pooling. Use when building FastAPI apps, microservices, or multi-tenant SaaS with PostgreSQL.\",\n      \"version\": \"1.0.0\",\n      \"category\": \"database\",\n      \"tags\": [\"pgdbm\", \"postgresql\", \"database\", \"async\", \"migrations\", \"bundle\"]\n    },\n    {\n      \"name\": \"pgdbm-choosing-pattern\",\n      \"source\": {\n        \"source\": \"github\",\n        \"repo\": \"juanre/pgdbm\"\n      },\n      \"description\": \"Decision guide for choosing the right pgdbm pattern (standalone, dual-mode, or shared pool) based on deployment context.\",\n      \"version\": \"1.0.0\",\n      \"category\": \"database\",\n      \"tags\": [\"pgdbm\", \"postgresql\", \"architecture\", \"patterns\"]\n    },\n    {\n      \"name\": \"pgdbm-shared-pool\",\n      \"source\": {\n        \"source\": \"github\",\n        \"repo\": \"juanre/pgdbm\"\n      },\n      \"description\": \"Production pattern for pgdbm using one shared connection pool across multiple schemas or microservices. Critical for FastAPI apps and multi-service architectures.\",\n      \"version\": \"1.0.0\",\n      \"category\": \"database\",\n      \"tags\": [\"pgdbm\", \"postgresql\", \"connection-pool\", \"production\", \"fastapi\"]\n    },\n    {\n      \"name\": \"pgdbm-dual-mode\",\n      \"source\": {\n        \"source\": \"github\",\n        \"repo\": \"juanre/pgdbm\"\n      },\n      \"description\": \"Pattern for building reusable PyPI packages with pgdbm that work standalone or embedded. Use when creating database libraries.\",\n      \"version\": \"1.0.0\",\n      \"category\": \"database\",\n      \"tags\": [\"pgdbm\", \"postgresql\", \"library\", \"pypi\", \"reusable\"]\n    },\n    {\n      \"name\": \"pgdbm-standalone\",\n      \"source\": {\n        \"source\": \"github\",\n        \"repo\": \"juanre/pgdbm\"\n      },\n      \"description\": \"Standalone service pattern for simple microservices with their own database. Simplest pgdbm setup.\",\n      \"version\": \"1.0.0\",\n      \"category\": \"database\",\n      \"tags\": [\"pgdbm\", \"postgresql\", \"microservices\", \"standalone\"]\n    },\n    {\n      \"name\": \"pgdbm-testing\",\n      \"source\": {\n        \"source\": \"github\",\n        \"repo\": \"juanre/pgdbm\"\n      },\n      \"description\": \"Testing database code with pgdbm fixtures: test fixtures, test databases, pytest integration. Use when writing database tests.\",\n      \"version\": \"1.0.0\",\n      \"category\": \"database\",\n      \"tags\": [\"pgdbm\", \"postgresql\", \"testing\", \"pytest\", \"fixtures\"]\n    },\n    {\n      \"name\": \"pgdbm-usage\",\n      \"source\": {\n        \"source\": \"github\",\n        \"repo\": \"juanre/pgdbm\"\n      },\n      \"description\": \"Mental model and core pgdbm operations: connecting, querying, transactions, migrations. Start here for understanding pgdbm patterns.\",\n      \"version\": \"1.0.0\",\n      \"category\": \"database\",\n      \"tags\": [\"pgdbm\", \"postgresql\", \"basics\", \"getting-started\"]\n    },\n    {\n      \"name\": \"pgdbm-core-api\",\n      \"source\": {\n        \"source\": \"github\",\n        \"repo\": \"juanre/pgdbm\"\n      },\n      \"description\": \"Complete AsyncDatabaseManager and DatabaseConfig API reference with all methods, parameters, and configuration options.\",\n      \"version\": \"1.0.0\",\n      \"category\": \"database\",\n      \"tags\": [\"pgdbm\", \"postgresql\", \"api\", \"reference\"]\n    },\n    {\n      \"name\": \"pgdbm-migrations-api\",\n      \"source\": {\n        \"source\": \"github\",\n        \"repo\": \"juanre/pgdbm\"\n      },\n      \"description\": \"Complete AsyncMigrationManager API reference with migration file format, checksum validation, and version control.\",\n      \"version\": \"1.0.0\",\n      \"category\": \"database\",\n      \"tags\": [\"pgdbm\", \"postgresql\", \"migrations\", \"api\", \"reference\"]\n    },\n    {\n      \"name\": \"pgdbm-common-mistakes\",\n      \"source\": {\n        \"source\": \"github\",\n        \"repo\": \"juanre/pgdbm\"\n      },\n      \"description\": \"Common pgdbm mistakes and how to avoid them: pool multiplication, schema errors, template syntax violations. Use before implementing.\",\n      \"version\": \"1.0.0\",\n      \"category\": \"database\",\n      \"tags\": [\"pgdbm\", \"postgresql\", \"best-practices\", \"anti-patterns\"]\n    },\n    {\n      \"name\": \"llmemory\",\n      \"source\": {\n        \"source\": \"github\",\n        \"repo\": \"juanre/llmemory\"\n      },\n      \"description\": \"Complete llmemory skill set: SOTA RAG library with hybrid search (vector + BM25), query expansion (heuristic + LLM), reranking, query routing, contextual retrieval, and multi-tenant support. Use when building production RAG systems, semantic search, or document Q&A.\",\n      \"version\": \"1.0.0\",\n      \"category\": \"ai\",\n      \"tags\": [\"llmemory\", \"rag\", \"vector-search\", \"hybrid-search\", \"pgvector\", \"multi-tenant\", \"bundle\"]\n    },\n    {\n      \"name\": \"llmemory-basic-usage\",\n      \"source\": {\n        \"source\": \"github\",\n        \"repo\": \"juanre/llmemory\"\n      },\n      \"description\": \"Getting started with llmemory: installation, initialization, adding documents, search operations, document management. Start here for llmemory basics.\",\n      \"version\": \"1.0.0\",\n      \"category\": \"ai\",\n      \"tags\": [\"llmemory\", \"rag\", \"getting-started\", \"basics\", \"vector-search\"]\n    },\n    {\n      \"name\": \"llmemory-hybrid-search\",\n      \"source\": {\n        \"source\": \"github\",\n        \"repo\": \"juanre/llmemory\"\n      },\n      \"description\": \"Hybrid search combining vector similarity and BM25 full-text search with Reciprocal Rank Fusion (RRF). Alpha tuning, HNSW configuration, search optimization.\",\n      \"version\": \"1.0.0\",\n      \"category\": \"ai\",\n      \"tags\": [\"llmemory\", \"rag\", \"hybrid-search\", \"vector-search\", \"bm25\", \"rrf\"]\n    },\n    {\n      \"name\": \"llmemory-multi-query\",\n      \"source\": {\n        \"source\": \"github\",\n        \"repo\": \"juanre/llmemory\"\n      },\n      \"description\": \"Query expansion with heuristic and LLM-based variants for improved retrieval recall. Multi-query search with RRF fusion across query variants.\",\n      \"version\": \"1.0.0\",\n      \"category\": \"ai\",\n      \"tags\": [\"llmemory\", \"rag\", \"query-expansion\", \"multi-query\", \"recall\"]\n    },\n    {\n      \"name\": \"llmemory-multi-tenant\",\n      \"source\": {\n        \"source\": \"github\",\n        \"repo\": \"juanre/llmemory\"\n      },\n      \"description\": \"Multi-tenant patterns with owner-based isolation for SaaS applications. Security implementation, FastAPI integration, workspace separation.\",\n      \"version\": \"1.0.0\",\n      \"category\": \"ai\",\n      \"tags\": [\"llmemory\", \"multi-tenant\", \"saas\", \"security\", \"isolation\"]\n    },\n    {\n      \"name\": \"llmemory-rag\",\n      \"source\": {\n        \"source\": \"github\",\n        \"repo\": \"juanre/llmemory\"\n      },\n      \"description\": \"Building production RAG systems: document ingestion, hybrid search retrieval, query routing, reranking, prompt augmentation. Complete RAG pipeline patterns.\",\n      \"version\": \"1.0.0\",\n      \"category\": \"ai\",\n      \"tags\": [\"llmemory\", \"rag\", \"retrieval\", \"reranking\", \"production\"]\n    },\n    {\n      \"name\": \"llmring\",\n      \"source\": {\n        \"source\": \"github\",\n        \"repo\": \"juanre/llmring\"\n      },\n      \"description\": \"Complete llmring skill set: unified LLM interface for OpenAI, Anthropic, Google, and Ollama with streaming, tools, structured output, and multi-provider patterns. Use when building LLM applications.\",\n      \"version\": \"1.0.0\",\n      \"category\": \"ai\",\n      \"tags\": [\"llmring\", \"llm\", \"openai\", \"anthropic\", \"google\", \"ollama\", \"bundle\"]\n    },\n    {\n      \"name\": \"llmring-chat\",\n      \"source\": {\n        \"source\": \"github\",\n        \"repo\": \"juanre/llmring\"\n      },\n      \"description\": \"Basic chat completions with llmring: unified interface, message structure, resource management. Start here for llmring basics.\",\n      \"version\": \"1.0.0\",\n      \"category\": \"ai\",\n      \"tags\": [\"llmring\", \"llm\", \"chat\", \"getting-started\", \"basics\"]\n    },\n    {\n      \"name\": \"llmring-streaming\",\n      \"source\": {\n        \"source\": \"github\",\n        \"repo\": \"juanre/llmring\"\n      },\n      \"description\": \"Streaming responses with llmring: async iteration, real-time output, usage tracking. Use when building chat interfaces or displaying incremental responses.\",\n      \"version\": \"1.0.0\",\n      \"category\": \"ai\",\n      \"tags\": [\"llmring\", \"llm\", \"streaming\", \"real-time\", \"async\"]\n    },\n    {\n      \"name\": \"llmring-tools\",\n      \"source\": {\n        \"source\": \"github\",\n        \"repo\": \"juanre/llmring\"\n      },\n      \"description\": \"Function calling and tool use with llmring: tool definitions, execution patterns, multi-turn conversations. Use when building agents or adding function calling.\",\n      \"version\": \"1.0.0\",\n      \"category\": \"ai\",\n      \"tags\": [\"llmring\", \"llm\", \"tools\", \"function-calling\", \"agents\"]\n    },\n    {\n      \"name\": \"llmring-structured\",\n      \"source\": {\n        \"source\": \"github\",\n        \"repo\": \"juanre/llmring\"\n      },\n      \"description\": \"Structured output with JSON schema: type-safe responses, data extraction, validation. Use when extracting structured data from LLMs or enforcing output schemas.\",\n      \"version\": \"1.0.0\",\n      \"category\": \"ai\",\n      \"tags\": [\"llmring\", \"llm\", \"json-schema\", \"structured-output\", \"validation\"]\n    },\n    {\n      \"name\": \"llmring-lockfile\",\n      \"source\": {\n        \"source\": \"github\",\n        \"repo\": \"juanre/llmring\"\n      },\n      \"description\": \"Lockfile configuration with llmring: semantic aliases, environment profiles, fallback models. Use when configuring model aliases or managing dev/staging/prod environments.\",\n      \"version\": \"1.0.0\",\n      \"category\": \"ai\",\n      \"tags\": [\"llmring\", \"llm\", \"configuration\", \"aliases\", \"profiles\"]\n    },\n    {\n      \"name\": \"llmring-providers\",\n      \"source\": {\n        \"source\": \"github\",\n        \"repo\": \"juanre/llmring\"\n      },\n      \"description\": \"Multi-provider patterns with llmring: provider switching, raw SDK access, provider-specific features (caching, logprobs). Use when switching providers or accessing advanced features.\",\n      \"version\": \"1.0.0\",\n      \"category\": \"ai\",\n      \"tags\": [\"llmring\", \"llm\", \"multi-provider\", \"openai\", \"anthropic\", \"google\", \"ollama\"]\n    }\n  ]\n}\n",
        "README.md": "# AI Tools Plugin Marketplace  for Claude Code\n\n**Python tools for AI development by [Juan Reyero](https://github.com/juanre)**\n\nProduction-ready packages for databases, LLM integration, and document search. Each package includes multiple Claude Code skills providing guidance on best practices and patterns.\n\n[![License: MIT](https://img.shields.io/badge/License-MIT-yellow.svg)](https://opensource.org/licenses/MIT)\n\n## Quick Start\n\n```bash\n# Add marketplace\n/plugin marketplace add juanre/ai-tools\n\n# Install all skills for a package\n/plugin install pgdbm@juanre-ai-tools\n/plugin install llmemory@juanre-ai-tools\n/plugin install llmring@juanre-ai-tools\n\n# Or install individual skills\n/plugin install pgdbm-shared-pool@juanre-ai-tools\n/plugin install llmemory-hybrid-search@juanre-ai-tools\n/plugin install llmring-streaming@juanre-ai-tools\n```\n\n## What Are These Skills?\n\nClaude Code skills are **expert guidance systems** that teach Claude how to work with your packages. When you ask Claude for help with databases, LLMs, or document search, these skills automatically activate and provide:\n\n- ‚úÖ Production-ready code examples\n- ‚úÖ Best practices and patterns\n- ‚úÖ Common pitfalls to avoid\n- ‚úÖ Architecture guidance\n- ‚úÖ Testing strategies\n\n**No manual needed** - just ask Claude naturally and the right skills load automatically!\n\n## Available Packages\n\n### üóÑÔ∏è pgdbm - PostgreSQL Database Management\n\nProduction-ready async PostgreSQL with migrations, connection pooling, and schema isolation.\n\n**[Package on GitHub](https://github.com/juanre/pgdbm) | [PyPI](https://pypi.org/project/pgdbm/)**\n\n**Skills included:**\n- `pgdbm` - Complete skill set (all 9 skills)\n- `pgdbm-choosing-pattern` - Decision guide for which pattern to use\n- `pgdbm-shared-pool` - Production pattern with connection pooling ‚≠ê\n- `pgdbm-dual-mode` - Create portable database libraries\n- `pgdbm-standalone` - Standalone service pattern\n- `pgdbm-testing` - Test your database code\n- `pgdbm-usage` - Basic operations and queries\n- `pgdbm-core-api` - Complete API reference\n- `pgdbm-migrations-api` - Migrations API reference\n- `pgdbm-common-mistakes` - Common pitfalls and how to avoid them\n\n**When to use:** Building FastAPI apps, microservices, multi-tenant SaaS, or any production application needing PostgreSQL.\n\n**Key features:**\n- Async operations with asyncpg\n- Automatic migrations with version control\n- Connection pooling for production\n- Schema isolation for multi-module apps\n- Built-in testing utilities\n\n```bash\n# Install all pgdbm skills\n/plugin install pgdbm@juanre-ai-tools\n\n# Or just what you need\n/plugin install pgdbm-shared-pool@juanre-ai-tools\n```\n\n### üîç llmemory - Document Memory with Vector Search\n\nHigh-performance document memory system with hybrid search, multi-query expansion, and reranking.\n\n**[Package on GitHub](https://github.com/juanre/llmemory) | [PyPI](https://pypi.org/project/llmemory/)**\n\n**Skills included:**\n- `llmemory` - Complete skill set (all 5 skills)\n- `llmemory-basic-usage` - Installation and basic operations\n- `llmemory-hybrid-search` - Combining vector + BM25 search ‚≠ê\n- `llmemory-multi-query` - Query expansion for better results\n- `llmemory-multi-tenant` - Owner-based isolation for SaaS\n- `llmemory-rag` - Building complete RAG systems\n\n**When to use:** Building RAG applications, semantic search, document management, or chatbots with knowledge bases.\n\n**Key features:**\n- Hybrid search (vector + BM25 with RRF)\n- Query expansion (heuristic + LLM semantic variants)\n- Multiple rerankers (OpenAI, CrossEncoder, Lexical)\n- Query routing (answerable detection, prevents hallucinations)\n- Contextual retrieval (Anthropic's approach)\n- Hierarchical chunking with true parent context\n- Multi-tenant with owner-based isolation\n- pgvector with HNSW indexes\n- Multi-language support (14+ languages)\n- SOTA RAG compliance (95/100)\n\n```bash\n# Install all llmemory skills\n/plugin install llmemory@juanre-ai-tools\n\n# Or specific skills\n/plugin install llmemory-hybrid-search@juanre-ai-tools\n/plugin install llmemory-rag@juanre-ai-tools\n```\n\n### ü§ñ llmring - Unified LLM Interface\n\nSingle interface for OpenAI, Anthropic, Google Gemini, and Ollama with streaming, tools, and structured output.\n\n**[Package on GitHub](https://github.com/juanre/llmring) | [PyPI](https://pypi.org/project/llmring/)**\n\n**Skills included:**\n- `llmring` - Complete skill set (all 6 skills)\n- `llmring-chat` - Basic chat completions ‚≠ê\n- `llmring-streaming` - Streaming responses\n- `llmring-tools` - Function calling and tool use\n- `llmring-structured` - JSON schema and typed responses\n- `llmring-lockfile` - Aliases, profiles, and configuration\n- `llmring-providers` - Multi-provider switching and fallbacks\n\n**When to use:** Building LLM applications, multi-provider setups, AI agents, or any application integrating with LLMs.\n\n**Key features:**\n- Unified API across all providers\n- Semantic aliases (fast, balanced, deep)\n- Automatic fallback models\n- Streaming support everywhere\n- Tool calling with consistent interface\n- Cost tracking and receipts\n- Profile support (dev/staging/prod)\n\n```bash\n# Install all llmring skills\n/plugin install llmring@juanre-ai-tools\n\n# Or specific skills\n/plugin install llmring-streaming@juanre-ai-tools\n/plugin install llmring-tools@juanre-ai-tools\n```\n\n## How Skills Work\n\n### Example: Building a FastAPI App\n\n**You ask:**\n> \"Help me build a FastAPI app with PostgreSQL connection pooling\"\n\n**What happens:**\n1. Claude sees \"FastAPI\", \"PostgreSQL\", \"connection pooling\"\n2. Automatically loads `pgdbm-shared-pool` skill\n3. Provides expert guidance with production patterns\n4. Shows you the exact code you need\n\n**Result:** Production-ready code following best practices, no manual lookup needed!\n\n### Example: Building a RAG System\n\n**You ask:**\n> \"Build a RAG system with hybrid search for customer support docs\"\n\n**What happens:**\n1. Claude sees \"RAG\", \"hybrid search\"\n2. Loads `llmemory-hybrid-search` and `llmemory-rag` skills\n3. Guides you through document ingestion, search setup, and retrieval\n4. Shows you how to combine vector + keyword search\n\n**Result:** Complete RAG implementation with best practices built-in!\n\n## Installation Guide\n\n### Step 1: Install Python Packages\n\n```bash\n# Install the packages you need\nuv add pgdbm\nuv add llmemory\nuv add llmring\n\n# Or with pip\npip install pgdbm llmemory llmring\n```\n\n### Step 2: Install Claude Code Skills\n\n```bash\n# In Claude Code terminal\n/plugin marketplace add juanre/ai-tools\n\n# Install complete skill sets\n/plugin install pgdbm@juanre-ai-tools\n/plugin install llmemory@juanre-ai-tools\n/plugin install llmring@juanre-ai-tools\n```\n\n### Step 3: Start Building!\n\nJust ask Claude naturally:\n\n```\n\"Create a FastAPI app with PostgreSQL\"\n\"Build a RAG system with document search\"\n\"Add streaming responses from OpenAI\"\n\"Help me test my database code\"\n```\n\nClaude will automatically use the relevant skills to provide expert guidance!\n\n## Complete Skill List\n\n### pgdbm (9 skills)\n| Skill | Description | Install |\n|-------|-------------|---------|\n| `pgdbm` | All pgdbm skills | `/plugin install pgdbm@juanre-ai-tools` |\n| `pgdbm-choosing-pattern` | Choose the right pattern | `/plugin install pgdbm-choosing-pattern@juanre-ai-tools` |\n| `pgdbm-shared-pool` | Production connection pooling | `/plugin install pgdbm-shared-pool@juanre-ai-tools` |\n| `pgdbm-dual-mode` | Portable database libraries | `/plugin install pgdbm-dual-mode@juanre-ai-tools` |\n| `pgdbm-standalone` | Standalone service pattern | `/plugin install pgdbm-standalone@juanre-ai-tools` |\n| `pgdbm-testing` | Database testing patterns | `/plugin install pgdbm-testing@juanre-ai-tools` |\n| `pgdbm-usage` | Basic operations | `/plugin install pgdbm-usage@juanre-ai-tools` |\n| `pgdbm-core-api` | Complete API reference | `/plugin install pgdbm-core-api@juanre-ai-tools` |\n| `pgdbm-migrations-api` | Migrations API reference | `/plugin install pgdbm-migrations-api@juanre-ai-tools` |\n| `pgdbm-common-mistakes` | Common pitfalls to avoid | `/plugin install pgdbm-common-mistakes@juanre-ai-tools` |\n\n### llmemory (5 skills)\n| Skill | Description | Install |\n|-------|-------------|---------|\n| `llmemory` | All llmemory skills | `/plugin install llmemory@juanre-ai-tools` |\n| `llmemory-basic-usage` | Getting started | `/plugin install llmemory-basic-usage@juanre-ai-tools` |\n| `llmemory-hybrid-search` | Vector + BM25 search | `/plugin install llmemory-hybrid-search@juanre-ai-tools` |\n| `llmemory-multi-query` | Query expansion | `/plugin install llmemory-multi-query@juanre-ai-tools` |\n| `llmemory-multi-tenant` | SaaS patterns | `/plugin install llmemory-multi-tenant@juanre-ai-tools` |\n| `llmemory-rag` | Complete RAG systems | `/plugin install llmemory-rag@juanre-ai-tools` |\n\n### llmring (6 skills)\n| Skill | Description | Install |\n|-------|-------------|---------|\n| `llmring` | All llmring skills | `/plugin install llmring@juanre-ai-tools` |\n| `llmring-chat` | Basic completions | `/plugin install llmring-chat@juanre-ai-tools` |\n| `llmring-streaming` | Streaming responses | `/plugin install llmring-streaming@juanre-ai-tools` |\n| `llmring-tools` | Function calling | `/plugin install llmring-tools@juanre-ai-tools` |\n| `llmring-structured` | JSON schemas | `/plugin install llmring-structured@juanre-ai-tools` |\n| `llmring-lockfile` | Configuration | `/plugin install llmring-lockfile@juanre-ai-tools` |\n| `llmring-providers` | Multi-provider setup | `/plugin install llmring-providers@juanre-ai-tools` |\n\n## Use Cases\n\n### Build a SaaS Application\n\n```bash\n# Install all needed skills\n/plugin install pgdbm@juanre-ai-tools\n/plugin install llmemory@juanre-ai-tools\n/plugin install llmring@juanre-ai-tools\n```\n\n**Then ask Claude:**\n- \"Create a FastAPI app with multi-tenant PostgreSQL\"\n- \"Add document search with vector embeddings per customer\"\n- \"Integrate OpenAI for chat with streaming responses\"\n\nSkills automatically guide you through best practices for each component!\n\n### Build a RAG Chatbot\n\n```bash\n/plugin install llmemory@juanre-ai-tools\n/plugin install llmring@juanre-ai-tools\n```\n\n**Then ask Claude:**\n- \"Set up hybrid search for product documentation\"\n- \"Add multi-query expansion for better retrieval\"\n- \"Integrate with Claude API for responses\"\n\n### Optimize Database Performance\n\n```bash\n/plugin install pgdbm@juanre-ai-tools\n```\n\n**Then ask Claude:**\n- \"Review my database setup for connection pooling\"\n- \"Help me add migrations to my project\"\n- \"Show me how to test database transactions\"\n\n## Why Use These Skills?\n\n### Without Skills\n‚ùå Generic database advice\n‚ùå You have to explain the package API\n‚ùå May suggest outdated patterns\n‚ùå No awareness of package-specific features\n\n### With Skills\n‚úÖ Specific to pgdbm/llmemory/llmring APIs\n‚úÖ Production-tested patterns\n‚úÖ Common pitfalls documented\n‚úÖ Best practices built-in\n‚úÖ Automatically activated when relevant\n\n## Package Links\n\n- **pgdbm** - [GitHub](https://github.com/juanre/pgdbm) | [PyPI](https://pypi.org/project/pgdbm/) | [Docs](https://github.com/juanre/pgdbm#readme)\n- **llmemory** - [GitHub](https://github.com/juanre/llmemory) | [PyPI](https://pypi.org/project/llmemory/) | [Docs](https://github.com/juanre/llmemory#readme)\n- **llmring** - [GitHub](https://github.com/juanre/llmring) | [PyPI](https://pypi.org/project/llmring/) | [Docs](https://github.com/juanre/llmring#readme)\n\n## Requirements\n\n- **Claude Code** installed and running\n- **Python 3.9+** for the packages\n- **PostgreSQL 14+** (for pgdbm and llmemory)\n\n## Support & Community\n\n- üí¨ **Issues & Questions**: [Open an issue](https://github.com/juanre/ai-tools/issues)\n- üêõ **Bug Reports**: Report bugs in the specific package repository\n- üí° **Feature Requests**: Suggest improvements in package repos\n- üìß **Contact**: [[email protected]](mailto:[email protected])\n\n## Contributing\n\nSkills are maintained in each package repository:\n- pgdbm skills: [pgdbm/.claude/skills/](https://github.com/juanre/pgdbm/tree/main/.claude/skills)\n- llmemory skills: [llmemory/.claude/skills/](https://github.com/juanre/llmemory/tree/main/.claude/skills)\n- llmring skills: [llmring/.claude/skills/](https://github.com/juanre/llmring/tree/main/.claude/skills)\n\nTo contribute:\n1. Fork the package repository\n2. Improve or add skills in `.claude/skills/`\n3. Test with Claude Code\n4. Submit a pull request\n\n## License\n\nAll packages and skills are released under the MIT License.\n\n## About the Author\n\n**Juan Reyero** is a software engineer with 30+ years of experience in engineering leadership and technical innovation. CTO at Quantica and previously senior technical roles at Hewlett-Packard and Xaar, Juan has extensive experience building production systems and developer tools.\n\n- GitHub: [@juanre](https://github.com/juanre)\n- Website: [juanreyero.com](https://juanreyero.com)\n- Email: [email protected]\n\n## Acknowledgments\n\nThanks to:\n- **Anthropic** for creating Claude Code and the skills system\n- **The Claude Code community** for feedback and contributions\n- **Early adopters** who helped refine these skills\n\n---\n\n**Made with ‚ù§Ô∏è for the AI development community**\n\n*Last updated: January 2026*\n"
      },
      "plugins": [
        {
          "name": "pgdbm",
          "source": {
            "source": "github",
            "repo": "juanre/pgdbm"
          },
          "description": "Complete pgdbm skill set: PostgreSQL database management with async operations, migrations, and connection pooling. Use when building FastAPI apps, microservices, or multi-tenant SaaS with PostgreSQL.",
          "version": "1.0.0",
          "category": "database",
          "tags": [
            "pgdbm",
            "postgresql",
            "database",
            "async",
            "migrations",
            "bundle"
          ],
          "categories": [
            "async",
            "bundle",
            "database",
            "migrations",
            "pgdbm",
            "postgresql"
          ],
          "install_commands": [
            "/plugin marketplace add juanre/ai-tools",
            "/plugin install pgdbm@juanre-ai-tools"
          ]
        },
        {
          "name": "pgdbm-choosing-pattern",
          "source": {
            "source": "github",
            "repo": "juanre/pgdbm"
          },
          "description": "Decision guide for choosing the right pgdbm pattern (standalone, dual-mode, or shared pool) based on deployment context.",
          "version": "1.0.0",
          "category": "database",
          "tags": [
            "pgdbm",
            "postgresql",
            "architecture",
            "patterns"
          ],
          "categories": [
            "architecture",
            "database",
            "patterns",
            "pgdbm",
            "postgresql"
          ],
          "install_commands": [
            "/plugin marketplace add juanre/ai-tools",
            "/plugin install pgdbm-choosing-pattern@juanre-ai-tools"
          ]
        },
        {
          "name": "pgdbm-shared-pool",
          "source": {
            "source": "github",
            "repo": "juanre/pgdbm"
          },
          "description": "Production pattern for pgdbm using one shared connection pool across multiple schemas or microservices. Critical for FastAPI apps and multi-service architectures.",
          "version": "1.0.0",
          "category": "database",
          "tags": [
            "pgdbm",
            "postgresql",
            "connection-pool",
            "production",
            "fastapi"
          ],
          "categories": [
            "connection-pool",
            "database",
            "fastapi",
            "pgdbm",
            "postgresql",
            "production"
          ],
          "install_commands": [
            "/plugin marketplace add juanre/ai-tools",
            "/plugin install pgdbm-shared-pool@juanre-ai-tools"
          ]
        },
        {
          "name": "pgdbm-dual-mode",
          "source": {
            "source": "github",
            "repo": "juanre/pgdbm"
          },
          "description": "Pattern for building reusable PyPI packages with pgdbm that work standalone or embedded. Use when creating database libraries.",
          "version": "1.0.0",
          "category": "database",
          "tags": [
            "pgdbm",
            "postgresql",
            "library",
            "pypi",
            "reusable"
          ],
          "categories": [
            "database",
            "library",
            "pgdbm",
            "postgresql",
            "pypi",
            "reusable"
          ],
          "install_commands": [
            "/plugin marketplace add juanre/ai-tools",
            "/plugin install pgdbm-dual-mode@juanre-ai-tools"
          ]
        },
        {
          "name": "pgdbm-standalone",
          "source": {
            "source": "github",
            "repo": "juanre/pgdbm"
          },
          "description": "Standalone service pattern for simple microservices with their own database. Simplest pgdbm setup.",
          "version": "1.0.0",
          "category": "database",
          "tags": [
            "pgdbm",
            "postgresql",
            "microservices",
            "standalone"
          ],
          "categories": [
            "database",
            "microservices",
            "pgdbm",
            "postgresql",
            "standalone"
          ],
          "install_commands": [
            "/plugin marketplace add juanre/ai-tools",
            "/plugin install pgdbm-standalone@juanre-ai-tools"
          ]
        },
        {
          "name": "pgdbm-testing",
          "source": {
            "source": "github",
            "repo": "juanre/pgdbm"
          },
          "description": "Testing database code with pgdbm fixtures: test fixtures, test databases, pytest integration. Use when writing database tests.",
          "version": "1.0.0",
          "category": "database",
          "tags": [
            "pgdbm",
            "postgresql",
            "testing",
            "pytest",
            "fixtures"
          ],
          "categories": [
            "database",
            "fixtures",
            "pgdbm",
            "postgresql",
            "pytest",
            "testing"
          ],
          "install_commands": [
            "/plugin marketplace add juanre/ai-tools",
            "/plugin install pgdbm-testing@juanre-ai-tools"
          ]
        },
        {
          "name": "pgdbm-usage",
          "source": {
            "source": "github",
            "repo": "juanre/pgdbm"
          },
          "description": "Mental model and core pgdbm operations: connecting, querying, transactions, migrations. Start here for understanding pgdbm patterns.",
          "version": "1.0.0",
          "category": "database",
          "tags": [
            "pgdbm",
            "postgresql",
            "basics",
            "getting-started"
          ],
          "categories": [
            "basics",
            "database",
            "getting-started",
            "pgdbm",
            "postgresql"
          ],
          "install_commands": [
            "/plugin marketplace add juanre/ai-tools",
            "/plugin install pgdbm-usage@juanre-ai-tools"
          ]
        },
        {
          "name": "pgdbm-core-api",
          "source": {
            "source": "github",
            "repo": "juanre/pgdbm"
          },
          "description": "Complete AsyncDatabaseManager and DatabaseConfig API reference with all methods, parameters, and configuration options.",
          "version": "1.0.0",
          "category": "database",
          "tags": [
            "pgdbm",
            "postgresql",
            "api",
            "reference"
          ],
          "categories": [
            "api",
            "database",
            "pgdbm",
            "postgresql",
            "reference"
          ],
          "install_commands": [
            "/plugin marketplace add juanre/ai-tools",
            "/plugin install pgdbm-core-api@juanre-ai-tools"
          ]
        },
        {
          "name": "pgdbm-migrations-api",
          "source": {
            "source": "github",
            "repo": "juanre/pgdbm"
          },
          "description": "Complete AsyncMigrationManager API reference with migration file format, checksum validation, and version control.",
          "version": "1.0.0",
          "category": "database",
          "tags": [
            "pgdbm",
            "postgresql",
            "migrations",
            "api",
            "reference"
          ],
          "categories": [
            "api",
            "database",
            "migrations",
            "pgdbm",
            "postgresql",
            "reference"
          ],
          "install_commands": [
            "/plugin marketplace add juanre/ai-tools",
            "/plugin install pgdbm-migrations-api@juanre-ai-tools"
          ]
        },
        {
          "name": "pgdbm-common-mistakes",
          "source": {
            "source": "github",
            "repo": "juanre/pgdbm"
          },
          "description": "Common pgdbm mistakes and how to avoid them: pool multiplication, schema errors, template syntax violations. Use before implementing.",
          "version": "1.0.0",
          "category": "database",
          "tags": [
            "pgdbm",
            "postgresql",
            "best-practices",
            "anti-patterns"
          ],
          "categories": [
            "anti-patterns",
            "best-practices",
            "database",
            "pgdbm",
            "postgresql"
          ],
          "install_commands": [
            "/plugin marketplace add juanre/ai-tools",
            "/plugin install pgdbm-common-mistakes@juanre-ai-tools"
          ]
        },
        {
          "name": "llmemory",
          "source": {
            "source": "github",
            "repo": "juanre/llmemory"
          },
          "description": "Complete llmemory skill set: SOTA RAG library with hybrid search (vector + BM25), query expansion (heuristic + LLM), reranking, query routing, contextual retrieval, and multi-tenant support. Use when building production RAG systems, semantic search, or document Q&A.",
          "version": "1.0.0",
          "category": "ai",
          "tags": [
            "llmemory",
            "rag",
            "vector-search",
            "hybrid-search",
            "pgvector",
            "multi-tenant",
            "bundle"
          ],
          "categories": [
            "ai",
            "bundle",
            "hybrid-search",
            "llmemory",
            "multi-tenant",
            "pgvector",
            "rag",
            "vector-search"
          ],
          "install_commands": [
            "/plugin marketplace add juanre/ai-tools",
            "/plugin install llmemory@juanre-ai-tools"
          ]
        },
        {
          "name": "llmemory-basic-usage",
          "source": {
            "source": "github",
            "repo": "juanre/llmemory"
          },
          "description": "Getting started with llmemory: installation, initialization, adding documents, search operations, document management. Start here for llmemory basics.",
          "version": "1.0.0",
          "category": "ai",
          "tags": [
            "llmemory",
            "rag",
            "getting-started",
            "basics",
            "vector-search"
          ],
          "categories": [
            "ai",
            "basics",
            "getting-started",
            "llmemory",
            "rag",
            "vector-search"
          ],
          "install_commands": [
            "/plugin marketplace add juanre/ai-tools",
            "/plugin install llmemory-basic-usage@juanre-ai-tools"
          ]
        },
        {
          "name": "llmemory-hybrid-search",
          "source": {
            "source": "github",
            "repo": "juanre/llmemory"
          },
          "description": "Hybrid search combining vector similarity and BM25 full-text search with Reciprocal Rank Fusion (RRF). Alpha tuning, HNSW configuration, search optimization.",
          "version": "1.0.0",
          "category": "ai",
          "tags": [
            "llmemory",
            "rag",
            "hybrid-search",
            "vector-search",
            "bm25",
            "rrf"
          ],
          "categories": [
            "ai",
            "bm25",
            "hybrid-search",
            "llmemory",
            "rag",
            "rrf",
            "vector-search"
          ],
          "install_commands": [
            "/plugin marketplace add juanre/ai-tools",
            "/plugin install llmemory-hybrid-search@juanre-ai-tools"
          ]
        },
        {
          "name": "llmemory-multi-query",
          "source": {
            "source": "github",
            "repo": "juanre/llmemory"
          },
          "description": "Query expansion with heuristic and LLM-based variants for improved retrieval recall. Multi-query search with RRF fusion across query variants.",
          "version": "1.0.0",
          "category": "ai",
          "tags": [
            "llmemory",
            "rag",
            "query-expansion",
            "multi-query",
            "recall"
          ],
          "categories": [
            "ai",
            "llmemory",
            "multi-query",
            "query-expansion",
            "rag",
            "recall"
          ],
          "install_commands": [
            "/plugin marketplace add juanre/ai-tools",
            "/plugin install llmemory-multi-query@juanre-ai-tools"
          ]
        },
        {
          "name": "llmemory-multi-tenant",
          "source": {
            "source": "github",
            "repo": "juanre/llmemory"
          },
          "description": "Multi-tenant patterns with owner-based isolation for SaaS applications. Security implementation, FastAPI integration, workspace separation.",
          "version": "1.0.0",
          "category": "ai",
          "tags": [
            "llmemory",
            "multi-tenant",
            "saas",
            "security",
            "isolation"
          ],
          "categories": [
            "ai",
            "isolation",
            "llmemory",
            "multi-tenant",
            "saas",
            "security"
          ],
          "install_commands": [
            "/plugin marketplace add juanre/ai-tools",
            "/plugin install llmemory-multi-tenant@juanre-ai-tools"
          ]
        },
        {
          "name": "llmemory-rag",
          "source": {
            "source": "github",
            "repo": "juanre/llmemory"
          },
          "description": "Building production RAG systems: document ingestion, hybrid search retrieval, query routing, reranking, prompt augmentation. Complete RAG pipeline patterns.",
          "version": "1.0.0",
          "category": "ai",
          "tags": [
            "llmemory",
            "rag",
            "retrieval",
            "reranking",
            "production"
          ],
          "categories": [
            "ai",
            "llmemory",
            "production",
            "rag",
            "reranking",
            "retrieval"
          ],
          "install_commands": [
            "/plugin marketplace add juanre/ai-tools",
            "/plugin install llmemory-rag@juanre-ai-tools"
          ]
        },
        {
          "name": "llmring",
          "source": {
            "source": "github",
            "repo": "juanre/llmring"
          },
          "description": "Complete llmring skill set: unified LLM interface for OpenAI, Anthropic, Google, and Ollama with streaming, tools, structured output, and multi-provider patterns. Use when building LLM applications.",
          "version": "1.0.0",
          "category": "ai",
          "tags": [
            "llmring",
            "llm",
            "openai",
            "anthropic",
            "google",
            "ollama",
            "bundle"
          ],
          "categories": [
            "ai",
            "anthropic",
            "bundle",
            "google",
            "llm",
            "llmring",
            "ollama",
            "openai"
          ],
          "install_commands": [
            "/plugin marketplace add juanre/ai-tools",
            "/plugin install llmring@juanre-ai-tools"
          ]
        },
        {
          "name": "llmring-chat",
          "source": {
            "source": "github",
            "repo": "juanre/llmring"
          },
          "description": "Basic chat completions with llmring: unified interface, message structure, resource management. Start here for llmring basics.",
          "version": "1.0.0",
          "category": "ai",
          "tags": [
            "llmring",
            "llm",
            "chat",
            "getting-started",
            "basics"
          ],
          "categories": [
            "ai",
            "basics",
            "chat",
            "getting-started",
            "llm",
            "llmring"
          ],
          "install_commands": [
            "/plugin marketplace add juanre/ai-tools",
            "/plugin install llmring-chat@juanre-ai-tools"
          ]
        },
        {
          "name": "llmring-streaming",
          "source": {
            "source": "github",
            "repo": "juanre/llmring"
          },
          "description": "Streaming responses with llmring: async iteration, real-time output, usage tracking. Use when building chat interfaces or displaying incremental responses.",
          "version": "1.0.0",
          "category": "ai",
          "tags": [
            "llmring",
            "llm",
            "streaming",
            "real-time",
            "async"
          ],
          "categories": [
            "ai",
            "async",
            "llm",
            "llmring",
            "real-time",
            "streaming"
          ],
          "install_commands": [
            "/plugin marketplace add juanre/ai-tools",
            "/plugin install llmring-streaming@juanre-ai-tools"
          ]
        },
        {
          "name": "llmring-tools",
          "source": {
            "source": "github",
            "repo": "juanre/llmring"
          },
          "description": "Function calling and tool use with llmring: tool definitions, execution patterns, multi-turn conversations. Use when building agents or adding function calling.",
          "version": "1.0.0",
          "category": "ai",
          "tags": [
            "llmring",
            "llm",
            "tools",
            "function-calling",
            "agents"
          ],
          "categories": [
            "agents",
            "ai",
            "function-calling",
            "llm",
            "llmring",
            "tools"
          ],
          "install_commands": [
            "/plugin marketplace add juanre/ai-tools",
            "/plugin install llmring-tools@juanre-ai-tools"
          ]
        },
        {
          "name": "llmring-structured",
          "source": {
            "source": "github",
            "repo": "juanre/llmring"
          },
          "description": "Structured output with JSON schema: type-safe responses, data extraction, validation. Use when extracting structured data from LLMs or enforcing output schemas.",
          "version": "1.0.0",
          "category": "ai",
          "tags": [
            "llmring",
            "llm",
            "json-schema",
            "structured-output",
            "validation"
          ],
          "categories": [
            "ai",
            "json-schema",
            "llm",
            "llmring",
            "structured-output",
            "validation"
          ],
          "install_commands": [
            "/plugin marketplace add juanre/ai-tools",
            "/plugin install llmring-structured@juanre-ai-tools"
          ]
        },
        {
          "name": "llmring-lockfile",
          "source": {
            "source": "github",
            "repo": "juanre/llmring"
          },
          "description": "Lockfile configuration with llmring: semantic aliases, environment profiles, fallback models. Use when configuring model aliases or managing dev/staging/prod environments.",
          "version": "1.0.0",
          "category": "ai",
          "tags": [
            "llmring",
            "llm",
            "configuration",
            "aliases",
            "profiles"
          ],
          "categories": [
            "ai",
            "aliases",
            "configuration",
            "llm",
            "llmring",
            "profiles"
          ],
          "install_commands": [
            "/plugin marketplace add juanre/ai-tools",
            "/plugin install llmring-lockfile@juanre-ai-tools"
          ]
        },
        {
          "name": "llmring-providers",
          "source": {
            "source": "github",
            "repo": "juanre/llmring"
          },
          "description": "Multi-provider patterns with llmring: provider switching, raw SDK access, provider-specific features (caching, logprobs). Use when switching providers or accessing advanced features.",
          "version": "1.0.0",
          "category": "ai",
          "tags": [
            "llmring",
            "llm",
            "multi-provider",
            "openai",
            "anthropic",
            "google",
            "ollama"
          ],
          "categories": [
            "ai",
            "anthropic",
            "google",
            "llm",
            "llmring",
            "multi-provider",
            "ollama",
            "openai"
          ],
          "install_commands": [
            "/plugin marketplace add juanre/ai-tools",
            "/plugin install llmring-providers@juanre-ai-tools"
          ]
        }
      ]
    }
  ]
}