{
  "author": {
    "id": "leepokai",
    "display_name": "leepokai",
    "avatar_url": "https://avatars.githubusercontent.com/u/109857817?u=4289d5e16851c73bd4cb63b9c3f14f4c90bf15da&v=4"
  },
  "marketplaces": [
    {
      "name": "leepokai",
      "version": "2.7.0",
      "description": "Auto build and deploy Swift/SwiftUI apps to simulator or device after Claude Code conversations",
      "repo_full_name": "leepokai/swiftui-smart-build",
      "repo_url": "https://github.com/leepokai/swiftui-smart-build",
      "repo_description": null,
      "signals": {
        "stars": 2,
        "forks": 0,
        "pushed_at": "2026-01-30T04:39:47Z"
      },
      "files": {
        ".claude-plugin/marketplace.json": "{\n  \"name\": \"leepokai\",\n  \"version\": \"2.7.0\",\n  \"owner\": {\n    \"name\": \"leepokai\"\n  },\n  \"metadata\": {\n    \"description\": \"Auto build and deploy Swift/SwiftUI apps to simulator or device after Claude Code conversations\"\n  },\n  \"plugins\": [\n    {\n      \"name\": \"swiftui-smart-build\",\n      \"source\": \"./\",\n      \"description\": \"Auto-install iOS apps after xcodebuild + SwiftUI best practices\",\n      \"version\": \"2.7.0\",\n      \"author\": {\n        \"name\": \"leepokai\"\n      },\n      \"category\": \"development\",\n      \"keywords\": [\"swift\", \"swiftui\", \"xcode\", \"ios\", \"build\", \"simulator\", \"deploy\", \"best-practices\"],\n      \"license\": \"MIT\",\n      \"repository\": \"https://github.com/leepokai/swiftui-smart-build\"\n    }\n  ]\n}\n",
        ".claude-plugin/plugin.json": "{\n  \"name\": \"swiftui-smart-build\",\n  \"version\": \"2.7.0\",\n  \"description\": \"Auto-install iOS apps after xcodebuild + SwiftUI best practices\",\n  \"author\": {\n    \"name\": \"leepokai\"\n  },\n  \"repository\": \"https://github.com/leepokai/swiftui-smart-build\",\n  \"license\": \"MIT\",\n  \"keywords\": [\"swift\", \"swiftui\", \"xcode\", \"ios\", \"simulator\", \"deploy\", \"best-practices\"]\n}\n",
        "README.md": "# SwiftUI Smart Build\n\nClaude Code plugin for Swift/SwiftUI development with automatic code checking and app deployment.\n\n## Why This Plugin?\n\n### The Problem\n\nWhen using AI to write Swift code, you often face:\n\n1. **Endless context switching** - AI writes code â†’ switch to Xcode â†’ build fails â†’ switch back to AI â†’ fix â†’ repeat\n2. **Build failures from AI-generated code** - AI doesn't know about syntax errors until you try to build\n3. **Manual deployment** - After each build, manually install and launch the app\n\n### The Solution\n\nThis plugin creates a **tight feedback loop** that catches errors early and deploys automatically:\n\n| Without Plugin | With Plugin |\n|----------------|-------------|\n| AI edits â†’ Build â†’ Fail â†’ Fix â†’ Build â†’ Fail â†’ ... | AI edits â†’ **Instant syntax check** â†’ Fix â†’ Build â†’ **Auto-deploy** |\n| 5-10 build attempts to get it right | **Higher first-build success rate** |\n| Switch between AI IDE â†” Xcode â†” Simulator | **Stay in AI IDE**, app appears automatically |\n\n### Time Saved\n\n- **No more Xcode switching** - Syntax errors caught instantly after each edit\n- **No more manual deployment** - App installs and launches automatically after build\n- **Fewer build cycles** - Catch errors before building, not after\n\n---\n\n## How It Works\n\n### Auto Check & Format (on Edit/Write)\n\nWhen you edit a `.swift` file, the plugin automatically:\n- Runs `swiftc -parse` to catch syntax errors (~0.1s)\n- Runs `swiftformat` to auto-fix style issues (only when syntax is OK)\n\nErrors appear immediately - no need to wait for a full build.\n\n### Pre-Build LSP Check (Optional)\n\nBefore building, use LSP to verify types - faster than waiting for xcodebuild:\n\n```\nLSP hover on new function â†’ verify return type resolves\nLSP findReferences on renamed symbol â†’ verify all call sites updated\n```\n\nCatches type errors and broken references before the full build.\n\n### Auto Install (on Build Success)\n\nWhen `xcodebuild` succeeds, the plugin automatically:\n- Boots the target simulator (using saved UDID for precision)\n- Installs the compiled `.app`\n- Launches the app\n\n**You stay in the AI IDE. The app just appears on the simulator.**\n\n---\n\n## Installation\n\n```bash\n# Add the marketplace\n/plugin marketplace add leepokai/swiftui-smart-build\n\n# Install the plugin\n/plugin install swiftui-smart-build@leepokai\n```\n\n---\n\n## Commands\n\n| Command | Description |\n|---------|-------------|\n| `/simulator-build-boot-install` | Build â†’ boot simulator â†’ install & launch |\n| `/simulator-build-boot-install revise` | Change simulator/scheme settings |\n| `/device-build-boot-install` | Build â†’ install to connected device â†’ launch |\n| `/device-build-boot-install revise` | Change device scheme settings |\n\n### Build Preferences\n\nOn first use, commands will ask you to choose:\n- **Scheme**: Which Xcode scheme to build\n- **iOS Version**: Which iOS runtime to use\n- **Device**: Which simulator device to use\n- **UDID**: Auto-saved for precise simulator targeting\n\nPreferences are saved to the project root (`.smart-build.json`):\n\n```json\n{\n  \"simulator\": {\n    \"scheme\": \"MyApp-Debug\",\n    \"device\": \"iPhone 16e\",\n    \"ios_version\": \"iOS 26.2\",\n    \"udid\": \"XXXXXXXX-XXXX-XXXX-XXXX-XXXXXXXXXXXX\"\n  },\n  \"device\": {\n    \"scheme\": \"MyApp-Release\"\n  }\n}\n```\n\nUse `revise` argument to change settings anytime.\n\n---\n\n## Skills\n\n| Skill | Description |\n|-------|-------------|\n| `/smart-build-workflow` | Build workflow guide with hooks documentation |\n\n---\n\n## Usage\n\n### First Time Setup\n\nLoad the workflow skill to configure your build preferences:\n\n```\n/smart-build-workflow\n```\n\nThe skill will:\n1. Check if `.smart-build.json` exists\n2. If not found, guide you through interactive setup:\n   - Choose your build scheme\n   - Choose iOS version\n   - Choose simulator device\n   - Save preferences with UDID for precise targeting\n\nTo change settings later, use:\n\n```\n/simulator-build-boot-install revise\n```\n\n### Building Your App\n\nAfter setup, just build your project:\n\n```\n> Build my app for the simulator\n\nClaude runs: xcodebuild -scheme MyApp -destination 'platform=iOS Simulator,id=XXXX' build\n\nBUILD SUCCEEDED\n\nâ”â”â”â”â”â”â”â”â”â”â”â”â”â”â”â”â”â”â”â”â”â”â”â”â”â”â”â”â”â”â”â”â”â”â”â”â”â”â”â”\nğŸ“¦ Auto-installing after successful build\nâ”â”â”â”â”â”â”â”â”â”â”â”â”â”â”â”â”â”â”â”â”â”â”â”â”â”â”â”â”â”â”â”â”â”â”â”â”â”â”â”\nğŸ“ Found: MyApp.app\nğŸ”– Bundle: com.example.MyApp\nğŸ“± Target: iPhone 16e (iOS 26.2)\n\nğŸš€ Booting: iPhone 16e\nâœ… Booted\n\nğŸ“² Installing...\nâœ… Installed\n\nğŸ¬ Launching...\nâœ… Launched\n\nğŸ‰ App running on iPhone 16e\nâ”â”â”â”â”â”â”â”â”â”â”â”â”â”â”â”â”â”â”â”â”â”â”â”â”â”â”â”â”â”â”â”â”â”â”â”â”â”â”â”\n```\n\n---\n\n## Workflow\n\n```\nâ”Œâ”€â”€â”€â”€â”€â”€â”€â”€â”€â”€â”€â”€â”€â”€â”€â”€â”€â”€â”€â”€â”€â”€â”€â”€â”€â”€â”€â”€â”€â”€â”€â”€â”€â”€â”€â”€â”€â”€â”€â”€â”€â”€â”€â”€â”€â”€â”€â”€â”€â”\nâ”‚  During Editing (Automatic)                     â”‚\nâ”‚  â”€â”€â”€â”€â”€â”€â”€â”€â”€â”€â”€â”€â”€â”€â”€â”€â”€â”€â”€â”€â”€â”€â”€â”€â”€â”€                     â”‚\nâ”‚  Edit .swift â†’ swiftc -parse (instant check)    â”‚\nâ”‚             â†’ swiftformat (auto-fix)            â”‚\nâ”‚  Errors shown immediately, no build needed      â”‚\nâ””â”€â”€â”€â”€â”€â”€â”€â”€â”€â”€â”€â”€â”€â”€â”€â”€â”€â”€â”€â”€â”€â”€â”€â”€â”€â”€â”€â”€â”€â”€â”€â”€â”€â”€â”€â”€â”€â”€â”€â”€â”€â”€â”€â”€â”€â”€â”€â”€â”€â”˜\n                      â†“\nâ”Œâ”€â”€â”€â”€â”€â”€â”€â”€â”€â”€â”€â”€â”€â”€â”€â”€â”€â”€â”€â”€â”€â”€â”€â”€â”€â”€â”€â”€â”€â”€â”€â”€â”€â”€â”€â”€â”€â”€â”€â”€â”€â”€â”€â”€â”€â”€â”€â”€â”€â”\nâ”‚  Pre-Build (Manual)                             â”‚\nâ”‚  â”€â”€â”€â”€â”€â”€â”€â”€â”€â”€â”€â”€â”€â”€â”€â”€â”€                              â”‚\nâ”‚  mcp__ide__getDiagnostics() â†’ type check        â”‚\nâ”‚  Catch type errors before building              â”‚\nâ””â”€â”€â”€â”€â”€â”€â”€â”€â”€â”€â”€â”€â”€â”€â”€â”€â”€â”€â”€â”€â”€â”€â”€â”€â”€â”€â”€â”€â”€â”€â”€â”€â”€â”€â”€â”€â”€â”€â”€â”€â”€â”€â”€â”€â”€â”€â”€â”€â”€â”˜\n                      â†“\nâ”Œâ”€â”€â”€â”€â”€â”€â”€â”€â”€â”€â”€â”€â”€â”€â”€â”€â”€â”€â”€â”€â”€â”€â”€â”€â”€â”€â”€â”€â”€â”€â”€â”€â”€â”€â”€â”€â”€â”€â”€â”€â”€â”€â”€â”€â”€â”€â”€â”€â”€â”\nâ”‚  Build & Deploy (Automatic)                     â”‚\nâ”‚  â”€â”€â”€â”€â”€â”€â”€â”€â”€â”€â”€â”€â”€â”€â”€â”€â”€â”€â”€â”€â”€â”€â”€â”€â”€â”€                     â”‚\nâ”‚  xcodebuild â†’ BUILD SUCCEEDED                   â”‚\nâ”‚  â†’ Boot simulator (if needed)                   â”‚\nâ”‚  â†’ Install app                                  â”‚\nâ”‚  â†’ Launch app                                   â”‚\nâ”‚  Stay in AI IDE, app appears on simulator       â”‚\nâ””â”€â”€â”€â”€â”€â”€â”€â”€â”€â”€â”€â”€â”€â”€â”€â”€â”€â”€â”€â”€â”€â”€â”€â”€â”€â”€â”€â”€â”€â”€â”€â”€â”€â”€â”€â”€â”€â”€â”€â”€â”€â”€â”€â”€â”€â”€â”€â”€â”€â”˜\n```\n\n---\n\n## Supported Targets\n\n- **iOS Simulator**: Auto-boots the correct simulator using saved UDID\n- **Physical iOS Device**: Requires device to be connected and trusted\n\n---\n\n## Requirements\n\n### Required\n\n| Requirement | Why | Install |\n|-------------|-----|---------|\n| **macOS** | iOS development only works on Mac | - |\n| **Xcode** | Build tools + sourcekit-lsp (built-in) | App Store or [developer.apple.com](https://developer.apple.com/xcode/) |\n| **jq** | JSON parsing for hook scripts | `brew install jq` |\n\n### Optional\n\n| Requirement | Why | Install |\n|-------------|-----|---------|\n| **swiftformat** | Auto-format on edit | `brew install swiftformat` |\n| **ios-deploy** | Install to physical devices | `brew install ios-deploy` |\n\n---\n\n## Included Features\n\n- **Swift syntax hook**: Auto-checks syntax (`swiftc -parse`) after each edit (~0.1s)\n- **Swift format hook**: Auto-formats (`swiftformat`) when syntax is OK\n- **Preferences validator**: Validates `.smart-build.json` after edit\n- **Auto-install hook**: Detects \"BUILD SUCCEEDED\" and deploys to simulator/device\n- **UDID-based targeting**: Boots the exact simulator you configured, not a random one\n- **LSP integration**: Use `hover` and `findReferences` for pre-build type verification\n\n---\n\n## License\n\nMIT\n"
      },
      "plugins": [
        {
          "name": "swiftui-smart-build",
          "source": "./",
          "description": "Auto-install iOS apps after xcodebuild + SwiftUI best practices",
          "version": "2.7.0",
          "author": {
            "name": "leepokai"
          },
          "category": "development",
          "keywords": [
            "swift",
            "swiftui",
            "xcode",
            "ios",
            "build",
            "simulator",
            "deploy",
            "best-practices"
          ],
          "license": "MIT",
          "repository": "https://github.com/leepokai/swiftui-smart-build",
          "categories": [
            "best-practices",
            "build",
            "deploy",
            "development",
            "ios",
            "simulator",
            "swift",
            "swiftui",
            "xcode"
          ],
          "install_commands": [
            "/plugin marketplace add leepokai/swiftui-smart-build",
            "/plugin install swiftui-smart-build@leepokai"
          ]
        }
      ]
    }
  ]
}