{
  "author": {
    "id": "masuP9",
    "display_name": "Soichi Masuda",
    "avatar_url": "https://avatars.githubusercontent.com/u/6724665?u=947bd807373b1797dc5b85b3520a522bee5fe9dd&v=4"
  },
  "marketplaces": [
    {
      "name": "a11y-specialist-skills",
      "version": null,
      "description": "Accessibility specialist skills for Claude Code. WCAG 2.2 review, conformance auditing, and improvement planning tools.",
      "repo_full_name": "masuP9/a11y-specialist-skills",
      "repo_url": "https://github.com/masuP9/a11y-specialist-skills",
      "repo_description": "Accessibility specialist skills plugin for Claude Code.",
      "signals": {
        "stars": 28,
        "forks": 0,
        "pushed_at": "2026-01-27T16:27:07Z"
      },
      "files": {
        ".claude-plugin/marketplace.json": "{\n  \"name\": \"a11y-specialist-skills\",\n  \"owner\": {\n    \"name\": \"masuP9\"\n  },\n  \"metadata\": {\n    \"description\": \"Accessibility specialist skills for Claude Code. WCAG 2.2 review, conformance auditing, and improvement planning tools.\",\n    \"version\": \"2.5.1\"\n  },\n  \"plugins\": [\n    {\n      \"name\": \"a11y-specialist-skills\",\n      \"description\": \"Accessibility skills: reviewing-a11y (WCAG reviews), auditing-wcag (conformance audits with automated scripts), planning-wcag-audit (audit planning), planning-a11y-improvement (maturity + roadmap).\",\n      \"source\": \"./\",\n      \"version\": \"2.5.1\",\n      \"author\": {\n        \"name\": \"masuP9\"\n      },\n      \"repository\": \"https://github.com/masuP9/a11y-specialist-skills\",\n      \"license\": \"MIT\",\n      \"keywords\": [\"accessibility\", \"a11y\", \"wcag\", \"aria\", \"review\", \"planning\", \"maturity\", \"audit\", \"compliance\", \"roadmap\", \"conformance\"],\n      \"category\": \"productivity\"\n    }\n  ]\n}\n",
        ".claude-plugin/plugin.json": "{\n  \"name\": \"a11y-specialist-skills\",\n  \"version\": \"2.5.1\",\n  \"description\": \"Accessibility specialist skills for Claude Code. WCAG 2.2 review, conformance auditing, and improvement planning tools.\",\n  \"author\": {\n    \"name\": \"masuP9\",\n    \"url\": \"https://github.com/masuP9\"\n  },\n  \"repository\": \"https://github.com/masuP9/a11y-specialist-skills\",\n  \"license\": \"MIT\",\n  \"keywords\": [\"accessibility\", \"a11y\", \"wcag\", \"aria\", \"review\", \"audit\", \"conformance\", \"planning\"]\n}\n",
        "README.md": "# a11y-specialist-skills\n\n[日本語版 (Japanese)](./README.ja.md)\n\nAccessibility specialist skills plugin for [Claude Code](https://claude.ai/claude-code).\n\nProvides accessibility review skills based on WCAG 2.2 & WAI-ARIA APG.\n\n## Skills\n\n| Skill | Description |\n|-------|-------------|\n| [reviewing-a11y](./skills/reviewing-a11y/) | Accessibility review for web pages, component implementations, design mockups, and specifications |\n| [auditing-wcag](./skills/auditing-wcag/) | Systematic WCAG 2.2 AA conformance auditing with automated test scripts |\n| [planning-wcag-audit](./skills/planning-wcag-audit/) | WCAG audit planning based on WAIC guidelines (page selection, test methods) |\n| [planning-a11y-improvement](./skills/planning-a11y-improvement/) | Accessibility improvement planning with maturity assessment, roadmap, KPI design |\n\n## Installation\n\n### As a Plugin (Recommended)\n\n```bash\n# Add marketplace\n/plugin marketplace add masuP9/a11y-specialist-skills\n\n# Install plugin\n/plugin install a11y-specialist-skills@a11y-specialist-skills\n```\n\n### As a Standalone Skill (Symlink)\n\n```bash\n# Clone the repository\ngit clone https://github.com/masuP9/a11y-specialist-skills.git\n\n# Create symlink to your skills directory\nln -s /path/to/a11y-specialist-skills/skills/reviewing-a11y ~/.claude/skills/reviewing-a11y\n```\n\n### For Development\n\n```bash\n# Test locally with --plugin-dir\nclaude --plugin-dir /path/to/a11y-specialist-skills\n```\n\n## Usage\n\n### reviewing-a11y (Accessibility Review)\n\nClaude will automatically detect when to use the skill based on your request:\n\n```\n# Examples\nReview accessibility\nCheck a11y\nAccessibility review please\n```\n\nYou can also provide specific targets:\n\n```\n# URL\nReview a11y for https://example.com\n\n# Local file\nCheck accessibility of src/components/Button.tsx\n\n# Design spec\nReview this design mockup from a11y perspective\n```\n\nYou can also invoke directly with slash command:\n\n```\n/reviewing-a11y\n```\n\n#### Review Output\n\nThe skill provides structured feedback including:\n\n- **Positive Findings**: What's done well from an accessibility perspective\n- **Issues**: Problems categorized by severity (Critical / Major / Minor)\n  - Location in code/page\n  - Description of the issue\n  - Related WCAG success criterion\n  - Suggested fix\n- **Manual Checks**: Items that require human verification\n\n### auditing-wcag (WCAG Conformance Audit)\n\nPerform systematic WCAG 2.2 AA conformance audits:\n\n```\n# Examples\nAudit this page for WCAG compliance\nRun WCAG audit on https://example.com\nCheck WCAG 2.2 AA conformance\n```\n\nYou can also invoke directly with slash command:\n\n```\n/auditing-wcag\n```\n\n#### Audit Process\n\nThe skill guides through a 4-phase audit:\n\n1. **Automated Checks**: axe-core + custom Playwright scripts\n2. **Interactive Checks**: Keyboard, focus, pointer operations\n3. **Manual Checks**: Human verification items\n4. **Content Review**: Alt text, labels, headings quality\n\nIncludes automated test scripts for:\n- Focus indicators (2.4.7, 2.4.12, 3.2.1)\n- Reflow at 320px (1.4.10)\n- Text spacing (1.4.12)\n- Target size (2.5.5, 2.5.8)\n- And more...\n\n### planning-wcag-audit (Audit Planning)\n\nPlan WCAG audits based on WAIC guidelines:\n\n```\n# Examples\nHelp me plan a WCAG audit\nCreate audit plan for our website\nSelect pages for accessibility testing\n```\n\nYou can also invoke directly with slash command:\n\n```\n/planning-wcag-audit\n```\n\n#### Planning Output\n\n- **Page Selection**: Representative pages based on WAIC methodology\n- **Test Methods**: Automated vs manual test allocation\n- **Audit Plan Document**: Formal audit plan template\n\n### planning-a11y-improvement (Improvement Planning)\n\nCreate organizational accessibility improvement plans:\n\n```\n# Examples\nHelp me plan accessibility improvements\nCreate an a11y strategy\nAssess our organization's a11y maturity\n```\n\nYou can also invoke directly with slash command:\n\n```\n/planning-a11y-improvement\n```\n\n#### Planning Output\n\nCollects information through interview format and generates:\n\n- **Maturity Assessment**: Current level (L1-L4) with rationale\n- **Roadmap**: Phased initiatives with owners\n- **KPI Design**: Leading and lagging indicators\n- **Stakeholder Materials**: Business impact and ROI\n\nYou can also load documents such as accessibility test results or initiative history for more accurate planning.\n\n## References\n\n- [WCAG 2.2](https://www.w3.org/TR/WCAG22/)\n- [WAI-ARIA Authoring Practices Guide](https://www.w3.org/WAI/ARIA/apg/)\n\n## License\n\n[MIT](./LICENSE)\n"
      },
      "plugins": [
        {
          "name": "a11y-specialist-skills",
          "description": "Accessibility skills: reviewing-a11y (WCAG reviews), auditing-wcag (conformance audits with automated scripts), planning-wcag-audit (audit planning), planning-a11y-improvement (maturity + roadmap).",
          "source": "./",
          "version": "2.5.1",
          "author": {
            "name": "masuP9"
          },
          "repository": "https://github.com/masuP9/a11y-specialist-skills",
          "license": "MIT",
          "keywords": [
            "accessibility",
            "a11y",
            "wcag",
            "aria",
            "review",
            "planning",
            "maturity",
            "audit",
            "compliance",
            "roadmap",
            "conformance"
          ],
          "category": "productivity",
          "categories": [
            "a11y",
            "accessibility",
            "aria",
            "audit",
            "compliance",
            "conformance",
            "maturity",
            "planning",
            "productivity",
            "review",
            "roadmap",
            "wcag"
          ],
          "install_commands": [
            "/plugin marketplace add masuP9/a11y-specialist-skills",
            "/plugin install a11y-specialist-skills@a11y-specialist-skills"
          ]
        }
      ]
    }
  ]
}