{
  "author": {
    "id": "matlab",
    "display_name": "MATLAB Development & AI Coding Projects",
    "avatar_url": "https://avatars.githubusercontent.com/u/100243663?v=4"
  },
  "marketplaces": [
    {
      "name": "matlab-skills",
      "version": null,
      "description": "A collection of agent skills for MATLAB development, including Live Script generation, unit testing, performance optimization, HTML/JavaScript app building, and digital filter design.",
      "repo_full_name": "matlab/skills",
      "repo_url": "https://github.com/matlab/skills",
      "repo_description": "A collection of Agent Skills for MATLAB development. Skills are specialized instruction sets that extend a coding agent's capabilities for specific tasks, automatically activating when needed.",
      "signals": {
        "stars": 22,
        "forks": 8,
        "pushed_at": "2026-01-28T23:16:43Z"
      },
      "files": {
        ".claude-plugin/marketplace.json": "{\n  \"name\": \"matlab-skills\",\n  \"owner\": {\n    \"name\": \"The MathWorks, Inc.\"\n  },\n  \"metadata\": {\n    \"description\": \"A collection of agent skills for MATLAB development, including Live Script generation, unit testing, performance optimization, HTML/JavaScript app building, and digital filter design.\",\n    \"version\": \"1.0.1\"\n  },\n  \"plugins\": [\n    {\n      \"name\": \"matlab-skills\",\n      \"source\": \"./\",\n      \"description\": \"A collection of agent skills for MATLAB development\",\n      \"version\": \"1.0.1\",\n      \"author\": {\n        \"name\": \"The MathWorks, Inc.\"\n      },\n      \"homepage\": \"https://github.com/matlab/skills\",\n      \"repository\": \"https://github.com/matlab/skills\",\n      \"license\": \"BSD-3-Clause\",\n      \"keywords\": [\n        \"matlab\",\n        \"live-scripts\",\n        \"testing\",\n        \"performance\",\n        \"optimization\",\n        \"vectorization\",\n        \"code-generation\",\n        \"scientific-computing\",\n        \"data-analysis\",\n        \"programming\",\n        \"html\",\n        \"javascript\",\n        \"uihtml\",\n        \"web\",\n        \"interactive\",\n        \"gui\",\n        \"webapp\",\n        \"filter\",\n        \"digital-filter\",\n        \"signal-processing\",\n        \"fir\",\n        \"iir\",\n        \"lowpass\",\n        \"highpass\",\n        \"bandpass\",\n        \"bandstop\",\n        \"notch\",\n        \"dsp\"\n      ]\n    }\n  ]\n}\n",
        ".claude-plugin/plugin.json": "{\n  \"name\": \"matlab-skills\",\n  \"version\": \"1.0.1\",\n  \"description\": \"A collection of agent skills for MATLAB development, including Live Script generation, unit testing, performance optimization, HTML/JavaScript app building, and digital filter design.\",\n  \"author\": {\n    \"name\": \"The MathWorks, Inc.\",\n    \"url\": \"https://github.com/matlab/skills\"\n  },\n  \"homepage\": \"https://github.com/matlab/skills\",\n  \"repository\": \"https://github.com/matlab/skills\",\n  \"license\": \"BSD-3-Clause\",\n  \"keywords\": [\n    \"matlab\",\n    \"live-scripts\",\n    \"testing\",\n    \"performance\",\n    \"optimization\",\n    \"vectorization\",\n    \"code-generation\",\n    \"scientific-computing\",\n    \"data-analysis\",\n    \"programming\",\n    \"html\",\n    \"javascript\",\n    \"uihtml\",\n    \"web\",\n    \"interactive\",\n    \"gui\",\n    \"webapp\",\n    \"filter\",\n    \"digital-filter\",\n    \"signal-processing\",\n    \"fir\",\n    \"iir\",\n    \"lowpass\",\n    \"highpass\",\n    \"bandpass\",\n    \"bandstop\",\n    \"notch\",\n    \"dsp\"\n  ]\n}\n",
        "README.md": "# MATLAB Skills for Coding Agents\n\nA collection of [Agent Skills](https://agentskills.io) for MATLAB development using coding agents. Skills are specialized instruction sets that extend the capabilities of coding agents for specific tasks, automatically activating when needed.\n\n## What are Skills?\n\nSkills are modular, portable capabilities that work across coding agents:\n\n- **Composable**: Skills stack together automatically when needed\n- **Efficient**: Only load when relevant to your current task\n- **Powerful**: Combine instructions with executable code for reliable results\n\n## Available Skills\n\n### MATLAB Live Script Generator\n**Skill ID**: `matlab-live-script`\n\nCreates properly formatted MATLAB plain text Live Scripts (.m files) with rich text documentation, equations, and visualizations. Automatically handles:\n\n- Section formatting with `%[text]` markers\n- LaTeX equation rendering with double backslashes\n- Bulleted lists with proper termination\n- Required appendix formatting\n- Plot and figure management\n- Code and documentation integration\n\n**When it activates**: Creating MATLAB scripts, educational content, Live Scripts, or .m files with documentation.\n\n### MATLAB Test Generator\n**Skill ID**: `matlab-test-generator`\n\nCreates unit tests using the MATLAB Testing Framework. Generates test classes, test methods, and test suites following best practices:\n\n- Class-based test structure with `matlab.unittest.TestCase`\n- Proper test method naming and organization\n- Comprehensive assertion methods (`verifyEqual`, `verifyError`, etc.)\n- Parameterized tests for data-driven testing\n- Setup and teardown methods for test fixtures\n- Test tagging and selective execution\n- Mock objects and performance testing\n\n**When it activates**: Generating test files, test cases, unit tests, test suites, or when testing MATLAB code is requested.\n\n### MATLAB Performance Optimizer\n**Skill ID**: `matlab-performance-optimizer`\n\nOptimizes MATLAB code for better performance through vectorization, memory management, and profiling guidance:\n\n- Vectorization of loops and operations\n- Array preallocation strategies\n- Memory optimization techniques (data types, sparse matrices)\n- Profiling and benchmarking workflows\n- Built-in function usage over manual implementations\n- Parallel computing with `parfor` and GPU arrays\n- Algorithm-specific optimizations\n- Performance pitfall identification\n\n**When it activates**: User requests optimization, mentions slow code, performance issues, speed improvements, or asks to make code faster or more efficient.\n\n### MATLAB uihtml App Builder\n**Skill ID**: `matlab-uihtml-app-builder`\n\nBuilds interactive web applications using HTML/JavaScript interfaces with MATLAB computational backends via the uihtml component:\n\n- Bidirectional HTML-MATLAB communication patterns\n- Event handling and data transfer strategies\n- Security and input validation best practices\n- Complete working examples (calculator, visualizer, forms)\n- Modern UI design with CSS styling\n- Error handling and debugging techniques\n- Performance optimization for web apps\n- Testing strategies for HTML/MATLAB integration\n\n**When it activates**: Creating HTML-based MATLAB apps, JavaScript MATLAB interfaces, web UIs, interactive GUIs, or when user mentions uihtml, HTML, JavaScript, web apps, or web interfaces.\n\n### MATLAB Digital Filter Design\n**Skill ID**: `matlab-digital-filter-design`\n\nDesigns and validates digital filters in MATLAB using Signal Processing Toolbox and DSP System Toolbox:\n\n- FIR and IIR filter design (lowpass, highpass, bandpass, bandstop, notch)\n- Architecture selection guidance (single-stage vs efficient alternatives)\n- `designfilt()` workflow with proper sample rate handling\n- Filter Analyzer for visual comparison of designs\n- Multirate and multistage filter optimization for narrow transitions\n- Streaming (causal) vs offline (batch) mode support\n- Zero-phase filtering with `filtfilt()` for offline processing\n- Numerical verification of passband ripple and stopband attenuation\n\n**When it activates**: Cleaning up noisy signals, removing interference, filtering signals, designing FIR/IIR filters, or comparing filters in Filter Analyzer.\n\n## Installation & Usage\n\n### Claude Code (CLI)\n\n**Recommended**: Install all MATLAB agent skills using the plugin marketplace:\n\n```bash\n# (Step 1) Add the marketplace to Claude Code\n/plugin marketplace add matlab/skills\n\n# (Step 2) Install all the MATLAB Agent Skills\n/plugin install matlab-skills@matlab-skills\n```\n\nThis installs all MATLAB skills (`matlab-live-script`, `matlab-test-generator`, `matlab-performance-optimizer`, `matlab-uihtml-app-builder`, `matlab-digital-filter-design`) in one command. Skills automatically activate when Claude detects relevant tasks.\n\n**Alternative**: Manually install to your personal skills directory:\n\n```bash\n# Clone the repository\ngit clone https://github.com/matlab/skills.git\n\n# Copy all skills to your Claude skills directory\ncp -r skills/skills/* ~/.claude/skills/\n```\n\nOnce installed, just ask Claude to \"create a MATLAB Live Script\" or \"optimize this code\" and the appropriate skill will load automatically.\n\n### Claude.ai (Web) and Claude Desktop\n\nSkills are available to Pro, Max, Team, and Enterprise users. Each skill must be uploaded separately as a ZIP file.\n\n**Uploading Skills:**\n\n1. Open **Settings** â†’ **Capabilities**\n2. Enable Skills (Team/Enterprise admins must enable organization-wide first)\n3. Click **Upload Skill** for each skill you want to add\n\n**Creating ZIP Files:**\n\nEach skill requires a ZIP file with `SKILL.md` at the root level. Some skills include additional resource folders (like `knowledge/`) that must be included.\n\n*Single skill (macOS/Linux):*\n\n```bash\ncd skills/<skill-name>\nzip -r ../<skill-name>.zip .\n```\n\n*Single skill (Windows PowerShell):*\n\n```powershell\ncd skills\nCompress-Archive -Path \"<skill-name>\\*\" -DestinationPath \"<skill-name>.zip\"\n```\n\n*All skills at once (macOS/Linux):*\n\n```bash\ncd skills\nfor d in */; do (cd \"$d\" && zip -r \"../${d%/}.zip\" .); done\n```\n\n*All skills at once (Windows PowerShell):*\n\n```powershell\ncd skills\nGet-ChildItem -Directory | ForEach-Object {\n    Compress-Archive -Path \"$($_.Name)\\*\" -DestinationPath \"$($_.Name).zip\" -Force\n}\n```\n\nUpload the ZIP files to get the MATLAB skills collection. Skills activate automatically when Claude detects relevant tasks.\n\n### Claude API\n\nUse the Skills API for programmatic control:\n\n```python\nimport anthropic\n\nclient = anthropic.Anthropic(api_key=\"your-api-key\")\n\nresponse = client.messages.create(\n    model=\"claude-sonnet-4-5-20250929\",\n    max_tokens=4096,\n    skills=[\"matlab-live-script\"],\n    messages=[\n        {\"role\": \"user\", \"content\": \"Create a Live Script showing Fourier transforms\"}\n    ]\n)\n```\n\n**Requirements**:\n- Skills API access (see [API documentation](https://docs.anthropic.com/))\n- Code Execution Tool beta enabled\n\n## Contributing\n\nWe welcome contributions! Whether you want to:\n\n- Add new MATLAB skills (code generation, debugging, testing, etc.)\n- Improve existing skills\n- Fix bugs or typos\n- Suggest enhancements\n\nPlease see [CONTRIBUTING.md](CONTRIBUTING.md) for detailed guidelines.\n\n### Quick Start for Contributors\n\n1. Fork this repository\n2. Create a new skill directory: `skills/your-skill-name/`\n3. Add a `SKILL.md` file with proper frontmatter\n4. Test thoroughly with a coding agent\n5. Submit a pull request\n\n## Skill Development Resources\n\n- [Official Skills Documentation](https://code.claude.com/docs/en/skills) - Claude Code documentation for using and creating skills\n- [Agent Skills Specification](https://agentskills.io/specification) - Complete format specification for SKILL.md files\n- [Agent Skills Repository](https://github.com/agentskills/agentskills) - Specification and documentation for Agent Skills\n- [Anthropic Skills Repository](https://github.com/anthropics/skills) - Example skills demonstrating Agent Skills capabilities\n- [Claude Code Plugin Guide](https://code.claude.com/docs/en/plugins) - Guide for installing and managing skill plugins\n\n## Related Projects\n\n- [matlab/matlab-mcp-core-server](https://github.com/matlab/matlab-mcp-core-server) - Official MATLAB MCP Server for running MATLAB using AI applications like Claude Code and VS Code\n- [matlab/rules](https://github.com/matlab/rules) - MATLAB coding rules and guidelines optimized for AI coding assistants\n- [matlab/prompts](https://github.com/matlab/prompts) - Curated collection of AI prompts for MATLAB development\n- [matlab/slash-commands](https://github.com/matlab/slash-commands) - Slash commands for streamlining MATLAB development workflows in Claude Code\n\n## License\n\nThis project is licensed under the MathWorks BSD-3-Clause License - see the [LICENSE](LICENSE) file for details.\n\nCopyright (c) 2025-2026, The MathWorks, Inc. All rights reserved.\n\n## Community\n\n- **Issues**: Report bugs or request features via [GitHub Issues](https://github.com/matlab/skills/issues)\n- **Discussions**: Share ideas and ask questions in [MATLAB Central GenAI Discussions Channel](https://www.mathworks.com/matlabcentral/discussions/ai)\n\n---\n\n**Supported Coding Agents**: Agent Skills are supported by [Claude Code](https://claude.ai/code), [Claude.ai](https://claude.ai), [Cursor](https://cursor.com), [VS Code](https://code.visualstudio.com), [GitHub Copilot](https://github.com), [Gemini CLI](https://geminicli.com), [OpenAI Codex](https://developers.openai.com/codex), [Amp](https://ampcode.com), [Goose](https://block.github.io/goose), [Roo Code](https://roocode.com), and [many more](https://agentskills.io). Feature availability may vary by plan and platform.\n"
      },
      "plugins": [
        {
          "name": "matlab-skills",
          "source": "./",
          "description": "A collection of agent skills for MATLAB development",
          "version": "1.0.1",
          "author": {
            "name": "The MathWorks, Inc."
          },
          "homepage": "https://github.com/matlab/skills",
          "repository": "https://github.com/matlab/skills",
          "license": "BSD-3-Clause",
          "keywords": [
            "matlab",
            "live-scripts",
            "testing",
            "performance",
            "optimization",
            "vectorization",
            "code-generation",
            "scientific-computing",
            "data-analysis",
            "programming",
            "html",
            "javascript",
            "uihtml",
            "web",
            "interactive",
            "gui",
            "webapp",
            "filter",
            "digital-filter",
            "signal-processing",
            "fir",
            "iir",
            "lowpass",
            "highpass",
            "bandpass",
            "bandstop",
            "notch",
            "dsp"
          ],
          "categories": [
            "bandpass",
            "bandstop",
            "code-generation",
            "data-analysis",
            "digital-filter",
            "dsp",
            "filter",
            "fir",
            "gui",
            "highpass",
            "html",
            "iir",
            "interactive",
            "javascript",
            "live-scripts",
            "lowpass",
            "matlab",
            "notch",
            "optimization",
            "performance",
            "programming",
            "scientific-computing",
            "signal-processing",
            "testing",
            "uihtml",
            "vectorization",
            "web",
            "webapp"
          ],
          "install_commands": [
            "/plugin marketplace add matlab/skills",
            "/plugin install matlab-skills@matlab-skills"
          ]
        }
      ]
    }
  ]
}