{
  "author": {
    "id": "nikeyes",
    "display_name": "Jorge Castro Nistal",
    "avatar_url": "https://avatars.githubusercontent.com/u/5775194?v=4"
  },
  "marketplaces": [
    {
      "name": "stepwise-dev",
      "version": null,
      "description": "Structured development workflow plugins for Claude Code",
      "repo_full_name": "nikeyes/stepwise-dev",
      "repo_url": "https://github.com/nikeyes/stepwise-dev",
      "repo_description": "Dev workflow for Claude Code",
      "signals": {
        "stars": 16,
        "forks": 0,
        "pushed_at": "2026-02-20T11:00:56Z"
      },
      "files": {
        ".claude-plugin/marketplace.json": "{\n  \"name\": \"stepwise-dev\",\n  \"owner\": {\n    \"name\": \"Jorge Castro\",\n    \"email\": \"nikeyes@gmail.com\"\n  },\n  \"metadata\": {\n    \"description\": \"Structured development workflow plugins for Claude Code\",\n    \"version\": \"0.0.8\"\n  },\n  \"plugins\": [\n    {\n      \"name\": \"stepwise-core\",\n      \"source\": \"./core\",\n      \"version\": \"0.0.8\",\n      \"description\": \"Core workflow for structured development: Research ‚Üí Plan ‚Üí Implement ‚Üí Validate with thoughts/ management\",\n      \"keywords\": [\"workflow\", \"research\", \"planning\", \"implementation\", \"validation\", \"thoughts\"]\n    },\n    {\n      \"name\": \"stepwise-git\",\n      \"source\": \"./git\",\n      \"version\": \"0.0.8\",\n      \"description\": \"Git commit workflow without Claude attribution\",\n      \"keywords\": [\"git\", \"commit\", \"version-control\"]\n    },\n    {\n      \"name\": \"stepwise-web\",\n      \"source\": \"./web\",\n      \"version\": \"0.0.8\",\n      \"description\": \"Web search and research capabilities for external context\",\n      \"keywords\": [\"web\", \"search\", \"research\", \"external\"]\n    },\n    {\n      \"name\": \"stepwise-research\",\n      \"source\": \"./research\",\n      \"version\": \"0.0.1\",\n      \"description\": \"Multi-agent deep research plugin with parallel web searches and synthesis\",\n      \"keywords\": [\"research\", \"multi-agent\", \"web\", \"synthesis\", \"orchestration\", \"citations\"]\n    }\n  ]\n}\n",
        "README.md": "# Stepwise Dev - Multi-Plugin Suite\n\n[![Plugin Available](https://img.shields.io/badge/Claude_Code-Plugin_Available-blue)](https://github.com/nikeyes/stepwise-dev)\n[![License](https://img.shields.io/badge/License-Apache_2.0-green.svg)](LICENSE)\n[![Tests](https://img.shields.io/badge/Tests-Passing-brightgreen)](test/)\n\nA modular development workflow suite for Claude Code inspired by [Ashley Ha's workflow](https://medium.com/@ashleyha/i-mastered-the-claude-code-workflow-145d25e502cf), adapted to work 100% locally with thoughts.\n\n**üìñ Read more**: [Tu CLAUDE.md no funciona sin Context Engineering](https://nikeyes.github.io/tu-claude-md-no-funciona-sin-context-engineering-es/) (Spanish article about Stepwise-dev)\n\n## üéØ What This Is\n\nSolves the context management problem: LLMs lose attention after 60% context usage.\n\nImplements **Research ‚Üí Plan ‚Üí Implement ‚Üí Validate** with frequent `/clear` and persistent `thoughts/` storage.\n\n### Philosophy\n\n- Keep context < 60% (attention threshold)\n- Split work into phases\n- Clear between phases, save to `thoughts/`\n- Never lose research or decisions\n\n## üì¶ Available Plugins\n\nThis repository contains **4 independent plugins** that can be installed separately based on your needs:\n\n### 1. **stepwise-core** (Core Workflow)\nThe foundation plugin with the complete Research ‚Üí Plan ‚Üí Implement ‚Üí Validate cycle.\n\n**Includes:**\n- 5 slash commands (`research_codebase`, `create_plan`, `iterate_plan`, `implement_plan`, `validate_plan`)\n- 5 specialized agents (codebase exploration and thoughts management)\n- 1 thoughts-management skill (with 3 bash scripts)\n\n[‚Üí Read more](./core/README.md)\n\n### 2. **stepwise-git** (Git Operations)\nClean git commit workflow without Claude attribution.\n\n**Includes:**\n- 1 slash command (`commit`)\n- Smart staging and commit message generation\n\n[‚Üí Read more](./git/README.md)\n\n### 3. **stepwise-web** (Web Research)\nWeb search and research capabilities for external context.\n\n**Includes:**\n- 1 specialized agent (`web-search-researcher`)\n- Deep web research with source citations\n\n[‚Üí Read more](./web/README.md)\n\n### 4. **stepwise-research** (Multi-Agent Deep Research)\nAdvanced multi-agent research system with parallel web searches and synthesis.\n\n**Includes:**\n- 1 slash command (`deep_research`)\n- 3 specialized agents (research-lead, research-worker, citation-analyst)\n- 1 research-reports skill (with report generation script)\n- Comprehensive research reports with citations and metadata\n\n[‚Üí Read more](./research/README.md)\n\n## üöÄ Installation\n\n### Option 1: Install All Plugins (Recommended for first-time users)\n\n```bash\n# Add marketplace from GitHub\n/plugin marketplace add nikeyes/stepwise-dev\n\n# Install all plugins\n/plugin install stepwise-core@stepwise-dev\n/plugin install stepwise-git@stepwise-dev\n/plugin install stepwise-web@stepwise-dev\n/plugin install stepwise-research@stepwise-dev\n```\n\n### Option 2: Install Only What You Need\n\n```bash\n# Add marketplace\n/plugin marketplace add nikeyes/stepwise-dev\n\n# Install only the core workflow\n/plugin install stepwise-core@stepwise-dev\n\n# Optionally add git operations\n/plugin install stepwise-git@stepwise-dev\n\n# Optionally add web research\n/plugin install stepwise-web@stepwise-dev\n\n# Optionally add multi-agent deep research\n/plugin install stepwise-research@stepwise-dev\n```\n\n**Restart Claude Code after installation.**\n\n## üß™ Try It Out\n\nDon't have a project to test with? Use [stepwise-todo-api-test](https://github.com/nikeyes/stepwise-todo-api-test) ‚Äî a sample repository designed for testing these plugins.\n\n## üìÅ Directory Structure\n\nAfter running `thoughts-init` (from stepwise-core) in a project:\n\n```\n<your-project>/\n‚îú‚îÄ‚îÄ thoughts/\n‚îÇ   ‚îú‚îÄ‚îÄ nikey_es/          # Your personal notes (you write)\n‚îÇ   ‚îÇ   ‚îú‚îÄ‚îÄ tickets/       # Ticket documentation\n‚îÇ   ‚îÇ   ‚îî‚îÄ‚îÄ notes/         # Personal notes\n‚îÇ   ‚îú‚îÄ‚îÄ shared/            # Team-shared documents (Claude writes)\n‚îÇ   ‚îÇ   ‚îú‚îÄ‚îÄ research/      # Research documents\n‚îÇ   ‚îÇ   ‚îú‚îÄ‚îÄ plans/         # Implementation plans\n‚îÇ   ‚îÇ   ‚îî‚îÄ‚îÄ prs/           # PR descriptions\n‚îÇ   ‚îî‚îÄ‚îÄ searchable/        # Hardlinks for grep (auto-generated)\n‚îÇ       ‚îú‚îÄ‚îÄ nikey_es/      # ‚Üí hardlinks to nikey_es/\n‚îÇ       ‚îî‚îÄ‚îÄ shared/        # ‚Üí hardlinks to shared/\n‚îú‚îÄ‚îÄ .gitignore            # (add thoughts/searchable/ to this)\n‚îî‚îÄ‚îÄ ...\n```\n\n**Key distinction:**\n- **`nikey_es/`**: Personal tickets/notes you create manually\n- **`shared/`**: Formal docs Claude generates from commands\n\n### Why Hardlinks?\n\n- **Fast searching**: Grep one directory instead of many\n- **No duplication**: Same file, same inode, no extra disk space\n- **Auto-sync**: Changes in source are immediately visible\n- **Efficient**: Better than symlinks for grep operations\n\n## üîÑ The Four-Phase Workflow\n\n### Phase 1: Research (stepwise-core)\n\n```bash\n/stepwise-core:research_codebase How does authentication work?\n```\n\nSpawns parallel agents, searches codebase and thoughts/, generates comprehensive research document.\n\n### Phase 2: Plan (stepwise-core)\n\n```bash\n/stepwise-core:create_plan Add rate limiting to the API\n```\n\nIterates with you 5+ times, creates detailed phases with verification steps.\n\n### Phase 3: Implement (stepwise-core)\n\n```bash\n/stepwise-core:implement_plan @thoughts/shared/plans/2025-11-09-rate-limiting.md\n```\n\nExecutes one phase at a time, validates before proceeding.\n\n### Phase 4: Validate (stepwise-core)\n\n```bash\n/stepwise-core:validate_plan @thoughts/shared/plans/2025-11-09-rate-limiting.md\n```\n\nSystematically verifies the entire implementation.\n\n### Commit (stepwise-git)\n\n```bash\n/stepwise-git:commit\n```\n\nCreates clean commits without Claude attribution.\n\n## üí° Usage Examples\n\n### Example 1: Complete Feature Development\n\n```bash\n# Research (core)\n/stepwise-core:research_codebase Where is user registration handled?\n# /clear\n\n# Plan (core)\n/stepwise-core:create_plan Add OAuth login support\n# /clear\n\n# Implement (core)\n/stepwise-core:implement_plan @thoughts/shared/plans/...md\n# /clear\n\n# Validate (core)\n/stepwise-core:validate_plan @thoughts/shared/plans/...md\n\n# Commit (git)\n/stepwise-git:commit\n```\n\n### Example 2: Using Web Research\n\n```bash\n# Research external best practices (web)\n\"What are the best practices for implementing rate limiting in REST APIs?\"\n# The web-search-researcher agent will be invoked automatically\n\n# Research your codebase (core)\n/stepwise-core:research_codebase Where do we handle API rate limiting?\n\n# Continue with plan and implementation...\n```\n\n## üè∑Ô∏è Version Management\n\n```bash\n# Check versions\n/plugin list\n\n# Update all plugins\n/plugin update stepwise-core@stepwise-dev\n/plugin update stepwise-git@stepwise-dev\n/plugin update stepwise-web@stepwise-dev\n/plugin update stepwise-research@stepwise-dev\n```\n\n## üìù Context Management\n\n**Golden Rule**: Never exceed 60% context capacity.\n\n```bash\n/context  # Check current usage\n/clear    # Clear between phases\n```\n\n## üîß Customization\n\n**Change Username**: Set `export THOUGHTS_USER=your_name` or edit the thoughts-init script.\n\n## üß™ Testing\n\n```bash\nmake test          # Run all automated tests\nmake test-verbose  # Run tests with debug output\nmake check         # Run shellcheck on bash scripts\nmake ci            # Run full CI validation\n```\n\n## üêõ Troubleshooting\n\n### Plugin Issues\n\n**Commands not showing**:\n- Restart Claude Code\n- Check plugins enabled: `/plugin list`\n- Reinstall if needed\n\n**Plugin installation fails**:\n- Verify marketplace: `/plugin marketplace list`\n- Check network connection\n\n### Workflow Issues\n\n**Hardlinks failing**: Auto-falls back to symlinks\n\n**No files synced**: Run `THOUGHTS_DEBUG=1 thoughts-sync`\n\n## üìö Learn More\n\n- **Original Article**: [I mastered the Claude Code workflow](https://medium.com/@ashleyha/i-mastered-the-claude-code-workflow-145d25e502cf) by Ashley Ha\n- **HumanLayer**: Original inspiration from [HumanLayer's .claude directory](https://github.com/humanlayer/humanlayer)\n\n## ü§ù Contributing\n\nTest improvements in your workflow, document changes, and share with the community.\n\n## üìÑ License\n\nApache License 2.0 - See LICENSE file for details.\n\n## üîñ Attribution\n\nDerived from [HumanLayer's Claude Code workflow](https://github.com/humanlayer/humanlayer/tree/main/.claude) under Apache License 2.0.\n\nSee [NOTICE](NOTICE) for detailed attribution.\n\n**Major enhancements**:\n- Multi-plugin architecture for modular installation\n- Specialized agent system\n- Local-only thoughts/ management with Agent Skill\n- Automated testing infrastructure\n- Enhanced TDD-focused success criteria\n\n## üôè Credits\n\n- **[Ashley Ha](https://medium.com/@ashleyha)** - Workflow documentation\n- **HumanLayer Team** ([Dex Horthy](https://x.com/dexhorthy) et al.) - Original commands and agents\n- **Anthropic** - [Claude Code](https://claude.com/product/claude-code)\n\n---\n\n**Happy Coding! üöÄ**\n\nQuestions? [Open an issue](https://github.com/nikeyes/stepwise-dev/issues) on GitHub.\n",
        "core/README.md": "# Stepwise Core Plugin\n\nCore workflow plugin for structured development following the Research ‚Üí Plan ‚Üí Implement ‚Üí Validate cycle.\n\n## What's Included\n\n### Commands (5)\n- `/stepwise-core:research_codebase` - Document codebase as-is with comprehensive research\n- `/stepwise-core:create_plan` - Create detailed implementation plans iteratively\n- `/stepwise-core:iterate_plan` - Update existing implementation plans\n- `/stepwise-core:implement_plan` - Execute plans phase by phase with validation\n- `/stepwise-core:validate_plan` - Validate implementation against plan\n\n### Agents (5)\n- `codebase-locator` - Find WHERE code lives in the codebase\n- `codebase-analyzer` - Understand HOW code works\n- `codebase-pattern-finder` - Find similar patterns to model after\n- `thoughts-locator` - Discover documents in thoughts/\n- `thoughts-analyzer` - Extract insights from thoughts docs\n\n### Skills (1)\n- `thoughts-management` - Manage thoughts/ directory with 3 bash scripts:\n  - `thoughts-init` - Initialize thoughts/ structure\n  - `thoughts-sync` - Sync hardlinks in searchable/\n  - `thoughts-metadata` - Generate git metadata\n\n## Installation\n\n```bash\n# Add marketplace\n/plugin marketplace add nikeyes/stepwise-dev\n\n# Install this plugin\n/plugin install stepwise-core@stepwise-dev\n```\n\n## Quick Start\n\n```bash\n# 1. Research\n/stepwise-core:research_codebase How does authentication work?\n\n# 2. Plan\n/stepwise-core:create_plan Add OAuth support\n\n# 3. Implement\n/stepwise-core:implement_plan @thoughts/shared/plans/YYYY-MM-DD-oauth.md\n\n# 4. Validate\n/stepwise-core:validate_plan @thoughts/shared/plans/YYYY-MM-DD-oauth.md\n```\n\n## Philosophy\n\n- Keep context < 60% (attention threshold)\n- Split work into phases\n- Clear between phases, save to thoughts/\n- Never lose research or decisions\n\n## Related Plugins\n\n- **stepwise-git**: Git commit workflow without Claude attribution\n- **stepwise-web**: Web search and research capabilities\n\n## License\n\nApache License 2.0 - See LICENSE file for details.\n",
        "git/README.md": "# Stepwise Git Plugin\n\nGit commit workflow for creating clean commits without Claude attribution.\n\n## What's Included\n\n### Commands (1)\n- `/stepwise-git:commit` - Create git commits with user approval and no Claude attribution\n\n## Installation\n\n```bash\n# Add marketplace\n/plugin marketplace add nikeyes/stepwise-dev\n\n# Install this plugin\n/plugin install stepwise-git@stepwise-dev\n```\n\n## Usage\n\n```bash\n# Create a commit\n/stepwise-git:commit\n```\n\nThis will:\n1. Run `git status` to see untracked files\n2. Run `git diff` to see changes\n3. Run `git log` to match commit message style\n4. Draft a commit message focusing on \"why\" not \"what\"\n5. Stage relevant files\n6. Create the commit\n7. Verify with `git status`\n\n## Features\n\n- **No Claude attribution**: Commits are attributed to you, not Claude\n- **Smart staging**: Only stages relevant files, warns about secrets\n- **Style matching**: Follows your existing commit message patterns\n- **Pre-commit hook support**: Handles hook failures gracefully\n\n## Related Plugins\n\n- **stepwise-core**: Core workflow for Research ‚Üí Plan ‚Üí Implement ‚Üí Validate\n- **stepwise-web**: Web search and research capabilities\n\n## License\n\nApache License 2.0 - See LICENSE file for details.\n",
        "web/README.md": "# Stepwise Web Plugin\n\nWeb search and research capabilities for gathering external context and information.\n\n## What's Included\n\n### Agents (1)\n- `web-search-researcher` - Deep web research agent that searches and analyzes web content to answer questions\n\n## Installation\n\n```bash\n# Add marketplace\n/plugin marketplace add nikeyes/stepwise-dev\n\n# Install this plugin\n/plugin install stepwise-web@stepwise-dev\n```\n\n## Usage\n\nThe `web-search-researcher` agent is automatically invoked by Claude when you ask questions that require external information:\n\n```\n\"What are the best practices for implementing OAuth 2.0?\"\n\"How do other projects handle rate limiting?\"\n\"What's the current state of React Server Components?\"\n```\n\nYou can also invoke it explicitly via the Task tool when you need Claude to perform deep web research on a specific topic.\n\n## Features\n\n- **Deep research**: Performs thorough web searches to find relevant information\n- **Source analysis**: Fetches and analyzes web pages for accurate answers\n- **Citation support**: Provides sources for all information gathered\n- **Context-aware**: Integrates findings with your existing codebase context\n\n## Related Plugins\n\n- **stepwise-core**: Core workflow for Research ‚Üí Plan ‚Üí Implement ‚Üí Validate\n- **stepwise-git**: Git commit workflow without Claude attribution\n\n## License\n\nApache License 2.0 - See LICENSE file for details.\n",
        "research/README.md": "# stepwise-research\n\nMulti-agent deep research plugin for Claude Code with parallel web searches and synthesis.\n\n## Overview\n\n`stepwise-research` implements a sophisticated multi-agent research system inspired by Anthropic's Claude.ai Research feature. It orchestrates parallel web searches across multiple specialized agents, synthesizes findings, and produces comprehensive research reports with proper citations.\n\n**Key Features:**\n- ü§ñ **Multi-agent orchestration** - Lead researcher spawns 1-6+ worker agents based on query complexity\n- ‚ö° **Parallel execution** - Workers search simultaneously for faster results\n- üìö **Comprehensive synthesis** - Cross-references findings from multiple sources\n- üîç **Citation verification** - Dedicated agent ensures accuracy and completeness\n- üìù **Structured reports** - Markdown with YAML frontmatter, numbered citations, and metadata\n- üíæ **Persistence** - Saves to `thoughts/` directory for future reference\n\n## Architecture\n\nBased on research showing that **multi-agent systems produce 90.2% better results** than single-agent approaches (Anthropic research).\n\n### Components\n\n1. **deep_research command** (`/stepwise-research:deep_research`)\n   - Main entry point\n   - Orchestrates high-level workflow\n   - Spawns lead agent and citation analyst\n\n2. **research-lead agent**\n   - Breaks query into sub-questions\n   - Spawns research-worker agents in parallel\n   - Synthesizes findings into coherent narrative\n   - Detects gaps and spawns follow-up workers\n   - Generates structured report\n\n3. **research-worker agents** (1-6+ spawned per query)\n   - Execute focused web searches (broad ‚Üí narrow strategy)\n   - Fetch and analyze source content\n   - Return compressed findings with citations\n   - Operate independently in separate contexts\n\n4. **citation-analyst agent**\n   - Maps claims to supporting sources\n   - Verifies URL accessibility\n   - Assesses source quality\n   - Flags unsupported claims\n   - Generates citation quality report\n\n5. **research-reports Skill**\n   - Formats reports with YAML frontmatter\n   - Standardizes citation format\n   - Integrates with `thoughts/` system\n\n## Installation\n\n```bash\n# Add marketplace\n/plugin marketplace add nikeyes/stepwise-dev\n\n# Install plugin\n/plugin install stepwise-research@stepwise-dev\n\n# Restart Claude Code\n```\n\n**No additional configuration required!** The plugin uses Claude Code's built-in `WebSearch` and `WebFetch` tools.\n\n## Usage\n\n### Basic Usage\n\n```bash\n/stepwise-research:deep_research <research topic>\n```\n\n### Examples\n\n**Simple query (1 worker, ~15 minutes):**\n```bash\n/stepwise-research:deep_research What is Docker and how does it work?\n```\n\n**Comparison query (2-3 workers, ~20-25 minutes):**\n```bash\n/stepwise-research:deep_research Compare React vs Vue.js for enterprise applications\n```\n\n**Complex research (4-6+ workers, ~30-40 minutes):**\n```bash\n/stepwise-research:deep_research Analyze the state of AI code generation tools in 2026\n```\n\n### What to Expect\n\n1. **Clarification** (if needed): May ask 1-2 questions if topic is ambiguous\n2. **Research phase**: Lead agent spawns workers, who search in parallel\n3. **Synthesis**: Lead agent cross-references and synthesizes findings\n4. **Verification**: Citation analyst checks accuracy\n5. **Report generation**: Structured markdown saved to `thoughts/shared/research/`\n\n### Output Structure\n\nReports are saved to:\n```\nthoughts/shared/research/[topic]-[date].md\n```\n\nExample report structure:\n```markdown\n---\ntitle: Research on Docker Containerization\ndate: 2026-02-19\nquery: What is Docker and how does it work?\nkeywords: docker, containerization, virtualization, devops, deployment\nstatus: complete\nagent_count: 2\nsource_count: 12\n---\n\n# Research on Docker Containerization\n\n## Executive Summary\n[3-5 sentence overview]\n\n## Detailed Findings\n\n### Docker Architecture\n[Synthesized findings with citations] [1] [2] [3]\n\n### Container Runtime\n[More findings] [4] [5]\n\n## Conclusions\n- [Key takeaway 1]\n- [Key takeaway 2]\n- [Key takeaway 3]\n\n## Bibliography\n[1] Docker Official Documentation - https://docs.docker.com/\n[2] CNCF Container Whitepaper - https://...\n...\n```\n\n## Worker Scaling\n\nThe lead agent automatically determines how many workers to spawn based on query complexity:\n\n| Query Type | Workers | Example |\n|------------|---------|---------|\n| Simple definition | 1 | \"What is Kubernetes?\" |\n| How-to guide | 1-2 | \"How does JWT authentication work?\" |\n| Comparison (2 items) | 2-3 | \"React vs Vue\" |\n| Comparison (3+ items) | 3-5 | \"Top 5 databases compared\" |\n| State-of-the-art | 4-6 | \"Current state of WebAssembly\" |\n| Multi-faceted analysis | 5-8 | \"Enterprise AI adoption analysis\" |\n\n## Source Quality\n\nWorkers prioritize sources in this order:\n\n**Tier 1 (Highest priority):**\n- .gov, .edu domains\n- Peer-reviewed journals\n- Official documentation\n- RFC documents\n\n**Tier 2 (Industry standard):**\n- Major tech company blogs\n- Reputable tech publications\n- Well-maintained project wikis\n\n**Tier 3 (Community):**\n- Personal blogs (expert authors)\n- Conference talks\n- Stack Overflow\n\n**Tier 4 (Avoided):**\n- SEO content farms\n- Aggregators\n- Low-quality forums\n\n## Integration with Thoughts System\n\nReports integrate with the `stepwise-core` thoughts management system:\n\n1. Reports saved to `thoughts/shared/research/`\n2. `thoughts-management` Skill automatically creates hardlinks in `searchable/`\n3. Reports discoverable via grep across entire thoughts directory\n4. YAML frontmatter enables metadata-based searching\n\n## Citation Quality\n\nThe citation-analyst agent ensures:\n- ‚úÖ All claims are supported by sources\n- ‚úÖ URLs are accessible\n- ‚úÖ Source quality is appropriate (prefer .gov, .edu)\n- ‚úÖ Multiple citations for major claims (2-3+)\n- ‚úÖ Bibliography is complete and formatted correctly\n\n## Performance Characteristics\n\n**Token Usage:**\n- Research shows **token usage correlates with quality** (80% variance explained)\n- Workers use 3-5 search iterations (broad ‚Üí narrow)\n- Each worker fetches 5-10 sources\n- Lead agent performs comprehensive synthesis\n- Total: ~50K-150K tokens depending on complexity\n\n**Time Estimates:**\n- Simple: 10-15 minutes\n- Comparison: 20-25 minutes\n- Complex: 30-45 minutes\n\n*(Note: Actual time varies based on web search latency and source availability)*\n\n**Cost Optimization:**\n- Workers use Sonnet model (efficiency)\n- Lead uses Opus model (synthesis quality)\n- Parallel execution minimizes wall-clock time\n\n## Limitations\n\n- **Web-only research:** Does not access local files, databases, or proprietary sources\n- **No multimedia analysis:** Text-only (no image, video, or audio analysis)\n- **English bias:** Web search results may favor English sources\n- **Recency:** Limited to publicly indexed web content\n- **Rate limiting:** May hit WebSearch rate limits on very complex queries\n\n## Troubleshooting\n\n**Lead agent fails to spawn workers:**\n- Check that `Task` tool is available\n- Verify `WebSearch` and `WebFetch` are accessible (built-in tools)\n- Try simpler query first\n\n**Citation analyst reports many broken URLs:**\n- May indicate sources behind paywalls or temporary outages\n- Workers should automatically prefer accessible sources\n- Consider re-running research with more specific query\n\n**Report not saved to thoughts/:**\n- Verify `thoughts/shared/research/` directory exists\n- Create manually if needed: `mkdir -p thoughts/shared/research`\n- Check write permissions\n\n**Workers return low-quality sources:**\n- Lead agent should detect this and spawn follow-up workers\n- Consider refining query to be more specific\n- Check if topic is too niche (limited high-quality sources available)\n\n## Future Enhancements\n\nPlanned for future releases:\n- Memory persistence across context truncations\n- Recursive depth-first exploration for complex queries\n- Multi-modal research (images, PDFs, videos)\n- Custom source filters (allow/deny domains)\n- Interactive refinement (mid-research questions)\n- Research templates for common patterns\n\n## Credits\n\nArchitecture inspired by:\n- Anthropic's Claude.ai Research system\n- Anthropic Cookbook multi-agent patterns\n- Community implementations (claude-deep-research, deep-research)\n\nAdapted for local-only operation in Claude Code CLI environment.\n\n## License\n\nApache License 2.0 (see main repository LICENSE file)\n\n## Links\n\n- Main repository: https://github.com/nikeyes/stepwise-dev\n- Issues: https://github.com/nikeyes/stepwise-dev/issues\n- Marketplace: `/plugin marketplace add nikeyes/stepwise-dev`\n"
      },
      "plugins": [
        {
          "name": "stepwise-core",
          "source": "./core",
          "version": "0.0.8",
          "description": "Core workflow for structured development: Research ‚Üí Plan ‚Üí Implement ‚Üí Validate with thoughts/ management",
          "keywords": [
            "workflow",
            "research",
            "planning",
            "implementation",
            "validation",
            "thoughts"
          ],
          "categories": [
            "implementation",
            "planning",
            "research",
            "thoughts",
            "validation",
            "workflow"
          ],
          "install_commands": [
            "/plugin marketplace add nikeyes/stepwise-dev",
            "/plugin install stepwise-core@stepwise-dev"
          ]
        },
        {
          "name": "stepwise-git",
          "source": "./git",
          "version": "0.0.8",
          "description": "Git commit workflow without Claude attribution",
          "keywords": [
            "git",
            "commit",
            "version-control"
          ],
          "categories": [
            "commit",
            "git",
            "version-control"
          ],
          "install_commands": [
            "/plugin marketplace add nikeyes/stepwise-dev",
            "/plugin install stepwise-git@stepwise-dev"
          ]
        },
        {
          "name": "stepwise-web",
          "source": "./web",
          "version": "0.0.8",
          "description": "Web search and research capabilities for external context",
          "keywords": [
            "web",
            "search",
            "research",
            "external"
          ],
          "categories": [
            "external",
            "research",
            "search",
            "web"
          ],
          "install_commands": [
            "/plugin marketplace add nikeyes/stepwise-dev",
            "/plugin install stepwise-web@stepwise-dev"
          ]
        },
        {
          "name": "stepwise-research",
          "source": "./research",
          "version": "0.0.1",
          "description": "Multi-agent deep research plugin with parallel web searches and synthesis",
          "keywords": [
            "research",
            "multi-agent",
            "web",
            "synthesis",
            "orchestration",
            "citations"
          ],
          "categories": [
            "citations",
            "multi-agent",
            "orchestration",
            "research",
            "synthesis",
            "web"
          ],
          "install_commands": [
            "/plugin marketplace add nikeyes/stepwise-dev",
            "/plugin install stepwise-research@stepwise-dev"
          ]
        }
      ]
    }
  ]
}