{
  "author": {
    "id": "NSFWteam",
    "display_name": "NSFWteam",
    "avatar_url": "https://avatars.githubusercontent.com/u/95986250?v=4"
  },
  "marketplaces": [
    {
      "name": "nsfw-feature-dev",
      "version": null,
      "description": "Nashville Super Fun Work Team's comprehensive feature development skill suite",
      "repo_full_name": "NSFWteam/skill-feature-dev",
      "repo_url": "https://github.com/NSFWteam/skill-feature-dev",
      "repo_description": null,
      "signals": {
        "stars": 0,
        "forks": 0,
        "pushed_at": "2026-01-24T22:15:01Z"
      },
      "files": {
        ".claude-plugin/marketplace.json": "{\n  \"name\": \"nsfw-feature-dev\",\n  \"owner\": {\n    \"name\": \"NSFW Team\",\n    \"email\": \"nsfw-gh.detoxify230@passmail.net\"\n  },\n  \"metadata\": {\n    \"description\": \"Nashville Super Fun Work Team's comprehensive feature development skill suite\",\n    \"version\": \"1.0.0\"\n  },\n  \"plugins\": [\n    {\n      \"name\": \"nsfw-feature-dev\",\n      \"source\": \"./\",\n      \"description\": \"Comprehensive feature development skill with interview, planning, decomposition, execution, and integration commands\",\n      \"version\": \"1.0.0\",\n      \"author\": {\n        \"name\": \"NSFW Team\",\n        \"email\": \"nsfw-gh.detoxify230@passmail.net\"\n      },\n      \"license\": \"MIT\",\n      \"homepage\": \"https://github.com/NSFWteam/skill-feature-dev\",\n      \"repository\": \"https://github.com/NSFWteam/skill-feature-dev\",\n      \"keywords\": [\n        \"feature-development\",\n        \"planning\",\n        \"architecture\",\n        \"security\",\n        \"scalability\",\n        \"performance\",\n        \"tdd\",\n        \"devops\"\n      ],\n      \"category\": \"development\",\n      \"commands\": [\"./.claude/commands/\"],\n      \"strict\": false\n    }\n  ]\n}\n",
        "README.md": "# Feature Development Skill Suite\r\n\r\n> Build features the right way from the start with comprehensive AI-guided planning\r\n\r\n## What Does This Do? (ELI5)\r\n\r\nImagine you're building a house. You don't just start laying bricksâ€”you need a blueprint first! This plugin asks you smart questions about your feature (like \"what are the security risks?\", \"how many users will it have?\", \"how will we test it?\"), then creates a detailed step-by-step plan that covers everything important.\r\n\r\nBut here's the cool part: the plan is SO detailed that it would be huge and hard to follow. So we break it into smaller, manageable plans that Claude can actually work with.\r\n\r\n**In short:** Questions â†’ Big Plan â†’ Smaller Plans â†’ Build!\r\n\r\n## Installation\r\n\r\n### One-Step Setup\r\n\r\n```\r\n/plugin marketplace add NSFWteam/skill-feature-dev\r\n/plugin install nsfw-feature-dev@nsfw-feature-dev\r\n```\r\n\r\n### Keep Updated\r\n\r\n```\r\n/plugin marketplace update\r\n```\r\n\r\nThis pulls the latest improvements and features from the main branch.\r\n\r\n## The 5-Step Workflow\r\n\r\n```mermaid\r\ngraph LR\r\n    A[ðŸŽ¤ Interview] -->|Questions| B[ðŸ“‹ Plan]\r\n    B -->|Big plan| C[âœ‚ï¸ Decompose]\r\n    C -->|Smaller plans| D[ðŸ”§ Integrate]\r\n    D -->|Tool setup| E[âš¡ Execute]\r\n    \r\n    style A fill:#4CAF50,color:#fff\r\n    style B fill:#2196F3,color:#fff\r\n    style C fill:#FF9800,color:#fff\r\n    style D fill:#9C27B0,color:#fff\r\n    style E fill:#F44336,color:#fff\r\n```\r\n\r\n### Step 1: **Interview** - Ask the right questions\r\nClaude asks you about your feature (security, scalability, testing, tech stack, etc.) and saves your answers.\r\n\r\n```\r\n/nsfw-interview\r\n```\r\n\r\n### Step 2: **Plan** - Create a detailed blueprint  \r\nUses your interview answers to write a comprehensive plan with architecture, security measures, testing strategy, and more.\r\n\r\n```\r\n/nsfw-plan\r\n```\r\n\r\n### Step 3: **Decompose** - Break it into chunks\r\nSplits the big plan into smaller, focused plans (30k-80k tokens each) that Claude can actually execute. Each includes TDD requirements.\r\n\r\n```\r\n/nsfw-decompose\r\n```\r\n\r\n### Step 4: **Integrate** - Pick the right tools\r\nFigures out which AI agents, MCP servers, or skills would be best for each mini-plan.\r\n\r\n```\r\n/nsfw-integrate\r\n```\r\n\r\n### Step 5: **Execute** - Build it!\r\nRuns each mini-plan with the configured tools. You can do them one at a time or in parallel.\r\n\r\n```\r\n/nsfw-execute\r\n```\r\n\r\n---\r\n\r\n## What Gets Generated?\r\n\r\nAfter running these commands, you'll have a `docs/plans/` folder with:\r\n\r\n```\r\ndocs/plans/\r\nâ”œâ”€â”€ payment-system/                           # Your feature\r\nâ”‚   â”œâ”€â”€ payment-system-comprehensive.md       # The big plan\r\nâ”‚   â”œâ”€â”€ payment-system-interview-data.json    # Your answers\r\nâ”‚   â””â”€â”€ mini-plans/\r\nâ”‚       â”œâ”€â”€ mini-plan-001.md                  # Database setup\r\nâ”‚       â”œâ”€â”€ mini-plan-002.md                  # Payment API\r\nâ”‚       â”œâ”€â”€ mini-plan-003.md                  # Security layer\r\nâ”‚       â””â”€â”€ decomposition-manifest.md         # How to execute them\r\nâ””â”€â”€ codebase-analysis/                        # (if existing project)\r\n    â””â”€â”€ summary-2024-01-24.md                 # Architecture notes\r\n```\r\n\r\n## What Always Gets Covered?\r\n\r\nEvery feature plan includes mandatory analysis of:\r\n\r\n- âœ… **Security** - OWASP TOP 10 vulnerabilities\r\n- âœ… **Scalability** - Can it handle growth?\r\n- âœ… **Performance** - Will it be fast?\r\n- âœ… **Logging** - Can we see what's happening?\r\n- âœ… **Containerization** - How does it deploy?\r\n- âœ… **TDD** - Test-driven development (HARD REQUIREMENT)\r\n\r\nPlus: Tech stack, databases, APIs, authentication, monitoring, CI/CD, error handling, and more.\r\n\r\n## Supported Tech Stacks\r\n\r\n| Language | Backend | Frontend | Testing |\r\n|----------|---------|----------|---------|\r\n| **.NET** | ASP.NET Core, Minimal APIs | Blazor Server/WASM/Hybrid | xUnit, NUnit, MSTest, bUnit |\r\n| **Node.js** | Express, Fastify, NestJS | React, Vue, Next.js, Angular | Jest, Mocha, Vitest, Cypress |\r\n\r\n## How It Uses AI\r\n\r\n- **Claude Opus 4.5** with Extended Thinking (deep analysis)\r\n- **Greenfield mode**: Questions assume a new project\r\n- **Brownfield mode**: Analyzes your existing codebase first\r\n\r\n## Why This Works\r\n\r\nâœ¨ **Smart Decomposition** - Breaks big plans into chunks Claude can handle (30k-80k tokens)  \r\nðŸ”’ **Security First** - OWASP TOP 10 analysis in every plan  \r\nðŸ§ª **TDD Built-in** - Testing requirements in every mini-plan  \r\nâš¡ **Run in Parallel** - Independent parts execute simultaneously  \r\nðŸ†• **Greenfield & Existing** - Works with new projects or existing codebases  \r\nðŸ§  **Deep Thinking** - Uses Claude's extended thinking for better decisions\r\n\r\n## Updates\r\n\r\nStay up to date with the latest features and improvements:\r\n\r\n```\r\n/plugin marketplace update\r\n```\r\n\r\nWe continuously improve the plugin with new features, bug fixes, and enhancements. Check the [GitHub releases](https://github.com/NSFWteam/skill-feature-dev/releases) to see what's new.\r\n\r\n## Future Enhancements\r\n\r\n- [ ] GitHub Copilot CLI integration\r\n- [ ] Real-time token tracking during execution\r\n- [ ] Visual progress dashboards\r\n- [ ] Integration with project management tools\r\n- [ ] Template library for common feature patterns\r\n- [ ] AI-powered mini-plan optimization based on historical data\r\n\r\n## Best Practices\r\n\r\n1. **Interview thoroughly**: The quality of your plan depends on interview completeness\r\n2. **Review comprehensive plan**: Before decomposition, validate the plan covers all needs\r\n3. **Customize integration**: Adjust tool recommendations based on your environment\r\n4. **Execute incrementally**: Run mini-plans one at a time initially to validate approach\r\n5. **Monitor token usage**: Track actual vs estimated tokens to improve future estimates\r\n\r\n## Support & Customization\r\n\r\nThis skill is highly customizable. Edit:\r\n- `prompts/*.md`: Modify interview questions or plan structure\r\n- `config/skill-config.json`: Adjust token budgets or add languages\r\n- `utils/agent-selector.js`: Add custom tool recommendation logic\r\n\r\n## License\r\n\r\nMIT\r\n\r\n---\r\n\r\n**Version**: 1.0.0  \r\n**Model**: Claude Opus 4.5 with Extended Thinking  \r\n**Platform**: Claude Code (with future GitHub Copilot support)\r\n"
      },
      "plugins": [
        {
          "name": "nsfw-feature-dev",
          "source": "./",
          "description": "Comprehensive feature development skill with interview, planning, decomposition, execution, and integration commands",
          "version": "1.0.0",
          "author": {
            "name": "NSFW Team",
            "email": "nsfw-gh.detoxify230@passmail.net"
          },
          "license": "MIT",
          "homepage": "https://github.com/NSFWteam/skill-feature-dev",
          "repository": "https://github.com/NSFWteam/skill-feature-dev",
          "keywords": [
            "feature-development",
            "planning",
            "architecture",
            "security",
            "scalability",
            "performance",
            "tdd",
            "devops"
          ],
          "category": "development",
          "commands": [
            "./.claude/commands/"
          ],
          "strict": false,
          "categories": [
            "architecture",
            "development",
            "devops",
            "feature-development",
            "performance",
            "planning",
            "scalability",
            "security",
            "tdd"
          ],
          "install_commands": [
            "/plugin marketplace add NSFWteam/skill-feature-dev",
            "/plugin install nsfw-feature-dev@nsfw-feature-dev"
          ]
        }
      ]
    }
  ]
}