{
  "author": {
    "id": "paid-tw",
    "display_name": "paid-tw",
    "avatar_url": "https://avatars.githubusercontent.com/u/256482458?v=4"
  },
  "marketplaces": [
    {
      "name": "taiwan-payment-skills",
      "version": null,
      "description": "å°ç£ç¬¬ä¸‰æ–¹é‡‘æµ Skills for AI Agents - è—æ–°é‡‘æµã€ç¶ ç•Œç§‘æŠ€ ECPayã€çµ±ä¸€é‡‘æµ PAYUNi",
      "repo_full_name": "paid-tw/skills",
      "repo_url": "https://github.com/paid-tw/skills",
      "repo_description": "å°ç£ç¬¬ä¸‰æ–¹é‡‘æµ Skills for AI Agents - è—æ–°é‡‘æµã€ç¶ ç•Œç§‘æŠ€ ECPayã€çµ±ä¸€é‡‘æµ PAYUNi",
      "signals": {
        "stars": 166,
        "forks": 13,
        "pushed_at": "2026-01-29T21:07:18Z"
      },
      "files": {
        ".claude-plugin/marketplace.json": "{\n  \"name\": \"taiwan-payment-skills\",\n  \"owner\": {\n    \"name\": \"paid-tw\",\n    \"email\": \"contact@paid.tw\"\n  },\n  \"metadata\": {\n    \"description\": \"å°ç£ç¬¬ä¸‰æ–¹é‡‘æµ Skills for AI Agents - è—æ–°é‡‘æµã€ç¶ ç•Œç§‘æŠ€ ECPayã€çµ±ä¸€é‡‘æµ PAYUNi\",\n    \"pluginRoot\": \"./plugins\"\n  },\n  \"plugins\": [\n    {\n      \"name\": \"newebpay\",\n      \"source\": \"./newebpay\",\n      \"category\": \"payment\"\n    },\n    {\n      \"name\": \"ecpay\",\n      \"source\": \"./ecpay\",\n      \"category\": \"payment\"\n    },\n    {\n      \"name\": \"payuni\",\n      \"source\": \"./payuni\",\n      \"category\": \"payment\"\n    },\n    {\n      \"name\": \"payment-help\",\n      \"source\": \"./payment-help\",\n      \"category\": \"tools\"\n    }\n  ]\n}\n",
        "README.md": "# å°ç£æ”¯ä»˜é‡‘æµ Skills\n\n[![Validate Plugins](https://github.com/paid-tw/skills/actions/workflows/validate.yml/badge.svg)](https://github.com/paid-tw/skills/actions/workflows/validate.yml)\n[![License: MIT](https://img.shields.io/badge/License-MIT-yellow.svg)](https://opensource.org/licenses/MIT)\n\nå°ç£ç¬¬ä¸‰æ–¹é‡‘æµ Skills for AI Agents - è—æ–°é‡‘æµã€ç¶ ç•Œç§‘æŠ€ ECPayã€çµ±ä¸€é‡‘æµ PAYUNi\n\næ”¯æ´ Claude Codeã€Cursorã€Codexã€GitHub Copilot ç­‰ AI coding agentsã€‚\n\n## æ”¯æ´çš„æ”¯ä»˜æœå‹™\n\n| æœå‹™ | Plugin | ç‹€æ…‹ | èªªæ˜ |\n|------|--------|------|------|\n| è—æ–°é‡‘æµ | `newebpay` | âœ… å¯ç”¨ | ä¿¡ç”¨å¡ã€LINE Payã€Apple Payã€ATMã€è¶…å•† |\n| ç¶ ç•Œç§‘æŠ€ | `ecpay` | ğŸš§ é–‹ç™¼ä¸­ | å…¨æ–¹ä½é‡‘æµã€é›»å­ç™¼ç¥¨ |\n| PAYUNi | `payuni` | ğŸš§ é–‹ç™¼ä¸­ | çµ±ä¸€é›†åœ˜é‡‘æµæœå‹™ |\n\n## å®‰è£\n\n### æ–¹å¼ä¸€ï¼šnpx skillsï¼ˆæ¨è–¦ï¼‰\n\nä½¿ç”¨ [skills CLI](https://skills.sh) é¸æ“‡æ€§å®‰è£éœ€è¦çš„ skillsï¼š\n\n```bash\n# æŸ¥çœ‹å¯ç”¨çš„ skills\nnpx skills add paid-tw/skills --list\n\n# é¸æ“‡æ€§å®‰è£\nnpx skills add paid-tw/skills --skill newebpay      # åªè£è—æ–°é‡‘æµ\nnpx skills add paid-tw/skills --skill ecpay         # åªè£ç¶ ç•Œç§‘æŠ€\nnpx skills add paid-tw/skills --skill payuni        # åªè£ PAYUNi\n\n# å®‰è£å¤šå€‹\nnpx skills add paid-tw/skills --skill newebpay ecpay\n\n# å®‰è£å…¨éƒ¨\nnpx skills add paid-tw/skills --all\n```\n\næ”¯æ´å¤šç¨® AI coding agentsï¼šClaude Codeã€Cursorã€Codexã€GitHub Copilotã€Antigravityã€Roo Code ç­‰ã€‚\n\n### æ–¹å¼äºŒï¼šClaude Code Plugin\n\n```bash\n# 1. æ–°å¢ marketplace\n/plugin marketplace add paid-tw/skills\n\n# 2. é¸æ“‡æ€§å®‰è£éœ€è¦çš„ plugin\n/plugin install newebpay@taiwan-payment-skills    # è—æ–°é‡‘æµ\n/plugin install ecpay@taiwan-payment-skills       # ç¶ ç•Œç§‘æŠ€\n/plugin install payuni@taiwan-payment-skills      # PAYUNi\n\n# æˆ–å®‰è£ help plugin æŸ¥çœ‹æ‰€æœ‰é¸é …\n/plugin install payment-help@taiwan-payment-skills\n```\n\n### æ–¹å¼ä¸‰ï¼šæ‰‹å‹•å®‰è£\n\n```bash\n# ä¸‹è¼‰ä¸¦å®‰è£ç‰¹å®š skill\ngit clone --depth 1 https://github.com/paid-tw/skills.git /tmp/paid-tw-skills\ncp -r /tmp/paid-tw-skills/plugins/newebpay/skills/newebpay ~/.claude/skills/\nrm -rf /tmp/paid-tw-skills\n```\n\n## å¿«é€Ÿé–‹å§‹\n\nä¸ç¢ºå®šå¾å“ªé–‹å§‹ï¼Ÿå®‰è£ `payment-help` skillï¼š\n\n```bash\nnpx skills add paid-tw/skills --skill payment-help\n```\n\nç„¶å¾Œå• Claudeï¼š\n\n```\nå°ç£æœ‰å“ªäº›é‡‘æµå¯ä»¥ç”¨ï¼Ÿ\n```\n\næˆ–è¼¸å…¥ `/payment-help` æŸ¥çœ‹æ‰€æœ‰å¯ç”¨çš„ skillsã€‚\n\n## å¯ç”¨çš„ Skills\n\n### payment-help\n\nåˆ—å‡ºæ‰€æœ‰å¯ç”¨çš„æ”¯ä»˜ skills å’Œæ¨è–¦ã€‚\n\n**è§¸ç™¼æ–¹å¼**ï¼šèªªã€Œå°ç£é‡‘æµã€ã€Œæ”¯ä»˜æ•´åˆã€ã€Œå“ªå€‹é‡‘æµæ¯”è¼ƒå¥½ã€\n\n### newebpayï¼ˆè—æ–°é‡‘æµï¼‰\n\nå®‰è£ `newebpay` plugin å¾Œå¯ä½¿ç”¨ä»¥ä¸‹ skillsï¼š\n\n| Skill | èªªæ˜ | ä½¿ç”¨æ™‚æ©Ÿ |\n|-------|------|---------|\n| `/newebpay` | ç¸½è¦½èˆ‡ç’°å¢ƒè¨­å®š | åˆæ¬¡äº†è§£ã€ç’°å¢ƒè¨­å®š |\n| `/newebpay-checkout` | MPG å¹•å‰æ”¯ä»˜ä¸²æ¥ | å»ºç«‹äº¤æ˜“ã€æ•´åˆæ”¯ä»˜é é¢ |\n| `/newebpay-query` | äº¤æ˜“æŸ¥è©¢ API | æŸ¥è©¢è¨‚å–®ç‹€æ…‹ |\n| `/newebpay-refund` | é€€æ¬¾ API | ä¿¡ç”¨å¡/é›»å­éŒ¢åŒ…é€€æ¬¾ |\n\n**è§¸ç™¼é—œéµå­—**ï¼šè—æ–°ã€NewebPayã€è—æ–°é‡‘æµ\n\n**æ”¯æ´çš„æ”¯ä»˜æ–¹å¼**ï¼š\n- ä¿¡ç”¨å¡ï¼ˆä¸€æ¬¡ä»˜æ¸…ã€åˆ†æœŸã€ç´…åˆ©ï¼‰\n- è¡Œå‹•æ”¯ä»˜ï¼ˆLINE Payã€Apple Payã€Google Payï¼‰\n- ATM è½‰å¸³ã€è¶…å•†ä»£ç¢¼/æ¢ç¢¼\n\n### ecpay\n\nğŸš§ é–‹ç™¼ä¸­\n\n### payuni\n\nğŸš§ é–‹ç™¼ä¸­\n\n## ä½¿ç”¨æ–¹å¼\n\nå®‰è£å¾Œï¼Œæœ‰ä¸‰ç¨®æ–¹å¼ä½¿ç”¨ï¼š\n\n### 1. è‡ªå‹•è§¸ç™¼\n\nåœ¨å°è©±ä¸­æåˆ°ç›¸é—œé—œéµå­—æ™‚ï¼ŒClaude æœƒè‡ªå‹•è¼‰å…¥å°æ‡‰çš„ skillï¼š\n\n```\n> å¹«æˆ‘ä¸²æ¥è—æ–°é‡‘æµçš„ä¿¡ç”¨å¡ä»˜æ¬¾\n> æˆ‘æƒ³ç”¨ç¶ ç•Œçš„é›»å­ç™¼ç¥¨ API\n```\n\n### 2. æ‰‹å‹•å‘¼å«\n\nä½¿ç”¨ `/skillåç¨±` ç›´æ¥å‘¼å«ï¼š\n\n```\n> /newebpay\n> /ecpay\n> /payuni\n```\n\n### 3. åŠŸèƒ½å°ˆç”¨ Skillï¼ˆæ¨è–¦ï¼‰\n\nç›´æ¥å‘¼å«ç‰¹å®šåŠŸèƒ½çš„ skillï¼Œç²å¾—æœ€ç²¾æº–çš„å›ç­”ï¼š\n\n```\n> /newebpay-checkout LINE Pay   # LINE Pay ä¸²æ¥\n> /newebpay-checkout ä¿¡ç”¨å¡åˆ†æœŸ  # ä¿¡ç”¨å¡åˆ†æœŸä¸²æ¥\n> /newebpay-query               # æŸ¥è©¢äº¤æ˜“ç‹€æ…‹\n> /newebpay-refund ä¿¡ç”¨å¡        # ä¿¡ç”¨å¡é€€æ¬¾\n```\n\n### è§¸ç™¼é—œéµå­—\n\n| Skill | è§¸ç™¼é—œéµå­— |\n|-------|-----------|\n| newebpay | è—æ–°ã€NewebPayã€è—æ–°é‡‘æµ |\n| newebpay-checkout | è—æ–°ä¸²æ¥ã€å»ºç«‹äº¤æ˜“ã€MPG |\n| newebpay-query | è—æ–°æŸ¥è©¢ã€æŸ¥è©¢è¨‚å–®ã€äº¤æ˜“ç‹€æ…‹ |\n| newebpay-refund | è—æ–°é€€æ¬¾ã€ä¿¡ç”¨å¡é€€æ¬¾ã€å–æ¶ˆäº¤æ˜“ |\n| payment-help | å°ç£é‡‘æµã€æ”¯ä»˜æ•´åˆã€å“ªå€‹é‡‘æµ |\n\n## ç›®éŒ„çµæ§‹\n\n```\npaid-tw/skills/\nâ”œâ”€â”€ .claude-plugin/\nâ”‚   â””â”€â”€ marketplace.json       # Marketplace ç›®éŒ„\nâ”œâ”€â”€ plugins/\nâ”‚   â”œâ”€â”€ payment-help/          # Help plugin\nâ”‚   â”‚   â””â”€â”€ skills/payment-help/\nâ”‚   â”œâ”€â”€ newebpay/              # è—æ–°é‡‘æµ pluginï¼ˆå«å¤šå€‹ skillsï¼‰\nâ”‚   â”‚   â”œâ”€â”€ .claude-plugin/\nâ”‚   â”‚   â”‚   â””â”€â”€ plugin.json\nâ”‚   â”‚   â””â”€â”€ skills/\nâ”‚   â”‚       â”œâ”€â”€ newebpay/           # ç¸½è¦½\nâ”‚   â”‚       â”œâ”€â”€ newebpay-checkout/  # ä¸²æ¥\nâ”‚   â”‚       â”‚   â””â”€â”€ references/\nâ”‚   â”‚       â”œâ”€â”€ newebpay-query/     # æŸ¥è©¢\nâ”‚   â”‚       â””â”€â”€ newebpay-refund/    # é€€æ¬¾\nâ”‚   â”œâ”€â”€ ecpay/                 # ç¶ ç•Œç§‘æŠ€ plugin\nâ”‚   â””â”€â”€ payuni/                # PAYUNi plugin\nâ”œâ”€â”€ README.md\nâ”œâ”€â”€ AGENTS.md\nâ””â”€â”€ LICENSE\n```\n\n## è²¢ç»\n\næ­¡è¿è²¢ç»ï¼è«‹åƒé–± [è²¢ç»æŒ‡å—](docs/contributing.md)ã€‚\n\n### æ–°å¢æ”¯ä»˜æœå‹™\n\n1. Fork é€™å€‹ repo\n2. åœ¨ `plugins/` ä¸‹å»ºç«‹æ–°ç›®éŒ„\n3. å»ºç«‹ `.claude-plugin/plugin.json` å’Œ `skills/<name>/SKILL.md`\n4. æ›´æ–° `.claude-plugin/marketplace.json`\n5. æäº¤ Pull Request\n\n## æ³¨æ„äº‹é …\n\n- å„æ”¯ä»˜æœå‹™çš„ API æ–‡ä»¶ç‰ˆæ¬Šæ­¸åŸæ¥­è€…æ‰€æœ‰\n- è«‹ä»¥å„æ¥­è€…å®˜æ–¹æœ€æ–°æ–‡ä»¶ç‚ºæº–\n- HashKeyã€HashIV ç­‰æ•æ„Ÿè³‡è¨Šè«‹å¦¥å–„ä¿ç®¡ï¼Œä¸å¯æš´éœ²æ–¼å‰ç«¯\n\n## ç›¸é—œè³‡æº\n\n- [è—æ–°é‡‘æµ](https://www.newebpay.com)\n- [ç¶ ç•Œç§‘æŠ€](https://www.ecpay.com.tw)\n- [PAYUNi](https://www.payuni.com.tw)\n\n## Contributors\n\n- [@_linyiru](https://www.threads.com/@_linyiru)\n- [@handbro666](https://www.threads.com/@handbro666)\n\n## æˆæ¬Š\n\nMIT License\n\n---\n\nMade with â¤ï¸ for Taiwan developers\n"
      },
      "plugins": [
        {
          "name": "newebpay",
          "source": "./newebpay",
          "category": "payment",
          "description": null,
          "categories": [
            "payment"
          ],
          "install_commands": [
            "/plugin marketplace add paid-tw/skills",
            "/plugin install newebpay@taiwan-payment-skills"
          ]
        },
        {
          "name": "ecpay",
          "source": "./ecpay",
          "category": "payment",
          "description": null,
          "categories": [
            "payment"
          ],
          "install_commands": [
            "/plugin marketplace add paid-tw/skills",
            "/plugin install ecpay@taiwan-payment-skills"
          ]
        },
        {
          "name": "payuni",
          "source": "./payuni",
          "category": "payment",
          "description": null,
          "categories": [
            "payment"
          ],
          "install_commands": [
            "/plugin marketplace add paid-tw/skills",
            "/plugin install payuni@taiwan-payment-skills"
          ]
        },
        {
          "name": "payment-help",
          "source": "./payment-help",
          "category": "tools",
          "description": null,
          "categories": [
            "tools"
          ],
          "install_commands": [
            "/plugin marketplace add paid-tw/skills",
            "/plugin install payment-help@taiwan-payment-skills"
          ]
        }
      ]
    }
  ]
}