{
  "author": {
    "id": "ROUCHER27",
    "display_name": "ROUCHER27",
    "avatar_url": "https://avatars.githubusercontent.com/u/152842631?u=b8017aca363ee79f52792089cb5300a674552bff&v=4"
  },
  "marketplaces": [
    {
      "name": "roucher27-plugins",
      "version": null,
      "description": "Personal knowledge management and productivity plugins for Claude Code",
      "repo_full_name": "ROUCHER27/GO-Obsidian",
      "repo_url": "https://github.com/ROUCHER27/GO-Obsidian",
      "repo_description": "Go Obsidian is a Skill that automatically converts blogs, tweets, technical documentation, or papers into structured Obsidian notes. It not only generates Markdown summaries but also creates visual Canvas knowledge maps and helps you track reading progress through a Reading Tracker. ",
      "signals": {
        "stars": 5,
        "forks": 1,
        "pushed_at": "2026-01-30T15:31:10Z"
      },
      "files": {
        ".claude-plugin/marketplace.json": "{\n  \"name\": \"roucher27-plugins\",\n  \"owner\": {\n    \"name\": \"ROUCHER27\"\n  },\n  \"metadata\": {\n    \"description\": \"Personal knowledge management and productivity plugins for Claude Code\",\n    \"version\": \"1.0.0\"\n  },\n  \"plugins\": [\n    {\n      \"name\": \"go-obsidian\",\n      \"source\": \"./plugins/go-obsidian\",\n      \"description\": \"Transform any article into structured Obsidian notes with visual Canvas diagrams and reading progress management\",\n      \"version\": \"1.0.0\",\n      \"author\": {\n        \"name\": \"ROUCHER27\"\n      },\n      \"repository\": \"https://github.com/ROUCHER27/GO-Obsidian\",\n      \"license\": \"MIT\",\n      \"tags\": [\"obsidian\", \"knowledge-management\", \"reading\", \"summarization\", \"canvas\", \"productivity\"]\n    }\n  ]\n}\n",
        "README.md": "# Go-Obsidian\n\nEnglish | [ä¸­æ–‡](https://github.com/ROUCHER27/GO-Obsidian/blob/main/README_CN.md)\n> An agent Skill that transforms any article into structured Obsidian notes with visual Canvas diagrams and reading progress management\n\n![startpage](startpage.png)\n\n[![Claude Code](https://img.shields.io/badge/Claude%20Code-Compatible-purple.svg)](https://claude.ai) [![Obsidian](https://img.shields.io/badge/Obsidian-Plugin--Ready-7C3AED.svg)](https://obsidian.md) [![License: MIT](https://img.shields.io/badge/License-MIT-blue.svg)](LICENSE.md) \n\nIn the age of information explosion, we consume vast amounts of technical blogs, academic papers, social media threads, and official documentation every day. But reading is just the beginningâ€”true knowledge accumulation happens when we organize and connect these fragments.\n\ngo-obsidian is a Skill that goes beyond simple article summarization. It's your **personal knowledge management assistant**:\n\n- **It learns your note-taking style** â€” By analyzing your existing Obsidian vault, it automatically masters your tagging habits, Callout preferences, and Canvas color schemes (it adapts to you, not the other way around)\n- **It creates visual knowledge graphs** â€” Transforming complex article content into structured Canvas diagrams that make knowledge relationships clear at a glance\n- **It tracks your reading progress** â€” Through an intelligent database that automatically indexes all reading notes, letting you track your learning journey anytime\n- **It maintains fidelity to the source** â€” No over-interpretation, no adding opinions not present in the original text, ensuring information integrity\n\nSimply provide a URL or file path, and go-obsidian will generate a professional, structured reading note that matches your personal style, saved directly to your Obsidian vault. This Skill helps you efficiently capture fragmented information, build a habit of consistent reading and learning, and build your own knowledge base for LLM/Agent/yourself.\n\n## Features\n\n- ğŸŒ **Content Fetching** â€” Fetch and parse blogs, tweets, papers, and technical docs via WebFetch\n- ğŸ“ **Deep Summarization** â€” Generate faithful, structured Markdown notes following your style\n- ğŸ¨ **Visual Canvas** â€” Create knowledge structure diagrams with color-coded nodes\n- ğŸ“Š **Reading Tracker** â€” Bases database for indexing and tracking reading progress\n- ğŸ§  **Habit Learning** â€” Auto-learn and follow your note style, tags, and preferences\n\n## Quick Start\n\n### Installation\n\n**Method 1: Via Plugin Marketplace (Recommended)**\n\nAdd the marketplace and install the plugin:\n```bash\n/plugin marketplace add roucher27/go-obsidian\n/plugin install go-obsidian@roucher27-plugins\n```\n\n**Method 2: Local Installation (For Development)**\n\nClone this repository and add as a local marketplace:\n```bash\ngit clone https://github.com/ROUCHER27/GO-Obsidian.git\ncd GO-Obsidian\n/plugin marketplace add .\n/plugin install go-obsidian@roucher27-plugins\n```\n\n### Basic Usage\n\nSimply provide a URL or file path to Claude Code:\n\n```\nSummarize this article: https://example.com/interesting-blog-post\n```\n\nClaude will:\n1. Scan your Obsidian vault for main content patterns (first use)\n2. Learn your note-taking habits and continuously update its understanding of you\n3. Fetch and analyze the content\n4. Generate a structured `.md` summary\n5. Optionally create a visual `.canvas` diagram\n6. Define note properties to update the Reading Tracker\n\n## How It Works\n\n![workflow](workflow.png)\n> ğŸ’¡ *Made by Go-Obsidian*\n\n## Project Structure\n\n```\nGO-Obsidian/\nâ”œâ”€â”€ .claude-plugin/\nâ”‚   â””â”€â”€ marketplace.json     # Plugin marketplace configuration\nâ”œâ”€â”€ plugins/\nâ”‚   â””â”€â”€ go-obsidian/         # Main plugin directory\nâ”‚       â”œâ”€â”€ .claude-plugin/\nâ”‚       â”‚   â””â”€â”€ plugin.json  # Plugin manifest\nâ”‚       â”œâ”€â”€ skills/\nâ”‚       â”‚   â””â”€â”€ go-obsidian/\nâ”‚       â”‚       â””â”€â”€ SKILL.md # Main skill definition\nâ”‚       â”œâ”€â”€ rules/           # Rule definitions\nâ”‚       â”‚   â”œâ”€â”€ canvas.md            # Canvas layout specifications\nâ”‚       â”‚   â”œâ”€â”€ content-types.md     # Content type detection rules\nâ”‚       â”‚   â”œâ”€â”€ fidelity.md          # Source fidelity guidelines\nâ”‚       â”‚   â””â”€â”€ frontmatter.md       # Frontmatter conventions\nâ”‚       â”œâ”€â”€ syntax/          # Syntax specifications\nâ”‚       â”‚   â”œâ”€â”€ obsidian-markdown.md # Obsidian Markdown syntax\nâ”‚       â”‚   â”œâ”€â”€ json-canvas.md       # JSON Canvas specification\nâ”‚       â”‚   â””â”€â”€ obsidian-bases.md    # Obsidian Bases syntax\nâ”‚       â”œâ”€â”€ templates/       # Template files\nâ”‚       â”‚   â”œâ”€â”€ canvas.json          # Canvas template\nâ”‚       â”‚   â”œâ”€â”€ reading-tracker.base # Reading tracker template\nâ”‚       â”‚   â””â”€â”€ summary.md           # Summary note template\nâ”‚       â”œâ”€â”€ scripts/\nâ”‚       â”‚   â””â”€â”€ validate-canvas.sh   # Canvas validation script\nâ”‚       â”œâ”€â”€ user-habits.md   # User preferences (auto-learned)\nâ”‚       â””â”€â”€ references.md    # Official documentation links\nâ”œâ”€â”€ README.md                # Project documentation\nâ”œâ”€â”€ LICENSE.md               # MIT License\nâ””â”€â”€ *.png                    # Screenshots and workflow diagrams\n```\n\n## Configuration\n\n### User Habits (`user-habits.md`)\n\nThis file stores your personal note-taking preferences:\n\n- **Frontmatter habits** â€” Your preferred YAML properties and tag naming conventions (these settings are used by the Reading Tracker for configuration and indexing)\n- **Tag naming** â€” The organizational architecture of your tags, mainly two styles:\n  - **Hierarchical**: Uses slash nesting, e.g., `#AI/LLM`, `#Programming/Python`, suitable for scenarios requiring fine-grained categorization\n  - **Flat**: Uses hyphens or underscores, e.g., `#AI-LLM`, `#Python_Programming`, suitable for fewer tags and pursuing simplicity\n- **Callout usage** â€” Your preferred callout types. Here are common Obsidian Callout types and their icons:\n\n  | Type | Icon | Purpose |\n  |------|------|---------|\n  | `[!info]` | â„¹ï¸ | Information, background context |\n  | `[!tip]` | ğŸ’¡ | Tips, best practices |\n  | `[!warning]` | âš ï¸ | Warnings, potential issues |\n  | `[!important]` | â— | Important content, core points |\n  | `[!quote]` | ğŸ“œ | Original quotes, excerpts |\n  | `[!note]` | ğŸ“ | Supplementary notes, personal thoughts |\n  | `[!success]` | âœ… | Success indicators, correct practices |\n  | `[!question]` | â“ | Questions, items to confirm |\n\n- **Canvas style** â€” Color schemes (at least 3 colors required), node sizes, layout direction (top-to-bottom or left-to-right)\n- **File naming** â€” Your naming conventions, such as `{Title} - Reading Notes.md` for notes or `YYYY-MM-DD` date format\n- **Linking habits** â€” Your preference between Wikilinks (`[[Note]]`) vs Markdown links (`[Note](path)`), and alias usage (`[[Note|Display Name]]`)\n\nThe file is automatically populated on first use by scanning your existing vault. You can also manually adjust preferences at any time.\n\n### Rules Directory\n\nThis directory defines the \"instruction set\" for how you want the Agent to execute tasks.\n\n- **canvas.md** â€” Defines Canvas visual style specifications: color schemes (minimum 3 colors), node sizes, layout direction, edge connections. For example, you can specify title nodes in blue, core concepts in green, and summaries in purple.\n\n- **content-types.md** â€” Processing strategies for different content types:\n  - Blog/Technical Articles: Extract core arguments, code examples, practical recommendations\n  - Papers: Preserve abstracts, methods, formulas, experimental results\n  - Tweets/Threads: Focus on original post content, extract key links\n  - Technical Docs: Organize quick starts, core features, API usage, common pitfalls\n  - You can also specify: \"Ask me before generating a Canvas for blog posts\"\n\n- **fidelity.md** â€” Content fidelity principles ensuring the Agent doesn't distort the original text:\n  - âœ… Must preserve: Core arguments, key original expressions, data evidence, formulas, source attribution\n  - âŒ Forbidden: Adding views not in original, over-simplifying to distortion, changing author's stance\n  - Special use case support: If you want analysis from a specific perspective (e.g., \"Evaluate this product from a marketing angle\"), you can add instructions here\n\n- **frontmatter.md** â€” Defines note metadata conventions, essential for the Reading Tracker to index notes correctly:\n  - Required fields: `title`, `date`, `source`, `type` (blog/paper/tweet/doc), `status` (unread/reading/done), `progress` (0-100), `tags` (must include `reading-notes`)\n  - Optional fields: `author`, `aliases`, `created`, etc.\n\n### Syntax Directory\n\nSyntax specification files derived from [kepano/obsidian-skills](https://github.com/kepano/obsidian-skills), including:\n- **obsidian-markdown.md** â€” Obsidian Flavored Markdown syntax (Wikilinks, Embeds, Callouts, Properties)\n- **json-canvas.md** â€” JSON Canvas file format specification (node types, edge properties, color codes)\n- **obsidian-bases.md** â€” Obsidian Bases database syntax (filters, formulas, view configurations)\n\nThese files provide the Agent with complete Obsidian ecosystem syntax references, ensuring generated files are properly formatted and compatible.\n\n### Templates Directory\n\nContains template files for Canvas, Summary, and Reading Tracker:\n- **canvas.json** â€” Canvas structure template defining default layouts and color schemes for title nodes, concept nodes, content nodes, and summary nodes\n- **reading-tracker.base** â€” Reading tracker database template with filters (only shows `#reading-notes` tagged files), formulas (status icons, progress bars, day calculations), and views (group by type, group by status, recent reading)\n- **summary.md** â€” Note template with YAML Frontmatter, source info Callout, core content area, \"My Thoughts\" placeholder, etc.\n\nIf you need to add fixed content to generated notes (like copyright notices, related links, personal ratings), modify these templates directly. **Note**: After modifying templates, remember to sync the corresponding rule files in `rules/` to ensure consistency.\n\n### Scripts Directory\n\nProvides automation script tools, currently containing:\n- **validate-canvas.sh** â€” Canvas validation script for checking if generated `.canvas` files meet specifications:\n  - JSON syntax validation (quote escaping, commas, bracket matching)\n  - Color usage validation (ensures at least 3 different colors used)\n  - Node ID uniqueness check\n  - Edge reference validity check (ensures `fromNode` and `toNode` point to real nodes)\n\nRunning this script can detect Canvas file format issues early, improving the success rate of one-shot generation.\n\n### Reading Tracker\n\nThe `Reading Tracker.base` file is an Obsidian Bases database that **automatically indexes** all notes with the `#reading-notes` tag in your vaultâ€”no manual maintenance required. Whenever go-obsidian generates a new reading note, it automatically appears in the tracker.\n\n**Core Features**:\n- **Smart Filtering** â€” Only shows notes tagged with `#reading-notes`, automatically excluding other daily notes\n- **Visual Progress** â€” Progress bars visually display reading completion for each note\n- **Status Icons** â€” Icons distinguish unread (ğŸ“–), reading (ğŸ‘€), and completed (âœ…) states\n- **Source Icons** â€” Automatically identifies different source types: blog (ğŸ“), paper (ğŸ“„), tweet (ğŸ’¬), doc (ğŸ“š)\n- **Time Tracking** â€” Shows days since last reading, helping you manage review cycles\n\n**Three View Modes**:\n\n| View | Description | Use Case |\n|------|-------------|----------|\n| All Notes | Overview grouped by source type (blog/paper/tweet/doc) | Browse overall reading history |\n| By Status | Grouped by reading progress (unread/reading/done) | Manage reading todo list |\n| Recent Reading | Notes active (created or updated) in last 7 days | View recent learning activity |\n\n**How It Works**:\nThe Reading Tracker achieves intelligent indexing by reading the `type`, `status`, and `progress` fields from note Frontmatter. This is why these fields must be properly filled in as required by `rules/frontmatter.md`.\n\n## Tools Used\n\n| Tool | Purpose |\n|------|---------|\n| WebFetch | Fetch web content |\n| Read | Read local PDF/papers, learn vault habits |\n| Glob | Scan vault for .md/.canvas files |\n| Write | Create .md and .canvas files |\n| Edit | Update user-habits.md |\n\n## Acknowledgments\n\nSpecial thanks to [@kepano](https://github.com/kepano) for the excellent open-source Skill documentation and for creating such a great product. I believe it is one of the best AI interfaces of this era.\n\n## License\n\nMIT License â€” see [LICENSE](LICENSE.md) for details.\n\n---\n\n<p align=\"center\">\n  Made with â¤ï¸ for the Obsidian community\n</p>\n"
      },
      "plugins": [
        {
          "name": "go-obsidian",
          "source": "./plugins/go-obsidian",
          "description": "Transform any article into structured Obsidian notes with visual Canvas diagrams and reading progress management",
          "version": "1.0.0",
          "author": {
            "name": "ROUCHER27"
          },
          "repository": "https://github.com/ROUCHER27/GO-Obsidian",
          "license": "MIT",
          "tags": [
            "obsidian",
            "knowledge-management",
            "reading",
            "summarization",
            "canvas",
            "productivity"
          ],
          "categories": [
            "canvas",
            "knowledge-management",
            "obsidian",
            "productivity",
            "reading",
            "summarization"
          ],
          "install_commands": [
            "/plugin marketplace add ROUCHER27/GO-Obsidian",
            "/plugin install go-obsidian@roucher27-plugins"
          ]
        }
      ]
    }
  ]
}