{
  "author": {
    "id": "signalwire",
    "display_name": "SignalWire",
    "avatar_url": "https://avatars.githubusercontent.com/u/34925332?v=4"
  },
  "marketplaces": [
    {
      "name": "signalwire",
      "version": null,
      "description": "SignalWire development tools and knowledge base for building communication applications",
      "repo_full_name": "signalwire/signalwire-claude",
      "repo_url": "https://github.com/signalwire/signalwire-claude",
      "repo_description": "A Claude Code skill that turns Claude into a SignalWire expert",
      "signals": {
        "stars": 4,
        "forks": 3,
        "pushed_at": "2025-12-17T05:59:00Z"
      },
      "files": {
        ".claude-plugin/marketplace.json": "{\n  \"name\": \"signalwire\",\n  \"owner\": {\n    \"name\": \"SignalWire\",\n    \"email\": \"support@signalwire.com\"\n  },\n  \"metadata\": {\n    \"description\": \"SignalWire development tools and knowledge base for building communication applications\",\n    \"version\": \"1.0.0\"\n  },\n  \"plugins\": [\n    {\n      \"name\": \"signalwire-builder\",\n      \"source\": {\n        \"source\": \"github\",\n        \"repo\": \"signalwire/signalwire-claude\"\n      },\n      \"description\": \"Expert knowledge for building SignalWire applications including all SDKs, REST APIs, SWML, Relay/Fabric, AI Agents, and modern JSON/YAML-based communication systems. Includes 110+ Python examples, 24+ JavaScript examples, 44+ SWML examples, and 19 comprehensive workflow guides.\",\n      \"version\": \"1.0.0\",\n      \"author\": {\n        \"name\": \"SignalWire\",\n        \"email\": \"support@signalwire.com\"\n      },\n      \"repository\": \"https://github.com/signalwire/signalwire-claude\",\n      \"tags\": [\n        \"signalwire\",\n        \"telephony\",\n        \"messaging\",\n        \"video\",\n        \"ai-agents\",\n        \"voice-ai\",\n        \"swml\",\n        \"swaig\",\n        \"python\",\n        \"javascript\",\n        \"webrtc\"\n      ]\n    }\n  ]\n}\n",
        ".claude-plugin/plugin.json": "{\n  \"name\": \"signalwire-builder\",\n  \"version\": \"1.0.0\",\n  \"description\": \"Expert knowledge for building SignalWire applications including all SDKs, REST APIs, SWML, Relay/Fabric, AI Agents, and modern JSON/YAML-based communication systems\",\n  \"author\": {\n    \"name\": \"SignalWire\",\n    \"email\": \"support@signalwire.com\",\n    \"url\": \"https://github.com/signalwire\"\n  },\n  \"repository\": \"https://github.com/signalwire/signalwire-claude\"\n}\n",
        "README.md": "# SignalWire Builder - Claude Code Plugin\n\nA comprehensive Claude Code plugin that transforms Claude into an expert SignalWire developer, combining complete API documentation with practical production knowledge from real-world deployments.\n\n## Quick install\n\nFrom inside a Claude Code session:\n\n```bash\n/plugin marketplace add signalwire/signalwire-claude\n/plugin install signalwire-builder\n```\n\n## Features\n\n- **Complete API Coverage**: All SignalWire REST APIs, SWML, Relay SDK, AI Agents SDK, Video API (excludes deprecated LAML/CXML)\n- **Practical Production Knowledge**: Best practices, patterns, and anti-patterns from 89 SignalWire training videos\n- **Multi-Language Examples**: 110+ Python examples, 24+ JavaScript examples, 44+ SWML examples\n- **Workflow-Organized**: Find what you need by developer workflow (calling, messaging, video, AI, etc.)\n- **Production-Ready Code**: Complete working examples with error handling and security best practices\n- **Real-World Patterns**: IVR systems, AI agents, video conferencing, context-aware transfers, MFA implementation\n\n## What's Included\n\n### Core Workflows (14,800+ lines of documentation)\n\nEach workflow combines technical API documentation with practical implementation guidance:\n\n**Telephony Core:**\n1. **Authentication & Setup** - Credentials, MFA patterns, metadata for security, token management\n2. **Outbound Calling** - REST API, CRM integration, appointment reminders, healthcare workflows\n3. **Inbound Call Handling** - Complete SWML reference, loop protection, variable management, IVR patterns\n4. **Call Control** - Context-aware transfers, screen pop, recording best practices, conference management\n5. **Messaging** - SMS/MMS, Campaign Registry, templates, opt-in/opt-out, Relay SDK v4\n6. **Video** - WebRTC integration, room management, Browser SDK, click-to-call widgets\n7. **Fabric & Relay** - Subscribers, resource architecture, context routing, high availability\n8. **Webhooks & Events** - Post-prompt analytics, webhook testing, transcription integration\n9. **Number Management** - Campaign Registry compliance, number association, bulk management\n\n**AI Voice Agents (Voice AI):**\n- **Voice AI Overview** - Navigation hub and decision guide for AI agents\n- **AI Agent SDK Basics** - Python SDK fundamentals, installation, tool decorator\n- **AI Agent Prompting** - Best practices, RISE-M framework, anti-patterns\n- **AI Agent Functions** - SWAIG patterns, progressive knowledge building, DataMap\n- **AI Agent Deployment** - Traditional server, Docker, serverless (Lambda/GCF/Azure)\n- **AI Agent Patterns** - Common reusable flows (data lookup, confirmation, MFA)\n- **AI Agent Error Handling** - Robust error handling patterns\n- **AI Agent Security** - Authentication, input validation, secrets management\n- **AI Agent Testing** - swaig-test CLI, pytest patterns, integration testing\n- **AI Agent Debug Webhooks** - Real-time monitoring and debugging\n\n### What Makes This Skill Different\n\n**Technical Knowledge (What APIs Do):**\n- REST API endpoints and parameters\n- SWML method reference\n- SDK function signatures\n- Authentication formats\n\n**Practical Knowledge (How to Best Use Them):**\n- Best practices from production deployments\n- Common patterns and real-world examples\n- Anti-patterns and mistakes to avoid\n- Testing and debugging strategies\n- Performance optimization techniques\n- Security patterns (metadata, encryption, MFA)\n\n### Knowledge Sources\n\n- **Technical Documentation**: Official SignalWire REST APIs, SWML, SDKs\n- **Practical Wisdom**: Analysis of 89 SignalWire training videos including:\n  - LiveWire sessions\n  - SignalWire in Seconds tutorials\n  - ClueCon 2025 workshops\n  - Digital Employees examples\n  - Production deployment case studies\n\n### Key Principles Documented\n\n1. **Treat AI Like a Person, Not a Program** - \"How would you instruct your mother?\" approach\n2. **Use Metadata for Security** - Keep sensitive data out of LLM context\n3. **Test Continuously** - AI behavior is probabilistic\n4. **Preserve Context Through Transfers** - 72% of customers expect it\n5. **Implement Loop Protection** - Always protect gather/prompt nodes\n\n## Installation\n\n### Option 1: Install from Marketplace (Recommended)\n\nInstall the plugin directly using Claude Code:\n\n```bash\n/plugin marketplace add signalwire/signalwire-claude\n/plugin install signalwire-builder\n```\n\nThe plugin will be installed to `~/.claude/plugins/signalwire-builder/` and will be available in all your Claude Code sessions.\n\n### Option 2: Manual Installation\n\nClone the repository and install manually:\n\n```bash\n# Clone the repository\ngit clone https://github.com/signalwire/signalwire-claude.git\ncd signalwire-claude\n\n# Run installer\n./install.sh\n```\n\n### Verify Installation\n\nRestart Claude Code after installation. The plugin will automatically activate when you work with SignalWire applications.\n\n## Usage\n\nOnce installed, Claude will automatically use this plugin when:\n\n- Building telephony, messaging, or video applications with SignalWire\n- Working with SignalWire REST APIs, SWML, or SDKs\n- Implementing AI agents or voice AI features\n- Setting up Call Fabric, Relay applications, or Subscribers\n- Debugging SignalWire webhooks or API responses\n- Answering questions about SignalWire capabilities or best practices\n\nThe plugin activates automatically based on your conversation context - no manual invocation needed.\n\n## Examples of What Claude Can Do\n\n### Generate Complete SWML IVR with Best Practices\n\n```\nYou: \"Create an IVR system that routes to sales, support, or billing\"\nClaude: [Generates complete SWML with proper structure, loop protection, error handling,\n         and variable management following production best practices]\n```\n\n### Write Production API Code\n\n```\nYou: \"Write Python code to send SMS with delivery tracking\"\nClaude: [Generates code with uv shebang, Campaign Registry compliance,\n         error handling, retry logic, and webhook handler]\n```\n\n### Build AI Voice Agents Following Best Practices\n\n```\nYou: \"Create a restaurant ordering AI agent with SWAIG\"\nClaude: [Uses Voice AI workflow hub to generate complete AI Agents SDK code with:\n         - Natural prompting following RISE-M framework\n         - Metadata for sensitive data (payment info)\n         - Progressive knowledge building via SWAIG functions\n         - Latency optimization with fillers\n         - Error handling and security patterns\n         - Post-prompt analytics]\n```\n\n### Implement Context-Aware Transfers\n\n```\nYou: \"Set up call transfers that preserve customer context\"\nClaude: [Generates SWAIG functions to collect context, screen pop implementation\n         for agent dashboard, and transfer patterns that never lose information]\n```\n\n### Configure Video with Security Best Practices\n\n```\nYou: \"Set up a video conference with moderator controls\"\nClaude: [Generates secure token creation, frontend client with never-expose-API-token\n         pattern, layout controls, and recording configuration]\n```\n\n## Plugin Structure\n\n```\nsignalwire-builder/\n├── .claude-plugin/\n│   ├── plugin.json                    # Plugin manifest\n│   └── marketplace.json               # Marketplace listing\n├── skills/\n│   └── signalwire/                    # SignalWire skill\n│       ├── SKILL.md                   # Main entry point (optimized, 624 words)\n│       ├── workflows/                 # 19 workflow files, 14,844 lines total\n│       │   ├── authentication-setup.md        # 593 lines: Auth, MFA, security\n│       │   ├── outbound-calling.md            # 819 lines: Dialer, CRM, reminders\n│       │   ├── inbound-call-handling.md       # 1,296 lines: SWML, loops, IVR\n│       │   ├── call-control.md                # 1,143 lines: Transfers, recording\n│       │   ├── messaging.md                   # 1,228 lines: Campaign Registry\n│       │   ├── video.md                       # 1,232 lines: WebRTC, rooms\n│       │   ├── fabric-relay.md                # 1,111 lines: Subscribers, resources\n│       │   ├── webhooks-events.md             # 1,114 lines: Analytics, testing\n│       │   ├── number-management.md           # 960 lines: Compliance\n│       │   ├── voice-ai.md                    # 444 lines: AI navigation hub\n│       │   ├── ai-agent-sdk-basics.md         # 529 lines: SDK fundamentals\n│       │   ├── ai-agent-prompting.md          # 683 lines: Best practices\n│       │   ├── ai-agent-functions.md          # 827 lines: SWAIG patterns\n│       │   ├── ai-agent-deployment.md         # 835 lines: Server/serverless\n│       │   ├── ai-agent-patterns.md           # 467 lines: Common flows\n│       │   ├── ai-agent-error-handling.md     # 391 lines: Error patterns\n│       │   ├── ai-agent-security.md           # 410 lines: Auth, secrets\n│       │   ├── ai-agent-testing.md            # 383 lines: Testing patterns\n│       │   └── ai-agent-debug-webhooks.md     # 379 lines: Monitoring\n│       └── reference/                 # SDK API docs (loaded only when needed)\n│           ├── sdk/                   # 12 files: AgentBase, SWAIG, etc.\n│           ├── deployment/            # 3 files: Serverless, env vars\n│           └── examples/              # 6 complete agent examples\n├── README.md                          # This file\n├── INSTALL.md                         # Installation guide\n├── install.sh                         # Installation script\n└── LICENSE\n```\n\nEach workflow file includes:\n- Technical API documentation\n- Best Practices sections\n- Common Patterns with complete examples\n- Anti-Patterns to avoid\n- Production Tips for deployment\n- Real-world code examples\n\n\n## Requirements\n\n- Claude Code (with skills support)\n- No additional dependencies required for the skill itself\n- For running generated code: Python 3.11+ with uv, or Node.js 18+\n\n## Updates\n\nThe skill is based on SignalWire APIs and training content as of December 2025. For the latest SignalWire features, check:\n\n- https://developer.signalwire.com/\n- https://github.com/signalwire\n\n## Contributing\n\nTo update or improve this plugin:\n\n1. Fork the repository at https://github.com/signalwire/signalwire-claude\n2. Edit the relevant workflow file in `skills/signalwire/workflows/`\n3. Follow the existing format (Technical + Practical knowledge)\n4. Include working code examples\n5. Add to Best Practices, Common Patterns, or Anti-Patterns sections\n6. Update this README if adding new workflows\n7. Test the plugin structure follows Claude Code requirements\n8. Submit a pull request\n\n## License\n\nThis project is licensed under the MIT License - see the LICENSE file for details.\n\nSignalWire is a trademark of SignalWire, Inc.\n\n## Support\n\nFor SignalWire API questions:\n- Documentation: https://developer.signalwire.com/\n- Support: https://signalwire.com/support\n\nFor plugin issues:\n- GitHub Issues: https://github.com/signalwire/signalwire-claude/issues\n- Check that files are in `~/.claude/plugins/signalwire-builder/`\n- Verify plugin.json and SKILL.md are present\n- Restart Claude Code after installation"
      },
      "plugins": [
        {
          "name": "signalwire-builder",
          "source": {
            "source": "github",
            "repo": "signalwire/signalwire-claude"
          },
          "description": "Expert knowledge for building SignalWire applications including all SDKs, REST APIs, SWML, Relay/Fabric, AI Agents, and modern JSON/YAML-based communication systems. Includes 110+ Python examples, 24+ JavaScript examples, 44+ SWML examples, and 19 comprehensive workflow guides.",
          "version": "1.0.0",
          "author": {
            "name": "SignalWire",
            "email": "support@signalwire.com"
          },
          "repository": "https://github.com/signalwire/signalwire-claude",
          "tags": [
            "signalwire",
            "telephony",
            "messaging",
            "video",
            "ai-agents",
            "voice-ai",
            "swml",
            "swaig",
            "python",
            "javascript",
            "webrtc"
          ],
          "categories": [
            "ai-agents",
            "javascript",
            "messaging",
            "python",
            "signalwire",
            "swaig",
            "swml",
            "telephony",
            "video",
            "voice-ai",
            "webrtc"
          ],
          "install_commands": [
            "/plugin marketplace add signalwire/signalwire-claude",
            "/plugin install signalwire-builder@signalwire"
          ]
        }
      ]
    }
  ]
}