{
  "author": {
    "id": "thienanblog",
    "display_name": "Ân Vũ",
    "avatar_url": "https://avatars.githubusercontent.com/u/8651688?u=cd7fde711b231bff81bf96e3c1350e1e9b523516&v=4"
  },
  "marketplaces": [
    {
      "name": "awesome-ai-agent-skills",
      "version": null,
      "description": "Community-shared skills for AI coding agents",
      "repo_full_name": "thienanblog/awesome-ai-agent-skills",
      "repo_url": "https://github.com/thienanblog/awesome-ai-agent-skills",
      "repo_description": "A curated list of essential skills, tools, and resources for building and enhancing advanced AI agents.",
      "signals": {
        "stars": 35,
        "forks": 9,
        "pushed_at": "2026-01-29T13:41:11Z"
      },
      "files": {
        ".claude-plugin/marketplace.json": "{\n  \"name\": \"awesome-ai-agent-skills\",\n  \"owner\": {\n    \"name\": \"Ân Vũ\",\n    \"email\": \"8651688+thienanblog@users.noreply.github.com\"\n  },\n  \"metadata\": {\n    \"description\": \"Community-shared skills for AI coding agents\",\n    \"version\": \"1.0.0\"\n  },\n  \"plugins\": [\n    {\n      \"name\": \"documentation-skills\",\n      \"description\": \"Skills for authoring AI agent instructions, backend documentation, and design systems.\",\n      \"source\": \"./\",\n      \"strict\": false,\n      \"skills\": [\n        \"./skills/agents-md-generator\",\n        \"./skills/documentation-guidelines\",\n        \"./skills/design-system-generator\"\n      ]\n    },\n    {\n      \"name\": \"laravel-app-skills\",\n      \"description\": \"Guidelines for building Laravel 11/12 apps across common stacks and tooling.\",\n      \"source\": \"./\",\n      \"strict\": false,\n      \"skills\": [\n        \"./skills/laravel-11-12-app-guidelines\"\n      ]\n    },\n    {\n      \"name\": \"devops-skills\",\n      \"description\": \"Skills for Docker, CI/CD, and local development environment configuration.\",\n      \"source\": \"./\",\n      \"strict\": false,\n      \"skills\": [\n        \"./skills/docker-local-dev\"\n      ]\n    },\n    {\n      \"name\": \"workflow-skills\",\n      \"description\": \"Skills for AI agent workflow and requirements clarification processes.\",\n      \"source\": \"./\",\n      \"strict\": false,\n      \"skills\": [\n        \"./skills/ask-questions-if-underspecified\"\n      ]\n    }\n  ]\n}\n",
        "README.md": "# Awesome AI Agent Skills\n\nA community-shared collection of reusable skills for AI coding agents. Works with Claude Code, Cursor, Kilo Code, Windsurf, OpenAI Codex, and any AI tools that support skills or custom instructions.\n\n## What are Skills?\n\nSkills are self-contained instruction sets that teach AI agents specific workflows, guidelines, or capabilities. Each skill includes:\n- A `SKILL.md` with metadata and instructions\n- Optional reference documentation for detailed guidance\n- Reusable across any project\n\n## Installation\n\n### Claude Code\n\n**Step 1: Add the marketplace**\n\n```\n/plugin marketplace add thienanblog/awesome-ai-agent-skills\n```\n\n**Step 2: Install skills**\n\n```\n# Install a plugin (can bundle multiple skills)\n/plugin install documentation-skills@awesome-ai-agent-skills\n\n# Install Laravel guidelines\n/plugin install laravel-app-skills@awesome-ai-agent-skills\n\n# Install Docker local development skill\n/plugin install devops-skills@awesome-ai-agent-skills\n\n# Install workflow/clarification skill\n/plugin install workflow-skills@awesome-ai-agent-skills\n```\n\n**Updating the marketplace**\n\n```\n/plugin marketplace update\n```\n\n### OpenAI Codex / Other AI Tools\n\nClone or reference this repository and point your AI tool to the `skills/` directory. Each skill follows a standard format with `SKILL.md` containing the instructions.\n\n```bash\ngit clone https://github.com/thienanblog/awesome-ai-agent-skills.git\n```\n\n### Manual Usage\n\nYou can also copy individual skill instructions directly into your AI agent's context or system prompt.\n\n## Available Skills\n\n<!-- SKILLS_TABLE_START -->\n| Skill | Author | Description |\n|-------|--------|-------------|\n| [agents-md-generator](./skills/agents-md-generator) | Official | Generate or update CLAUDE.md/AGENTS.md files for AI coding agents through auto-scanning project files combined with interactive Q&A. Supports multiple tech stacks, development environments, and preserves customizations when updating. |\n| [ask-questions-if-underspecified](./skills/ask-questions-if-underspecified) | Tibo (Codex Team) | Clarify requirements before implementing. Do not use automatically, only when invoked explicitly. |\n| [design-system-generator](./skills/design-system-generator) | Official | Generate a project-specific DESIGN_SYSTEM.md that enforces consistent UI/UX across SPAs, traditional server-rendered sites, and hybrid systems. Includes tokens, component rules, accessibility gates, and production asset/manifest guidance. |\n| [docker-local-dev](./skills/docker-local-dev) | Official | Generate Docker Compose and Dockerfile configurations for local development through interactive Q&A. Supports PHP/Laravel, WordPress, Drupal, Joomla, Node.js, and Python stacks with Nginx, Supervisor/PM2, databases, Redis, and email testing. Always asks clarifying questions before generating configurations. |\n| [documentation-guidelines](./skills/documentation-guidelines) | Official | Write or update backend feature documentation that follows a repo's DOCUMENTATION_GUIDELINES.md (or equivalent) across any project. Use when asked to create/update module docs, API contracts, or backend documentation that must include architecture, endpoints, payloads, Mermaid diagrams, and seeding instructions. |\n| [laravel-11-12-app-guidelines](./skills/laravel-11-12-app-guidelines) | Official | Guidelines and workflow for working on Laravel 11 or Laravel 12 applications across common stacks (API-only or full-stack), including optional Docker Compose/Sail, Inertia + React, Livewire, Vue, Blade, Tailwind v4, Fortify, Wayfinder, PHPUnit, Pint, and Laravel Boost MCP tools. Use when implementing features, fixing bugs, or making UI/backend changes while following project-specific instructions (AGENTS.md, docs/). |\n<!-- SKILLS_TABLE_END -->\n\n## Plugin Groups\n\nPlugins bundle related skills so you can install by domain. The source of truth is `plugin-groups.json`.\n\n<!-- PLUGINS_TABLE_START -->\n| Plugin | Description | Skills |\n|--------|-------------|--------|\n| [documentation-skills](./plugin-groups.json) | Skills for authoring AI agent instructions, backend documentation, and design systems. | [agents-md-generator](./skills/agents-md-generator)<br>[documentation-guidelines](./skills/documentation-guidelines)<br>[design-system-generator](./skills/design-system-generator) |\n| [laravel-app-skills](./plugin-groups.json) | Guidelines for building Laravel 11/12 apps across common stacks and tooling. | [laravel-11-12-app-guidelines](./skills/laravel-11-12-app-guidelines) |\n| [devops-skills](./plugin-groups.json) | Skills for Docker, CI/CD, and local development environment configuration. | [docker-local-dev](./skills/docker-local-dev) |\n| [workflow-skills](./plugin-groups.json) | Skills for AI agent workflow and requirements clarification processes. | [ask-questions-if-underspecified](./skills/ask-questions-if-underspecified) |\n<!-- PLUGINS_TABLE_END -->\n\n## Contributing\n\nWe welcome contributions! Here's a quick start:\n\n1. Fork this repository\n2. Create a skill folder: `skills/your-skill-name/`\n3. Add a `SKILL.md` with metadata:\n   ```yaml\n   ---\n   name: your-skill-name\n   description: What the skill does and when to use it.\n   ---\n   ```\n4. **Validate locally before pushing:**\n   ```bash\n   npm install\n   npm run validate\n   ```\n5. Submit a pull request\n\nSee **[CONTRIBUTING.md](./CONTRIBUTING.md)** for detailed guidelines, validation instructions, and troubleshooting.\n\n## For AI Agents\n\nSee [CLAUDE.md](./CLAUDE.md) (or [AGENTS.md](./AGENTS.md)) for instructions on how to work with this repository, including how to group skills into plugins and update the marketplace when new skills are added.\n\n## Compatibility\n\nThis skill format is designed to be universal and works with:\n- Claude Code (Anthropic)\n- OpenAI Codex\n- Cursor\n- Kilo Code\n- GitHub Copilot\n- Windsurf\n- Any AI coding assistant that supports custom instructions or skills\n\n## Known Limitations\n\n- Claude Code currently indexes skills from the repository root, so `/skills` can list all marketplace skills even if you installed only one plugin. This is a Claude Code limitation. We follow the official Claude Skills marketplace example and keep `source: \"./\"` with explicit `skills` lists so plugin boundaries remain clear and other tools can scope installs properly. If `/skills` looks larger than expected, use the plugin `skills` list and the tables above as the source of truth.\n\n## License\n\nMIT\n"
      },
      "plugins": [
        {
          "name": "documentation-skills",
          "description": "Skills for authoring AI agent instructions, backend documentation, and design systems.",
          "source": "./",
          "strict": false,
          "skills": [
            "./skills/agents-md-generator",
            "./skills/documentation-guidelines",
            "./skills/design-system-generator"
          ],
          "categories": [],
          "install_commands": [
            "/plugin marketplace add thienanblog/awesome-ai-agent-skills",
            "/plugin install documentation-skills@awesome-ai-agent-skills"
          ]
        },
        {
          "name": "laravel-app-skills",
          "description": "Guidelines for building Laravel 11/12 apps across common stacks and tooling.",
          "source": "./",
          "strict": false,
          "skills": [
            "./skills/laravel-11-12-app-guidelines"
          ],
          "categories": [],
          "install_commands": [
            "/plugin marketplace add thienanblog/awesome-ai-agent-skills",
            "/plugin install laravel-app-skills@awesome-ai-agent-skills"
          ]
        },
        {
          "name": "devops-skills",
          "description": "Skills for Docker, CI/CD, and local development environment configuration.",
          "source": "./",
          "strict": false,
          "skills": [
            "./skills/docker-local-dev"
          ],
          "categories": [],
          "install_commands": [
            "/plugin marketplace add thienanblog/awesome-ai-agent-skills",
            "/plugin install devops-skills@awesome-ai-agent-skills"
          ]
        },
        {
          "name": "workflow-skills",
          "description": "Skills for AI agent workflow and requirements clarification processes.",
          "source": "./",
          "strict": false,
          "skills": [
            "./skills/ask-questions-if-underspecified"
          ],
          "categories": [],
          "install_commands": [
            "/plugin marketplace add thienanblog/awesome-ai-agent-skills",
            "/plugin install workflow-skills@awesome-ai-agent-skills"
          ]
        }
      ]
    }
  ]
}