{
  "author": {
    "id": "ThomasRohde",
    "display_name": "ThomasRohde",
    "avatar_url": "https://avatars.githubusercontent.com/u/10770175?v=4"
  },
  "marketplaces": [
    {
      "name": "thomas-rohde-plugins",
      "version": null,
      "description": "A curated collection of Claude Code plugins by Thomas Klok Rohde",
      "repo_full_name": "ThomasRohde/marketplace",
      "repo_url": "https://github.com/ThomasRohde/marketplace",
      "repo_description": null,
      "signals": {
        "stars": 0,
        "forks": 0,
        "pushed_at": "2026-02-06T03:49:25Z"
      },
      "files": {
        ".claude-plugin/marketplace.json": "{\n  \"name\": \"thomas-rohde-plugins\",\n  \"owner\": {\n    \"name\": \"Thomas Klok Rohde\",\n    \"email\": \"thomas@rohde.name\"\n  },\n  \"metadata\": {\n    \"description\": \"A curated collection of Claude Code plugins by Thomas Klok Rohde\",\n    \"version\": \"1.0.0\"\n  },\n  \"plugins\": [\n    {\n      \"name\": \"drawio\",\n      \"source\": \"./plugins/drawio\",\n      \"description\": \"Create production-ready DrawIO diagram files with comprehensive XML knowledge for flowcharts, architecture diagrams, UML, network diagrams, and more\",\n      \"version\": \"1.0.0\",\n      \"author\": {\n        \"name\": \"Thomas Klok Rohde\",\n        \"email\": \"thomas@rohde.name\"\n      },\n      \"repository\": \"https://github.com/ThomasRohde/marketplace\",\n      \"keywords\": [\"drawio\", \"diagrams\", \"flowchart\", \"architecture\", \"uml\", \"visualization\"],\n      \"category\": \"productivity\"\n    },\n    {\n      \"name\": \"jarchi\",\n      \"source\": \"./plugins/jarchi\",\n      \"description\": \"Commands and skills for jArchi scripting: automate Archi models, views, and exports\",\n      \"version\": \"1.0.0\",\n      \"author\": {\n        \"name\": \"Thomas Klok Rohde\",\n        \"email\": \"thomas@rohde.name\"\n      },\n      \"repository\": \"https://github.com/ThomasRohde/marketplace\",\n      \"keywords\": [\"jarchi\", \"archi\", \"automation\", \"scripts\", \"archimate\"],\n      \"category\": \"productivity\"\n    },\n    {\n      \"name\": \"archimate\",\n      \"source\": \"./plugins/archimate\",\n      \"description\": \"ArchiMate enterprise architecture modeling assistance - element selection, relationships, patterns, and model quality guidance\",\n      \"version\": \"0.1.0\",\n      \"author\": {\n        \"name\": \"Thomas Klok Rohde\",\n        \"email\": \"thomas@rohde.name\"\n      },\n      \"repository\": \"https://github.com/ThomasRohde/marketplace\",\n      \"keywords\": [\"archimate\", \"enterprise-architecture\", \"modeling\", \"archi\", \"togaf\"],\n      \"category\": \"productivity\"\n    },\n    {\n      \"name\": \"copilot-customization\",\n      \"source\": \"./plugins/copilot-customization\",\n      \"description\": \"Create, scaffold, and configure GitHub Copilot customizations for VS Code projects, including instructions, prompts, agents, skills, hooks, and MCP integration\",\n      \"version\": \"1.0.0\",\n      \"author\": {\n        \"name\": \"Thomas Klok Rohde\",\n        \"email\": \"thomas@rohde.name\"\n      },\n      \"repository\": \"https://github.com/ThomasRohde/marketplace\",\n      \"keywords\": [\"copilot\", \"github-copilot\", \"customization\", \"instructions\", \"agents\", \"skills\", \"hooks\", \"mcp\"],\n      \"category\": \"productivity\"\n    }\n  ]\n}\n",
        "README.md": "# Thomas Rohde's Claude Code Plugin Marketplace\n\nA curated collection of Claude Code plugins by Thomas Klok Rohde.\n\n## Quick Start\n\n### Add the Marketplace\n\nOnce this marketplace is hosted on GitHub, users can add it with:\n\n```shell\n/plugin marketplace add ThomasRohde/marketplace\n```\n\nFor local testing, use:\n\n```shell\n/plugin marketplace add ./path/to/marketplace\n```\n\n### Install Plugins\n\nAfter adding the marketplace, install any plugin with:\n\n```shell\n/plugin install <plugin-name>@thomas-rohde-plugins\n```\n\nFor example:\n\n```shell\n/plugin install drawio@thomas-rohde-plugins\n```\n\n## Available Plugins\n\n### drawio\n\nCreate production-ready DrawIO diagram files with comprehensive XML knowledge for flowcharts, architecture diagrams, UML, network diagrams, and more.\n\n**Install:**\n```shell\n/plugin install drawio@thomas-rohde-plugins\n```\n\n**Keywords:** drawio, diagrams, flowchart, architecture, uml, visualization\n\n### jarchi\n\nCommands and skills for jArchi scripting: automate Archi models, views, and exports.\n\n**Install:**\n```shell\n/plugin install jarchi@thomas-rohde-plugins\n```\n\n**Keywords:** jarchi, archi, automation, scripts, archimate\n\n### archimate\n\nArchiMate enterprise architecture modeling assistance for element selection, relationships, patterns, and model quality guidance.\n\n**Install:**\n```shell\n/plugin install archimate@thomas-rohde-plugins\n```\n\n**Keywords:** archimate, enterprise-architecture, modeling, archi, togaf\n\n### copilot-customization\n\nCreate, scaffold, and configure GitHub Copilot customizations for VS Code projects, including instructions, prompts, agents, skills, hooks, and MCP integration.\n\n**Install:**\n```shell\n/plugin install copilot-customization@thomas-rohde-plugins\n```\n\n**Keywords:** copilot, github-copilot, customization, instructions, agents, skills, hooks, mcp\n\n## Managing Updates\n\nUpdate your local copy of this marketplace:\n\n```shell\n/plugin marketplace update thomas-rohde-plugins\n```\n\nUpdate all installed plugins from this marketplace:\n\n```shell\n/plugin update\n```\n\n## Contributing\n\nFor issues, suggestions, or contributions, please visit the [GitHub repository](https://github.com/ThomasRohde/marketplace).\n\n## Marketplace Structure\n\n```\nmarketplace/\n├── .claude-plugin/\n│   └── marketplace.json     # Marketplace configuration\n├── plugins/\n│   ├── archimate/           # ArchiMate modeling plugin\n│   ├── copilot-customization/ # GitHub Copilot customization plugin\n│   ├── drawio/              # DrawIO diagram plugin\n│   └── jarchi/              # jArchi scripting plugin\n└── README.md               # This file\n```\n\n## Contact\n\n**Maintainer:** Thomas Klok Rohde\n**Email:** thomas@rohde.name\n**GitHub:** [@ThomasRohde](https://github.com/ThomasRohde)\n\n## License\n\nEach plugin may have its own license. Please check individual plugin directories for licensing information.\n",
        "plugins/drawio/README.md": "# DrawIO Plugin for Claude Code\n\nCreate production-ready `.drawio` diagram files directly from Claude Code.\n\n## Features\n\n- **Comprehensive diagram support**: Flowcharts, architecture diagrams, UML (sequence, class), ER diagrams, network diagrams, org charts, ArchiMate, C4 model\n- **Production-ready output**: Proper XML structure, styling, connectors, and layouts\n- **Skill-based knowledge**: Automatically activates when you discuss diagrams\n- **Quick command**: Use `/drawio` for rapid diagram generation\n\n## Installation\n\nAdd this plugin to your Claude Code configuration:\n\n```bash\nclaude --plugin-dir /path/to/drawio\n```\n\nOr copy to your project's `.claude-plugin/` directory.\n\n## Usage\n\n### Automatic Skill Activation\n\nThe DrawIO skill activates automatically when you:\n- Ask to \"create a diagram\" or \"make a flowchart\"\n- Mention \".drawio\" files or \"draw.io\"\n- Request architecture, sequence, ER, or network diagrams\n\n### Command Usage\n\n```\n/drawio <description>\n```\n\n**Examples:**\n- `/drawio user authentication flow with login, MFA, and session management`\n- `/drawio microservices architecture with API gateway, auth service, and database`\n- `/drawio ER diagram for e-commerce with users, orders, and products`\n- `/drawio ArchiMate diagram for order management system`\n- `/drawio C4 container diagram for banking application`\n\n## Components\n\n- **Skill**: `drawio-creation` - Comprehensive DrawIO XML format knowledge\n- **Command**: `/drawio` - Quick diagram generation\n\n## Supported Diagram Types\n\n| Type | Description |\n|------|-------------|\n| Flowchart | Process flows, decision trees, workflows |\n| Architecture | System design, microservices, cloud infrastructure |\n| Sequence | UML sequence diagrams for interactions |\n| Class | UML class diagrams with relationships |\n| ER | Entity-relationship database diagrams |\n| Network | Network topology and infrastructure |\n| Org Chart | Organizational hierarchies |\n| ArchiMate | Enterprise architecture (Business/Application/Technology layers) |\n| C4 Model | Context, Container, Component diagrams for software architecture |\n\n## License\n\nMIT\n",
        "plugins/jarchi/README.md": "# JArchi Plugin for Claude Code\n\nCreate jArchi scripts for [Archi](https://www.archimatetool.com/) - the open-source ArchiMate modeling tool.\n\n## Features\n\n- **Script Generation**: Create complete `.ajs` scripts with detailed explanations\n- **Comprehensive API Knowledge**: Full jArchi API coverage (elements, relationships, views, visual objects)\n- **CLI Automation**: Generate PowerShell and bash commands for headless execution\n- **Working Examples**: Ready-to-use script templates for common tasks\n\n## Usage\n\n### Command\n\n```\n/jarchi [description of what the script should do]\n```\n\n**Examples:**\n- `/jarchi export all business processes to CSV`\n- `/jarchi create a view showing all application components and their relationships`\n- `/jarchi batch update documentation for all elements without descriptions`\n- `/jarchi generate an HTML report of the current model`\n\n### Skill\n\nThe `jarchi-scripting` skill activates automatically when you ask about:\n- jArchi scripting or Archi automation\n- ArchiMate model manipulation\n- Creating or modifying ArchiMate elements, relationships, or views\n- Exporting or reporting from Archi models\n- Running Archi scripts headlessly\n\n## Requirements\n\n- [Archi](https://www.archimatetool.com/) with the jArchi plugin installed\n- For headless execution: Archi accessible from command line\n\n## Resources\n\n- [jArchi Wiki](https://github.com/archimatetool/archi-scripting-plugin/wiki)\n- [Archi Website](https://www.archimatetool.com/)\n- [ArchiMate Specification](https://pubs.opengroup.org/architecture/archimate3-doc/)\n",
        "plugins/archimate/README.md": "# ArchiMate Plugin for Claude Code\n\nEnterprise architecture modeling assistance using ArchiMate - The Open Group's standard for describing, analyzing, and communicating enterprise architectures.\n\n## Features\n\n- **Element Selection**: Guidance on choosing the right ArchiMate elements across 6 layers\n- **Relationship Modeling**: Proper usage of 11 relationship types with cross-layer patterns\n- **Architecture Patterns**: Modern patterns for microservices, cloud, APIs, security, and more\n- **Model Quality**: Naming conventions, anti-patterns detection, and quality checks\n\n## Components\n\n### Skills\n\n| Skill | Purpose |\n|-------|---------|\n| `archimate-modeling` | Core fundamentals: layers, elements, aspects |\n| `archimate-relationships` | Relationship types, directions, cross-layer usage |\n| `archimate-patterns` | Modern architecture modeling patterns |\n| `archimate-quality` | Naming conventions, anti-patterns, quality |\n\n### Commands\n\n| Command | Purpose |\n|---------|---------|\n| `/archimate:element` | Interactive help choosing the right element type |\n| `/archimate:pattern` | Look up specific architecture patterns |\n\n### Agents\n\n| Agent | Purpose |\n|-------|---------|\n| `archimate-modeler` | Proactively assists with ArchiMate model creation |\n\n## Installation\n\n```bash\n# Test locally\nclaude --plugin-dir /path/to/archimate\n\n# Or copy to project\ncp -r archimate/ your-project/.claude-plugin/\n```\n\n## Usage Examples\n\n**Get element guidance:**\n```\n\"What ArchiMate element should I use for a REST API?\"\n\"Help me choose between Business Process and Business Function\"\n```\n\n**Model an architecture:**\n```\n\"Help me model our microservices architecture in ArchiMate\"\n\"Create an ArchiMate model for our customer onboarding process\"\n```\n\n**Look up patterns:**\n```\n/archimate:pattern microservices\n/archimate:pattern cloud infrastructure\n```\n\n## Future: Archi MCP Integration\n\nThis plugin is designed for future integration with an Archi MCP server, enabling direct model manipulation in Archi from Claude Code.\n\n## License\n\nMIT\n",
        "plugins/copilot-customization/README.md": "# GitHub Copilot Customization Plugin for Claude Code\n\nCreate and manage GitHub Copilot customizations for VS Code projects.\n\n## Features\n\n- **Full customization coverage**: Instructions, prompts, custom agents, agent skills, hooks, and MCP server integration\n- **Scaffolding support**: Templates for `.instructions.md`, `.prompt.md`, `.agent.md`, `SKILL.md`, and `hooks.json`\n- **Decision-tree guidance**: Picks the right Copilot primitive based on user intent\n- **Progressive discovery**: References and examples for both quick setup and enterprise workflows\n\n## Installation\n\nAdd this plugin to your Claude Code configuration:\n\n```bash\nclaude --plugin-dir /path/to/copilot-customization\n```\n\nOr copy to your project's `.claude-plugin/` directory.\n\n## Usage\n\n### Automatic Skill Activation\n\nThe `copilot-customization` skill activates automatically when you ask to:\n- Set up Copilot customization for a project\n- Create or refine custom instructions\n- Add prompt files or custom agents\n- Scaffold agent skills\n- Configure hooks or MCP server integration\n\n### Example Requests\n\n- \"Set up Copilot customization for this repository\"\n- \"Create instructions for all TypeScript files\"\n- \"Add a reusable prompt to scaffold React components\"\n- \"Create a custom code-review agent\"\n- \"Configure hooks for pre-tool lint checks\"\n- \"Set up MCP server configuration for local development\"\n\n## Components\n\n- **Skill**: `copilot-customization`\n- **References**: Deep-dive docs for instructions, prompts, agents, skills, hooks, and MCP\n- **Templates**: Starter files for each customization primitive\n- **Examples**: Team workflow and enterprise setup examples\n\n## Requirements\n\n- GitHub Copilot in VS Code\n- For agent skills: enable `chat.useAgentSkills` (preview feature)\n- For hooks: use Copilot coding agent or Copilot CLI\n\n## License\n\nMIT\n"
      },
      "plugins": [
        {
          "name": "drawio",
          "source": "./plugins/drawio",
          "description": "Create production-ready DrawIO diagram files with comprehensive XML knowledge for flowcharts, architecture diagrams, UML, network diagrams, and more",
          "version": "1.0.0",
          "author": {
            "name": "Thomas Klok Rohde",
            "email": "thomas@rohde.name"
          },
          "repository": "https://github.com/ThomasRohde/marketplace",
          "keywords": [
            "drawio",
            "diagrams",
            "flowchart",
            "architecture",
            "uml",
            "visualization"
          ],
          "category": "productivity",
          "categories": [
            "architecture",
            "diagrams",
            "drawio",
            "flowchart",
            "productivity",
            "uml",
            "visualization"
          ],
          "install_commands": [
            "/plugin marketplace add ThomasRohde/marketplace",
            "/plugin install drawio@thomas-rohde-plugins"
          ]
        },
        {
          "name": "jarchi",
          "source": "./plugins/jarchi",
          "description": "Commands and skills for jArchi scripting: automate Archi models, views, and exports",
          "version": "1.0.0",
          "author": {
            "name": "Thomas Klok Rohde",
            "email": "thomas@rohde.name"
          },
          "repository": "https://github.com/ThomasRohde/marketplace",
          "keywords": [
            "jarchi",
            "archi",
            "automation",
            "scripts",
            "archimate"
          ],
          "category": "productivity",
          "categories": [
            "archi",
            "archimate",
            "automation",
            "jarchi",
            "productivity",
            "scripts"
          ],
          "install_commands": [
            "/plugin marketplace add ThomasRohde/marketplace",
            "/plugin install jarchi@thomas-rohde-plugins"
          ]
        },
        {
          "name": "archimate",
          "source": "./plugins/archimate",
          "description": "ArchiMate enterprise architecture modeling assistance - element selection, relationships, patterns, and model quality guidance",
          "version": "0.1.0",
          "author": {
            "name": "Thomas Klok Rohde",
            "email": "thomas@rohde.name"
          },
          "repository": "https://github.com/ThomasRohde/marketplace",
          "keywords": [
            "archimate",
            "enterprise-architecture",
            "modeling",
            "archi",
            "togaf"
          ],
          "category": "productivity",
          "categories": [
            "archi",
            "archimate",
            "enterprise-architecture",
            "modeling",
            "productivity",
            "togaf"
          ],
          "install_commands": [
            "/plugin marketplace add ThomasRohde/marketplace",
            "/plugin install archimate@thomas-rohde-plugins"
          ]
        },
        {
          "name": "copilot-customization",
          "source": "./plugins/copilot-customization",
          "description": "Create, scaffold, and configure GitHub Copilot customizations for VS Code projects, including instructions, prompts, agents, skills, hooks, and MCP integration",
          "version": "1.0.0",
          "author": {
            "name": "Thomas Klok Rohde",
            "email": "thomas@rohde.name"
          },
          "repository": "https://github.com/ThomasRohde/marketplace",
          "keywords": [
            "copilot",
            "github-copilot",
            "customization",
            "instructions",
            "agents",
            "skills",
            "hooks",
            "mcp"
          ],
          "category": "productivity",
          "categories": [
            "agents",
            "copilot",
            "customization",
            "github-copilot",
            "hooks",
            "instructions",
            "mcp",
            "productivity",
            "skills"
          ],
          "install_commands": [
            "/plugin marketplace add ThomasRohde/marketplace",
            "/plugin install copilot-customization@thomas-rohde-plugins"
          ]
        }
      ]
    }
  ]
}