{
  "author": {
    "id": "tmdgusya",
    "display_name": "roach",
    "avatar_url": "https://avatars.githubusercontent.com/u/57784077?u=387caf2969a851378614ad7712d1e78c7731d792&v=4"
  },
  "marketplaces": [
    {
      "name": "roach-claude-plugins",
      "version": null,
      "description": "A collection of Claude Code plugins for enhanced development workflows",
      "repo_full_name": "tmdgusya/roach-claude-plugins",
      "repo_url": "https://github.com/tmdgusya/roach-claude-plugins",
      "repo_description": null,
      "signals": {
        "stars": 0,
        "forks": 0,
        "pushed_at": "2026-01-16T09:08:36Z"
      },
      "files": {
        ".claude-plugin/marketplace.json": "{\n  \"name\": \"roach-claude-plugins\",\n  \"owner\": {\n    \"name\": \"tmdgusya\",\n    \"email\": \"dev0jsh@gmail.com\"\n  },\n  \"metadata\": {\n    \"description\": \"A collection of Claude Code plugins for enhanced development workflows\",\n    \"version\": \"1.0.0\"\n  },\n  \"plugins\": [\n    {\n      \"name\": \"senior-planner\",\n      \"source\": \"./senior-planner\",\n      \"description\": \"Senior engineering team conducts comprehensive interviews (technical, UX, security, performance, integration) to produce detailed Engineering Spec documents\",\n      \"version\": \"1.0.0\"\n    }\n  ]\n}\n",
        "senior-planner/README.md": "# Senior Planner Plugin\n\nA comprehensive Claude Code plugin that deploys a team of senior engineers to conduct in-depth planning interviews and produce detailed Engineering Specifications with complete TDD test plans.\n\n## Overview\n\nBuilding complex features requires more than a simple task list. You need:\n- Deep understanding across multiple domains (technical, UX, security, performance)\n- Thoughtful architectural decisions with trade-off analysis\n- Comprehensive test specifications written BEFORE implementation (TDD)\n- Complete engineering spec that serves as single source of truth\n\nThis plugin provides a structured interview process with **9 specialized senior engineers** covering every critical domain.\n\n## Senior Engineering Team\n\nYour team includes:\n\n1. **Code Rule Reader** - Discovers project-specific coding standards\n2. **Technical Architect** - System design, data models, API contracts\n3. **UX Engineer** - User workflows, interface design, accessibility\n4. **Security Engineer** - Auth, data protection, compliance (GDPR/SOC2)\n5. **Lead Test Engineer** - TDD strategy, comprehensive test cases with RED‚ÜíGREEN‚ÜíREFACTOR guides\n6. **Test Coverage Verifier** - Validates tests match user intent, identifies gaps\n7. **Performance Engineer** - Scalability, caching, optimization, SLOs\n8. **Integration Engineer** - External dependencies, deployment strategy\n9. **Technical Writer** - Synthesizes all findings into SPEC.md\n\n## What You Get\n\n### Engineering Specification (`.claude/SPEC.md`)\n\nA comprehensive 14-section specification:\n1. **Problem Statement** - Background, goals, non-goals\n2. **Solution Design** - Architecture, key decisions with rationale\n3. **API/Interface Design** - Contracts, request/response formats\n4. **Data Models** - Database schema, entities, relationships\n5. **User Experience** - Workflows, UI components, error handling\n6. **Technical Implementation** - Stack, components, code organization\n7. **Security & Compliance** - Auth, encryption, audit logging\n8. **Performance & Scalability** - SLOs, caching strategy, optimization\n9. **Test Specification** - Complete TDD test cases with implementation guides\n10. **Integration & Deployment** - Dependencies, rollout strategy, rollback\n11. **Trade-offs & Alternatives** - What we chose and why\n12. **Implementation Phases** - Breakdown of work into phases\n13. **Risks & Mitigations** - Risk assessment with mitigation strategies\n14. **References** - Supporting documentation\n\n### TDD Test Specification\n\nDetailed test cases for Test-Driven Development:\n- **Given/When/Then** format for every test\n- **Example test code** showing exact implementation\n- **RED ‚Üí GREEN ‚Üí REFACTOR** workflow guides\n- **Step-by-step instructions** for junior developers\n- **Comprehensive coverage** across unit, integration, E2E tests\n- **Mocking strategies** for external dependencies\n- **Coverage goals** by component criticality\n\n### Test Coverage Verification\n\nQuality assurance that tests match your intent:\n- **Gap analysis** - Identifies missing test scenarios\n- **User validation** - Confirms tests verify what you care about\n- **Clarification questions** - Resolves ambiguities before implementation\n- **Confidence report** - Sign-off that coverage is complete\n\n## Installation\n\n### Prerequisites\n\n- Claude Code installed and running\n- Git repository (recommended, not required)\n\n### Installation Methods\n\n#### Method 1: Install from Marketplace (Recommended)\n\nThe simplest way to install this plugin:\n\n```bash\n# 1. Add the marketplace\n/plugin marketplace add tmdgusya/roach-claude-plugins\n\n# 2. Install the plugin\n/plugin install senior-planner@roach-claude-plugins\n```\n\nThat's it! The plugin will be available immediately.\n\n> **Note**: This plugin is part of the `roach-claude-plugins` marketplace, which contains multiple plugins.\n\n#### Method 2: Install from Local Directory\n\nWhen developing or testing locally:\n\n```bash\n# From the directory containing senior-planner folder\nclaude plugin install ./senior-planner --scope user\n\n# Or navigate into the plugin directory first\ncd senior-planner\nclaude plugin install . --scope user\n```\n\n#### Method 3: Install from Git URL (Alternative)\n\nInstall the entire marketplace repository directly:\n\n```bash\n# HTTPS\nclaude plugin install https://github.com/tmdgusya/roach-claude-plugins.git --scope user\n\n# SSH\nclaude plugin install git@github.com:tmdgusya/roach-claude-plugins.git --scope user\n\n# Specific branch or tag\nclaude plugin install https://github.com/tmdgusya/roach-claude-plugins.git#develop --scope user\n```\n\n> **Note**: This installs all plugins in the marketplace, not just `senior-planner`.\n\n### Installation Scopes\n\nChoose where to install the plugin based on your needs:\n\n| Scope | Command Flag | Settings File | Use Case |\n|-------|-------------|---------------|----------|\n| **User** (default) | `--scope user` | `~/.claude/settings.json` | Personal plugins across all projects |\n| **Project** | `--scope project` | `.claude/settings.json` | Team plugins shared via Git |\n| **Local** | `--scope local` | `.claude/settings.local.json` | Project-specific, not committed to Git |\n\n**Examples:**\n\n```bash\n# Install for yourself only (default)\nclaude plugin install ./senior-planner --scope user\n\n# Install for entire team (committed to Git)\nclaude plugin install ./senior-planner --scope project\n\n# Install for this project only (not committed)\nclaude plugin install ./senior-planner --scope local\n```\n\n### Verify Installation\n\nAfter installation, verify the plugin is available:\n\n```bash\n# Check installed plugins\n/plugin\n\n# The /senior-planning command should now be available\n/senior-planning --help\n```\n\n### Plugin Management\n\n**View and manage plugins:**\n```bash\n/plugin                    # Open interactive plugin manager\n```\n\n**Common commands:**\n```bash\n# Disable plugin temporarily\n/plugin disable senior-planner@roach-claude-plugins\n\n# Re-enable plugin\n/plugin enable senior-planner@roach-claude-plugins\n\n# Uninstall plugin\n/plugin uninstall senior-planner@roach-claude-plugins\n\n# Update marketplace (pulls latest plugin versions)\n/plugin marketplace update roach-claude-plugins\n```\n\n### Troubleshooting Installation\n\n**\"Plugin not found\" error:**\n```bash\n# Check if plugin is in the list\n/plugin\n\n# View any loading errors\n# Open /plugin interface and check the \"Errors\" tab\n```\n\n**\"Command not available\" after installation:**\n```bash\n# Restart Claude Code or reload the session\n# The plugin should be automatically discovered\n\n# Verify the plugin loaded successfully\n/plugin  # Check \"Installed\" tab\n```\n\n**Plugin conflicts:**\n- If another plugin has a `/senior-planning` command, you may need to use the namespaced version\n- Use `/senior-planner:senior-planning` to explicitly call this plugin's command\n\n## Usage\n\n### Basic Usage\n\n```bash\n# Start senior planning interview\n/senior-planning Add user authentication with OAuth\n\n# Or simply\n/senior-planning\n```\n\nThe team will then guide you through a comprehensive interview process.\n\n### What Happens\n\n**Phase 1: Discovery** (5 min)\n- Understand feature requirements\n- Explore existing codebase patterns\n- Discover project coding standards (parallel)\n\n**Phase 2: Technical Interview** (15-20 min)\n- System architecture and component design\n- Data models and database schema\n- API contracts and technology choices\n\n**Phase 3: UX Interview** (10-15 min)\n- User workflows and journeys\n- Interface design and components\n- Accessibility and error states\n\n**Phase 4: Security Interview** (10 min)\n- Authentication and authorization\n- Data protection and compliance\n- Threat modeling and audit logging\n\n**Phase 5: TDD Test Specification** (20-30 min)\n- Comprehensive test cases for all components\n- RED ‚Üí GREEN ‚Üí REFACTOR implementation guides\n- Mocking strategy and test data\n\n**Phase 6: Test Coverage Verification** (10-15 min)\n- Validate tests match user intent\n- Identify and address coverage gaps\n- Confirm confidence in test completeness\n\n**Phase 7: Performance Interview** (10 min)\n- Performance SLOs and scale requirements\n- Caching strategy and optimization\n- Monitoring and alerting\n\n**Phase 8: Integration Interview** (10 min)\n- External dependencies and APIs\n- Deployment strategy and rollback\n- Migration and backward compatibility\n\n**Phase 9: Spec Synthesis** (10 min)\n- Consolidate all findings\n- Resolve conflicts\n- Create `.claude/SPEC.md`\n\n**Total Time**: 60-90 minutes of comprehensive planning\n\n### Example Session\n\n```\nYou: /senior-planning Add password reset feature\n\nSenior Planner: I'll guide you through comprehensive planning with our senior engineering team.\n\n[Discovery Phase]\nSenior Planner: I understand you want to add password reset. Let me explore your codebase...\n[Searches for similar features, reads auth patterns]\n\n[Code Standards Phase - Parallel]\nCode Rule Reader: Discovering project coding standards...\n[Finds .claude/AGENTS.md, reads conventions]\n\n[Technical Interview]\nTech Interviewer: For the password reset feature, which data approach fits best?\n  ‚òê Token in database (secure, requires DB)\n  ‚òê Signed JWT token (stateless, requires key management)\n  ‚òê Time-limited hash (simple, less secure)\n  ‚òë Token in database (you select)\n\n[Continues with detailed technical questions...]\n\n[UX Interview]\nUX Interviewer: When a reset link expires, what should users see?\n  ‚òê Generic error message\n  ‚òê Clear expiration notice with re-request option\n  ‚òë Clear notice + re-request (you select)\n\n[Continues with UX questions...]\n\n[Security Interview]\nSecurity Engineer: For rate limiting password resets, what's appropriate?\n  ‚òê 3 attempts per hour (strict)\n  ‚òê 10 attempts per hour (moderate)\n  ‚òë 10 attempts per hour (you select)\n\n[Continues with security questions...]\n\n[TDD Test Specification]\nTest Engineer: Creating comprehensive test cases for password reset...\n[Generates 25 detailed test cases with RED‚ÜíGREEN‚ÜíREFACTOR guides]\n\n[Test Coverage Verification]\nCoverage Verifier: I notice tests don't cover the scenario where user's email changes mid-reset. Should we test this?\n  ‚òë Yes, this could happen (you select)\n[Adds test case for email change scenario]\n\n[Performance Interview]\nPerformance Engineer: What response time is acceptable for \"send reset email\"?\n  ‚òê < 100ms (instant)\n  ‚òë < 500ms (fast, email sends async) (you select)\n\n[Integration Interview]\nIntegration Engineer: If email service is down, what happens?\n  ‚òê Fail and show error\n  ‚òë Queue for retry, show \"check email soon\" (you select)\n\n[Spec Synthesis]\nSpec Writer: Synthesizing all findings into SPEC.md...\n[Creates comprehensive specification]\n\nSenior Planner: ‚úì Planning Complete!\n\nSPEC.md created at .claude/SPEC.md with:\n- Complete technical architecture\n- Detailed UX flows\n- Security requirements\n- 25 TDD test cases with implementation guides\n- Performance targets\n- Integration strategy\n\nReady to implement using TDD! Start with Test Case 1.\n```\n## When to Use\n\n### ‚úÖ Use Senior Planner For:\n\n- **Complex features** requiring architectural decisions\n- **Features touching multiple systems** (frontend + backend + database + external APIs)\n- **Security-sensitive features** (auth, payments, PII handling)\n- **Features with unclear requirements** (need clarification through interviews)\n- **Features requiring scale considerations** (performance critical)\n- **Team-developed features** (shared understanding needed)\n- **Features with compliance requirements** (GDPR, SOC2, HIPAA)\n\n### ‚ùå Don't Use Senior Planner For:\n\n- **Simple bug fixes** - Just fix it\n- **Trivial changes** - (typo fixes, small tweaks)\n- **Well-defined, small tasks** - Clear implementation, no planning needed\n- **Exploratory work** - Use exploration agents instead\n- **Pure research questions** - Use research tools\n\n## Key Features\n\n### Comprehensive Domain Coverage\n\n- **9 specialized interviewers** each expert in their domain\n- **Sequential interviews** build on each other (later interviews use earlier context)\n- **Cross-domain synthesis** resolves conflicts, fills gaps\n\n### Test-Driven Development Focus\n\n- **Tests written BEFORE code** following TDD best practices\n- **RED ‚Üí GREEN ‚Üí REFACTOR** cycle guides for every test\n- **Example test code** showing exact implementation\n- **Junior-friendly** - step-by-step instructions anyone can follow\n\n### Test Coverage Verification\n\n- **Quality check** on test specifications\n- **User validation** ensures tests match intent\n- **Gap identification** catches missing scenarios\n- **Confidence sign-off** before implementation\n\n### Project-Aware\n\n- **Discovers coding standards** from AGENTS.md, CLAUDE.md files\n- **Follows existing patterns** found in codebase\n- **Respects conventions** (naming, architecture, testing)\n\n### Active User Participation\n\n- **You make decisions** - not passive planning\n- **AskUserQuestion** throughout - 3-4 questions per interview round\n- **Multiple rounds** per interviewer until complete\n- **Your preferences** shape the final spec\n\n## Benefits\n\n### For Solo Developers\n\n- **Senior-level guidance** for complex decisions\n- **Comprehensive checklist** - don't forget important aspects\n- **Test-first mindset** - TDD guides reduce bugs\n- **Documentation** - SPEC.md serves as implementation reference\n\n### For Teams\n\n- **Shared understanding** - entire team reviews same SPEC.md\n- **Consistent approach** - everyone follows same architecture\n- **Onboarding tool** - new team members read SPEC.md\n- **Communication aid** - non-technical stakeholders read Problem Statement and UX sections\n\n### For Quality\n\n- **Fewer bugs** - comprehensive test cases catch issues early\n- **Better architecture** - thoughtful design upfront\n- **Security built-in** - security interview catches vulnerabilities\n- **Performance considered** - scalability planned from start\n\n### Time Savings\n\n- **60-90 min planning** saves hours/days of rework\n- **TDD prevents bugs** - less debugging time\n- **Clear spec** - less \"what should I build?\" confusion\n- **Team alignment** - less back-and-forth discussions\n\n## Requirements\n\n- Claude Code installed\n- Git repository (recommended, not required)\n- Time commitment: 60-90 minutes for comprehensive planning\n\n## Configuration\n\nNo configuration needed! The plugin works out of the box.\n\n### Optional: Project Coding Standards\n\nCreate `.claude/AGENTS.md` or `CLAUDE.md` to document project-specific conventions:\n\n```markdown\n# Project Coding Standards\n\n## Architecture\n- Use layered architecture: Controller ‚Üí Service ‚Üí Repository\n- All database access via Prisma ORM\n\n## Testing\n- Co-locate test files with source\n- Use Jest for unit tests\n- 80% coverage minimum\n\n## Naming\n- Components: PascalCase\n- Functions: camelCase\n- Files: kebab-case\n\n[... more conventions ...]\n```\n\nThe code-rule-reader agent will automatically discover and apply these standards.\n\n## Output Files\n\n### Primary Output\n\n- `.claude/SPEC.md` - Engineering Specification (single source of truth)\n\n### Optional (if in plan mode)\n\n- `.claude/plans/*.md` - Implementation plan file (references SPEC.md)\n\n## Integration with Claude Code\n\n### With Plan Mode\n\nIf you run `/senior-planning` while in plan mode:\n- SPEC.md provides the **design** (what and why)\n- Plan file provides the **execution** (how and when)\n- Both work together\n\n### Standalone\n\nIf you run `/senior-planning` outside plan mode:\n- SPEC.md is the primary deliverable\n- Contains both design and implementation phases\n- Can create plan file later if needed\n\n## Troubleshooting\n\n### \"Plugin not found\"\n\n```bash\n# Verify installation\nclaude plugin list\n\n# Reinstall if needed\nclaude plugin install ./senior-planner --scope user\n```\n\n### \"Agents not triggering\"\n\nAgents trigger based on descriptions. Make sure you:\n- Use `/senior-planning` to start (not individual agent names)\n- Let the orchestration skill manage agent delegation\n\n### \"Interview taking too long\"\n\n- Interviews are thorough by design (60-90 min typical)\n- Can't skip interviews - each builds on previous\n- Time investment prevents bugs and rework\n\n### \"Too many questions\"\n\n- Each interviewer asks 3-4 questions per round, multiple rounds\n- Questions are necessary for comprehensive spec\n- Your answers drive better implementation\n- Skip if feature is truly simple (use regular planning)\n\n## Examples\n\n### Example 1: Authentication Feature\n\n```\nInput: /senior-planning Add OAuth2 social login\nOutput: SPEC.md with:\n- OAuth flow architecture\n- Token management strategy\n- Security considerations (CSRF, state validation)\n- 30 test cases for auth flows\n- Integration with Google/GitHub/Facebook\n- Deployment strategy (feature flags)\n```\n\n### Example 2: Payment Processing\n\n```\nInput: /senior-planning Add Stripe payment processing\nOutput: SPEC.md with:\n- Payment flow (cart ‚Üí checkout ‚Üí confirm ‚Üí receipt)\n- Stripe API integration details\n- PCI compliance considerations\n- Webhook handling for async events\n- 40 test cases including edge cases\n- Idempotency and retry logic\n- Rollback strategy for failed payments\n```\n\n### Example 3: Real-time Chat\n\n```\nInput: /senior-planning Add real-time chat feature\nOutput: SPEC.md with:\n- WebSocket architecture\n- Message persistence strategy\n- Scaling considerations (Redis pub/sub)\n- Typing indicators, read receipts\n- 35 test cases for messaging scenarios\n- Performance targets (< 50ms message delivery)\n- Deployment strategy (gradual WebSocket rollout)\n```\n\n## Contributing\n\nContributions welcome! Areas for improvement:\n\n- Additional specialized interviewers (e.g., Database Architect, DevOps Engineer)\n- Enhanced test coverage verification\n- Integration with CI/CD for test execution\n- Support for additional project conventions files\n\n## License\n\nMIT License\n\n## Acknowledgments\n\nBuilt on Claude Code's agent and skill system, leveraging:\n- Agent delegation for specialized interviews\n- AskUserQuestion for user participation\n- Sequential workflow orchestration\n- TodoWrite for progress tracking\n\n## Version History\n\n### v1.0.0 (Current)\n- Initial release\n- 9 specialized interviewer agents\n- TDD test specification with RED‚ÜíGREEN‚ÜíREFACTOR guides\n- Test coverage verification\n- Project coding standards discovery\n- Complete Engineering Spec output\n\n---\n\n**Philosophy**: \"Measure twice, cut once\" - Comprehensive planning enables confident, bug-free implementation.\n\nReady to plan your next feature? Run `/senior-planning` and let the senior team guide you! üöÄ\n"
      },
      "plugins": [
        {
          "name": "senior-planner",
          "source": "./senior-planner",
          "description": "Senior engineering team conducts comprehensive interviews (technical, UX, security, performance, integration) to produce detailed Engineering Spec documents",
          "version": "1.0.0",
          "categories": [],
          "install_commands": [
            "/plugin marketplace add tmdgusya/roach-claude-plugins",
            "/plugin install senior-planner@roach-claude-plugins"
          ]
        }
      ]
    },
    {
      "name": "ralph-agent-marketplace",
      "version": null,
      "description": "Implementation agents with planning, building, and loop control workflows using IMPLEMENTATION_PLAN.md with continuous task execution, verification, git workflow, and iteration limits",
      "repo_full_name": "tmdgusya/roach-loop",
      "repo_url": "https://github.com/tmdgusya/roach-loop",
      "repo_description": null,
      "signals": {
        "stars": 0,
        "forks": 0,
        "pushed_at": "2026-01-23T02:53:40Z"
      },
      "files": {
        ".claude-plugin/marketplace.json": "{\n  \"name\": \"ralph-agent-marketplace\",\n  \"owner\": {\n    \"name\": \"tmdgusya\",\n    \"email\": \"dev0jsh@gmail.com\"\n  },\n  \"plugins\": [\n    {\n      \"name\": \"ralph-agent\",\n      \"source\": \"./ralph-agent\",\n      \"description\": \"Implementation agents with planning, building, and loop control workflows using IMPLEMENTATION_PLAN.md with continuous task execution, verification, git workflow, and iteration limits\",\n      \"version\": \"0.5.0\",\n      \"author\": {\n        \"name\": \"tmdgusya\"\n      },\n      \"keywords\": [\n        \"automation\",\n        \"implementation\",\n        \"task-runner\",\n        \"verification\",\n        \"planning\",\n        \"git-workflow\",\n        \"iteration-control\",\n        \"loop\"\n      ],\n      \"homepage\": \"https://github.com/tmdgusya/roach-loop\",\n      \"repository\": \"https://github.com/tmdgusya/roach-loop.git\",\n      \"license\": \"MIT\",\n      \"strict\": false\n    }\n  ]\n}\n",
        "README.md": "# Ralph Agent Plugin\n\nImplementation agents for Claude Code that follow structured implementation plans with continuous task execution, verification, and optional git workflow.\n\n## Overview\n\nThis plugin provides two complementary workflows for automated implementation:\n\n### Geoff's Iterative Planning & Building\nFor projects with specification files in `specs/` directory:\n- **Geoff's Planner** (`/ralph-agent:gplan`): Analyzes specs and code, creates prioritized `IMPLEMENTATION_PLAN.md`\n- **Geoff's Builder** (`/ralph-agent:gbuild`): Implements tasks with automatic git commits, pushes, and version tags\n- Best for: Spec-driven projects requiring git workflow and version tracking\n\n### Ralph's Direct Execution\nFor projects with manual or existing implementation plans:\n- **Ralph** (`/ralph-agent:ralph`): Executes tasks from `IMPLEMENTATION_PLAN.md` sequentially\n- Best for: Simple task lists where you manage your own git workflow\n\n## Features\n\n### Geoff's Workflow\n- **Parallel Analysis**: Configurable parallel subagents for specs and codebase analysis\n- **Spec-Driven Planning**: Automatic plan generation from `specs/` directory\n- **Git Workflow**: Automatic add ‚Üí commit ‚Üí push ‚Üí tag (0.0.0 ‚Üí 0.0.1 ‚Üí ...)\n- **Gap Detection**: Compares implementation against specs, identifies missing features\n- **Ultrathink Prioritization**: Uses Opus for deep analysis and task ordering\n\n### Ralph's Workflow\n- **Continuous Execution**: Automatically moves to the next task after verification passes\n- **Verification Gated**: Never marks a task complete without passing verification\n- **Progress Tracking**: Uses markdown checklist format (`- [ ]` / `- [x]`) for task status\n- **Error Recovery**: Fixes failed verification and retries until tasks pass\n- **Clear Reporting**: Shows progress after each task completion\n\n## Installation\n\n### Method 1: Via Marketplace (Recommended)\n\nAdd the ralph-agent marketplace to Claude Code:\n\n```bash\n/plugin marketplace add tmdgusya/roach-loop\n```\n\nThen install the plugin:\n\n```bash\n/plugin install ralph-agent@ralph-agent-marketplace\n```\n\nThe plugin will be installed globally and available in all projects.\n\n**To update to the latest version:**\n\n```bash\n/plugin update ralph-agent\n```\n\n### Method 2: Project Local\n\nCopy the plugin to your project's `.claude-plugin/` directory:\n\n```bash\ncp -r ralph-agent /path/to/your-project/.claude-plugin/\n```\n\n**Optional:** Copy `loop.py` script for external iteration control:\n\n```bash\ncp ralph-agent/ralph-agent:loop.py /path/to/your-project/\nchmod +x loop.py\n```\n\n### Method 3: Global Manual Installation\n\n```bash\ncp -r ralph-agent ~/.claude/plugins/ralph-agent:ralph-agent\n```\n\n**Optional:** Install `loop.py` globally:\n\n```bash\nsudo cp ralph-agent/ralph-agent:loop.py /usr/local/bin/ralph-agent:ralph-loop\n# Or create a symlink\nln -s ~/.claude/plugins/ralph-agent:ralph-agent/ralph-agent:loop.py ~/bin/ralph-agent:ralph-loop\n```\n\n### Method 4: Command-Line Flag\n\n```bash\ncc --plugin-dir /path/to/ralph-agent:ralph-agent\n```\n\n**Note:** The `loop.py` script requires access to the ralph-agent plugin. If using global installation, use `--plugin-dir` to specify the plugin path:\n\n```bash\n./ralph-agent:loop.py ralph 10 --plugin-dir ~/.claude/plugins/ralph-agent:ralph-agent\n```\n\n## Quick Start\n\n### Workflow A: Geoff's Iterative (Recommended for spec-driven projects)\n\n#### 1. Create Specifications Directory\n\n```bash\nmkdir specs\n```\n\n#### 2. Write Your Specs\n\nCreate specification files in `specs/`:\n\n```markdown\n# specs/user-auth.md\n\n## Feature: User Authentication\n\n### Requirements\n- Users can register with email/password\n- Users can login with JWT tokens\n- Passwords are hashed with bcrypt\n\n### Acceptance Criteria\n- POST /auth/register creates new user\n- POST /auth/login returns JWT token\n- Passwords stored as hash, not plaintext\n```\n\n#### 3. Generate Implementation Plan\n\n```bash\n/ralph-agent:gplan\n```\n\nThis analyzes your specs and creates `IMPLEMENTATION_PLAN.md`.\n\n#### 4. Build with Git Workflow\n\n```bash\n/ralph-agent:gbuild\n```\n\nGeoff's Builder will:\n- Implement each task\n- Run tests and fix failures\n- Git commit ‚Üí push ‚Üí tag (0.0.0, 0.0.1, ...)\n- Continue until all tasks complete\n\n### Workflow B: Ralph's Direct (For simple task lists)\n\n#### 1. Create an Implementation Plan\n\n```bash\n/ralph-agent:ralph-init\n```\n\nThis creates `IMPLEMENTATION_PLAN.md` with a template.\n\n#### 2. Edit the Plan\n\nOpen `IMPLEMENTATION_PLAN.md` and add your tasks:\n\n```markdown\n# Implementation Plan\n\n## Tasks\n- [ ] Create database models\n- [ ] Implement API endpoints\n- [ ] Write unit tests\n- [ ] Add authentication\n```\n\n#### 3. Set Up Verification\n\nCreate or edit `AGENTS.md` with verification commands:\n\n```markdown\n# Verification Commands\n- `pytest tests/`\n- `ruff check .`\n```\n\n#### 4. Start Ralph\n\n```bash\n/ralph-agent:ralph\n```\n\nRalph will work through all tasks continuously until complete.\n\n**Note:** Ralph does NOT handle git workflow. Commit manually or use `/ralph-agent:gbuild`.\n\n## Commands\n\n### `/ralph-agent:gplan` - Geoff's Planner\n\nCreate or update `IMPLEMENTATION_PLAN.md` by analyzing your `specs/` directory.\n\n**Usage:**\n```\n/ralph-agent:gplan\n```\n\nWith custom parallelism:\n```\n/ralph-agent:gplan --parallel=50\n```\n\n**What happens:**\n1. Studies all files in `specs/` directory using parallel subagents\n2. Studies existing `IMPLEMENTATION_PLAN.md` and `src/lib/*`\n3. Compares `src/*` implementation against `specs/*` requirements\n4. Uses Opus with \"Ultrathink\" for task prioritization\n5. Creates/updates `IMPLEMENTATION_PLAN.md` with prioritized tasks\n\n**Requirements:**\n- `specs/` directory must exist with specification files\n\n### `/ralph-agent:gbuild` - Geoff's Builder\n\nImplement tasks from `IMPLEMENTATION_PLAN.md` with git workflow and auto-tagging.\n\n**Usage:**\n```\n/ralph-agent:gbuild\n```\n\nWith custom parallelism:\n```\n/ralph-agent:gbuild --parallel=100\n```\n\n**What happens:**\n1. Studies `specs/*` with parallel subagents\n2. Reads `IMPLEMENTATION_PLAN.md` for task list\n3. Searches codebase (doesn't assume not implemented)\n4. Implements task completely (no placeholders)\n5. Runs tests, fixes failures until pass\n6. Git add ‚Üí commit ‚Üí push\n7. Creates git tag (0.0.0 ‚Üí 0.0.1 ‚Üí ...)\n8. Continues to next task until all complete\n\n**Requirements:**\n- `IMPLEMENTATION_PLAN.md` must exist\n- Git repository with remote configured\n\n### `/ralph-agent:ralph`\n\nStart Ralph to work through tasks in `IMPLEMENTATION_PLAN.md`.\n\n**Usage:**\n```\n/ralph-agent:ralph\n```\n\n**What happens:**\n1. Ralph reads `IMPLEMENTATION_PLAN.md`\n2. Finds the first unchecked task\n3. Implements the task\n4. Runs verification commands from `AGENTS.md`\n5. Marks task complete when verification passes\n6. Continues to the next task automatically\n\n**Note:** Ralph does NOT handle git workflow. Use `/ralph-agent:gbuild` for automatic commits/tags.\n\n### `/ralph-agent:ralph-init`\n\nCreate a new `IMPLEMENTATION_PLAN.md` template file.\n\n**Usage:**\n```\n/ralph-agent:ralph-init\n```\n\nCreates a template with:\n- Project description section\n- Prerequisites section\n- Task checklist\n- Verification section\n- Notes section\n\n### `/ralph-agent:loop` - Loop Wrapper Command\n\nExecute any agent with explicit iteration control, pause prompts, and checkpoint summaries.\n\n**Usage:**\n```\n/ralph-agent:loop ralph max=5 pause=true\n/ralph-agent:loop geoff-builder max=10 pause=true parallel=50\n/ralph-agent:loop geoff-builder max=0 pause=false\n```\n\n**Features:**\n- `max=N`: Maximum iterations (0 = unlimited)\n- `pause=true`: Prompt user after each task for review\n- `parallel=M`: Pass to geoff agents for parallelism\n\n**Best for:**\n- Interactive development (5-20 tasks with review)\n- Learning agent behavior\n- Testing workflows\n\n## Iteration Control\n\nAll agents support iteration limits for controlled execution:\n\n### Agent Flags (Simple Limit)\n\n```bash\n# Limit to 5 tasks\n/ralph-agent:ralph --max-iterations=5\n\n# Limit to 10 tasks with git workflow\n/ralph-agent:gbuild --max-iterations=10\n\n# Unlimited (default)\n/ralph-agent:gbuild\n```\n\n### `/ralph-agent:loop` Command (Full Control)\n\n```bash\n# Pause between tasks for review\n/ralph-agent:loop ralph max=5 pause=true\n\n# Continuous batch execution\n/ralph-agent:loop geoff-builder max=20 pause=false\n```\n\n### External `loop.py` Script (Production)\n\nFor long-running autonomous work that survives Claude Code session limits:\n\n**Installation:**\n\nThe `loop.py` script is included in the ralph-agent plugin. To use it:\n\n```bash\n# Option 1: Copy to your project\ncp ralph-agent/ralph-agent:loop.py ./\n\n# Option 2: Install globally\nsudo cp ralph-agent/ralph-agent:loop.py /usr/local/bin/ralph-agent:ralph-loop\n\n# Option 3: Create symlink\nln -s /path/to/ralph-agent:ralph-agent/ralph-agent:loop.py ~/bin/ralph-agent:ralph-loop\n```\n\n**Usage:**\n\n```bash\n# Ralph unlimited\n./ralph-agent:loop.py ralph\n\n# Ralph max 10 iterations\n./ralph-agent:loop.py ralph 10\n\n# Geoff Builder unlimited with custom parallelism\n./ralph-agent:loop.py gbuild 0 --parallel 100\n\n# Geoff Builder max 50 iterations\n./ralph-agent:loop.py gbuild 50\n\n# With custom plugin path\n./ralph-agent:loop.py ralph 20 --plugin-dir /path/to/ralph-agent:ralph-agent\n```\n\n**Features:**\n- Spawns NEW Claude process each iteration\n- Survives Claude Code crashes/restarts\n- Git commit between each iteration\n- True \"infinite loop\" capability\n- Best for: Production workflows, overnight builds\n\n**Comparison:**\n\n| Method | Session | Max Iterations | Best For |\n|--------|---------|---------------|----------|\n| Agent flags | Internal | Yes (`--max-iterations`) | Simple limits |\n| `/ralph-agent:loop` command | Internal | Yes + pause prompts | Interactive review |\n| `loop.py` script | External | Yes + true infinite | Production, long-running |\n\n## File Format\n\n### IMPLEMENTATION_PLAN.md\n\nUses standard markdown checklist format:\n\n```markdown\n# Implementation Plan\n\n## Description\nBrief description of plan objectives.\n\n## Prerequisites\n- [ ] Dependency 1\n- [ ] Dependency 2\n\n## Tasks\n- [ ] Task 1: First task description\n- [ ] Task 2: Second task description\n- [x] Task 3: Already completed\n\n## Verification\n- `pytest tests/`\n- `npm test`\n\n## Notes\nAdditional context or reminders.\n```\n\n### AGENTS.md\n\nContains verification commands:\n\n```markdown\n# Verification Commands\n\n## General\n- `pytest tests/` - Run all tests\n- `npm test` - Run test suite\n\n## Linting\n- `ruff check .` - Python linting\n- `eslint .` - JavaScript linting\n```\n\n## How Ralph Works\n\n```\n‚îå‚îÄ‚îÄ‚îÄ‚îÄ‚îÄ‚îÄ‚îÄ‚îÄ‚îÄ‚îÄ‚îÄ‚îÄ‚îÄ‚îÄ‚îÄ‚îÄ‚îÄ‚îÄ‚îÄ‚îÄ‚îÄ‚îÄ‚îÄ‚îÄ‚îÄ‚îÄ‚îÄ‚îÄ‚îÄ‚îÄ‚îÄ‚îÄ‚îÄ‚îÄ‚îÄ‚îÄ‚îÄ‚îÄ‚îÄ‚îÄ‚îÄ‚îÄ‚îÄ‚îÄ‚îÄ‚îÄ‚îÄ‚îÄ‚îÄ‚îÄ‚îÄ‚îÄ‚îÄ‚îÄ‚îÄ‚îÄ‚îÄ‚îÄ‚îÄ‚îÄ‚îÄ‚îê\n‚îÇ  1. Read IMPLEMENTATION_PLAN.md                              ‚îÇ\n‚îÇ     ‚Üí Find first unchecked task (- [ ])                       ‚îÇ\n‚îú‚îÄ‚îÄ‚îÄ‚îÄ‚îÄ‚îÄ‚îÄ‚îÄ‚îÄ‚îÄ‚îÄ‚îÄ‚îÄ‚îÄ‚îÄ‚îÄ‚îÄ‚îÄ‚îÄ‚îÄ‚îÄ‚îÄ‚îÄ‚îÄ‚îÄ‚îÄ‚îÄ‚îÄ‚îÄ‚îÄ‚îÄ‚îÄ‚îÄ‚îÄ‚îÄ‚îÄ‚îÄ‚îÄ‚îÄ‚îÄ‚îÄ‚îÄ‚îÄ‚îÄ‚îÄ‚îÄ‚îÄ‚îÄ‚îÄ‚îÄ‚îÄ‚îÄ‚îÄ‚îÄ‚îÄ‚îÄ‚îÄ‚îÄ‚îÄ‚îÄ‚îÄ‚î§\n‚îÇ  2. Understand task requirements                              ‚îÇ\n‚îÇ     ‚Üí Read related files if needed                            ‚îÇ\n‚îú‚îÄ‚îÄ‚îÄ‚îÄ‚îÄ‚îÄ‚îÄ‚îÄ‚îÄ‚îÄ‚îÄ‚îÄ‚îÄ‚îÄ‚îÄ‚îÄ‚îÄ‚îÄ‚îÄ‚îÄ‚îÄ‚îÄ‚îÄ‚îÄ‚îÄ‚îÄ‚îÄ‚îÄ‚îÄ‚îÄ‚îÄ‚îÄ‚îÄ‚îÄ‚îÄ‚îÄ‚îÄ‚îÄ‚îÄ‚îÄ‚îÄ‚îÄ‚îÄ‚îÄ‚îÄ‚îÄ‚îÄ‚îÄ‚îÄ‚îÄ‚îÄ‚îÄ‚îÄ‚îÄ‚îÄ‚îÄ‚îÄ‚îÄ‚îÄ‚îÄ‚îÄ‚î§\n‚îÇ  3. Implement the task                                       ‚îÇ\n‚îÇ     ‚Üí Write/modify code                                      ‚îÇ\n‚îú‚îÄ‚îÄ‚îÄ‚îÄ‚îÄ‚îÄ‚îÄ‚îÄ‚îÄ‚îÄ‚îÄ‚îÄ‚îÄ‚îÄ‚îÄ‚îÄ‚îÄ‚îÄ‚îÄ‚îÄ‚îÄ‚îÄ‚îÄ‚îÄ‚îÄ‚îÄ‚îÄ‚îÄ‚îÄ‚îÄ‚îÄ‚îÄ‚îÄ‚îÄ‚îÄ‚îÄ‚îÄ‚îÄ‚îÄ‚îÄ‚îÄ‚îÄ‚îÄ‚îÄ‚îÄ‚îÄ‚îÄ‚îÄ‚îÄ‚îÄ‚îÄ‚îÄ‚îÄ‚îÄ‚îÄ‚îÄ‚îÄ‚îÄ‚îÄ‚îÄ‚îÄ‚î§\n‚îÇ  4. Verify work                                              ‚îÇ\n‚îÇ     ‚Üí Read AGENTS.md for verification commands               ‚îÇ\n‚îÇ     ‚Üí Run ALL verification commands                          ‚îÇ\n‚îÇ     ‚Üí If fail: fix code and retry                            ‚îÇ\n‚îú‚îÄ‚îÄ‚îÄ‚îÄ‚îÄ‚îÄ‚îÄ‚îÄ‚îÄ‚îÄ‚îÄ‚îÄ‚îÄ‚îÄ‚îÄ‚îÄ‚îÄ‚îÄ‚îÄ‚îÄ‚îÄ‚îÄ‚îÄ‚îÄ‚îÄ‚îÄ‚îÄ‚îÄ‚îÄ‚îÄ‚îÄ‚îÄ‚îÄ‚îÄ‚îÄ‚îÄ‚îÄ‚îÄ‚îÄ‚îÄ‚îÄ‚îÄ‚îÄ‚îÄ‚îÄ‚îÄ‚îÄ‚îÄ‚îÄ‚îÄ‚îÄ‚îÄ‚îÄ‚îÄ‚îÄ‚îÄ‚îÄ‚îÄ‚îÄ‚îÄ‚îÄ‚î§\n‚îÇ  5. Mark task complete                                       ‚îÇ\n‚îÇ     ‚Üí Change - [ ] to - [x] in plan                          ‚îÇ\n‚îú‚îÄ‚îÄ‚îÄ‚îÄ‚îÄ‚îÄ‚îÄ‚îÄ‚îÄ‚îÄ‚îÄ‚îÄ‚îÄ‚îÄ‚îÄ‚îÄ‚îÄ‚îÄ‚îÄ‚îÄ‚îÄ‚îÄ‚îÄ‚îÄ‚îÄ‚îÄ‚îÄ‚îÄ‚îÄ‚îÄ‚îÄ‚îÄ‚îÄ‚îÄ‚îÄ‚îÄ‚îÄ‚îÄ‚îÄ‚îÄ‚îÄ‚îÄ‚îÄ‚îÄ‚îÄ‚îÄ‚îÄ‚îÄ‚îÄ‚îÄ‚îÄ‚îÄ‚îÄ‚îÄ‚îÄ‚îÄ‚îÄ‚îÄ‚îÄ‚îÄ‚îÄ‚î§\n‚îÇ  6. Continue or report                                       ‚îÇ\n‚îÇ     ‚Üí More tasks? Go to step 2                               ‚îÇ\n‚îÇ     ‚Üí All done? Report completion and exit                   ‚îÇ\n‚îî‚îÄ‚îÄ‚îÄ‚îÄ‚îÄ‚îÄ‚îÄ‚îÄ‚îÄ‚îÄ‚îÄ‚îÄ‚îÄ‚îÄ‚îÄ‚îÄ‚îÄ‚îÄ‚îÄ‚îÄ‚îÄ‚îÄ‚îÄ‚îÄ‚îÄ‚îÄ‚îÄ‚îÄ‚îÄ‚îÄ‚îÄ‚îÄ‚îÄ‚îÄ‚îÄ‚îÄ‚îÄ‚îÄ‚îÄ‚îÄ‚îÄ‚îÄ‚îÄ‚îÄ‚îÄ‚îÄ‚îÄ‚îÄ‚îÄ‚îÄ‚îÄ‚îÄ‚îÄ‚îÄ‚îÄ‚îÄ‚îÄ‚îÄ‚îÄ‚îÄ‚îÄ‚îò\n```\n\n## User Interaction Flow\n\nThis plugin provides two workflows for different use cases:\n\n### Workflow 1: Geoff's Iterative Planning & Building\n\nFor projects with specification files in `specs/` directory:\n\n```\n‚îå‚îÄ‚îÄ‚îÄ‚îÄ‚îÄ‚îÄ‚îÄ‚îÄ‚îÄ‚îÄ‚îÄ‚îÄ‚îÄ‚îÄ‚îÄ‚îÄ‚îÄ‚îÄ‚îÄ‚îÄ‚îÄ‚îÄ‚îÄ‚îÄ‚îÄ‚îÄ‚îÄ‚îÄ‚îÄ‚îÄ‚îÄ‚îÄ‚îÄ‚îÄ‚îÄ‚îÄ‚îÄ‚îÄ‚îÄ‚îÄ‚îÄ‚îÄ‚îÄ‚îÄ‚îÄ‚îÄ‚îÄ‚îÄ‚îÄ‚îÄ‚îÄ‚îÄ‚îÄ‚îÄ‚îÄ‚îÄ‚îÄ‚îÄ‚îÄ‚îÄ‚îÄ‚îÄ‚îÄ‚îÄ‚îÄ‚îÄ‚îÄ‚îÄ‚îÄ‚îÄ‚îÄ‚îÄ‚îÄ‚îÄ‚îÄ‚îÄ‚îÄ‚îê\n‚îÇ                        GEOFF'S ITERATIVE WORKFLOW                            ‚îÇ\n‚îú‚îÄ‚îÄ‚îÄ‚îÄ‚îÄ‚îÄ‚îÄ‚îÄ‚îÄ‚îÄ‚îÄ‚îÄ‚îÄ‚îÄ‚îÄ‚îÄ‚îÄ‚îÄ‚îÄ‚îÄ‚îÄ‚îÄ‚îÄ‚îÄ‚îÄ‚îÄ‚îÄ‚îÄ‚îÄ‚îÄ‚îÄ‚îÄ‚îÄ‚îÄ‚îÄ‚îÄ‚îÄ‚îÄ‚îÄ‚îÄ‚îÄ‚îÄ‚îÄ‚îÄ‚îÄ‚îÄ‚îÄ‚îÄ‚îÄ‚îÄ‚îÄ‚îÄ‚îÄ‚îÄ‚îÄ‚îÄ‚îÄ‚îÄ‚îÄ‚îÄ‚îÄ‚îÄ‚îÄ‚îÄ‚îÄ‚îÄ‚îÄ‚îÄ‚îÄ‚îÄ‚îÄ‚îÄ‚îÄ‚îÄ‚îÄ‚îÄ‚îÄ‚î§\n‚îÇ                                                                             ‚îÇ\n‚îÇ  ‚îå‚îÄ‚îÄ‚îÄ‚îÄ‚îÄ‚îÄ‚îÄ‚îÄ‚îÄ‚îÄ‚îÄ‚îÄ‚îÄ‚îê      ‚îå‚îÄ‚îÄ‚îÄ‚îÄ‚îÄ‚îÄ‚îÄ‚îÄ‚îÄ‚îÄ‚îÄ‚îÄ‚îÄ‚îê      ‚îå‚îÄ‚îÄ‚îÄ‚îÄ‚îÄ‚îÄ‚îÄ‚îÄ‚îÄ‚îÄ‚îÄ‚îÄ‚îÄ‚îÄ‚îÄ‚îÄ‚îÄ‚îÄ‚îÄ‚îÄ‚îÄ‚îÄ‚îÄ‚îÄ‚îÄ‚îê    ‚îÇ\n‚îÇ  ‚îÇ   specs/    ‚îÇ‚îÄ‚îÄ‚îÄ‚îÄ‚îÄ‚ñ∂‚îÇ    /ralph-agent:gplan   ‚îÇ‚îÄ‚îÄ‚îÄ‚îÄ‚îÄ‚ñ∂‚îÇ IMPLEMENTATION_PLAN.md ‚îÇ    ‚îÇ\n‚îÇ  ‚îÇ  directory  ‚îÇ      ‚îÇ  (planner)  ‚îÇ      ‚îÇ   (prioritized tasks)   ‚îÇ    ‚îÇ\n‚îÇ  ‚îî‚îÄ‚îÄ‚îÄ‚îÄ‚îÄ‚îÄ‚îÄ‚îÄ‚îÄ‚îÄ‚îÄ‚îÄ‚îÄ‚îò      ‚îî‚îÄ‚îÄ‚îÄ‚îÄ‚îÄ‚îÄ‚îÄ‚îÄ‚îÄ‚îÄ‚îÄ‚îÄ‚îÄ‚îò      ‚îî‚îÄ‚îÄ‚îÄ‚îÄ‚îÄ‚îÄ‚îÄ‚îÄ‚îÄ‚îÄ‚îÄ‚î¨‚îÄ‚îÄ‚îÄ‚îÄ‚îÄ‚îÄ‚îÄ‚îÄ‚îÄ‚îÄ‚îÄ‚îÄ‚îÄ‚îò    ‚îÇ\n‚îÇ         ‚îÇ                                            ‚îÇ review?             ‚îÇ\n‚îÇ         ‚îÇ           ‚îå‚îÄ‚îÄ‚îÄ‚îÄ‚îÄ‚îÄ‚îÄ‚îÄ‚îÄ‚îÄ‚îÄ‚îÄ‚îÄ‚îê                  ‚îÇ                     ‚îÇ\n‚îÇ         ‚îÇ           ‚îÇ  Edit plan  ‚îÇ‚óÄ‚îÄ‚îÄ‚îÄ‚îÄ‚îÄ‚îÄ‚îÄ‚îÄ‚îÄ‚îÄ‚îÄ‚îÄ‚îÄ‚îÄ‚îÄ‚îÄ‚îÄ‚îò                     ‚îÇ\n‚îÇ         ‚îÇ           ‚îÇ  (optional) ‚îÇ                                       ‚îÇ\n‚îÇ         ‚îÇ           ‚îî‚îÄ‚îÄ‚îÄ‚îÄ‚îÄ‚îÄ‚î¨‚îÄ‚îÄ‚îÄ‚îÄ‚îÄ‚îÄ‚îò                                       ‚îÇ\n‚îÇ         ‚îÇ                  ‚îÇ                                              ‚îÇ\n‚îÇ         ‚îÇ                  ‚ñº                                              ‚îÇ\n‚îÇ         ‚îÇ           ‚îå‚îÄ‚îÄ‚îÄ‚îÄ‚îÄ‚îÄ‚îÄ‚îÄ‚îÄ‚îÄ‚îÄ‚îÄ‚îÄ‚îê      ‚îå‚îÄ‚îÄ‚îÄ‚îÄ‚îÄ‚îÄ‚îÄ‚îÄ‚îÄ‚îÄ‚îÄ‚îÄ‚îÄ‚îÄ‚îÄ‚îÄ‚îÄ‚îÄ‚îÄ‚îÄ‚îÄ‚îÄ‚îÄ‚îÄ‚îÄ‚îê    ‚îÇ\n‚îÇ         ‚îÇ           ‚îÇ   /ralph-agent:gbuild   ‚îÇ‚îÄ‚îÄ‚îÄ‚îÄ‚îÄ‚ñ∂‚îÇ  Git commits + tags     ‚îÇ    ‚îÇ\n‚îÇ         ‚îî‚îÄ‚îÄ‚îÄ‚îÄ‚îÄ‚îÄ‚îÄ‚îÄ‚îÄ‚îÄ‚ñ∂‚îÇ  (builder)  ‚îÇ      ‚îÇ  (0.0.0 ‚Üí 0.0.1 ‚Üí ...)  ‚îÇ    ‚îÇ\n‚îÇ                     ‚îî‚îÄ‚îÄ‚îÄ‚îÄ‚îÄ‚îÄ‚îÄ‚îÄ‚îÄ‚îÄ‚îÄ‚îÄ‚îÄ‚îò      ‚îî‚îÄ‚îÄ‚îÄ‚îÄ‚îÄ‚îÄ‚îÄ‚îÄ‚îÄ‚îÄ‚îÄ‚î¨‚îÄ‚îÄ‚îÄ‚îÄ‚îÄ‚îÄ‚îÄ‚îÄ‚îÄ‚îÄ‚îÄ‚îÄ‚îÄ‚îò    ‚îÇ\n‚îÇ                                                           ‚îÇ               ‚îÇ\n‚îÇ  Specs change? ‚îÄ‚îÄ‚îÄ‚îÄ‚îÄ‚îÄ‚îÄ‚îÄ‚îÄ‚îÄ‚îÄ‚îÄ‚îÄ‚îÄ‚îÄ‚îÄ‚îÄ‚îÄ‚îÄ‚îÄ‚îÄ‚îÄ‚îÄ‚îÄ‚îÄ‚îÄ‚îÄ‚îÄ‚îÄ‚îÄ‚îÄ‚îÄ‚îÄ‚îÄ‚îÄ‚îÄ‚îÄ‚îÄ‚îÄ‚îÄ‚îÄ‚îÄ‚îò               ‚îÇ\n‚îÇ       ‚îÇ                                                                   ‚îÇ\n‚îÇ       ‚ñº                                                                   ‚îÇ\n‚îÇ   Re-run /ralph-agent:gplan                                                           ‚îÇ\n‚îÇ   (updates plan with gaps)                                                ‚îÇ\n‚îÇ                                                                             ‚îÇ\n‚îî‚îÄ‚îÄ‚îÄ‚îÄ‚îÄ‚îÄ‚îÄ‚îÄ‚îÄ‚îÄ‚îÄ‚îÄ‚îÄ‚îÄ‚îÄ‚îÄ‚îÄ‚îÄ‚îÄ‚îÄ‚îÄ‚îÄ‚îÄ‚îÄ‚îÄ‚îÄ‚îÄ‚îÄ‚îÄ‚îÄ‚îÄ‚îÄ‚îÄ‚îÄ‚îÄ‚îÄ‚îÄ‚îÄ‚îÄ‚îÄ‚îÄ‚îÄ‚îÄ‚îÄ‚îÄ‚îÄ‚îÄ‚îÄ‚îÄ‚îÄ‚îÄ‚îÄ‚îÄ‚îÄ‚îÄ‚îÄ‚îÄ‚îÄ‚îÄ‚îÄ‚îÄ‚îÄ‚îÄ‚îÄ‚îÄ‚îÄ‚îÄ‚îÄ‚îÄ‚îÄ‚îÄ‚îÄ‚îÄ‚îÄ‚îÄ‚îÄ‚îÄ‚îò\n\nKey Features:\n‚Ä¢ Parallel analysis of specs/ and src/ (configurable with --parallel=N)\n‚Ä¢ Auto-generates IMPLEMENTATION_PLAN.md from specifications\n‚Ä¢ Git workflow: commit ‚Üí push ‚Üí auto-tag (each task = new version)\n‚Ä¢ Continuous: repeats until all tasks complete\n‚Ä¢ Iteration control: --max-iterations=N, /ralph-agent:loop command, or loop.py script\n```\n\n### Workflow 2: Ralph's Direct Execution\n\nFor projects with manual or existing implementation plans:\n\n```\n‚îå‚îÄ‚îÄ‚îÄ‚îÄ‚îÄ‚îÄ‚îÄ‚îÄ‚îÄ‚îÄ‚îÄ‚îÄ‚îÄ‚îÄ‚îÄ‚îÄ‚îÄ‚îÄ‚îÄ‚îÄ‚îÄ‚îÄ‚îÄ‚îÄ‚îÄ‚îÄ‚îÄ‚îÄ‚îÄ‚îÄ‚îÄ‚îÄ‚îÄ‚îÄ‚îÄ‚îÄ‚îÄ‚îÄ‚îÄ‚îÄ‚îÄ‚îÄ‚îÄ‚îÄ‚îÄ‚îÄ‚îÄ‚îÄ‚îÄ‚îÄ‚îÄ‚îÄ‚îÄ‚îÄ‚îÄ‚îÄ‚îÄ‚îÄ‚îÄ‚îÄ‚îÄ‚îÄ‚îÄ‚îÄ‚îÄ‚îÄ‚îÄ‚îÄ‚îÄ‚îÄ‚îÄ‚îÄ‚îÄ‚îÄ‚îÄ‚îÄ‚îÄ‚îê\n‚îÇ                          RALPH'S DIRECT WORKFLOW                            ‚îÇ\n‚îú‚îÄ‚îÄ‚îÄ‚îÄ‚îÄ‚îÄ‚îÄ‚îÄ‚îÄ‚îÄ‚îÄ‚îÄ‚îÄ‚îÄ‚îÄ‚îÄ‚îÄ‚îÄ‚îÄ‚îÄ‚îÄ‚îÄ‚îÄ‚îÄ‚îÄ‚îÄ‚îÄ‚îÄ‚îÄ‚îÄ‚îÄ‚îÄ‚îÄ‚îÄ‚îÄ‚îÄ‚îÄ‚îÄ‚îÄ‚îÄ‚îÄ‚îÄ‚îÄ‚îÄ‚îÄ‚îÄ‚îÄ‚îÄ‚îÄ‚îÄ‚îÄ‚îÄ‚îÄ‚îÄ‚îÄ‚îÄ‚îÄ‚îÄ‚îÄ‚îÄ‚îÄ‚îÄ‚îÄ‚îÄ‚îÄ‚îÄ‚îÄ‚îÄ‚îÄ‚îÄ‚îÄ‚îÄ‚îÄ‚îÄ‚îÄ‚îÄ‚îÄ‚î§\n‚îÇ                                                                             ‚îÇ\n‚îÇ  ‚îå‚îÄ‚îÄ‚îÄ‚îÄ‚îÄ‚îÄ‚îÄ‚îÄ‚îÄ‚îÄ‚îÄ‚îÄ‚îÄ‚îÄ‚îÄ‚îÄ‚îÄ‚îê      ‚îå‚îÄ‚îÄ‚îÄ‚îÄ‚îÄ‚îÄ‚îÄ‚îÄ‚îÄ‚îÄ‚îÄ‚îÄ‚îÄ‚îê      ‚îå‚îÄ‚îÄ‚îÄ‚îÄ‚îÄ‚îÄ‚îÄ‚îÄ‚îÄ‚îÄ‚îÄ‚îÄ‚îÄ‚îÄ‚îÄ‚îÄ‚îÄ‚îÄ‚îÄ‚îÄ‚îÄ‚îÄ‚îÄ‚îê  ‚îÇ\n‚îÇ  ‚îÇ Manual plan OR  ‚îÇ‚îÄ‚îÄ‚îÄ‚îÄ‚îÄ‚ñ∂‚îÇ /ralph-agent:ralph-init ‚îÇ‚îÄ‚îÄ‚îÄ‚îÄ‚îÄ‚ñ∂‚îÇ IMPLEMENTATION_PLAN.md‚îÇ  ‚îÇ\n‚îÇ  ‚îÇ /ralph-agent:ralph-init     ‚îÇ      ‚îÇ (optional)  ‚îÇ      ‚îÇ  (you create tasks)   ‚îÇ  ‚îÇ\n‚îÇ  ‚îî‚îÄ‚îÄ‚îÄ‚îÄ‚îÄ‚îÄ‚îÄ‚îÄ‚îÄ‚îÄ‚îÄ‚îÄ‚îÄ‚îÄ‚îÄ‚îÄ‚îÄ‚îò      ‚îî‚îÄ‚îÄ‚îÄ‚îÄ‚îÄ‚îÄ‚îÄ‚îÄ‚îÄ‚îÄ‚îÄ‚îÄ‚îÄ‚îò      ‚îî‚îÄ‚îÄ‚îÄ‚îÄ‚îÄ‚îÄ‚îÄ‚îÄ‚îÄ‚îÄ‚îÄ‚î¨‚îÄ‚îÄ‚îÄ‚îÄ‚îÄ‚îÄ‚îÄ‚îÄ‚îÄ‚îÄ‚îÄ‚îò  ‚îÇ\n‚îÇ                                                     ‚îÇ                     ‚îÇ\n‚îÇ                              ‚îå‚îÄ‚îÄ‚îÄ‚îÄ‚îÄ‚îÄ‚îÄ‚îÄ‚îÄ‚îÄ‚îÄ‚îÄ‚îÄ‚îê        ‚îÇ                     ‚îÇ\n‚îÇ                              ‚îÇ   Edit plan ‚îÇ‚óÄ‚îÄ‚îÄ‚îÄ‚îÄ‚îÄ‚îÄ‚îÄ‚îò                     ‚îÇ\n‚îÇ                              ‚îÇ  (required) ‚îÇ                              ‚îÇ\n‚îÇ                              ‚îî‚îÄ‚îÄ‚îÄ‚îÄ‚îÄ‚îÄ‚î¨‚îÄ‚îÄ‚îÄ‚îÄ‚îÄ‚îÄ‚îò                              ‚îÇ\n‚îÇ                                     ‚îÇ                                      ‚îÇ\n‚îÇ                              ‚îå‚îÄ‚îÄ‚îÄ‚îÄ‚îÄ‚îÄ‚ñº‚îÄ‚îÄ‚îÄ‚îÄ‚îÄ‚îÄ‚îê                              ‚îÇ\n‚îÇ                              ‚îÇ   /ralph-agent:ralph    ‚îÇ                              ‚îÇ\n‚îÇ                              ‚îÇ  (executor) ‚îÇ                              ‚îÇ\n‚îÇ                              ‚îî‚îÄ‚îÄ‚îÄ‚îÄ‚îÄ‚îÄ‚î¨‚îÄ‚îÄ‚îÄ‚îÄ‚îÄ‚îÄ‚îò                              ‚îÇ\n‚îÇ                                     ‚îÇ                                      ‚îÇ\n‚îÇ                              ‚îå‚îÄ‚îÄ‚îÄ‚îÄ‚îÄ‚îÄ‚ñº‚îÄ‚îÄ‚îÄ‚îÄ‚îÄ‚îÄ‚îê                              ‚îÇ\n‚îÇ                              ‚îÇ Tasks done  ‚îÇ                              ‚îÇ\n‚îÇ                              ‚îÇ  one by one‚îÇ                              ‚îÇ\n‚îÇ                              ‚îî‚îÄ‚îÄ‚îÄ‚îÄ‚îÄ‚îÄ‚îÄ‚îÄ‚îÄ‚îÄ‚îÄ‚îÄ‚îÄ‚îò                              ‚îÇ\n‚îÇ                                                                             ‚îÇ\n‚îî‚îÄ‚îÄ‚îÄ‚îÄ‚îÄ‚îÄ‚îÄ‚îÄ‚îÄ‚îÄ‚îÄ‚îÄ‚îÄ‚îÄ‚îÄ‚îÄ‚îÄ‚îÄ‚îÄ‚îÄ‚îÄ‚îÄ‚îÄ‚îÄ‚îÄ‚îÄ‚îÄ‚îÄ‚îÄ‚îÄ‚îÄ‚îÄ‚îÄ‚îÄ‚îÄ‚îÄ‚îÄ‚îÄ‚îÄ‚îÄ‚îÄ‚îÄ‚îÄ‚îÄ‚îÄ‚îÄ‚îÄ‚îÄ‚îÄ‚îÄ‚îÄ‚îÄ‚îÄ‚îÄ‚îÄ‚îÄ‚îÄ‚îÄ‚îÄ‚îÄ‚îÄ‚îÄ‚îÄ‚îÄ‚îÄ‚îÄ‚îÄ‚îÄ‚îÄ‚îÄ‚îÄ‚îÄ‚îÄ‚îÄ‚îÄ‚îÄ‚îÄ‚îò\n\nKey Features:\n‚Ä¢ Simple: create plan ‚Üí run /ralph-agent:ralph\n‚Ä¢ No git workflow (you handle commits)\n‚Ä¢ No specs/ directory required\n‚Ä¢ Continuous: repeats until all tasks complete\n‚Ä¢ Iteration control: --max-iterations=N, /ralph-agent:loop command, or loop.py script\n```\n\n### Choosing Your Workflow\n\n| Use Case | Recommended Workflow | Commands |\n|----------|---------------------|----------|\n| I have `specs/` with feature specifications | Geoff's Iterative | `/ralph-agent:gplan` ‚Üí `/ralph-agent:gbuild` |\n| I want automatic git commits + version tags | Geoff's Iterative | `/ralph-agent:gplan` ‚Üí `/ralph-agent:gbuild` |\n| I have a simple task list | Ralph's Direct | `/ralph-agent:ralph-init` ‚Üí `/ralph-agent:ralph` |\n| I manage my own git workflow | Ralph's Direct | `/ralph-agent:ralph` |\n| I need to update plan after spec changes | Geoff's Iterative | `/ralph-agent:gplan` (re-run) |\n\n### Comparison\n\n| Feature | Geoff's Workflow | Ralph's Workflow |\n|---------|------------------|------------------|\n| Specs required | Yes (`specs/` directory) | No |\n| Git workflow | Automatic (commit/push/tag) | Manual |\n| Planning | Automatic from specs | Manual |\n| Version tags | Yes (0.0.0, 0.0.1, ...) | No |\n| Parallel analysis | Yes (configurable) | No |\n| Iteration control | `--max-iterations`, `/ralph-agent:loop`, `loop.py` | `--max-iterations`, `/ralph-agent:loop`, `loop.py` |\n| Best for | Spec-driven projects | Quick task lists |\n\n## Stopping Ralph\n\nTo stop Ralph while it's working:\n\n```\nstop\n```\n\nOr:\n```\ncancel\n```\n\nRalph will:\n- Complete the current task (if in progress)\n- Save current state in `IMPLEMENTATION_PLAN.md`\n- Report how many tasks remain\n\n## Requirements\n\n- **IMPLEMENTATION_PLAN.md**: Must exist in the current directory\n- **AGENTS.md**: Should contain verification commands (optional but recommended)\n\n## Example Workflow\n\n```bash\n# Create initial plan\n/ralph-agent:ralph-init\n\n# Edit the plan with your tasks\n# Edit AGENTS.md with verification commands\n\n# Start Ralph\n/ralph-agent:ralph\n\n# Ralph output:\n‚úì Task completed: Task 1: Create database models\n  - Files modified: models.py\n  - Verification: PASSED\n  - Next task: Task 2: Implement API endpoints\n\n‚úì Task completed: Task 2: Implement API endpoints\n  - Files modified: api.py\n  - Verification: PASSED\n  - Next task: Task 3: Write unit tests\n\n‚ïî‚ïê‚ïê‚ïê‚ïê‚ïê‚ïê‚ïê‚ïê‚ïê‚ïê‚ïê‚ïê‚ïê‚ïê‚ïê‚ïê‚ïê‚ïê‚ïê‚ïê‚ïê‚ïê‚ïê‚ïê‚ïê‚ïê‚ïê‚ïê‚ïê‚ïê‚ïê‚ïê‚ïê‚ïê‚ïê‚ïê‚ïê‚ïê‚ïê‚ïê‚ïê‚ïê‚ïó\n‚ïë   ALL TASKS COMPLETED SUCCESSFULLY ‚úì    ‚ïë\n‚ïö‚ïê‚ïê‚ïê‚ïê‚ïê‚ïê‚ïê‚ïê‚ïê‚ïê‚ïê‚ïê‚ïê‚ïê‚ïê‚ïê‚ïê‚ïê‚ïê‚ïê‚ïê‚ïê‚ïê‚ïê‚ïê‚ïê‚ïê‚ïê‚ïê‚ïê‚ïê‚ïê‚ïê‚ïê‚ïê‚ïê‚ïê‚ïê‚ïê‚ïê‚ïê‚ïê‚ïù\n\nSummary:\n- Total tasks: 3\n- Completed: 3\n- Verification: All passed\n```\n\n## Components\n\n### Agents\n\n#### `ralph`\nCore executor agent that implements tasks from `IMPLEMENTATION_PLAN.md` sequentially.\n\n#### `geoff-planner`\nPlanning agent that analyzes `specs/` directory and codebase to create/update `IMPLEMENTATION_PLAN.md` with prioritized tasks.\n\n#### `geoff-builder`\nImplementation agent that executes tasks with git workflow (add/commit/push/tag) and continuous verification.\n\n### Commands\n\n#### `/ralph-agent:ralph`\nStart Ralph to execute tasks sequentially without git workflow.\n\n#### `/ralph-agent:ralph-init`\nCreate an empty `IMPLEMENTATION_PLAN.md` template file.\n\n#### `/ralph-agent:gplan`\nTrigger Geoff's Planner to analyze specs and generate/update implementation plan.\n\n#### `/ralph-agent:gbuild`\nTrigger Geoff's Builder to implement tasks with full git workflow and auto-tagging.\n\n### Skill: `implementation-plan`\nProvides knowledge about:\n- Parsing markdown checklists\n- Reading verification commands\n- Updating task completion status\n- Continuous execution patterns\n\n## Plugin Structure\n\n```\nralph-agent/\n‚îú‚îÄ‚îÄ .claude-plugin/\n‚îÇ   ‚îî‚îÄ‚îÄ plugin.json          # Plugin manifest\n‚îú‚îÄ‚îÄ agents/\n‚îÇ   ‚îú‚îÄ‚îÄ ralph.md             # Ralph executor agent\n‚îÇ   ‚îú‚îÄ‚îÄ geoff-planner.md     # Geoff's Planner agent\n‚îÇ   ‚îî‚îÄ‚îÄ geoff-builder.md     # Geoff's Builder agent\n‚îú‚îÄ‚îÄ commands/\n‚îÇ   ‚îú‚îÄ‚îÄ ralph.md             # /ralph-agent:ralph command\n‚îÇ   ‚îú‚îÄ‚îÄ ralph-init.md        # /ralph-agent:ralph-init command\n‚îÇ   ‚îú‚îÄ‚îÄ gplan.md             # /ralph-agent:gplan command\n‚îÇ   ‚îú‚îÄ‚îÄ gbuild.md            # /ralph-agent:gbuild command\n‚îÇ   ‚îî‚îÄ‚îÄ loop.md              # /ralph-agent:loop wrapper command\n‚îú‚îÄ‚îÄ skills/\n‚îÇ   ‚îî‚îÄ‚îÄ implementation-plan/\n‚îÇ       ‚îú‚îÄ‚îÄ SKILL.md         # Main skill file\n‚îÇ       ‚îú‚îÄ‚îÄ references/      # Detailed references\n‚îÇ       ‚îÇ   ‚îú‚îÄ‚îÄ task-examples.md\n‚îÇ       ‚îÇ   ‚îî‚îÄ‚îÄ verification-patterns.md\n‚îÇ       ‚îú‚îÄ‚îÄ examples/        # Working examples\n‚îÇ       ‚îÇ   ‚îú‚îÄ‚îÄ IMPLEMENTATION_PLAN.md.template\n‚îÇ       ‚îÇ   ‚îî‚îÄ‚îÄ AGENTS.md.example\n‚îÇ       ‚îî‚îÄ‚îÄ scripts/         # Utility scripts\n‚îÇ           ‚îî‚îÄ‚îÄ parse-tasks.sh\n‚îú‚îÄ‚îÄ loop.py                  # External loop controller script\n‚îú‚îÄ‚îÄ README.md\n‚îî‚îÄ‚îÄ .gitignore\n```\n\n## Best Practices\n\n### Writing Tasks\n- Be specific: \"Add JWT authentication\" instead of \"Work on auth\"\n- Keep tasks independent: Each task should be completable separately\n- Make tasks verifiable: Include acceptance criteria\n- Reasonable scope: Tasks should take 30 minutes to 2 hours\n\n### Verification Commands\n- Order by speed: Fast checks first (linting) then slow (tests)\n- Be specific: Use paths to test only affected code when possible\n- Include all checks: Linting, type checking, and tests\n- Use AGENTS.md: Keep verification commands out of the plan file\n\n### Using Ralph\n- Let it run: Ralph works best when allowed to complete multiple tasks\n- Check progress: Ralph reports after each task\n- Stop gracefully: Use \"stop\" to halt between tasks\n- Verify before commit: All verification commands pass automatically\n\n## Troubleshooting\n\n### \"No IMPLEMENTATION_PLAN.md found\"\nRun `/ralph-agent:ralph-init` to create a template plan file.\n\n### \"No verification commands found\"\nCreate `AGENTS.md` with verification commands.\n\n### Verification keeps failing\nRalph will automatically fix and retry. If it fails repeatedly, Ralph will ask for guidance.\n\n### Ralph stopped unexpectedly\nRalph saves progress after each task. Just run `/ralph-agent:ralph` again to continue.\n\n## Publishing & Distribution\n\nThis plugin is distributed via the Claude Code marketplace system from the [roach-loop repository](https://github.com/tmdgusya/roach-loop).\n\n### For Users - Quick Start\n\n**Install the plugin in 2 commands:**\n\n```bash\n# 1. Add the marketplace\n/plugin marketplace add tmdgusya/roach-loop\n\n# 2. Install the plugin\n/plugin install ralph-agent@ralph-agent-marketplace\n```\n\n**Update to latest version:**\n\n```bash\n/plugin update ralph-agent\n```\n\n**Verify installation:**\n\n```bash\n/plugin list\n```\n\nYou should see `ralph-agent` in the installed plugins list.\n\n### For Plugin Developers\n\nTo publish updates to this plugin:\n\n1. **Update version** in both files:\n   - `ralph-agent/.claude-plugin/plugin.json` (line 3)\n   - `.claude-plugin/marketplace.json` at repository root (line 11)\n\n2. **Commit and push changes**:\n   ```bash\n   git add .\n   git commit -m \"Release v0.4.0: Add new features\"\n   git push origin main\n   ```\n\n3. **Create a release tag** (recommended):\n   ```bash\n   git tag v0.4.0\n   git push origin v0.4.0\n   ```\n\n4. **Users update automatically**:\n   Users who have added your marketplace can update with:\n   ```bash\n   /plugin update ralph-agent\n   ```\n\n### Repository Structure\n\n```\nroach-loop/                              # GitHub repository root\n‚îú‚îÄ‚îÄ .claude-plugin/\n‚îÇ   ‚îî‚îÄ‚îÄ marketplace.json                 # Marketplace catalog (source: ./ralph-agent:ralph-agent)\n‚îú‚îÄ‚îÄ ralph-agent/                         # Plugin directory\n‚îÇ   ‚îú‚îÄ‚îÄ .claude-plugin/\n‚îÇ   ‚îÇ   ‚îú‚îÄ‚îÄ plugin.json                  # Plugin manifest\n‚îÇ   ‚îÇ   ‚îî‚îÄ‚îÄ marketplace.json             # (backup/reference)\n‚îÇ   ‚îú‚îÄ‚îÄ agents/                          # ralph, geoff-planner, geoff-builder\n‚îÇ   ‚îú‚îÄ‚îÄ commands/                        # /ralph-agent:ralph, /ralph-agent:gplan, /ralph-agent:gbuild, etc.\n‚îÇ   ‚îú‚îÄ‚îÄ skills/                          # implementation-plan skill\n‚îÇ   ‚îú‚îÄ‚îÄ loop.py                          # External loop controller\n‚îÇ   ‚îî‚îÄ‚îÄ README.md                        # This file\n‚îî‚îÄ‚îÄ ...\n```\n\n### Marketplace System\n\nClaude Code uses a **decentralized marketplace model**:\n\n| Traditional App Store | Claude Code Marketplace |\n|----------------------|------------------------|\n| ‚ùå Submit to centralized authority | ‚úÖ Host on your own GitHub |\n| ‚ùå Wait for approval | ‚úÖ Instant distribution |\n| ‚ùå Follow store policies | ‚úÖ Full control over updates |\n| ‚ùå Revenue sharing | ‚úÖ Free and open |\n\n**How it works:**\n1. **Plugin author** creates `marketplace.json` in their GitHub repo\n2. **Users** add the marketplace: `/plugin marketplace add tmdgusya/roach-loop`\n3. **Claude Code** fetches plugin from GitHub when user installs\n4. **Updates** are pulled from GitHub when user runs `/plugin update`\n\n**Advantages:**\n- ‚úÖ No gatekeepers - publish instantly\n- ‚úÖ Version control via Git\n- ‚úÖ Users choose which marketplaces to trust\n- ‚úÖ Open source and transparent\n- ‚úÖ No lock-in to Anthropic's marketplace\n\n### Distribution URLs\n\n**Primary distribution (Recommended):**\n```bash\n/plugin marketplace add tmdgusya/roach-loop\n/plugin install ralph-agent@ralph-agent-marketplace\n```\n\n**Alternative - Direct Git URL:**\n```bash\n/plugin install https://github.com/tmdgusya/roach-loop.git --subdirectory ralph-agent\n```\n\n**Alternative - Clone and install locally:**\n```bash\ngit clone https://github.com/tmdgusya/roach-loop.git\n/plugin install ./roach-loop/ralph-agent:ralph-agent\n```\n\n## License\n\nMIT\n\n## Contributing\n\nContributions welcome! Please feel free to submit issues or pull requests.\n"
      },
      "plugins": [
        {
          "name": "ralph-agent",
          "source": "./ralph-agent",
          "description": "Implementation agents with planning, building, and loop control workflows using IMPLEMENTATION_PLAN.md with continuous task execution, verification, git workflow, and iteration limits",
          "version": "0.5.0",
          "author": {
            "name": "tmdgusya"
          },
          "keywords": [
            "automation",
            "implementation",
            "task-runner",
            "verification",
            "planning",
            "git-workflow",
            "iteration-control",
            "loop"
          ],
          "homepage": "https://github.com/tmdgusya/roach-loop",
          "repository": "https://github.com/tmdgusya/roach-loop.git",
          "license": "MIT",
          "strict": false,
          "categories": [
            "automation",
            "git-workflow",
            "implementation",
            "iteration-control",
            "loop",
            "planning",
            "task-runner",
            "verification"
          ],
          "install_commands": [
            "/plugin marketplace add tmdgusya/roach-loop",
            "/plugin install ralph-agent@ralph-agent-marketplace"
          ]
        }
      ]
    }
  ]
}