{
  "author": {
    "id": "utsmok",
    "display_name": "Samuel Mok",
    "avatar_url": "https://avatars.githubusercontent.com/u/131749029?u=da02783b2429cf7abfb5335b1c85671d10afd05a&v=4"
  },
  "marketplaces": [
    {
      "name": "mailtool-plugin-marketplace",
      "version": null,
      "description": "Outlook integration via MCP. Manage emails, calendar, and tasks.",
      "repo_full_name": "utsmok/mailtool-plugin",
      "repo_url": "https://github.com/utsmok/mailtool-plugin",
      "repo_description": null,
      "signals": {
        "stars": 0,
        "forks": 0,
        "pushed_at": "2026-01-19T22:57:34Z"
      },
      "files": {
        ".claude-plugin/marketplace.json": "{\n  \"name\": \"mailtool-plugin-marketplace\",\n  \"owner\": {\n    \"name\": \"utsmok\"\n  },\n  \"plugins\": [\n    {\n      \"name\": \"mailtool\",\n      \"source\": \"./\",\n      \"description\": \"Outlook integration via MCP. Manage emails, calendar, and tasks.\",\n      \"version\": \"1.0.0\",\n      \"author\": {\n        \"name\": \"utsmok\"\n      },\n      \"homepage\": \"https://github.com/utsmok/mailtool-plugin\",\n      \"repository\": \"https://github.com/utsmok/mailtool-plugin\",\n      \"license\": \"MIT\",\n      \"keywords\": [\n        \"outlook\",\n        \"email\",\n        \"calendar\",\n        \"tasks\",\n        \"mcp\",\n        \"productivity\"\n      ],\n      \"category\": \"productivity\"\n    }\n  ]\n}",
        ".claude-plugin/plugin.json": "{\n  \"name\": \"mailtool\",\n  \"version\": \"1.0.0\",\n  \"description\": \"Outlook integration via MCP. Manage emails, calendar, and tasks.\"\n}",
        "README.md": "# Mailtool Plugin for Claude Code\n\nThis is the Claude Code plugin for [mailtool](https://github.com/utsmok/mailtool), which provides Outlook integration via MCP.\n\n## Installation\n\n### Via Claude Code Marketplace (Recommended)\n\n```bash\n/plugin marketplace add utsmok/mailtool-plugin\n/plugin install mailtool\n```\n\nThis will automatically:\n- Configure the MCP server using `uvx mailtool` (no installation needed!)\n- Install the Daily Planner skill for intelligent daily planning\n\n## What's Included\n\n### MCP Server (24 tools)\n\nThe plugin configures mailtool as an MCP server with tools for:\n- ðŸ“§ **Email** (10 tools): List, read, send, reply, forward, mark, move, delete, search\n- ðŸ“… **Calendar** (7 tools): List, create, get, edit, respond to meetings, check free/busy\n- âœ… **Tasks** (7 tools): List, create, get, edit, complete, delete tasks\n\n### Daily Planner Skill\n\nAn intelligent assistant that:\n- Analyzes your calendar, tasks, and emails\n- Creates actionable daily plans with priorities\n- Provides interactive walkthrough for email responses\n- Suggests task execution order\n- Offers proactive insights\n\n## How It Works\n\nThis plugin is just a thin wrapper that:\n1. Configures Claude Code to connect to the mailtool MCP server\n2. Uses `uvx` to run `mailtool` without requiring installation\n3. Bundles the Daily Planner skill for enhanced productivity\n\nThe actual Python package is published separately on PyPI as [mailtool](https://pypi.org/project/mailtool/).\n\n## Requirements\n\n- Windows with Outlook installed and running\n- `uv` installed (for `uvx` command)\n  - Install via: `curl -LsSf https://astral.sh/uv/install.sh | sh` (Linux/WSL2)\n  - Or: `powershell -c \"irm https://astral.sh/uv/install.ps1 | iex\"` (Windows)\n\n## Usage Examples\n\nOnce installed, you can:\n\n```\n# Check your daily plan\nPlan my day\n\n# Show unread emails\nShow me my last 5 unread emails\n\n# Create a task\nCreate a task \"Review Q1 report\" due Friday with high priority\n\n# Schedule a meeting\nSchedule a team meeting for tomorrow at 2pm in Room 101\n\n# Accept a meeting invitation\nAccept the meeting invitation from John\n\n# Check your calendar\nWhat\"s on my calendar this week?\n```\n\n## Development\n\nThis plugin repo contains only configuration files. For development:\n\n- **Python package**: [utsmok/mailtool](https://github.com/utsmok/mailtool)\n- **This plugin**: [utsmok/mailtool-plugin](https://github.com/utsmok/mailtool-plugin)\n\n## License\n\nMIT\n\n## Author\n\nSam (utsmok)\n"
      },
      "plugins": [
        {
          "name": "mailtool",
          "source": "./",
          "description": "Outlook integration via MCP. Manage emails, calendar, and tasks.",
          "version": "1.0.0",
          "author": {
            "name": "utsmok"
          },
          "homepage": "https://github.com/utsmok/mailtool-plugin",
          "repository": "https://github.com/utsmok/mailtool-plugin",
          "license": "MIT",
          "keywords": [
            "outlook",
            "email",
            "calendar",
            "tasks",
            "mcp",
            "productivity"
          ],
          "category": "productivity",
          "categories": [
            "calendar",
            "email",
            "mcp",
            "outlook",
            "productivity",
            "tasks"
          ],
          "install_commands": [
            "/plugin marketplace add utsmok/mailtool-plugin",
            "/plugin install mailtool@mailtool-plugin-marketplace"
          ]
        }
      ]
    }
  ]
}