{
  "author": {
    "id": "VdustR",
    "display_name": "ViPro (‰∫¨‰∫¨)",
    "avatar_url": "https://avatars.githubusercontent.com/u/29639463?u=9a328e250217e0cd6048ba9e20e8fead29ff2ca3&v=4"
  },
  "marketplaces": [
    {
      "name": "vdustr",
      "version": null,
      "description": "Claude Code plugins by VdustR",
      "repo_full_name": "VdustR/vp-claude-code-marketplace",
      "repo_url": "https://github.com/VdustR/vp-claude-code-marketplace",
      "repo_description": null,
      "signals": {
        "stars": 0,
        "forks": 0,
        "pushed_at": "2026-01-27T02:29:29Z"
      },
      "files": {
        ".claude-plugin/marketplace.json": "{\n  \"name\": \"vdustr\",\n  \"owner\": {\n    \"name\": \"VdustR\"\n  },\n  \"metadata\": {\n    \"description\": \"Claude Code plugins by VdustR\"\n  },\n  \"plugins\": [\n    {\n      \"name\": \"vp-add-skill\",\n      \"source\": \"./plugins/vp-add-skill\",\n      \"description\": \"Manage agent skills installation with registry tracking\",\n      \"license\": \"MIT\",\n      \"keywords\": [\"skills\", \"registry\", \"management\"]\n    },\n    {\n      \"name\": \"vp-gitignore-builder\",\n      \"source\": \"./plugins/vp-gitignore-builder\",\n      \"description\": \"Build and merge .gitignore files using github/gitignore templates\",\n      \"license\": \"MIT\",\n      \"keywords\": [\"gitignore\", \"git\", \"ignore\", \"templates\", \"github\"]\n    },\n    {\n      \"name\": \"vp-nyan-mode\",\n      \"source\": \"./plugins/vp-nyan-mode\",\n      \"description\": \"Cat persona with verbal tic, emoji support, and language matching\",\n      \"license\": \"MIT\",\n      \"keywords\": [\"cat\", \"nyan\", \"persona\", \"emoji\", \"kawaii\", \"verbal-tic\"]\n    },\n    {\n      \"name\": \"vp-pr-comment-resolver\",\n      \"source\": \"./plugins/vp-pr-comment-resolver\",\n      \"description\": \"Automate PR comment review, fix, and resolution workflow\",\n      \"license\": \"MIT\",\n      \"keywords\": [\"pr\", \"pull-request\", \"review\", \"comments\", \"github\", \"automation\"]\n    },\n    {\n      \"name\": \"vp-typescript-best-practices\",\n      \"source\": \"./plugins/vp-typescript-best-practices\",\n      \"description\": \"TypeScript coding guidelines with dos and don'ts for type design and patterns\",\n      \"license\": \"MIT\",\n      \"keywords\": [\"typescript\", \"best-practices\", \"type-design\", \"coding-guidelines\", \"style-guide\"]\n    },\n    {\n      \"name\": \"vp-wenyan-mode\",\n      \"source\": \"./plugins/vp-wenyan-mode\",\n      \"description\": \"Classical Chinese (ÊñáË®ÄÊñá) writing style with concise, elegant expressions\",\n      \"license\": \"MIT\",\n      \"keywords\": [\"wenyan\", \"classical-chinese\", \"ÊñáË®ÄÊñá\", \"persona\", \"writing-style\"]\n    }\n  ]\n}\n",
        "README.md": "# Claude Code Marketplace\n\nClaude Code plugins by [VdustR](https://github.com/VdustR).\n\n> All plugins in this marketplace use the `vp-` prefix (VdustR Plugin).\n\n## Installation\n\n```bash\n/plugin marketplace add VdustR/vp-claude-code-marketplace\n```\n\n## Available Plugins\n\n> Plugins are listed in alphabetical order.\n\n### vp-add-skill\n\nManage agent skills installation with registry tracking.\n\n```bash\n/plugin install vp-add-skill@vdustr\n```\n\nFeatures:\n- Install skills from any git repository using `npx add-skill`\n- Track installed skills with a JSON registry\n- Support for global, project (shared), and project (local) scopes\n- JSON Schema validation for registry format\n\n### vp-gitignore-builder\n\nBuild and merge .gitignore files using github/gitignore templates.\n\n```bash\n/plugin install vp-gitignore-builder@vdustr\n```\n\nFeatures:\n- Smart project detection (Node, Python, Rust, Go, etc.)\n- Live fetch from [github/gitignore](https://github.com/github/gitignore) for latest templates\n- Intelligent merge with existing .gitignore files\n- EOL conflict detection and resolution\n- Auto-suggest `*.local` and `*.local.*` patterns\n- Support for both project-level and global gitignore\n\n### vp-nyan-mode\n\nCat persona with 'nyan~' verbal tic, emoji support, and language matching.\n\n```bash\n/plugin install vp-nyan-mode@vdustr\n```\n\nFeatures:\n- Adds 'nyan~' verbal tic to responses\n- Enables emoji usage\n- Matches user's language preference\n\n### vp-pr-comment-resolver\n\nAutomate PR comment review, fix, and resolution workflow.\n\n```bash\n/plugin install vp-pr-comment-resolver@vdustr\n```\n\nFeatures:\n- Interactive mode (review each comment) and auto mode (process all automatically)\n- Atomic commits per fix with smart grouping for related comments\n- Detailed reply format with commit links: `- [hash message](url)`\n- Summary report generation after processing all comments\n- Human collaboration - asks when uncertain about fixes\n\n### vp-typescript-best-practices\n\nTypeScript coding guidelines with dos and don'ts for type design and patterns.\n\n```bash\n/plugin install vp-typescript-best-practices@vdustr\n```\n\nFeatures:\n- Type-first design with namespace pattern for organizing types\n- Clear DO/DON'T tables for interface vs type, any usage, function declarations\n- Naming conventions (PascalCase, `T` prefix for generics, `Id` not `ID`)\n- Type extraction patterns (prefer extracting over redefining)\n- Generic const pattern for strict literal inference\n- Type testing guidelines with `*.test-d.ts`\n- Environment setup with strictest tsconfig and ts-reset\n\n### vp-wenyan-mode\n\nClassical Chinese (ÊñáË®ÄÊñá) writing style with concise, elegant expressions.\n\n```bash\n/plugin install vp-wenyan-mode@vdustr\n```\n\nFeatures:\n- Always-active classical Chinese writing style\n- Concise expressions (Ë®ÄÁ∞°ÊÑèË≥Ö)\n- Technical terms preserved (function, API, commit, etc.)\n- Minimal use of classical particles (‰πã‰πéËÄÖ‰πü)\n\n## Development\n\nThis marketplace is developed using the [plugin-dev](https://github.com/anthropics/claude-code/tree/main/.claude/plugins/plugin-dev) plugin.\n\n## License\n\n[MIT](https://github.com/VdustR/vp-claude-code-marketplace/blob/main/LICENSE) - Made with ü§ñ‚ù§Ô∏è by [VdustR](https://github.com/VdustR)\n"
      },
      "plugins": [
        {
          "name": "vp-add-skill",
          "source": "./plugins/vp-add-skill",
          "description": "Manage agent skills installation with registry tracking",
          "license": "MIT",
          "keywords": [
            "skills",
            "registry",
            "management"
          ],
          "categories": [
            "management",
            "registry",
            "skills"
          ],
          "install_commands": [
            "/plugin marketplace add VdustR/vp-claude-code-marketplace",
            "/plugin install vp-add-skill@vdustr"
          ]
        },
        {
          "name": "vp-gitignore-builder",
          "source": "./plugins/vp-gitignore-builder",
          "description": "Build and merge .gitignore files using github/gitignore templates",
          "license": "MIT",
          "keywords": [
            "gitignore",
            "git",
            "ignore",
            "templates",
            "github"
          ],
          "categories": [
            "git",
            "github",
            "gitignore",
            "ignore",
            "templates"
          ],
          "install_commands": [
            "/plugin marketplace add VdustR/vp-claude-code-marketplace",
            "/plugin install vp-gitignore-builder@vdustr"
          ]
        },
        {
          "name": "vp-nyan-mode",
          "source": "./plugins/vp-nyan-mode",
          "description": "Cat persona with verbal tic, emoji support, and language matching",
          "license": "MIT",
          "keywords": [
            "cat",
            "nyan",
            "persona",
            "emoji",
            "kawaii",
            "verbal-tic"
          ],
          "categories": [
            "cat",
            "emoji",
            "kawaii",
            "nyan",
            "persona",
            "verbal-tic"
          ],
          "install_commands": [
            "/plugin marketplace add VdustR/vp-claude-code-marketplace",
            "/plugin install vp-nyan-mode@vdustr"
          ]
        },
        {
          "name": "vp-pr-comment-resolver",
          "source": "./plugins/vp-pr-comment-resolver",
          "description": "Automate PR comment review, fix, and resolution workflow",
          "license": "MIT",
          "keywords": [
            "pr",
            "pull-request",
            "review",
            "comments",
            "github",
            "automation"
          ],
          "categories": [
            "automation",
            "comments",
            "github",
            "pr",
            "pull-request",
            "review"
          ],
          "install_commands": [
            "/plugin marketplace add VdustR/vp-claude-code-marketplace",
            "/plugin install vp-pr-comment-resolver@vdustr"
          ]
        },
        {
          "name": "vp-typescript-best-practices",
          "source": "./plugins/vp-typescript-best-practices",
          "description": "TypeScript coding guidelines with dos and don'ts for type design and patterns",
          "license": "MIT",
          "keywords": [
            "typescript",
            "best-practices",
            "type-design",
            "coding-guidelines",
            "style-guide"
          ],
          "categories": [
            "best-practices",
            "coding-guidelines",
            "style-guide",
            "type-design",
            "typescript"
          ],
          "install_commands": [
            "/plugin marketplace add VdustR/vp-claude-code-marketplace",
            "/plugin install vp-typescript-best-practices@vdustr"
          ]
        },
        {
          "name": "vp-wenyan-mode",
          "source": "./plugins/vp-wenyan-mode",
          "description": "Classical Chinese (ÊñáË®ÄÊñá) writing style with concise, elegant expressions",
          "license": "MIT",
          "keywords": [
            "wenyan",
            "classical-chinese",
            "ÊñáË®ÄÊñá",
            "persona",
            "writing-style"
          ],
          "categories": [
            "classical-chinese",
            "persona",
            "wenyan",
            "writing-style",
            "ÊñáË®ÄÊñá"
          ],
          "install_commands": [
            "/plugin marketplace add VdustR/vp-claude-code-marketplace",
            "/plugin install vp-wenyan-mode@vdustr"
          ]
        }
      ]
    }
  ]
}