{
  "author": {
    "id": "VdustR",
    "display_name": "ViPro (‰∫¨‰∫¨)",
    "avatar_url": "https://avatars.githubusercontent.com/u/29639463?u=9a328e250217e0cd6048ba9e20e8fead29ff2ca3&v=4"
  },
  "marketplaces": [
    {
      "name": "vdustr",
      "version": null,
      "description": "Claude Code plugins by VdustR",
      "repo_full_name": "VdustR/vp-claude-code-marketplace",
      "repo_url": "https://github.com/VdustR/vp-claude-code-marketplace",
      "repo_description": null,
      "signals": {
        "stars": 0,
        "forks": 0,
        "pushed_at": "2026-02-20T10:50:01Z"
      },
      "files": {
        ".claude-plugin/marketplace.json": "{\n  \"name\": \"vdustr\",\n  \"owner\": {\n    \"name\": \"VdustR\"\n  },\n  \"metadata\": {\n    \"description\": \"Claude Code plugins by VdustR\"\n  },\n  \"plugins\": [\n    {\n      \"name\": \"vp-checklist-runner\",\n      \"source\": \"./plugins/vp-checklist-runner\",\n      \"description\": \"Parse and verify GitHub PR/issue checklists with auto-check and CI integration\",\n      \"license\": \"MIT\",\n      \"keywords\": [\"checklist\", \"pr\", \"issue\", \"github\", \"verification\", \"ci\", \"automation\", \"checkbox\"]\n    },\n    {\n      \"name\": \"vp-cspell\",\n      \"source\": \"./plugins/vp-cspell\",\n      \"description\": \"Handle cspell unknown word warnings with prioritized decision tree and config bootstrapping\",\n      \"license\": \"MIT\",\n      \"keywords\": [\"cspell\", \"spelling\", \"linting\", \"ide\"]\n    },\n    {\n      \"name\": \"vp-deps-shift\",\n      \"source\": \"./plugins/vp-deps-shift\",\n      \"description\": \"Dependency upgrade and library migration with breaking change detection and test-first verification\",\n      \"license\": \"MIT\",\n      \"keywords\": [\"dependencies\", \"upgrade\", \"migration\", \"breaking-changes\", \"codemod\", \"dependabot\", \"renovate\", \"context7\"]\n    },\n    {\n      \"name\": \"vp-gitignore-builder\",\n      \"source\": \"./plugins/vp-gitignore-builder\",\n      \"description\": \"Build and merge .gitignore files using github/gitignore templates\",\n      \"license\": \"MIT\",\n      \"keywords\": [\"gitignore\", \"git\", \"ignore\", \"templates\", \"github\"]\n    },\n    {\n      \"name\": \"vp-localsend\",\n      \"source\": \"./plugins/vp-localsend\",\n      \"description\": \"Send and receive files over local network using LocalSend protocol\",\n      \"license\": \"MIT\",\n      \"keywords\": [\"localsend\", \"file-transfer\", \"local-network\", \"airdrop\", \"send\", \"receive\", \"share\"]\n    },\n    {\n      \"name\": \"vp-nyan-mode\",\n      \"source\": \"./plugins/vp-nyan-mode\",\n      \"description\": \"Cat persona with verbal tic, emoji support, and language matching\",\n      \"license\": \"MIT\",\n      \"keywords\": [\"cat\", \"nyan\", \"persona\", \"emoji\", \"kawaii\", \"verbal-tic\"]\n    },\n    {\n      \"name\": \"vp-pr-comment-resolver\",\n      \"source\": \"./plugins/vp-pr-comment-resolver\",\n      \"description\": \"Automate PR comment review, fix, and resolution workflow\",\n      \"license\": \"MIT\",\n      \"keywords\": [\"pr\", \"pull-request\", \"review\", \"comments\", \"github\", \"automation\"]\n    },\n    {\n      \"name\": \"vp-review-loop\",\n      \"source\": \"./plugins/vp-review-loop\",\n      \"description\": \"Iterative multi-pass subagent review loop with confidence scoring for code and plans\",\n      \"license\": \"MIT\",\n      \"keywords\": [\"code-review\", \"plan-review\", \"multi-pass\", \"confidence-index\", \"subagent\", \"iterative\", \"loop-control\"]\n    },\n    {\n      \"name\": \"vp-skills\",\n      \"source\": \"./plugins/vp-skills\",\n      \"description\": \"Manage agent skills using npx skills CLI\",\n      \"license\": \"MIT\",\n      \"keywords\": [\"skills\", \"management\", \"npx\"]\n    },\n    {\n      \"name\": \"vp-somafm\",\n      \"source\": \"./plugins/vp-somafm\",\n      \"description\": \"Play SomaFM internet radio as background music during coding sessions\",\n      \"license\": \"MIT\",\n      \"keywords\": [\"somafm\", \"radio\", \"music\", \"streaming\", \"ambient\", \"mpv\"]\n    },\n    {\n      \"name\": \"vp-stacked-pr-rebase\",\n      \"source\": \"./plugins/vp-stacked-pr-rebase\",\n      \"description\": \"Rebase stacked PRs after parent PR is merged, preserving only your commits\",\n      \"license\": \"MIT\",\n      \"keywords\": [\"pr\", \"pull-request\", \"rebase\", \"stacked\", \"cherry-pick\", \"github\", \"dependency\"]\n    },\n    {\n      \"name\": \"vp-typescript-best-practices\",\n      \"source\": \"./plugins/vp-typescript-best-practices\",\n      \"description\": \"TypeScript coding guidelines with dos and don'ts for type design and patterns\",\n      \"license\": \"MIT\",\n      \"keywords\": [\"typescript\", \"best-practices\", \"type-design\", \"coding-guidelines\", \"style-guide\"]\n    },\n    {\n      \"name\": \"vp-wenyan-mode\",\n      \"source\": \"./plugins/vp-wenyan-mode\",\n      \"description\": \"Classical Chinese (ÊñáË®ÄÊñá) writing style with concise, elegant expressions\",\n      \"license\": \"MIT\",\n      \"keywords\": [\"wenyan\", \"classical-chinese\", \"ÊñáË®ÄÊñá\", \"persona\", \"writing-style\"]\n    }\n  ]\n}\n",
        "README.md": "# Claude Code Marketplace\n\nClaude Code plugins by [VdustR](https://github.com/VdustR).\n\n> All plugins in this marketplace use the `vp-` prefix (VdustR Plugin).\n\n## Installation\n\n```bash\n/plugin marketplace add VdustR/vp-claude-code-marketplace\n```\n\n## Available Plugins\n\n> Plugins are listed in alphabetical order.\n\n### vp-checklist-runner\n\nParse and verify GitHub PR/issue checklists with auto-check and CI integration.\n\n```bash\n/plugin install vp-checklist-runner@vdustr\n```\n\nFeatures:\n- 5-phase workflow: source resolution, classification, verification, checkbox update, summary report\n- Auto-classifies checklist items into Auto / CI / Shell / Scan / Human categories\n- CI-first verification ‚Äî checks CI status before running tests locally\n- Ownership-aware updates ‚Äî respects GitHub permissions, defaults to comment mode for others' posts\n- Race condition prevention via `updated_at` timestamp comparison\n- Confidence-based automation ‚Äî only pauses for uncertain items\n- Scan subagents for semantic checks (secrets, docs, changelog) with user confirmation\n\n### vp-cspell\n\nHandle cspell unknown word warnings with prioritized decision tree and config bootstrapping.\n\n```bash\n/plugin install vp-cspell@vdustr\n```\n\nFeatures:\n- Prioritized decision tree: adjust text > project dictionary > inline directives\n- Smart inline directive selection (cspell:words vs cspell:ignore vs cspell:disable)\n- Interactive config bootstrapping via `cspell init` with guided Q&A\n- Runtime documentation via Context7 ‚Äî no stale reference files\n\n### vp-deps-shift\n\nDependency upgrade and library migration with breaking change detection and test-first verification.\n\n```bash\n/plugin install vp-deps-shift@vdustr\n```\n\n**Skills included:**\n- **deps-upgrade** ‚Äî Version upgrades with breaking change detection, deps bot PR handling\n- **deps-migrate** ‚Äî Library replacement and API pattern migration (e.g., forwardRef removal)\n\nFeatures:\n- Test-first verification in /tmp before batch execution\n- Context7 + changelog parallel documentation lookup\n- Official codemod detection and compat layer support\n- 3-pass subagent review loop (direct, best practice, critical think)\n- Multi-ecosystem support (npm, pnpm, yarn, bun, cargo, pip, go, bundler, composer)\n- Deps bot PR handling (dependabot, renovate)\n- Repo convention compliance (changesets, conventional commits, CI checks)\n\n### vp-gitignore-builder\n\nBuild and merge .gitignore files using github/gitignore templates.\n\n```bash\n/plugin install vp-gitignore-builder@vdustr\n```\n\nFeatures:\n- Smart project detection (Node, Python, Rust, Go, etc.)\n- Live fetch from [github/gitignore](https://github.com/github/gitignore) for latest templates\n- Intelligent merge with existing .gitignore files\n- EOL conflict detection and resolution\n- Auto-suggest `*.local` and `*.local.*` patterns\n- Support for both project-level and global gitignore\n\n### vp-localsend\n\nSend and receive files over local network using [LocalSend](https://localsend.org/) protocol (like AirDrop).\n\n```bash\n/plugin install vp-localsend@vdustr\n```\n\nFeatures:\n- Scan for nearby LocalSend devices on local network\n- Send files and directories to any LocalSend client (phone, tablet, PC)\n- Receive files from other devices with background server\n- Auto-downloads [localsend-cli](https://github.com/0w0mewo/localsend-cli) on first use\n- Idle server reminder to prevent forgotten background processes\n- Compatible with all LocalSend apps (iOS, Android, macOS, Windows, Linux)\n\n### vp-nyan-mode\n\nCat persona with 'nyan~' verbal tic, emoji support, and language matching.\n\n```bash\n/plugin install vp-nyan-mode@vdustr\n```\n\nFeatures:\n- Adds 'nyan~' verbal tic to responses\n- Enables emoji usage\n- Matches user's language preference\n\n### vp-pr-comment-resolver\n\nAutomate PR comment review, fix, and resolution workflow.\n\n```bash\n/plugin install vp-pr-comment-resolver@vdustr\n```\n\nFeatures:\n- Interactive mode (review each comment) and auto mode (process all automatically)\n- Atomic commits per fix with smart grouping for related comments\n- Detailed reply format with commit links: `- [hash message](url)`\n- Summary report generation after processing all comments\n- Human collaboration - asks when uncertain about fixes\n\n### vp-review-loop\n\nIterative multi-pass subagent review loop with confidence scoring for code and plans.\n\n```bash\n/plugin install vp-review-loop@vdustr\n```\n\n**Skills included:**\n- **review-loop** ‚Äî Multi-pass code review (Direct, Best Practice, Critical Think) with iterative fix cycles\n- **plan-review** ‚Äî Plan optimization with confidence index scoring and pros/cons analysis\n\nFeatures:\n- 3 built-in passes: Direct (correctness), Best Practice (quality), Critical Think (risk)\n- Context-aware suggested passes: Testability, Accessibility, API Surface, Performance, i18n, Concurrency (code); Incremental Delivery, Stakeholder Impact, Maintenance Burden, Team Coordination (plans)\n- Iterative fix-review loop with stall detection and ping-pong mitigation\n- Generalized confidence index with 5 factors, floor rule, and boost options\n- Structured pros/cons analysis for plan decisions\n- Extensible: custom subagent passes + manual external AI review support\n\n### vp-skills\n\nManage agent skills using the npx skills CLI.\n\n```bash\n/plugin install vp-skills@vdustr\n```\n\nFeatures:\n- Install skills from any git repository using `npx skills`\n- List, search, and discover available skills\n- Update all installed skills with one command\n- Support for global and project-level skill scopes\n\n### vp-somafm\n\nPlay SomaFM internet radio as background music during coding sessions.\n\n```bash\n/plugin install vp-somafm@vdustr\n```\n\nFeatures:\n- Stream any SomaFM channel with one command (default: groovesalad)\n- Browse channels with live listener counts from SomaFM API\n- Now-playing track info and playback status\n- Seamless volume control via mpv IPC socket\n- Auto-detect missing dependencies with install guidance\n\n### vp-stacked-pr-rebase\n\nRebase stacked PRs after parent PR is merged, preserving only your commits.\n\n```bash\n/plugin install vp-stacked-pr-rebase@vdustr\n```\n\nFeatures:\n- Smart parent PR detection via commit analysis\n- Handles all merge types (regular, squash, rebase)\n- Automatic commit classification (parent vs your own)\n- Simple conflict auto-resolution, asks for complex conflicts\n- Safe operations with backup branches and `--force-with-lease`\n- Detailed summary report with before/after visualization\n\n### vp-typescript-best-practices\n\nTypeScript coding guidelines with dos and don'ts for type design and patterns.\n\n```bash\n/plugin install vp-typescript-best-practices@vdustr\n```\n\nFeatures:\n- Type-first design with namespace pattern for organizing types\n- Clear DO/DON'T tables for interface vs type, any usage, function declarations\n- Naming conventions (PascalCase, `T` prefix for generics, `Id` not `ID`)\n- Type extraction patterns (prefer extracting over redefining)\n- Generic const pattern for strict literal inference\n- Type testing guidelines with `*.test-d.ts`\n- Environment setup with strictest tsconfig and ts-reset\n\n### vp-wenyan-mode\n\nClassical Chinese (ÊñáË®ÄÊñá) writing style with concise, elegant expressions.\n\n```bash\n/plugin install vp-wenyan-mode@vdustr\n```\n\nFeatures:\n- Always-active classical Chinese writing style\n- Concise expressions (Ë®ÄÁ∞°ÊÑèË≥Ö)\n- Technical terms preserved (function, API, commit, etc.)\n- Minimal use of classical particles (‰πã‰πéËÄÖ‰πü)\n\n## Development\n\nThis marketplace is developed using the [plugin-dev](https://github.com/anthropics/claude-code/tree/main/.claude/plugins/plugin-dev) plugin.\n\n## License\n\n[MIT](https://github.com/VdustR/vp-claude-code-marketplace/blob/main/LICENSE) - Made with ü§ñ‚ù§Ô∏è by [VdustR](https://github.com/VdustR)\n"
      },
      "plugins": [
        {
          "name": "vp-checklist-runner",
          "source": "./plugins/vp-checklist-runner",
          "description": "Parse and verify GitHub PR/issue checklists with auto-check and CI integration",
          "license": "MIT",
          "keywords": [
            "checklist",
            "pr",
            "issue",
            "github",
            "verification",
            "ci",
            "automation",
            "checkbox"
          ],
          "categories": [
            "automation",
            "checkbox",
            "checklist",
            "ci",
            "github",
            "issue",
            "pr",
            "verification"
          ],
          "install_commands": [
            "/plugin marketplace add VdustR/vp-claude-code-marketplace",
            "/plugin install vp-checklist-runner@vdustr"
          ]
        },
        {
          "name": "vp-cspell",
          "source": "./plugins/vp-cspell",
          "description": "Handle cspell unknown word warnings with prioritized decision tree and config bootstrapping",
          "license": "MIT",
          "keywords": [
            "cspell",
            "spelling",
            "linting",
            "ide"
          ],
          "categories": [
            "cspell",
            "ide",
            "linting",
            "spelling"
          ],
          "install_commands": [
            "/plugin marketplace add VdustR/vp-claude-code-marketplace",
            "/plugin install vp-cspell@vdustr"
          ]
        },
        {
          "name": "vp-deps-shift",
          "source": "./plugins/vp-deps-shift",
          "description": "Dependency upgrade and library migration with breaking change detection and test-first verification",
          "license": "MIT",
          "keywords": [
            "dependencies",
            "upgrade",
            "migration",
            "breaking-changes",
            "codemod",
            "dependabot",
            "renovate",
            "context7"
          ],
          "categories": [
            "breaking-changes",
            "codemod",
            "context7",
            "dependabot",
            "dependencies",
            "migration",
            "renovate",
            "upgrade"
          ],
          "install_commands": [
            "/plugin marketplace add VdustR/vp-claude-code-marketplace",
            "/plugin install vp-deps-shift@vdustr"
          ]
        },
        {
          "name": "vp-gitignore-builder",
          "source": "./plugins/vp-gitignore-builder",
          "description": "Build and merge .gitignore files using github/gitignore templates",
          "license": "MIT",
          "keywords": [
            "gitignore",
            "git",
            "ignore",
            "templates",
            "github"
          ],
          "categories": [
            "git",
            "github",
            "gitignore",
            "ignore",
            "templates"
          ],
          "install_commands": [
            "/plugin marketplace add VdustR/vp-claude-code-marketplace",
            "/plugin install vp-gitignore-builder@vdustr"
          ]
        },
        {
          "name": "vp-localsend",
          "source": "./plugins/vp-localsend",
          "description": "Send and receive files over local network using LocalSend protocol",
          "license": "MIT",
          "keywords": [
            "localsend",
            "file-transfer",
            "local-network",
            "airdrop",
            "send",
            "receive",
            "share"
          ],
          "categories": [
            "airdrop",
            "file-transfer",
            "local-network",
            "localsend",
            "receive",
            "send",
            "share"
          ],
          "install_commands": [
            "/plugin marketplace add VdustR/vp-claude-code-marketplace",
            "/plugin install vp-localsend@vdustr"
          ]
        },
        {
          "name": "vp-nyan-mode",
          "source": "./plugins/vp-nyan-mode",
          "description": "Cat persona with verbal tic, emoji support, and language matching",
          "license": "MIT",
          "keywords": [
            "cat",
            "nyan",
            "persona",
            "emoji",
            "kawaii",
            "verbal-tic"
          ],
          "categories": [
            "cat",
            "emoji",
            "kawaii",
            "nyan",
            "persona",
            "verbal-tic"
          ],
          "install_commands": [
            "/plugin marketplace add VdustR/vp-claude-code-marketplace",
            "/plugin install vp-nyan-mode@vdustr"
          ]
        },
        {
          "name": "vp-pr-comment-resolver",
          "source": "./plugins/vp-pr-comment-resolver",
          "description": "Automate PR comment review, fix, and resolution workflow",
          "license": "MIT",
          "keywords": [
            "pr",
            "pull-request",
            "review",
            "comments",
            "github",
            "automation"
          ],
          "categories": [
            "automation",
            "comments",
            "github",
            "pr",
            "pull-request",
            "review"
          ],
          "install_commands": [
            "/plugin marketplace add VdustR/vp-claude-code-marketplace",
            "/plugin install vp-pr-comment-resolver@vdustr"
          ]
        },
        {
          "name": "vp-review-loop",
          "source": "./plugins/vp-review-loop",
          "description": "Iterative multi-pass subagent review loop with confidence scoring for code and plans",
          "license": "MIT",
          "keywords": [
            "code-review",
            "plan-review",
            "multi-pass",
            "confidence-index",
            "subagent",
            "iterative",
            "loop-control"
          ],
          "categories": [
            "code-review",
            "confidence-index",
            "iterative",
            "loop-control",
            "multi-pass",
            "plan-review",
            "subagent"
          ],
          "install_commands": [
            "/plugin marketplace add VdustR/vp-claude-code-marketplace",
            "/plugin install vp-review-loop@vdustr"
          ]
        },
        {
          "name": "vp-skills",
          "source": "./plugins/vp-skills",
          "description": "Manage agent skills using npx skills CLI",
          "license": "MIT",
          "keywords": [
            "skills",
            "management",
            "npx"
          ],
          "categories": [
            "management",
            "npx",
            "skills"
          ],
          "install_commands": [
            "/plugin marketplace add VdustR/vp-claude-code-marketplace",
            "/plugin install vp-skills@vdustr"
          ]
        },
        {
          "name": "vp-somafm",
          "source": "./plugins/vp-somafm",
          "description": "Play SomaFM internet radio as background music during coding sessions",
          "license": "MIT",
          "keywords": [
            "somafm",
            "radio",
            "music",
            "streaming",
            "ambient",
            "mpv"
          ],
          "categories": [
            "ambient",
            "mpv",
            "music",
            "radio",
            "somafm",
            "streaming"
          ],
          "install_commands": [
            "/plugin marketplace add VdustR/vp-claude-code-marketplace",
            "/plugin install vp-somafm@vdustr"
          ]
        },
        {
          "name": "vp-stacked-pr-rebase",
          "source": "./plugins/vp-stacked-pr-rebase",
          "description": "Rebase stacked PRs after parent PR is merged, preserving only your commits",
          "license": "MIT",
          "keywords": [
            "pr",
            "pull-request",
            "rebase",
            "stacked",
            "cherry-pick",
            "github",
            "dependency"
          ],
          "categories": [
            "cherry-pick",
            "dependency",
            "github",
            "pr",
            "pull-request",
            "rebase",
            "stacked"
          ],
          "install_commands": [
            "/plugin marketplace add VdustR/vp-claude-code-marketplace",
            "/plugin install vp-stacked-pr-rebase@vdustr"
          ]
        },
        {
          "name": "vp-typescript-best-practices",
          "source": "./plugins/vp-typescript-best-practices",
          "description": "TypeScript coding guidelines with dos and don'ts for type design and patterns",
          "license": "MIT",
          "keywords": [
            "typescript",
            "best-practices",
            "type-design",
            "coding-guidelines",
            "style-guide"
          ],
          "categories": [
            "best-practices",
            "coding-guidelines",
            "style-guide",
            "type-design",
            "typescript"
          ],
          "install_commands": [
            "/plugin marketplace add VdustR/vp-claude-code-marketplace",
            "/plugin install vp-typescript-best-practices@vdustr"
          ]
        },
        {
          "name": "vp-wenyan-mode",
          "source": "./plugins/vp-wenyan-mode",
          "description": "Classical Chinese (ÊñáË®ÄÊñá) writing style with concise, elegant expressions",
          "license": "MIT",
          "keywords": [
            "wenyan",
            "classical-chinese",
            "ÊñáË®ÄÊñá",
            "persona",
            "writing-style"
          ],
          "categories": [
            "classical-chinese",
            "persona",
            "wenyan",
            "writing-style",
            "ÊñáË®ÄÊñá"
          ],
          "install_commands": [
            "/plugin marketplace add VdustR/vp-claude-code-marketplace",
            "/plugin install vp-wenyan-mode@vdustr"
          ]
        }
      ]
    }
  ]
}