{
  "author": {
    "id": "Ven0m0",
    "display_name": "Ven0m0",
    "avatar_url": "https://avatars.githubusercontent.com/u/82972344?u=14d899336795c235cde8bb6f6dfd981096f8ba2d&v=4"
  },
  "marketplaces": [
    {
      "name": "claude-config-marketplace",
      "version": null,
      "description": "A curated collection of Claude Code plugins, skills, and tools for enhanced productivity",
      "repo_full_name": "Ven0m0/claude-config",
      "repo_url": "https://github.com/Ven0m0/claude-config",
      "repo_description": null,
      "signals": {
        "stars": 0,
        "forks": 0,
        "pushed_at": "2026-02-04T20:38:05Z"
      },
      "files": {
        ".claude-plugin/marketplace.json": "{\n\t\"name\": \"claude-config-marketplace\",\n\t\"owner\": {\n\t\t\"name\": \"Ven0m0\",\n\t\t\"email\": \"ven0m0@users.noreply.github.com\"\n\t},\n\t\"metadata\": {\n\t\t\"description\": \"A curated collection of Claude Code plugins, skills, and tools for enhanced productivity\",\n\t\t\"version\": \"1.0.0\",\n\t\t\"pluginRoot\": \"./plugins\"\n\t},\n\t\"plugins\": [\n\t\t{\n\t\t\t\"name\": \"coding-assistant\",\n\t\t\t\"description\": \"Advanced coding assistant with code review, refactoring, and best practices\",\n\t\t\t\"version\": \"1.0.0\",\n\t\t\t\"author\": {\n\t\t\t\t\"name\": \"Ven0m0\"\n\t\t\t},\n\t\t\t\"homepage\": \"https://github.com/Ven0m0/claude-config\",\n\t\t\t\"repository\": \"https://github.com/Ven0m0/claude-config\",\n\t\t\t\"license\": \"MIT\",\n\t\t\t\"source\": \"coding-assistant\",\n\t\t\t\"keywords\": [\"coding\", \"development\", \"code-review\", \"refactoring\"],\n\t\t\t\"category\": \"productivity\"\n\t\t},\n\t\t{\n\t\t\t\"name\": \"conserve\",\n\t\t\t\"description\": \"Resource optimization and performance monitoring toolkit for efficient Claude Code workflows\",\n\t\t\t\"version\": \"1.3.0\",\n\t\t\t\"author\": {\n\t\t\t\t\"name\": \"Alex Thola\",\n\t\t\t\t\"url\": \"https://github.com/athola\"\n\t\t\t},\n\t\t\t\"homepage\": \"https://github.com/athola/claude-night-market\",\n\t\t\t\"repository\": \"https://github.com/athola/claude-night-market\",\n\t\t\t\"license\": \"MIT\",\n\t\t\t\"source\": \"conserve\",\n\t\t\t\"keywords\": [\n\t\t\t\t\"performance\",\n\t\t\t\t\"resource-management\",\n\t\t\t\t\"token-optimization\",\n\t\t\t\t\"context-optimization\",\n\t\t\t\t\"efficiency\",\n\t\t\t\t\"bloat-detection\"\n\t\t\t],\n\t\t\t\"category\": \"productivity\"\n\t\t},\n\t\t{\n\t\t\t\"name\": \"prompt-improver\",\n\t\t\t\"description\": \"Intelligent prompt optimization using skill-based architecture. Enriches vague prompts with research-based clarifying questions before Claude Code executes them\",\n\t\t\t\"version\": \"0.5.0\",\n\t\t\t\"author\": {\n\t\t\t\t\"name\": \"severity1\"\n\t\t\t},\n\t\t\t\"homepage\": \"https://github.com/severity1/claude-code-prompt-improver\",\n\t\t\t\"repository\": \"https://github.com/severity1/claude-code-prompt-improver\",\n\t\t\t\"license\": \"MIT\",\n\t\t\t\"source\": \"prompt-improver\",\n\t\t\t\"keywords\": [\n\t\t\t\t\"prompt\",\n\t\t\t\t\"optimization\",\n\t\t\t\t\"clarification\",\n\t\t\t\t\"user-experience\"\n\t\t\t],\n\t\t\t\"category\": \"productivity\"\n\t\t},\n\t\t{\n\t\t\t\"name\": \"block-dotfiles\",\n\t\t\t\"description\": \"Blocks access to sensitive dotfiles and configuration files containing credentials\",\n\t\t\t\"version\": \"1.0.0\",\n\t\t\t\"author\": {\n\t\t\t\t\"name\": \"wombat9000\",\n\t\t\t\t\"url\": \"https://github.com/wombat9000\"\n\t\t\t},\n\t\t\t\"homepage\": \"https://github.com/wombat9000/claude-plugins\",\n\t\t\t\"repository\": \"https://github.com/wombat9000/claude-plugins\",\n\t\t\t\"license\": \"MIT\",\n\t\t\t\"source\": \"block-dotfiles\",\n\t\t\t\"keywords\": [\"security\", \"dotfiles\", \"credentials\", \"protection\"],\n\t\t\t\"category\": \"security\"\n\t\t},\n\t\t{\n\t\t\t\"name\": \"config-wizard\",\n\t\t\t\"description\": \"Interactive wizard to help create new Claude Code plugins\",\n\t\t\t\"version\": \"1.0.0\",\n\t\t\t\"author\": {\n\t\t\t\t\"name\": \"wombat9000\"\n\t\t\t},\n\t\t\t\"homepage\": \"https://github.com/wombat9000/claude-plugins\",\n\t\t\t\"repository\": \"https://github.com/wombat9000/claude-plugins\",\n\t\t\t\"license\": \"MIT\",\n\t\t\t\"source\": \"config-wizard\",\n\t\t\t\"keywords\": [\"wizard\", \"configuration\", \"plugin-development\", \"skills\"],\n\t\t\t\"category\": \"utilities\"\n\t\t},\n\t\t{\n\t\t\t\"name\": \"dependency-blocker\",\n\t\t\t\"description\": \"Prevents Claude from accessing dependency directories to save tokens\",\n\t\t\t\"version\": \"1.0.0\",\n\t\t\t\"author\": {\n\t\t\t\t\"name\": \"wombat9000\"\n\t\t\t},\n\t\t\t\"homepage\": \"https://github.com/wombat9000/claude-plugins\",\n\t\t\t\"repository\": \"https://github.com/wombat9000/claude-plugins\",\n\t\t\t\"license\": \"MIT\",\n\t\t\t\"source\": \"dependency-blocker\",\n\t\t\t\"keywords\": [\"performance\", \"token-saving\", \"dependencies\"],\n\t\t\t\"category\": \"utilities\"\n\t\t},\n\t\t{\n\t\t\t\"name\": \"gemini-delegation\",\n\t\t\t\"description\": \"Delegate research and web search tasks to Gemini AI via CLI\",\n\t\t\t\"version\": \"1.0.0\",\n\t\t\t\"author\": {\n\t\t\t\t\"name\": \"wombat9000\"\n\t\t\t},\n\t\t\t\"homepage\": \"https://github.com/wombat9000/claude-plugins\",\n\t\t\t\"repository\": \"https://github.com/wombat9000/claude-plugins\",\n\t\t\t\"license\": \"MIT\",\n\t\t\t\"source\": \"gemini-delegation\",\n\t\t\t\"keywords\": [\"gemini\", \"delegation\", \"research\", \"web-search\"],\n\t\t\t\"category\": \"utilities\"\n\t\t}\n\t]\n}\n",
        "README.md": "# Claude Code Plugin Marketplace\n\nA curated collection of Claude Code plugins, skills, and tools for enhanced productivity. This marketplace provides professional-grade plugins for coding, documentation, and data analysis workflows.\n\n## üöÄ Quick Start\n\n### Installing the Marketplace\n\nAdd this marketplace to your Claude Code installation:\n\n```bash\n/plugin marketplace add Ven0m0/claude-config\n```\n\n### Installing Plugins\n\nInstall individual plugins from the marketplace:\n\n```bash\n# Install coding assistant\n/plugin install coding-assistant@claude-config-marketplace\n\n# Install prompt improver\n/plugin install prompt-improver@claude-config-marketplace\n\n# Install conserve\n/plugin install conserve@claude-config-marketplace\n\n# Install config wizard\n/plugin install config-wizard@claude-config-marketplace\n\n# Install dependency blocker\n/plugin install dependency-blocker@claude-config-marketplace\n\n# Install block dotfiles\n/plugin install block-dotfiles@claude-config-marketplace\n\n# Install gemini delegation\n/plugin install gemini-delegation@claude-config-marketplace\n```\n\nOr install all plugins at once:\n\n```bash\n/plugin install coding-assistant prompt-improver conserve config-wizard dependency-blocker block-dotfiles gemini-delegation @claude-config-marketplace\n```\n\n## üì¶ Available Plugins\n\n### üîß Coding Assistant\n\nAdvanced coding assistant with code review, debugging, and refactoring capabilities.\n\n**Skills:**\n\n- `/code-review` - Comprehensive code reviews with security and performance checks\n- `/debug` - Systematic debugging and root cause analysis\n- `/refactor` - Code refactoring for better structure and maintainability\n\n**Features:**\n\n- Automatic code formatting after edits (Biome, ruff, gofmt, rustfmt)\n- Security vulnerability detection\n- Performance optimization suggestions\n- Best practices guidance\n\n[View Plugin Documentation](./plugins/coding-assistant/README.md)\n\n### ‚ö° Conserve\n\nResource optimization and performance monitoring toolkit for efficient Claude Code workflows.\n\n**Commands:**\n\n- `/bloat-scan` - Identify dead code, duplication, and documentation bloat\n- `/optimize-context` - Optimize context usage and token efficiency\n- `/analyze-growth` - Analyze codebase growth patterns\n- `/ai-hygiene-audit` - Audit AI-generated code quality\n- `/unbloat` - Remove unnecessary code and improve efficiency\n\n**Features:**\n\n- Maximum Effective Context Window (MECW) principle\n- MCP patterns for efficient data processing\n- Progressive loading for reduced session footprint\n- Token usage optimization\n- Dead code detection and remediation\n\n**Author:** Alex Thola ([athola](https://github.com/athola))\n\n[View Plugin Documentation](./plugins/conserve/README.md)\n\n### üí° Prompt Improver\n\nIntelligent prompt optimization using skill-based architecture. Enriches vague prompts with research-based clarifying questions before Claude Code executes them.\n\n**Features:**\n\n- Automatic prompt clarity evaluation\n- Research-based clarifying questions (1-6 questions)\n- Zero overhead for clear prompts\n- 31% token reduction through skill-based architecture\n- Uses AskUserQuestion tool for targeted clarification\n\n**Author:** [severity1](https://github.com/severity1)\n\n[View Plugin Documentation](./plugins/prompt-improver/README.md)\n\n### üîí Block Dotfiles\n\nSecurity plugin that blocks access to sensitive dotfiles and configuration files containing credentials.\n\n**Features:**\n\n- Blocks access to shell configuration files (.bashrc, .zshrc, etc.)\n- Blocks access to environment variable files (.env, .env.local, etc.)\n- Blocks access to credential directories (.ssh, .aws, .docker, .kube, etc.)\n- Blocks access to credential files (.npmrc, .pypirc, .gitconfig, .netrc)\n- Comprehensive test suite with 104 tests\n\n**Author:** wombat9000\n\n[View Plugin Documentation](./plugins/block-dotfiles/README.md)\n\n### üßô Config Wizard\n\nInteractive wizard to help create new Claude Code plugins.\n\n**Commands:**\n\n- `/config-wizard:cmd-init` - Initialize a new slash command\n- `/config-wizard:cmd-review` - Review an existing slash command\n\n**Skills:**\n\n- `designing-claude-skills` - Guide for creating, reviewing, and improving skills\n- `managing-permissions` - Guide for configuring Claude Code permissions\n\n**Author:** wombat9000\n\n[View Plugin Documentation](./plugins/config-wizard/README.md)\n\n### üö´ Dependency Blocker\n\nPerformance plugin that prevents Claude from accessing dependency directories to save tokens.\n\n**Features:**\n\n- Blocks access to `node_modules`, `.git`, `dist`, `build`, `vendor`, `target`, `.venv`, and `venv`\n- Blocks Bash commands targeting excluded directories\n- Blocks Read operations from excluded directories\n- Blocks Glob patterns targeting excluded directories\n- Blocks Grep searches in excluded directories\n\n**Author:** wombat9000\n\n[View Plugin Documentation](./plugins/dependency-blocker/README.md)\n\n### ü§ñ Gemini Delegation\n\nDelegate research and web search tasks to Gemini AI via CLI.\n\n**Features:**\n\n- Delegate web research to Gemini AI\n- Session context integration\n- CLI-based task delegation\n\n**Author:** wombat9000\n\n[View Plugin Documentation](./plugins/gemini-delegation/README.md)\n\n## üìÅ Repository Structure\n\n```\n.\n‚îú‚îÄ‚îÄ .claude-plugin/\n‚îÇ   ‚îî‚îÄ‚îÄ marketplace.json        # Marketplace catalog\n‚îú‚îÄ‚îÄ .gemini/                    # Gemini Code Assist config\n‚îú‚îÄ‚îÄ claude/                     # Claude Code config and tools\n‚îú‚îÄ‚îÄ gemini/                     # Gemini CLI config\n‚îú‚îÄ‚îÄ copilot-cli/                # Copilot CLI templates\n‚îú‚îÄ‚îÄ cursor/                     # Cursor rules and templates\n‚îú‚îÄ‚îÄ opencode/                   # OpenCode references\n‚îú‚îÄ‚îÄ qwen/                       # Qwen prompt templates\n‚îú‚îÄ‚îÄ plugins/\n‚îÇ   ‚îú‚îÄ‚îÄ block-dotfiles/         # Block dotfile access\n‚îÇ   ‚îú‚îÄ‚îÄ coding-assistant/       # Code review, debug, refactor\n‚îÇ   ‚îú‚îÄ‚îÄ config-wizard/          # Plugin configuration wizard\n‚îÇ   ‚îú‚îÄ‚îÄ conserve/               # Context and token optimization\n‚îÇ   ‚îú‚îÄ‚îÄ dependency-blocker/     # Block dependency directories\n‚îÇ   ‚îú‚îÄ‚îÄ gemini-delegation/      # Gemini CLI delegation\n‚îÇ   ‚îî‚îÄ‚îÄ prompt-improver/        # Prompt clarity improvements\n‚îú‚îÄ‚îÄ examples/                   # Usage examples\n‚îú‚îÄ‚îÄ LLM_CONFIG_STANDARDS.md     # Shared config defaults\n‚îú‚îÄ‚îÄ README.md                   # This file\n‚îú‚îÄ‚îÄ SETUP.md                    # Setup guide\n‚îú‚îÄ‚îÄ CHANGELOG.md                # Version history\n‚îî‚îÄ‚îÄ LICENSE\n```\n\n## üéØ Usage Examples\n\n### Code Review Workflow\n\n```bash\n# Review a file or directory\n/code-review src/components/UserProfile.tsx\n\n# Review with specific focus\n/code-review --focus security src/api/\n```\n\n### Context Optimization\n\n```bash\n# Scan for bloat signals\n/bloat-scan\n\n# Reduce context usage\n/optimize-context\n```\n\n## üîß Requirements\n\n### Global Requirements\n\n- Claude Code CLI (latest version)\n- Git\n\n### Plugin-Specific Requirements\n\n**Coding Assistant:**\n\n- Optional formatters: Biome, ruff, gofmt, rustfmt\n\n**Prompt Improver:**\n\n- Claude Code 2.0.22+ (AskUserQuestion tool)\n\n## üé® Features\n\n### Plugin System\n\n- Modular plugin architecture\n- Easy installation and updates\n- Version management\n\n### Skills\n\n- User-invocable commands via `/skill-name`\n- Context-aware assistance\n- Specialized tools for each domain\n\n### Hooks\n\n- Automatic code formatting\n- Post-edit validations\n- Custom workflows\n\n### MCP Servers\n\n- SQLite database integration\n- Extensible server architecture\n\n## üìö Documentation\n\n- [Setup Guide](./SETUP.md) - Detailed installation and configuration\n- [Plugin Documentation](./plugins/) - Individual plugin documentation\n- [Examples](./examples/) - Usage examples and tutorials\n- [Changelog](./CHANGELOG.md) - Version history and updates\n\n## ü§ù Contributing\n\nContributions are welcome! Feel free to:\n\n- Add new plugins\n- Improve existing skills\n- Create additional templates\n- Report issues or suggest features\n\n## üîí Security\n\n- Never commit API keys or sensitive data\n- Use environment variables for credentials\n- Review the code before installing plugins\n- Report security issues privately\n\n## üìÑ License\n\nThis project is licensed under the MIT License. See [LICENSE](./LICENSE) for details.\n\n## üîó Links\n\n- [Claude Code Documentation](https://code.claude.com/docs)\n- [Plugin Development Guide](https://code.claude.com/docs/en/plugins.md)\n- [MCP Documentation](https://code.claude.com/docs/en/mcp.md)\n- [Skills Guide](https://code.claude.com/docs/en/skills.md)\n\n## üôã Support\n\nFor issues or questions:\n\n- Open an issue on GitHub\n- Check the [Setup Guide](./SETUP.md)\n- Review individual plugin documentation\n\n______________________________________________________________________\n\n**Happy coding with Claude! üöÄ**\n"
      },
      "plugins": [
        {
          "name": "coding-assistant",
          "description": "Advanced coding assistant with code review, refactoring, and best practices",
          "version": "1.0.0",
          "author": {
            "name": "Ven0m0"
          },
          "homepage": "https://github.com/Ven0m0/claude-config",
          "repository": "https://github.com/Ven0m0/claude-config",
          "license": "MIT",
          "source": "coding-assistant",
          "keywords": [
            "coding",
            "development",
            "code-review",
            "refactoring"
          ],
          "category": "productivity",
          "categories": [
            "code-review",
            "coding",
            "development",
            "productivity",
            "refactoring"
          ],
          "install_commands": [
            "/plugin marketplace add Ven0m0/claude-config",
            "/plugin install coding-assistant@claude-config-marketplace"
          ]
        },
        {
          "name": "conserve",
          "description": "Resource optimization and performance monitoring toolkit for efficient Claude Code workflows",
          "version": "1.3.0",
          "author": {
            "name": "Alex Thola",
            "url": "https://github.com/athola"
          },
          "homepage": "https://github.com/athola/claude-night-market",
          "repository": "https://github.com/athola/claude-night-market",
          "license": "MIT",
          "source": "conserve",
          "keywords": [
            "performance",
            "resource-management",
            "token-optimization",
            "context-optimization",
            "efficiency",
            "bloat-detection"
          ],
          "category": "productivity",
          "categories": [
            "bloat-detection",
            "context-optimization",
            "efficiency",
            "performance",
            "productivity",
            "resource-management",
            "token-optimization"
          ],
          "install_commands": [
            "/plugin marketplace add Ven0m0/claude-config",
            "/plugin install conserve@claude-config-marketplace"
          ]
        },
        {
          "name": "prompt-improver",
          "description": "Intelligent prompt optimization using skill-based architecture. Enriches vague prompts with research-based clarifying questions before Claude Code executes them",
          "version": "0.5.0",
          "author": {
            "name": "severity1"
          },
          "homepage": "https://github.com/severity1/claude-code-prompt-improver",
          "repository": "https://github.com/severity1/claude-code-prompt-improver",
          "license": "MIT",
          "source": "prompt-improver",
          "keywords": [
            "prompt",
            "optimization",
            "clarification",
            "user-experience"
          ],
          "category": "productivity",
          "categories": [
            "clarification",
            "optimization",
            "productivity",
            "prompt",
            "user-experience"
          ],
          "install_commands": [
            "/plugin marketplace add Ven0m0/claude-config",
            "/plugin install prompt-improver@claude-config-marketplace"
          ]
        },
        {
          "name": "block-dotfiles",
          "description": "Blocks access to sensitive dotfiles and configuration files containing credentials",
          "version": "1.0.0",
          "author": {
            "name": "wombat9000",
            "url": "https://github.com/wombat9000"
          },
          "homepage": "https://github.com/wombat9000/claude-plugins",
          "repository": "https://github.com/wombat9000/claude-plugins",
          "license": "MIT",
          "source": "block-dotfiles",
          "keywords": [
            "security",
            "dotfiles",
            "credentials",
            "protection"
          ],
          "category": "security",
          "categories": [
            "credentials",
            "dotfiles",
            "protection",
            "security"
          ],
          "install_commands": [
            "/plugin marketplace add Ven0m0/claude-config",
            "/plugin install block-dotfiles@claude-config-marketplace"
          ]
        },
        {
          "name": "config-wizard",
          "description": "Interactive wizard to help create new Claude Code plugins",
          "version": "1.0.0",
          "author": {
            "name": "wombat9000"
          },
          "homepage": "https://github.com/wombat9000/claude-plugins",
          "repository": "https://github.com/wombat9000/claude-plugins",
          "license": "MIT",
          "source": "config-wizard",
          "keywords": [
            "wizard",
            "configuration",
            "plugin-development",
            "skills"
          ],
          "category": "utilities",
          "categories": [
            "configuration",
            "plugin-development",
            "skills",
            "utilities",
            "wizard"
          ],
          "install_commands": [
            "/plugin marketplace add Ven0m0/claude-config",
            "/plugin install config-wizard@claude-config-marketplace"
          ]
        },
        {
          "name": "dependency-blocker",
          "description": "Prevents Claude from accessing dependency directories to save tokens",
          "version": "1.0.0",
          "author": {
            "name": "wombat9000"
          },
          "homepage": "https://github.com/wombat9000/claude-plugins",
          "repository": "https://github.com/wombat9000/claude-plugins",
          "license": "MIT",
          "source": "dependency-blocker",
          "keywords": [
            "performance",
            "token-saving",
            "dependencies"
          ],
          "category": "utilities",
          "categories": [
            "dependencies",
            "performance",
            "token-saving",
            "utilities"
          ],
          "install_commands": [
            "/plugin marketplace add Ven0m0/claude-config",
            "/plugin install dependency-blocker@claude-config-marketplace"
          ]
        },
        {
          "name": "gemini-delegation",
          "description": "Delegate research and web search tasks to Gemini AI via CLI",
          "version": "1.0.0",
          "author": {
            "name": "wombat9000"
          },
          "homepage": "https://github.com/wombat9000/claude-plugins",
          "repository": "https://github.com/wombat9000/claude-plugins",
          "license": "MIT",
          "source": "gemini-delegation",
          "keywords": [
            "gemini",
            "delegation",
            "research",
            "web-search"
          ],
          "category": "utilities",
          "categories": [
            "delegation",
            "gemini",
            "research",
            "utilities",
            "web-search"
          ],
          "install_commands": [
            "/plugin marketplace add Ven0m0/claude-config",
            "/plugin install gemini-delegation@claude-config-marketplace"
          ]
        }
      ]
    }
  ]
}