{
  "author": {
    "id": "vocalbridgeai",
    "display_name": "vocalbridgeai",
    "avatar_url": "https://avatars.githubusercontent.com/u/256449723?v=4"
  },
  "marketplaces": [
    {
      "name": "vocal-bridge",
      "version": null,
      "description": "Manage Vocal Bridge voice agents from Claude Code. View call logs, update prompts and configuration, stream debug events, and more.",
      "repo_full_name": "vocalbridgeai/vocal-bridge-marketplace",
      "repo_url": "https://github.com/vocalbridgeai/vocal-bridge-marketplace",
      "repo_description": null,
      "signals": {
        "stars": 0,
        "forks": 0,
        "pushed_at": "2026-01-30T07:55:20Z"
      },
      "files": {
        ".claude-plugin/marketplace.json": "{\n  \"name\": \"vocal-bridge\",\n  \"owner\": {\n    \"name\": \"Vocal Bridge\",\n    \"email\": \"support@vocalbridgeai.com\"\n  },\n  \"plugins\": [\n    {\n      \"name\": \"vocal-bridge\",\n      \"source\": {\n        \"source\": \"github\",\n        \"repo\": \"vocalbridgeai/vocal-bridge-claude-plugin\"\n      },\n      \"description\": \"Manage Vocal Bridge voice agents from Claude Code. View call logs, update prompts and configuration, stream debug events, and more.\",\n      \"version\": \"0.7.3\",\n      \"author\": {\n        \"name\": \"Vocal Bridge\"\n      },\n      \"homepage\": \"https://vocalbridgeai.com\",\n      \"repository\": \"https://github.com/vocalbridgeai/vocal-bridge-claude-plugin\",\n      \"license\": \"Apache-2.0\",\n      \"keywords\": [\"voice\", \"agent\", \"vocal-bridge\", \"voice-agent\"],\n      \"category\": \"developer-tools\"\n    }\n  ]\n}\n",
        "README.md": "# Vocal Bridge Plugin Marketplace\n\nOfficial Claude Code plugin marketplace for Vocal Bridge.\n\n## Installation\n\nAdd this marketplace to Claude Code:\n\n```\n/plugin marketplace add vocalbridgeai/vocal-bridge-marketplace\n```\n\n## Available Plugins\n\n### vocal-bridge\n\nManage Vocal Bridge voice agents from Claude Code.\n\n**Features:**\n- View call logs and transcripts\n- Update agent prompts and greetings\n- Configure session limits (max call duration, history size)\n- Stream real-time debug events\n- Check call statistics\n- Authenticate with your Vocal Bridge account\n\n**Install:**\n```\n/plugin install vocal-bridge@vocal-bridge\n```\n\n**Get started:**\n```\n/vocal-bridge:login vb_your_api_key\n/vocal-bridge:help\n```\n\n## Links\n\n- [Vocal Bridge](https://vocalbridgeai.com) - Deploy voice agents in minutes\n- [Plugin Repository](https://github.com/vocalbridgeai/vocal-bridge-claude-plugin)\n- [CLI on PyPI](https://pypi.org/project/vocal-bridge/)\n\n## License\n\nApache-2.0\n"
      },
      "plugins": [
        {
          "name": "vocal-bridge",
          "source": {
            "source": "github",
            "repo": "vocalbridgeai/vocal-bridge-claude-plugin"
          },
          "description": "Manage Vocal Bridge voice agents from Claude Code. View call logs, update prompts and configuration, stream debug events, and more.",
          "version": "0.7.3",
          "author": {
            "name": "Vocal Bridge"
          },
          "homepage": "https://vocalbridgeai.com",
          "repository": "https://github.com/vocalbridgeai/vocal-bridge-claude-plugin",
          "license": "Apache-2.0",
          "keywords": [
            "voice",
            "agent",
            "vocal-bridge",
            "voice-agent"
          ],
          "category": "developer-tools",
          "categories": [
            "agent",
            "developer-tools",
            "vocal-bridge",
            "voice",
            "voice-agent"
          ],
          "install_commands": [
            "/plugin marketplace add vocalbridgeai/vocal-bridge-marketplace",
            "/plugin install vocal-bridge@vocal-bridge"
          ]
        }
      ]
    }
  ]
}