{
  "author": {
    "id": "xiaolai",
    "display_name": "xiaolai",
    "avatar_url": "https://avatars.githubusercontent.com/u/152970?u=8b2fcedd53d6e46faf809b001cecf3f1981692fe&v=4"
  },
  "marketplaces": [
    {
      "name": "xiaolai-init-workspace",
      "version": null,
      "description": "Multi-agent workspace initialization plugin",
      "repo_full_name": "xiaolai/init-workspace",
      "repo_url": "https://github.com/xiaolai/init-workspace",
      "repo_description": "Initialize any project for AI-assisted development with Claude Code, Codex CLI, and Gemini CLI",
      "signals": {
        "stars": 5,
        "forks": 1,
        "pushed_at": "2026-02-06T10:43:45Z"
      },
      "files": {
        ".claude-plugin/marketplace.json": "{\n  \"name\": \"xiaolai-init-workspace\",\n  \"description\": \"Multi-agent workspace initialization plugin\",\n  \"plugins\": [\n    {\n      \"name\": \"init-workspace\",\n      \"description\": \"Initialize a multi-agent workspace with shared configuration for Claude Code, Codex CLI, and Gemini CLI. Creates AGENTS.md (shared instructions), CLAUDE.md, GEMINI.md, .claude/ directory structure, dev-docs/, and comprehensive .gitignore.\",\n      \"source\": \".\"\n    }\n  ]\n}\n",
        ".claude-plugin/plugin.json": "{\n  \"name\": \"init-workspace\",\n  \"description\": \"Initialize a multi-agent workspace with shared configuration for Claude Code, Codex CLI, and Gemini CLI\",\n  \"version\": \"1.0.0\",\n  \"author\": {\n    \"name\": \"xiaolai\"\n  },\n  \"homepage\": \"https://github.com/xiaolai/init-workspace\",\n  \"repository\": \"https://github.com/xiaolai/init-workspace\",\n  \"license\": \"MIT\"\n}\n",
        "README.md": "# init-workspace\n\nInitialize any project for AI-assisted development with a single command.\n\n## The Problem\n\nYou're using multiple AI coding tools — Claude Code, OpenAI Codex CLI, Google Gemini CLI. Each has its own config file. You end up with:\n\n- Instructions scattered across `CLAUDE.md`, `AGENTS.md`, `GEMINI.md`\n- Each tool learning things the others don't know\n- Inconsistent behavior when switching between tools\n- Missing `.gitignore` entries that leak secrets or bloat repos\n- No structure for custom skills, agents, or rules\n\n## The Solution\n\nRun `/init-workspace` once. Get a project structure where:\n\n- **One file to rule them all**: Write instructions in `AGENTS.md` only. Claude Code, Codex CLI, and Gemini CLI all read from it automatically.\n- **Shared memory**: When any tool learns something new, it updates `AGENTS.md`. All tools stay in sync.\n- **Ready for customization**: Directories for skills, agents, and rules are already in place.\n- **Safe defaults**: Comprehensive `.gitignore` protects secrets and keeps repos clean.\n\n## Installation\n\n### Option 1: Plugin Marketplace (Recommended)\n\nIn Claude Code, run:\n\n```\n/plugin marketplace add xiaolai/init-workspace\n/plugin install init-workspace@xiaolai-init-workspace\n```\n\nThen use `/init-workspace:init-workspace` to run.\n\n### Option 2: Personal Skill (Simpler)\n\n```bash\nmkdir -p ~/.claude/skills/init-workspace\ncurl -o ~/.claude/skills/init-workspace/SKILL.md \\\n  https://raw.githubusercontent.com/xiaolai/init-workspace/main/skills/init-workspace/SKILL.md\n```\n\nOr clone the entire repo:\n\n```bash\ngit clone https://github.com/xiaolai/init-workspace /tmp/iw && \\\n  mkdir -p ~/.claude/skills/init-workspace && \\\n  cp /tmp/iw/skills/init-workspace/SKILL.md ~/.claude/skills/init-workspace/ && \\\n  rm -rf /tmp/iw\n```\n\nThen use `/init-workspace` to run.\n\n## Usage\n\nIn any project directory, run:\n\n```\n/init-workspace                         # if installed as personal skill\n/init-workspace:init-workspace          # if installed as plugin\n```\n\nClaude will ask two questions:\n\n1. **Project description** — A single line describing your project\n2. **Public or Private** — Whether to share AI config files via git:\n   - **Public** (recommended): Team shares the same AI context\n   - **Private**: AI files are gitignored, each dev has their own\n\nThen it creates:\n\n```\nproject/\n├── .claude/\n│   ├── settings.json        # Team-shared settings\n│   ├── agents/              # Custom subagents\n│   ├── skills/              # Claude Code skills\n│   └── rules/               # Modular rules\n├── .codex/\n│   ├── skills/              # Codex CLI skills\n│   └── prompts/             # Codex CLI custom slash commands\n├── .gemini/\n│   ├── skills/              # Gemini CLI skills\n│   └── commands/            # Gemini CLI custom slash commands (TOML)\n├── .mcp.json                # MCP server configuration\n├── .gitignore               # Comprehensive gitignore\n├── AGENTS.md                # Shared instructions (all tools read this)\n├── CLAUDE.md                # Claude Code (imports AGENTS.md)\n└── GEMINI.md                # Gemini CLI (imports AGENTS.md)\n```\n\n## What Gets Created\n\n| File/Directory | Purpose |\n|----------------|---------|\n| `AGENTS.md` | Your single source of truth for all AI tools |\n| `CLAUDE.md` | Imports `@AGENTS.md` (Claude Code reads this) |\n| `GEMINI.md` | Imports `@AGENTS.md` (Gemini CLI reads this) |\n| `.claude/settings.json` | Team-shared permissions |\n| `.claude/agents/` | Custom subagents |\n| `.claude/skills/` | Claude Code skills (slash commands) |\n| `.claude/rules/` | Modular rules auto-loaded into context |\n| `.codex/skills/` | Codex CLI skills |\n| `.codex/prompts/` | Codex CLI custom slash commands |\n| `.gemini/skills/` | Gemini CLI skills |\n| `.gemini/commands/` | Gemini CLI custom slash commands (TOML) |\n| `.mcp.json` | MCP server configuration |\n| `.gitignore` | Comprehensive ignore rules |\n\n## Customization\n\nAfter initialization:\n\n1. Edit `AGENTS.md` to add project-specific instructions\n2. Add skills to `.claude/skills/`, `.codex/skills/`, or `.gemini/skills/`\n3. Add subagents to `.claude/agents/`, rules to `.claude/rules/`\n4. Configure MCP servers in `.mcp.json`\n\n## License\n\nMIT\n\n## Sources\n\n- [Claude Code Skills Documentation](https://code.claude.com/docs/en/skills)\n- [Claude Code Plugins Documentation](https://code.claude.com/docs/en/plugins)\n- [Codex CLI Skills Documentation](https://developers.openai.com/codex/skills/)\n- [Gemini CLI Skills Documentation](https://geminicli.com/docs/cli/skills/)\n- [AGENTS.md Open Format](https://agents.md/)\n"
      },
      "plugins": [
        {
          "name": "init-workspace",
          "description": "Initialize a multi-agent workspace with shared configuration for Claude Code, Codex CLI, and Gemini CLI. Creates AGENTS.md (shared instructions), CLAUDE.md, GEMINI.md, .claude/ directory structure, dev-docs/, and comprehensive .gitignore.",
          "source": ".",
          "categories": [],
          "install_commands": [
            "/plugin marketplace add xiaolai/init-workspace",
            "/plugin install init-workspace@xiaolai-init-workspace"
          ]
        }
      ]
    },
    {
      "name": "xiaolai",
      "version": null,
      "description": "OpenAI Codex MCP integration for Claude Code",
      "repo_full_name": "xiaolai/codex-toolkit-for-claude",
      "repo_url": "https://github.com/xiaolai/codex-toolkit-for-claude",
      "repo_description": "OpenAI Codex MCP integration for Claude Code — audit, implement, verify, and debug via Codex",
      "signals": {
        "stars": 4,
        "forks": 0,
        "pushed_at": "2026-02-21T04:57:42Z"
      },
      "files": {
        ".claude-plugin/marketplace.json": "{\n  \"name\": \"xiaolai\",\n  \"owner\": {\n    \"name\": \"xiaolai\"\n  },\n  \"metadata\": {\n    \"description\": \"OpenAI Codex MCP integration for Claude Code\"\n  },\n  \"plugins\": [\n    {\n      \"name\": \"codex-toolkit\",\n      \"source\": {\n        \"source\": \"github\",\n        \"repo\": \"xiaolai/codex-toolkit-for-claude\"\n      },\n      \"description\": \"Audit, implement, verify, review, and debug via OpenAI Codex MCP\",\n      \"version\": \"0.3.0\",\n      \"author\": {\n        \"name\": \"xiaolai\"\n      },\n      \"repository\": \"https://github.com/xiaolai/codex-toolkit-for-claude\",\n      \"license\": \"MIT\",\n      \"keywords\": [\"codex\", \"openai\", \"audit\", \"mcp\", \"code-review\"],\n      \"category\": \"developer-tools\"\n    }\n  ]\n}\n",
        ".claude-plugin/plugin.json": "{\n  \"name\": \"codex-toolkit\",\n  \"version\": \"0.3.0\",\n  \"description\": \"OpenAI Codex MCP integration for Claude Code — audit, implement, verify, review, and debug via Codex\",\n  \"author\": {\n    \"name\": \"xiaolai\"\n  }\n}\n",
        "README.md": "# codex-toolkit\n\nOpenAI Codex MCP integration for Claude Code.\n\nUse OpenAI's Codex models as an autonomous worker from within Claude Code — for code audits, implementation, verification, bug analysis, and plan review.\n\n## Installation\n\n### Prerequisites\n\n1. Install [Codex CLI](https://github.com/openai/codex) (v0.101.0 or later):\n\n```bash\nnpm install -g @openai/codex\n```\n\n2. Authenticate with OpenAI — we recommend using a subscription (ChatGPT Plus/Pro) rather than an API key:\n\n```bash\ncodex login\n```\n\nIf you prefer using an API key instead, set it in your environment:\n\n```bash\nexport OPENAI_API_KEY=\"your-key-here\"\n```\n\n### Install the plugin\n\nFirst, add the marketplace (once):\n\n```\n/plugin marketplace add xiaolai/codex-toolkit-for-claude\n```\n\nThen install:\n\n```\n/plugin install codex-toolkit@xiaolai\n```\n\nChoose an install scope based on your needs:\n\n| Scope | Command | Effect |\n|-------|---------|--------|\n| **User** (default) | `/plugin install codex-toolkit@xiaolai` | Available in all your projects |\n| **Project** | `/plugin install codex-toolkit@xiaolai --scope project` | Shared with team via `.claude/settings.json` (committed to repo) |\n| **Local** | `/plugin install codex-toolkit@xiaolai --scope local` | Only you, only this repo (gitignored) |\n\n### Configure for your project (optional)\n\nRun `/init` inside your project to generate a `.codex-toolkit.md` config file. This lets you set project-specific defaults:\n\n- Default model and reasoning effort\n- Audit focus (balanced, security-first, performance-first, quality-first)\n- File patterns to skip during audits\n- Project-specific instructions for Codex (your stack, conventions, constraints)\n\nIf no config file exists, commands use sensible built-in defaults.\n\n## Commands\n\n| Command | Description |\n|---------|-------------|\n| `/init` | Initialize project config — set default model, audit focus, skip patterns |\n| `/preflight` | Check Codex connectivity, auth status, and discover available models |\n| `/implement` | Delegate an implementation plan to Codex for autonomous execution |\n| `/audit` | Code audit — fast 5-dimension (`--mini`, default) or thorough 9-dimension (`--full`) |\n| `/verify` | Verify that issues from a previous audit have been fixed |\n| `/bug-analyze` | Root cause analysis for user-described bugs |\n| `/review-plan` | Architectural review of implementation plans |\n| `/audit-fix` | Full audit→fix→verify loop — runs until all issues are resolved or you stop |\n| `/continue` | Continue a previous Codex session — iterate on findings or request fixes |\n\n> When installed as a plugin, commands appear as `/codex-toolkit:<command>` (e.g. `/codex-toolkit:audit`).\n\n## How it works\n\nEach command follows the same pattern:\n\n1. **Choose model and settings** — pick a Codex model, reasoning effort, and sandbox level\n2. **Send to Codex** — the task is dispatched to `mcp__codex__codex` (Codex running as an MCP server) with `developer-instructions` to set the role persona and `config` for reasoning effort\n3. **Fallback** — if Codex is unavailable or returns empty, Claude performs the task manually\n4. **Report** — structured output with findings, verdicts, thread ID, and next steps\n\nEvery command output includes a **thread ID** that you can pass to `/continue` to iterate on findings, request fixes, or drill deeper — without re-sending the full context.\n\n## Audit→Fix→Verify workflow\n\nThe `/audit-fix` command runs the full cycle automatically:\n\n```\naudit → fix → verify → (issues remain?) → fix → verify → ... → ACCEPTED\n```\n\n1. Audits your code (mini or full — your choice)\n2. Sends findings to Claude or Codex to fix (your choice)\n3. Verifies each fix was actually resolved\n4. Repeats up to 3 rounds or until clean\n5. Reports final status: ACCEPTED / PARTIAL / UNCHANGED\n\nYou can also run each step manually:\n\n```\n/audit               # find issues (defaults to --mini)\n/audit --full        # thorough 9-dimension audit\n# fix them yourself\n/verify report.md    # check your fixes\n```\n\n## Available models\n\nModels are discovered dynamically at runtime. Each command runs `scripts/codex-preflight.sh`, which probes a list of candidate models in parallel. Invalid models fail fast; valid ones are kept. When multiple versions of the same model family are available (e.g. `gpt-5.3-codex` and `gpt-5.2-codex`), only the newest is shown.\n\nThe candidate list lives in `scripts/codex-preflight.sh` — add new model names there as OpenAI releases them. Stale entries are harmless; they simply probe as unavailable.\n\nTo check availability manually:\n\n```bash\nbash scripts/codex-preflight.sh    # JSON to stdout\n```\n\nOr run `/preflight` inside Claude Code for a human-friendly report.\n\n## MCP server\n\nThis plugin bundles a `.mcp.json` that registers the Codex MCP server. Codex authenticates via subscription (recommended, use `codex login`) or an `OPENAI_API_KEY` environment variable.\n\nIf you already have Codex configured in your `~/.claude/config.json`, the plugin's MCP config will coexist — but you may want to remove the duplicate from `config.json` to avoid running two Codex MCP servers.\n"
      },
      "plugins": [
        {
          "name": "codex-toolkit",
          "source": {
            "source": "github",
            "repo": "xiaolai/codex-toolkit-for-claude"
          },
          "description": "Audit, implement, verify, review, and debug via OpenAI Codex MCP",
          "version": "0.3.0",
          "author": {
            "name": "xiaolai"
          },
          "repository": "https://github.com/xiaolai/codex-toolkit-for-claude",
          "license": "MIT",
          "keywords": [
            "codex",
            "openai",
            "audit",
            "mcp",
            "code-review"
          ],
          "category": "developer-tools",
          "categories": [
            "audit",
            "code-review",
            "codex",
            "developer-tools",
            "mcp",
            "openai"
          ],
          "install_commands": [
            "/plugin marketplace add xiaolai/codex-toolkit-for-claude",
            "/plugin install codex-toolkit@xiaolai"
          ]
        }
      ]
    }
  ]
}