{
  "author": {
    "id": "yamz8",
    "display_name": "z8",
    "avatar_url": "https://avatars.githubusercontent.com/u/108418515?u=b8c3a7d7251d37eb97d93166e4b52ee8d6f8c853&v=4"
  },
  "marketplaces": [
    {
      "name": "open-ceo",
      "version": null,
      "description": "Open CEO plugin marketplace - tools for VC-backed startup CEOs",
      "repo_full_name": "yamz8/open-ceo",
      "repo_url": "https://github.com/yamz8/open-ceo",
      "repo_description": null,
      "signals": {
        "stars": 0,
        "forks": 0,
        "pushed_at": "2026-01-22T18:18:03Z"
      },
      "files": {
        ".claude-plugin/marketplace.json": "{\n  \"name\": \"open-ceo\",\n  \"owner\": {\n    \"name\": \"yamz8\"\n  },\n  \"metadata\": {\n    \"description\": \"Open CEO plugin marketplace - tools for VC-backed startup CEOs\"\n  },\n  \"plugins\": [\n    {\n      \"name\": \"metrics\",\n      \"version\": \"0.1.0\",\n      \"description\": \"Startup metrics toolkit for CEOs. Track, calculate, and benchmark SaaS and marketplace metrics. Integrates with fundraising, board-prep, and investor-updates plugins.\",\n      \"source\": \"./metrics\",\n      \"author\": {\n        \"name\": \"yamz8\"\n      },\n      \"repository\": \"https://github.com/yamz8/open-ceo\",\n      \"homepage\": \"https://github.com/yamz8/open-ceo#metrics\",\n      \"license\": \"MIT\",\n      \"category\": \"productivity\",\n      \"tags\": [\"metrics\", \"saas\", \"marketplace\", \"kpi\", \"arr\", \"mrr\", \"churn\", \"startup\", \"analytics\"]\n    },\n    {\n      \"name\": \"fundraising\",\n      \"version\": \"0.1.0\",\n      \"description\": \"Fundraising toolkit for VC-backed startup CEOs. Create pitch decks, manage investor outreach, analyze term sheets, and track pipeline.\",\n      \"source\": \"./fundraising\",\n      \"author\": {\n        \"name\": \"yamz8\"\n      },\n      \"repository\": \"https://github.com/yamz8/open-ceo\",\n      \"homepage\": \"https://github.com/yamz8/open-ceo#fundraising\",\n      \"license\": \"MIT\",\n      \"category\": \"productivity\",\n      \"tags\": [\"fundraising\", \"pitch\", \"investors\", \"term-sheet\", \"startup\", \"ceo\", \"vc\"]\n    },\n    {\n      \"name\": \"board-prep\",\n      \"version\": \"0.1.0\",\n      \"description\": \"Board meeting preparation toolkit for VC-backed startup CEOs. Helps create agendas, draft board decks, prepare metrics, and anticipate investor questions.\",\n      \"source\": \"./board-prep\",\n      \"author\": {\n        \"name\": \"yamz8\"\n      },\n      \"repository\": \"https://github.com/yamz8/open-ceo\",\n      \"homepage\": \"https://github.com/yamz8/open-ceo#board-prep\",\n      \"license\": \"MIT\",\n      \"category\": \"productivity\",\n      \"tags\": [\"board\", \"startup\", \"ceo\", \"investor\", \"saas\", \"metrics\", \"deck\"]\n    },\n    {\n      \"name\": \"investor-updates\",\n      \"version\": \"0.1.0\",\n      \"description\": \"Monthly investor update toolkit for VC-backed startup CEOs. Helps draft professional investor emails, generate metrics snapshots, and follow communication best practices.\",\n      \"source\": \"./investor-updates\",\n      \"author\": {\n        \"name\": \"yamz8\"\n      },\n      \"repository\": \"https://github.com/yamz8/open-ceo\",\n      \"homepage\": \"https://github.com/yamz8/open-ceo#investor-updates\",\n      \"license\": \"MIT\",\n      \"category\": \"productivity\",\n      \"tags\": [\"investor\", \"updates\", \"startup\", \"ceo\", \"email\", \"metrics\", \"communication\"]\n    },\n    {\n      \"name\": \"hiring\",\n      \"version\": \"0.1.0\",\n      \"description\": \"Startup hiring toolkit for CEOs. Generate job descriptions, interview scorecards, offer letters, and calculate equity compensation. Includes salary and equity benchmarks by role, level, and stage.\",\n      \"source\": \"./hiring\",\n      \"author\": {\n        \"name\": \"yamz8\"\n      },\n      \"repository\": \"https://github.com/yamz8/open-ceo\",\n      \"homepage\": \"https://github.com/yamz8/open-ceo#hiring\",\n      \"license\": \"MIT\",\n      \"category\": \"productivity\",\n      \"tags\": [\"hiring\", \"recruiting\", \"job-description\", \"offer-letter\", \"equity\", \"compensation\", \"interview\", \"startup\", \"hr\"]\n    },\n    {\n      \"name\": \"founder-mode\",\n      \"version\": \"0.1.0\",\n      \"description\": \"Founder productivity and wellness toolkit. Prioritize chaos, delegate effectively, manage energy, and maintain mental resilience. Includes decision journaling, stakeholder mapping, and weekly reset rituals.\",\n      \"source\": \"./founder-mode\",\n      \"author\": {\n        \"name\": \"yamz8\"\n      },\n      \"repository\": \"https://github.com/yamz8/open-ceo\",\n      \"homepage\": \"https://github.com/yamz8/open-ceo#founder-mode\",\n      \"license\": \"MIT\",\n      \"category\": \"productivity\",\n      \"tags\": [\"founder\", \"ceo\", \"productivity\", \"prioritization\", \"delegation\", \"wellness\", \"burnout\", \"decision-making\", \"startup\", \"mental-health\"]\n    },\n    {\n      \"name\": \"crisis-playbook\",\n      \"version\": \"0.1.0\",\n      \"description\": \"Crisis management toolkit for startup CEOs. Navigate layoffs, pivots, down rounds, PR crises, and existential threats with frameworks, communication templates, and step-by-step guidance.\",\n      \"source\": \"./crisis-playbook\",\n      \"author\": {\n        \"name\": \"yamz8\"\n      },\n      \"repository\": \"https://github.com/yamz8/open-ceo\",\n      \"homepage\": \"https://github.com/yamz8/open-ceo#crisis-playbook\",\n      \"license\": \"MIT\",\n      \"category\": \"productivity\",\n      \"tags\": [\"crisis\", \"layoff\", \"pivot\", \"down-round\", \"pr\", \"communication\", \"restructuring\", \"turnaround\", \"startup\", \"ceo\"]\n    }\n  ]\n}\n",
        "README.md": "# Startup CEO Marketplace for Claude Code\n\nThis marketplace provides plugins for VC-backed startup CEOs. Install these plugins to access AI-powered tools for fundraising, board meeting preparation, and investor communication directly within Claude Code.\n\n**What's included:**\n- **Commands**: Structured workflows for metrics, pitch decks, board decks, investor updates, hiring, founder productivity, and crisis management\n- **Agents**: Proactive assistants that trigger automatically when working on metrics, fundraising, board prep, investor communication, hiring, founder challenges, or company crises\n- **Skills**: Domain-specific knowledge for startup metrics, fundraising, board meetings, investor relations, compensation, founder wellness, and crisis communication\n\n## The CEO Workflow\n\n**Each plugin works standalone** - install only what you need. When used together, they can optionally share configuration:\n\n```\n┌─────────┐  ┌─────────────┐  ┌────────────┐  ┌──────────────────┐  ┌────────┐  ┌──────────────┐  ┌──────────────────┐\n│ Metrics │  │ Fundraising │  │ Board Prep │  │ Investor Updates │  │ Hiring │  │ Founder Mode │  │ Crisis Playbook  │\n└────┬────┘  └──────┬──────┘  └─────┬──────┘  └────────┬─────────┘  └───┬────┘  └──────┬───────┘  └────────┬─────────┘\n     │              │               │                  │                │              │                   │\n     └──────────────┴───────────────┴──────────────────┴────────────────┴──────────────┴───────────────────┘\n                                 Optional: share config to avoid re-entering data\n```\n\n## Quick Start\n\n```bash\n# Add the marketplace\n/plugin marketplace add yamz8/open-ceo\n\n# Install only what you need (each plugin works standalone)\n/plugin install metrics@open-ceo\n/plugin install fundraising@open-ceo\n/plugin install board-prep@open-ceo\n/plugin install investor-updates@open-ceo\n/plugin install hiring@open-ceo\n/plugin install founder-mode@open-ceo\n/plugin install crisis-playbook@open-ceo\n```\n\n**No configuration required** - each plugin will ask for information when needed. Optional config files can save time if you use plugins frequently.\n\n## Available Plugins\n\n### Metrics\n**Plugin ID**: `metrics@open-ceo`\n\nTrack, calculate, and benchmark startup metrics. Works standalone or as optional shared config for other plugins.\n\n**Commands:**\n| Command | Description |\n|---------|-------------|\n| `/metrics-setup [model] [stage]` | Configure metrics tracking |\n| `/metrics-snapshot [format]` | Generate metrics report |\n| `/metrics-benchmark [stage]` | Compare to industry benchmarks |\n| `/metrics-calculate [metric]` | Calculate derived metrics |\n\n**Features:**\n- SaaS metrics (ARR, MRR, NRR, churn, CAC, LTV, burn multiple, etc.)\n- Marketplace metrics (GMV, take rate, liquidity, network effects)\n- Stage-appropriate benchmarks (pre-seed to Series C)\n- Optional: Other plugins can read your metrics config\n\n**Requirements**: None - works standalone with any project\n\n---\n\n### Fundraising\n**Plugin ID**: `fundraising@open-ceo`\n\nComplete fundraising toolkit for VC-backed startup CEOs. Create pitch decks, write investor outreach, analyze term sheets, and manage your fundraising pipeline.\n\n**Commands:**\n| Command | Description |\n|---------|-------------|\n| `/pitch-deck [format] [stage]` | Generate pitch deck outline (Sequoia, YC, a16z formats) |\n| `/outreach [type] [investor]` | Create investor emails (cold, warm, follow-up) |\n| `/term-sheet [action]` | Analyze or compare term sheets |\n| `/due-diligence [stage]` | Generate DD checklist by stage |\n| `/pipeline [action]` | Track investor pipeline |\n\n**Features:**\n- Pitch deck templates for Sequoia, YC, and a16z formats\n- Cold/warm outreach email sequences\n- Term sheet analysis with red flag detection\n- Stage-specific due diligence checklists (pre-seed to Series C)\n- Light investor pipeline CRM\n\n**Requirements**: None - works with any project\n\n---\n\n### Board Prep\n**Plugin ID**: `board-prep@open-ceo`\n\nComprehensive board meeting preparation toolkit for VC-backed startup CEOs. Create professional board decks, agendas, and prepare for investor Q&A.\n\n**Commands:**\n| Command | Description |\n|---------|-------------|\n| `/board-prep:start` | Full board prep workflow with checklist |\n| `/board-prep:agenda` | Generate professional board meeting agenda |\n| `/board-prep:deck` | Draft board deck sections in markdown |\n| `/board-prep:qa-prep` | Prepare for anticipated investor questions |\n\n**Features:**\n- 10-section board deck generation (summary, metrics, business updates, financials, GTM, product, team, strategic, asks, appendix)\n- SaaS metrics tracking (ARR, MRR, growth rates, churn, CAC, LTV, burn rate, runway)\n- Investor Q&A preparation across 5 focus areas\n- Configurable agenda formats (90-min, 2-hour, 3-hour)\n\n**Requirements**: None - works with any project\n\n### Investor Updates\n**Plugin ID**: `investor-updates@open-ceo`\n\nMonthly investor communication assistant. Draft professional investor updates optimized for busy investors.\n\n**Commands:**\n| Command | Description |\n|---------|-------------|\n| `/investor-updates:draft` | Draft monthly investor update |\n| `/investor-updates:metrics` | Generate metrics snapshot |\n| `/investor-updates:send-checklist` | Pre-send verification checklist |\n\n**Features:**\n- Structured update format (TL;DR, Highlights, Metrics, Challenges, Asks, Looking Ahead)\n- 2-3 minute read optimization (300-500 words)\n- Email or markdown output formats\n- 20+ item pre-send checklist across 6 categories\n\n**Requirements**: None - works with any project\n\n---\n\n### Founder Mode\n**Plugin ID**: `founder-mode@open-ceo`\n\nProductivity and wellness toolkit for the chaotic reality of being a startup CEO. Part executive coach, part therapist, part tough-love advisor.\n\n**Commands:**\n| Command | Description |\n|---------|-------------|\n| `/founder-setup` | Configure founder profile and preferences |\n| `/prioritize-chaos` | Triage overwhelming to-do lists |\n| `/energy-audit` | Assess where energy goes vs. should go |\n| `/delegate-or-die` | Framework for effective delegation |\n| `/founder-therapy` | Structured reflection for hard moments |\n| `/weekly-reset` | End-of-week reflection + planning ritual |\n| `/decision-journal` | Log and review major decisions |\n| `/stakeholder-map` | Map relationships and who needs attention |\n\n**Features:**\n- Prioritization frameworks adapted for founders\n- Delegation ladder and letting-go strategies\n- Energy management and sustainable pace\n- Decision journaling with review\n- Burnout prevention and wellness support\n- Stakeholder relationship mapping\n\n**Requirements**: None - works with any project\n\n---\n\n### Crisis Playbook\n**Plugin ID**: `crisis-playbook@open-ceo`\n\nCrisis management toolkit for navigating the hardest moments. Layoffs, pivots, down rounds, PR crises, and existential threats with frameworks, communication templates, and step-by-step guidance.\n\n**Commands:**\n| Command | Description |\n|---------|-------------|\n| `/crisis-assess` | Assess crisis severity and determine response |\n| `/layoff-plan` | Plan and execute a reduction in force |\n| `/pivot-decision` | Framework for deciding whether and how to pivot |\n| `/down-round-prep` | Navigate raising at a lower valuation |\n| `/pr-response` | Respond to PR crises and reputation threats |\n\n**Features:**\n- Crisis severity assessment and triage\n- Complete layoff planning with legal considerations\n- Pivot vs. persevere decision frameworks\n- Down round negotiation and communication\n- PR response templates and strategies\n- Restructuring and turnaround playbooks\n- Stakeholder communication templates\n\n**Requirements**: None - works with any project\n\n---\n\n### Hiring\n**Plugin ID**: `hiring@open-ceo`\n\nStartup hiring toolkit for CEOs. Generate job descriptions, interview scorecards, offer letters, and calculate equity compensation with benchmarks by role, level, and stage.\n\n**Commands:**\n| Command | Description |\n|---------|-------------|\n| `/hiring-setup` | Configure company hiring preferences and equity structure |\n| `/job-description [role] [level]` | Generate role-specific job descriptions |\n| `/interview-scorecard [role] [stage]` | Create structured interview evaluations |\n| `/offer-letter [role] [candidate]` | Draft professional offer letters |\n| `/equity-calculator [role] [level]` | Calculate equity grants and value projections |\n\n**Features:**\n- Job descriptions for any role (Engineering, Product, Sales, Marketing, etc.)\n- Interview scorecards with competency-based evaluation\n- Offer letters with salary and equity details\n- Equity calculator with vesting schedules and exit scenarios\n- Compensation benchmarks by stage, level, and location tier\n\n**Requirements**: None - works with any project\n\n## Detailed Installation\n\n### 1. Add the marketplace (one time)\n\n```bash\n/plugin marketplace add https://github.com/yamz8/open-ceo.git\n```\n\n### 2. Install specific plugins\n\n```bash\n# Install only what you need - each works standalone\n/plugin install metrics@open-ceo         # Metrics tracking\n/plugin install fundraising@open-ceo     # Fundraising toolkit\n/plugin install board-prep@open-ceo      # Board meeting prep\n/plugin install investor-updates@open-ceo # Monthly updates\n/plugin install hiring@open-ceo          # Hiring toolkit\n/plugin install founder-mode@open-ceo    # Founder productivity\n/plugin install crisis-playbook@open-ceo # Crisis management\n```\n\n### 3. Configure company context (optional)\n\n**Configuration is optional** - each plugin will ask for information when needed.\n\nFor convenience, you can create config files to avoid re-entering information:\n\n**For Metrics** (`.claude/metrics.local.md`):\n```yaml\n---\ncompany_name: \"YourCo\"\nbusiness_model: \"saas\"\nstage: \"series-a\"\nmrr: 185000\nnrr: 112\ngross_margin: 78\nburn_multiple: 1.8\n---\n```\n\n**For Fundraising** (`.claude/fundraising.local.md`):\n```yaml\n---\ncompany_name: \"YourCo\"\none_liner: \"AI-powered analytics for SMBs\"\nstage: \"seed\"\narr: 500000\nmrr_growth: 15\nraise_amount: 3000000\ntarget_valuation: 15000000\n---\n```\n\n**For Board Prep** (`.claude/board-prep.local.md`):\n```yaml\n---\ncompany_name: \"YourCo\"\nstage: \"Series A\"\nboard_members:\n  - name: \"Jane Smith\"\n    firm: \"Acme Ventures\"\n---\n```\n\n**For Investor Updates** (`.claude/investor-updates.local.md`):\n```yaml\n---\ncompany_name: \"YourCo\"\nstage: \"Series A\"\ninvestors:\n  - name: \"Jane Smith\"\n    firm: \"Acme Ventures\"\n---\n```\n\n**For Hiring** (`.claude/hiring.local.md`):\n```yaml\n---\ncompany_name: \"YourCo\"\nstage: \"series-a\"\ntotal_equity_pool_percent: 15\nstandard_vesting_years: 4\ncliff_months: 12\nfmv_per_share: 0.50\nsalary_percentile_target: 50\n---\n```\n\nSee each plugin's `examples/` folder for complete templates.\n\n**Note**: If you have multiple plugins, they can optionally read each other's configs - you don't need to duplicate information. Each plugin checks for configs in a fallback order.\n\n### 4. Start using\n\n```bash\n# Set up metrics tracking\n/metrics-setup saas series-a\n\n# Generate a metrics snapshot\n/metrics-snapshot\n\n# Benchmark your metrics\n/metrics-benchmark\n\n# Generate a pitch deck outline\n/pitch-deck sequoia seed\n\n# Create investor outreach email\n/outreach cold\n\n# Analyze a term sheet\n/term-sheet analyze\n\n# Start a full board prep workflow\n/board-prep:start\n\n# Draft a monthly investor update\n/investor-updates:draft\n\n# Generate a job description\n/job-description senior software engineer\n\n# Create interview scorecard\n/interview-scorecard product-manager technical\n\n# Calculate equity for an offer\n/equity-calculator senior series-a\n\n# Prioritize when overwhelmed\n/prioritize-chaos\n\n# Weekly reflection and planning\n/weekly-reset\n\n# Log a major decision\n/decision-journal\n\n# Assess a crisis situation\n/crisis-assess\n\n# Plan a layoff\n/layoff-plan\n\n# Evaluate a pivot\n/pivot-decision\n```\n\n## Support\n\nFor issues with:\n- **Claude Code plugin system**: See https://github.com/anthropics/claude-code/issues\n- **These plugins**: Report at https://github.com/yamz8/open-ceo/issues\n\n## License\n\nMIT\n",
        "metrics/README.md": "# Metrics Plugin\n\nA comprehensive metrics toolkit for startup CEOs. Track, calculate, and benchmark SaaS and marketplace metrics. Part of the [Open CEO](https://github.com/yamz8/open-ceo) marketplace.\n\n## Features\n\n- **Metrics Setup**: Configure which metrics to track based on your business model and stage\n- **Metrics Snapshot**: Generate current metrics reports for different audiences\n- **Benchmarking**: Compare your metrics to stage and industry benchmarks\n- **Calculations**: Calculate derived metrics (LTV, CAC Payback, Burn Multiple, etc.)\n- **Shared Config**: Metrics integrate with other Open CEO plugins\n\n## Installation\n\n```bash\n# Install via Claude Code marketplace\nclaude mcp add marketplace:metrics@open-ceo\n```\n\nOr add manually to your Claude Code configuration.\n\n## Commands\n\n| Command | Description |\n|---------|-------------|\n| `/metrics-setup [model] [stage]` | Configure metrics tracking |\n| `/metrics-snapshot [format]` | Generate metrics report |\n| `/metrics-benchmark [stage]` | Compare to benchmarks |\n| `/metrics-calculate [metric]` | Calculate derived metrics |\n\n### Examples\n\n```bash\n# Set up metrics for a Series A SaaS company\n/metrics-setup saas series-a\n\n# Generate a full metrics snapshot\n/metrics-snapshot full\n\n# Get investor-ready metrics summary\n/metrics-snapshot investor\n\n# Benchmark against Series A standards\n/metrics-benchmark series-a\n\n# Calculate LTV:CAC ratio\n/metrics-calculate ltv\n```\n\n## Supported Business Models\n\n### SaaS Metrics\n- **Revenue**: MRR, ARR, New/Expansion/Churned MRR\n- **Growth**: MoM/YoY growth, NRR, GRR\n- **Unit Economics**: CAC, LTV, LTV:CAC, CAC Payback\n- **Efficiency**: Burn Multiple, Magic Number, Rule of 40\n- **Customers**: Logo count, churn rate, ARPU\n\n### Marketplace Metrics\n- **Volume**: GMV, Net Revenue, Take Rate, AOV\n- **Liquidity**: Search-to-Fill, Time-to-Fill, Utilization\n- **Supply/Demand**: Active buyers/sellers, B:S ratio\n- **Retention**: Repeat rate, Seller retention\n- **Economics**: Buyer/Seller LTV:CAC, Contribution margin\n\n## Configuration\n\nCreate `.claude/metrics.local.md` with your metrics:\n\n```yaml\n---\ncompany_name: \"YourCo\"\nbusiness_model: \"saas\"\nstage: \"series-a\"\n\nmrr: 185000\nnrr: 112\ngross_margin: 78\nburn_multiple: 1.8\n---\n```\n\nSee `examples/metrics.local.example.md` for complete templates.\n\n## Integration with Other Plugins (Optional)\n\nThis plugin works **completely standalone**. However, if you're using other Open CEO plugins, they can optionally read from `.claude/metrics.local.md` to avoid re-entering the same data:\n\n```\n              ┌─────────────┐\n              │   Metrics   │ ← Optional shared config\n              └──────┬──────┘\n         ┌──────────┼──────────┐\n         ▼          ▼          ▼\n   Fundraising  Board Prep  Investor Updates\n   (standalone)  (standalone)  (standalone)\n```\n\n**Each plugin works independently** - the integration just saves you from entering the same metrics twice.\n\nOther plugins check for configs in this order:\n1. Their own config file (e.g., `.claude/fundraising.local.md`)\n2. `.claude/metrics.local.md` (if it exists)\n3. Ask the user directly (if no config found)\n\n## Benchmarks Included\n\nStage-appropriate benchmarks for:\n- Pre-seed through Series C+\n- SaaS by segment (SMB, Mid-Market, Enterprise)\n- Marketplace by category\n- Industry-specific targets\n\n## Related Plugins\n\n- **[Fundraising](../fundraising)**: Use metrics in pitch decks\n- **[Board Prep](../board-prep)**: Board meeting metrics\n- **[Investor Updates](../investor-updates)**: Monthly metrics reports\n\n## License\n\nMIT\n",
        "fundraising/README.md": "# Fundraising Plugin\n\nA comprehensive fundraising toolkit for VC-backed startup CEOs. Part of the [Open CEO](https://github.com/yamz8/open-ceo) marketplace.\n\n## Features\n\n- **Pitch Deck Generation**: Create deck outlines in Sequoia, YC, or a16z formats\n- **Investor Outreach**: Draft cold emails, warm intro requests, and follow-up sequences\n- **Term Sheet Analysis**: Analyze terms, compare offers, identify red flags\n- **Due Diligence Prep**: Stage-appropriate checklists and data room organization\n- **Pipeline Tracking**: Light CRM for managing investor conversations\n\n## Installation\n\n```bash\n# Install via Claude Code marketplace\nclaude mcp add marketplace:fundraising@open-ceo\n```\n\nOr add manually to your Claude Code configuration.\n\n## Commands\n\n| Command | Description |\n|---------|-------------|\n| `/pitch-deck [format] [stage]` | Generate pitch deck outline |\n| `/outreach [type] [investor]` | Create investor emails |\n| `/term-sheet [action]` | Analyze or compare term sheets |\n| `/due-diligence [stage]` | Generate DD checklist |\n| `/pipeline [action] [investor]` | Manage investor pipeline |\n\n### Examples\n\n```bash\n# Generate a Sequoia-format deck for Series A\n/pitch-deck sequoia series-a\n\n# Create a cold outreach email\n/outreach cold \"Sarah at Acme Ventures\"\n\n# Analyze a term sheet\n/term-sheet analyze\n\n# Compare two term sheets\n/term-sheet compare\n\n# Get DD checklist for seed round\n/due-diligence seed\n\n# View pipeline summary\n/pipeline summary\n\n# Add investor to pipeline\n/pipeline add \"Acme Ventures\"\n```\n\n## Configuration (Optional)\n\nFor personalized guidance, create `.claude/fundraising.local.md` with your company details:\n\n```yaml\n---\ncompany_name: \"Your Company\"\none_liner: \"What you do in one sentence\"\nstage: \"seed\"\narr: 500000\nmrr_growth: 15\nraise_amount: 3000000\n---\n\n## Company Context\n[Additional context about your company...]\n```\n\nSee `examples/fundraising.local.example.md` for a complete template.\n\n## Stages Supported\n\n- **Pre-seed**: SAFE/convertible focus, team + vision emphasis\n- **Seed**: Early traction, product-market fit signals\n- **Series A**: Proven PMF, repeatable GTM\n- **Series B+**: Scale, unit economics, path to profitability\n\n## What's Included\n\n### Skill: Fundraising Knowledge\nComprehensive knowledge base covering:\n- Pitch deck templates (Sequoia, YC, a16z formats)\n- Stage-specific guidance and benchmarks\n- Term sheet glossary and red flags\n- Outreach best practices and sequences\n\n### Agent: Fundraising Assistant\nProactive assistant that activates when you're working on:\n- Investor communications\n- Pitch decks and presentations\n- Term sheet review\n- Meeting preparation\n\n## Related Plugins\n\nThis plugin is part of the Open CEO ecosystem:\n\n```\nFundraising → Board Prep → Investor Updates\n```\n\n- **[Board Prep](../board-prep)**: Prepare for board meetings\n- **[Investor Updates](../investor-updates)**: Send monthly investor updates\n\n## License\n\nMIT\n",
        "board-prep/README.md": "# Board Prep Plugin\n\nA Claude Code plugin to help VC-backed startup CEOs prepare for board meetings.\n\n## Features\n\n- **Full prep workflow** - Guided process from start to finish\n- **Agenda creation** - Generate professional board meeting agendas\n- **Board deck drafting** - Create structured markdown decks with SaaS metrics\n- **Q&A preparation** - Anticipate and prepare for tough investor questions\n- **Proactive assistance** - Agent helps when board prep tasks are detected\n\n## Commands\n\n| Command | Description |\n|---------|-------------|\n| `/board-prep:start` | Kick off the full board prep workflow |\n| `/board-prep:agenda` | Generate a board meeting agenda |\n| `/board-prep:deck` | Draft board deck sections |\n| `/board-prep:qa-prep` | Prepare for anticipated questions |\n\n## Configuration\n\nCreate `.claude/board-prep.local.md` in your project to store company-specific information:\n\n```markdown\n---\ncompany_name: Your Company\nboard_members:\n  - name: Jane Smith\n    role: Lead Investor\n    firm: Acme Ventures\n  - name: John Doe\n    role: Independent Director\nmeeting_cadence: quarterly\n---\n\n## Key Metrics Sources\n- Revenue data: spreadsheet.csv\n- User metrics: analytics dashboard\n\n## Previous Board Materials\n- Last deck: docs/board-deck-q3.md\n```\n\n## Metrics Tracked\n\nStandard SaaS metrics included:\n- ARR / MRR and growth rates\n- Churn (gross and net)\n- CAC and LTV\n- Burn rate and runway\n- Headcount\n\n## Installation\n\nAdd to your Claude Code settings or use via the open-ceo marketplace.\n",
        "investor-updates/README.md": "# Investor Updates Plugin\n\nA Claude Code plugin to help VC-backed startup CEOs send professional monthly investor updates.\n\n## Features\n\n- **Draft updates** - Generate complete investor email drafts or markdown outlines\n- **Metrics snapshots** - Quick metrics summary for your update\n- **Send checklist** - Pre-send verification for recipients, tone, and data accuracy\n- **Proactive assistance** - Agent helps when investor update work is detected\n\n## Commands\n\n| Command | Description |\n|---------|-------------|\n| `/investor-updates:draft` | Draft a monthly investor update email |\n| `/investor-updates:metrics` | Generate a metrics snapshot for the update |\n| `/investor-updates:send-checklist` | Pre-send checklist before sending |\n\n## Configuration (Optional)\n\nCreate `.claude/investor-updates.local.md` in your project for personalized updates:\n\n```yaml\n---\ncompany_name: \"Your Company\"\nstage: \"Series A\"\ninvestors:\n  - name: \"Jane Smith\"\n    firm: \"Acme Ventures\"\n    email: \"jane@acmeventures.com\"\nmetrics:\n  arr: \"$2.4M\"\n  mrr_growth: \"8%\"\n  runway: \"18 months\"\n---\n```\n\n**No configuration?** No problem - the plugin will ask for details when needed.\n\n**Using other Open CEO plugins?** This plugin can also read from `.claude/board-prep.local.md` or `.claude/metrics.local.md` if they exist, so you don't need to duplicate information.\n\n## Metrics Tracked\n\nLighter subset of SaaS metrics for monthly updates:\n- ARR / MRR and growth rates\n- Key wins and milestones\n- Runway update\n- Team highlights\n\n## Installation\n\nAdd to your Claude Code settings or use via the open-ceo marketplace.\n",
        "hiring/README.md": "# Hiring Plugin\n\nStartup hiring toolkit for CEOs. Streamline your recruiting process with structured workflows for job descriptions, interviews, offers, and equity compensation.\n\n## Features\n\n- **Job Descriptions** - Generate role-specific JDs for any department (Engineering, Product, Sales, etc.)\n- **Interview Scorecards** - Create structured evaluation forms for each interview stage\n- **Offer Letters** - Draft professional offer letters with compensation details\n- **Equity Calculator** - Calculate option grants with vesting schedules and value projections\n- **Compensation Benchmarks** - Reference salary and equity data by role, level, stage, and location\n\n## Commands\n\n| Command | Description |\n|---------|-------------|\n| `/hiring-setup` | Configure company hiring preferences and compensation structure |\n| `/job-description [role]` | Generate a job description for a specific role |\n| `/interview-scorecard [role] [stage]` | Create an interview scorecard for a role and interview stage |\n| `/offer-letter [role]` | Draft an offer letter with compensation details |\n| `/equity-calculator` | Calculate equity grants and model future value |\n\n## Installation\n\n```bash\n/plugin install hiring@open-ceo\n```\n\n## Configuration\n\nRun `/hiring-setup` to create `.claude/hiring.local.md` with your company's:\n\n- Company stage (Seed, Series A, etc.)\n- Total equity pool and vesting schedule\n- 409A/FMV price per share (optional)\n- Benefits summary\n- Location/remote policy\n- Hiring philosophy\n\nSee `examples/hiring.local.example.md` for a complete template.\n\n## Integration with Other Plugins\n\nThis plugin works standalone but can optionally read from `.claude/metrics.local.md` to pull company stage and other context if available.\n\n## Usage Examples\n\n### Generate a Job Description\n```\n/job-description senior software engineer\n```\n\n### Create Interview Scorecards\n```\n/interview-scorecard product manager hiring-manager\n```\n\n### Draft an Offer Letter\n```\n/offer-letter senior software engineer\n```\n\n### Calculate Equity\n```\n/equity-calculator\n```\n\n## Disclaimers\n\n- **Not legal advice**: Offer letter templates should be reviewed by your legal counsel before use\n- **Benchmark data**: Compensation benchmarks are general market references; actual offers should consider your specific market, budget, and candidate\n",
        "founder-mode/README.md": "# Founder Mode\n\nA Claude Code plugin for the chaotic reality of being a startup CEO. Part executive coach, part therapist, part tough-love advisor.\n\n## Overview\n\nBuilding a company is uniquely hard. You're expected to be visionary AND operational, confident AND humble, fast AND thoughtful. You're often alone at the top with decisions that keep you up at night.\n\n**Founder Mode** provides frameworks and support for:\n- **Prioritization** - Cut through chaos to focus on what matters\n- **Delegation** - Learn to let go and scale yourself\n- **Energy management** - Work sustainably for the long haul\n- **Decision quality** - Make better decisions and learn from them\n- **Mental wellness** - Prevent burnout and maintain resilience\n- **Stakeholder navigation** - Manage relationships that matter\n\n## Installation\n\n```bash\n# If using the Open CEO marketplace\n/plugin install founder-mode@open-ceo\n\n# Or install directly\n/plugin add https://github.com/yamz8/open-ceo.git --subdir founder-mode\n```\n\n## Commands\n\n| Command | Description |\n|---------|-------------|\n| `/founder-setup` | Configure your founder profile and preferences |\n| `/prioritize-chaos` | Triage overwhelming to-do lists |\n| `/energy-audit` | Assess where energy goes vs. should go |\n| `/delegate-or-die` | Framework for effective delegation |\n| `/founder-therapy` | Structured reflection for hard moments |\n| `/weekly-reset` | End-of-week reflection + planning ritual |\n| `/decision-journal` | Log and review major decisions |\n| `/stakeholder-map` | Map relationships and identify who needs attention |\n\n## Quick Start\n\n1. **Set up your profile:**\n   ```\n   /founder-setup\n   ```\n   This creates `.claude/founder-mode.local.md` with your context.\n\n2. **When overwhelmed:**\n   ```\n   /prioritize-chaos\n   ```\n   Get clarity on what actually matters.\n\n3. **Weekly ritual:**\n   ```\n   /weekly-reset\n   ```\n   Reflect on the week and plan the next one.\n\n## The Three Modes\n\nFounder Mode adapts its tone based on context:\n\n| Mode | When Used | Style |\n|------|-----------|-------|\n| **Practical Coach** | Operational challenges | Direct, actionable, framework-driven |\n| **Empathetic Mentor** | Emotional struggles | Supportive, validating, perspective-sharing |\n| **Tough Love** | Avoidance and excuses | Challenging, direct, no-nonsense |\n\n## Skills\n\n### Founder Frameworks\nTriggered when asking about prioritization, delegation, decision-making, or time management.\n\nIncludes:\n- Eisenhower Matrix (adapted for founders)\n- Leverage Test\n- Delegation Ladder\n- Decision quality frameworks\n- CEO time allocation by stage\n\n### Founder Wellness\nTriggered when discussing burnout, stress, work-life balance, or mental health.\n\nIncludes:\n- Burnout recognition and prevention\n- Building support systems\n- Sustainable pace practices\n- Crisis recovery guidance\n\n## Integration with Other Plugins\n\nFounder Mode works standalone but can optionally read from:\n- `.claude/metrics.local.md` - Company stage, runway, key metrics\n- `.claude/founder-mode.local.md` - Your personal founder profile\n\nThis enables context-aware advice without re-entering information.\n\n## Example Workflows\n\n### Morning Overwhelm\n```\nYou: I have a million things to do and don't know where to start\n\n/prioritize-chaos\n\n[Assistant helps triage and identify the ONE thing that matters]\n```\n\n### Delegation Struggle\n```\nYou: I keep doing everything myself but I know I shouldn't\n\n/delegate-or-die\n\n[Assistant walks through what to delegate and how to let go]\n```\n\n### Weekly Planning\n```\nYou: Let's do my weekly review\n\n/weekly-reset\n\n[Assistant guides through reflection and planning ritual]\n```\n\n### Hard Decision\n```\nYou: I need to decide whether to fire my VP Sales\n\n/decision-journal\n\n[Assistant structures the decision with frameworks and documentation]\n```\n\n## Configuration\n\n### founder-mode.local.md\n\nThe setup command creates a config file with:\n- Company context (stage, runway, team size)\n- Your role and tenure\n- Energy patterns and preferences\n- Current priorities\n- Support systems\n- Non-negotiables\n\nExample: See `examples/founder-mode.local.example.md`\n\n### Integration with metrics.local.md\n\nIf you're using the metrics plugin, founder-mode can pull company stage and key metrics automatically.\n\n## Best Practices\n\n1. **Do `/founder-setup` first** - Context makes advice better\n2. **Use `/weekly-reset` consistently** - The power is in the habit\n3. **Journal decisions** - You'll learn from patterns over time\n4. **Be honest** - The assistant can only help with what you share\n5. **Take breaks seriously** - This isn't productivity theater\n\n## Mental Health Note\n\nThis plugin provides frameworks and support but is **not a substitute for professional mental health care**. If you're experiencing serious depression, anxiety, or thoughts of self-harm, please seek professional help.\n\n**Crisis Resources:**\n- National Suicide Prevention Lifeline: 988\n- Crisis Text Line: Text HOME to 741741\n\n## Contributing\n\nThis plugin is part of the [Open CEO](https://github.com/yamz8/open-ceo) project. Contributions welcome!\n\n## License\n\nMIT\n",
        "crisis-playbook/README.md": "# Crisis Playbook\n\nA Claude Code plugin for navigating the hardest moments in a startup's life. Layoffs, pivots, down rounds, PR crises, and existential threats - with frameworks, communication templates, and step-by-step guidance.\n\n## Overview\n\nEvery startup faces crises. How you handle them determines whether the company survives and what kind of leader you become. This plugin provides battle-tested frameworks for:\n\n- **Assessing crises** - Understand severity and appropriate response\n- **Executing layoffs** - With dignity, legal compliance, and clear communication\n- **Making pivot decisions** - Frameworks for when to pivot and how to execute\n- **Navigating down rounds** - Protect what matters while getting funded\n- **Responding to PR crises** - When to respond, how to respond, and when to stay silent\n- **Restructuring and turnaround** - Cost cutting, bridge financing, and recovery\n\n## Installation\n\n```bash\n# If using the Open CEO marketplace\n/plugin install crisis-playbook@open-ceo\n\n# Or install directly\n/plugin add https://github.com/yamz8/open-ceo.git --subdir crisis-playbook\n```\n\n## Commands\n\n| Command | Description |\n|---------|-------------|\n| `/crisis-assess` | Assess crisis severity and determine response |\n| `/layoff-plan` | Plan and execute a reduction in force |\n| `/pivot-decision` | Framework for deciding whether and how to pivot |\n| `/down-round-prep` | Navigate raising at a lower valuation |\n| `/pr-response` | Respond to PR crises and reputation threats |\n\n## Quick Start\n\n1. **When crisis hits, start with assessment:**\n   ```\n   /crisis-assess\n   ```\n   This will categorize the crisis and point you to the right next steps.\n\n2. **For specific situations, go directly to the relevant command:**\n   - Considering layoffs? → `/layoff-plan`\n   - Product not working? → `/pivot-decision`\n   - Can't raise at last valuation? → `/down-round-prep`\n   - Bad press or social media crisis? → `/pr-response`\n\n## Skills\n\n### Crisis Communication\nTriggered when asking about communicating bad news, stakeholder messaging, or crisis announcements.\n\nIncludes:\n- Layoff announcement scripts\n- Pivot communication templates\n- Board and investor notification templates\n- Customer communication templates\n\n### Restructuring Guide\nTriggered when asking about restructuring, turnaround, cost cutting, or winddown.\n\nIncludes:\n- Cost reduction playbook\n- Runway extension strategies\n- Turnaround frameworks\n- Winddown checklist\n\n## Example Workflows\n\n### Considering Layoffs\n```\nYou: I think we need to do layoffs\n\n/layoff-plan\n\n[Assistant guides through decision validation, planning, execution, and communication]\n```\n\n### Facing a PR Crisis\n```\nYou: There's negative press about us circulating on Twitter\n\n/pr-response\n\n[Assistant helps assess severity, decide whether to respond, and craft appropriate messaging]\n```\n\n### Need to Pivot\n```\nYou: Our current product isn't getting traction. Should we pivot?\n\n/pivot-decision\n\n[Assistant walks through pivot vs persevere framework and, if pivoting, execution plan]\n```\n\n## Integration with Other Plugins\n\nCrisis Playbook works standalone but can read from:\n- `.claude/metrics.local.md` - For runway, burn rate, team size context\n- `.claude/crisis-playbook.local.md` - Your crisis-specific configuration\n\nThis enables context-aware guidance without re-entering information.\n\n## Important Notes\n\n### This Is Not Legal Advice\n\nThis plugin provides frameworks and guidance, not legal advice. For serious matters:\n- **Layoffs**: Consult employment counsel\n- **Restructuring**: Consult corporate counsel\n- **Down rounds**: Work with your lawyers and advisors\n- **PR crises**: Consider professional PR support for major issues\n\n### Confidentiality\n\nBe thoughtful about what you share. While Claude doesn't retain conversations:\n- Don't include specific employee names in layoff planning\n- Be careful with material non-public information\n- Treat sensitive situations appropriately\n\n### Mental Health\n\nCrises are hard on founders. If you're struggling:\n- Use `/founder-therapy` from the founder-mode plugin\n- Consider professional support (therapist, coach)\n- Lean on your support network\n\n## Philosophy\n\nThis plugin is built on core principles:\n\n1. **Crises are defining moments** - How you handle them matters\n2. **Speed matters, but so does doing it right** - Don't skip important steps\n3. **Communication is as important as action** - How you tell people matters\n4. **Protect people even in hard situations** - Treat everyone with dignity\n5. **Most companies face crises** - You're not alone, and you can get through this\n\n## Contributing\n\nThis plugin is part of the [Open CEO](https://github.com/yamz8/open-ceo) project. Contributions welcome!\n\n## License\n\nMIT\n"
      },
      "plugins": [
        {
          "name": "metrics",
          "version": "0.1.0",
          "description": "Startup metrics toolkit for CEOs. Track, calculate, and benchmark SaaS and marketplace metrics. Integrates with fundraising, board-prep, and investor-updates plugins.",
          "source": "./metrics",
          "author": {
            "name": "yamz8"
          },
          "repository": "https://github.com/yamz8/open-ceo",
          "homepage": "https://github.com/yamz8/open-ceo#metrics",
          "license": "MIT",
          "category": "productivity",
          "tags": [
            "metrics",
            "saas",
            "marketplace",
            "kpi",
            "arr",
            "mrr",
            "churn",
            "startup",
            "analytics"
          ],
          "categories": [
            "analytics",
            "arr",
            "churn",
            "kpi",
            "marketplace",
            "metrics",
            "mrr",
            "productivity",
            "saas",
            "startup"
          ],
          "install_commands": [
            "/plugin marketplace add yamz8/open-ceo",
            "/plugin install metrics@open-ceo"
          ]
        },
        {
          "name": "fundraising",
          "version": "0.1.0",
          "description": "Fundraising toolkit for VC-backed startup CEOs. Create pitch decks, manage investor outreach, analyze term sheets, and track pipeline.",
          "source": "./fundraising",
          "author": {
            "name": "yamz8"
          },
          "repository": "https://github.com/yamz8/open-ceo",
          "homepage": "https://github.com/yamz8/open-ceo#fundraising",
          "license": "MIT",
          "category": "productivity",
          "tags": [
            "fundraising",
            "pitch",
            "investors",
            "term-sheet",
            "startup",
            "ceo",
            "vc"
          ],
          "categories": [
            "ceo",
            "fundraising",
            "investors",
            "pitch",
            "productivity",
            "startup",
            "term-sheet",
            "vc"
          ],
          "install_commands": [
            "/plugin marketplace add yamz8/open-ceo",
            "/plugin install fundraising@open-ceo"
          ]
        },
        {
          "name": "board-prep",
          "version": "0.1.0",
          "description": "Board meeting preparation toolkit for VC-backed startup CEOs. Helps create agendas, draft board decks, prepare metrics, and anticipate investor questions.",
          "source": "./board-prep",
          "author": {
            "name": "yamz8"
          },
          "repository": "https://github.com/yamz8/open-ceo",
          "homepage": "https://github.com/yamz8/open-ceo#board-prep",
          "license": "MIT",
          "category": "productivity",
          "tags": [
            "board",
            "startup",
            "ceo",
            "investor",
            "saas",
            "metrics",
            "deck"
          ],
          "categories": [
            "board",
            "ceo",
            "deck",
            "investor",
            "metrics",
            "productivity",
            "saas",
            "startup"
          ],
          "install_commands": [
            "/plugin marketplace add yamz8/open-ceo",
            "/plugin install board-prep@open-ceo"
          ]
        },
        {
          "name": "investor-updates",
          "version": "0.1.0",
          "description": "Monthly investor update toolkit for VC-backed startup CEOs. Helps draft professional investor emails, generate metrics snapshots, and follow communication best practices.",
          "source": "./investor-updates",
          "author": {
            "name": "yamz8"
          },
          "repository": "https://github.com/yamz8/open-ceo",
          "homepage": "https://github.com/yamz8/open-ceo#investor-updates",
          "license": "MIT",
          "category": "productivity",
          "tags": [
            "investor",
            "updates",
            "startup",
            "ceo",
            "email",
            "metrics",
            "communication"
          ],
          "categories": [
            "ceo",
            "communication",
            "email",
            "investor",
            "metrics",
            "productivity",
            "startup",
            "updates"
          ],
          "install_commands": [
            "/plugin marketplace add yamz8/open-ceo",
            "/plugin install investor-updates@open-ceo"
          ]
        },
        {
          "name": "hiring",
          "version": "0.1.0",
          "description": "Startup hiring toolkit for CEOs. Generate job descriptions, interview scorecards, offer letters, and calculate equity compensation. Includes salary and equity benchmarks by role, level, and stage.",
          "source": "./hiring",
          "author": {
            "name": "yamz8"
          },
          "repository": "https://github.com/yamz8/open-ceo",
          "homepage": "https://github.com/yamz8/open-ceo#hiring",
          "license": "MIT",
          "category": "productivity",
          "tags": [
            "hiring",
            "recruiting",
            "job-description",
            "offer-letter",
            "equity",
            "compensation",
            "interview",
            "startup",
            "hr"
          ],
          "categories": [
            "compensation",
            "equity",
            "hiring",
            "hr",
            "interview",
            "job-description",
            "offer-letter",
            "productivity",
            "recruiting",
            "startup"
          ],
          "install_commands": [
            "/plugin marketplace add yamz8/open-ceo",
            "/plugin install hiring@open-ceo"
          ]
        },
        {
          "name": "founder-mode",
          "version": "0.1.0",
          "description": "Founder productivity and wellness toolkit. Prioritize chaos, delegate effectively, manage energy, and maintain mental resilience. Includes decision journaling, stakeholder mapping, and weekly reset rituals.",
          "source": "./founder-mode",
          "author": {
            "name": "yamz8"
          },
          "repository": "https://github.com/yamz8/open-ceo",
          "homepage": "https://github.com/yamz8/open-ceo#founder-mode",
          "license": "MIT",
          "category": "productivity",
          "tags": [
            "founder",
            "ceo",
            "productivity",
            "prioritization",
            "delegation",
            "wellness",
            "burnout",
            "decision-making",
            "startup",
            "mental-health"
          ],
          "categories": [
            "burnout",
            "ceo",
            "decision-making",
            "delegation",
            "founder",
            "mental-health",
            "prioritization",
            "productivity",
            "startup",
            "wellness"
          ],
          "install_commands": [
            "/plugin marketplace add yamz8/open-ceo",
            "/plugin install founder-mode@open-ceo"
          ]
        },
        {
          "name": "crisis-playbook",
          "version": "0.1.0",
          "description": "Crisis management toolkit for startup CEOs. Navigate layoffs, pivots, down rounds, PR crises, and existential threats with frameworks, communication templates, and step-by-step guidance.",
          "source": "./crisis-playbook",
          "author": {
            "name": "yamz8"
          },
          "repository": "https://github.com/yamz8/open-ceo",
          "homepage": "https://github.com/yamz8/open-ceo#crisis-playbook",
          "license": "MIT",
          "category": "productivity",
          "tags": [
            "crisis",
            "layoff",
            "pivot",
            "down-round",
            "pr",
            "communication",
            "restructuring",
            "turnaround",
            "startup",
            "ceo"
          ],
          "categories": [
            "ceo",
            "communication",
            "crisis",
            "down-round",
            "layoff",
            "pivot",
            "pr",
            "productivity",
            "restructuring",
            "startup",
            "turnaround"
          ],
          "install_commands": [
            "/plugin marketplace add yamz8/open-ceo",
            "/plugin install crisis-playbook@open-ceo"
          ]
        }
      ]
    }
  ]
}