{
  "author": {
    "id": "yosugi",
    "display_name": "yosugi",
    "avatar_url": "https://avatars.githubusercontent.com/u/2996425?v=4"
  },
  "marketplaces": [
    {
      "name": "cc-zundamon-plugins",
      "version": null,
      "description": "ずんだもんキャラクターモードで開発をサポート",
      "repo_full_name": "yosugi/cc-zundamon-plugins",
      "repo_url": "https://github.com/yosugi/cc-zundamon-plugins",
      "repo_description": null,
      "signals": {
        "stars": 3,
        "forks": 0,
        "pushed_at": "2025-12-28T00:53:47Z"
      },
      "files": {
        ".claude-plugin/marketplace.json": "{\n  \"name\": \"cc-zundamon-plugins\",\n  \"owner\": {\n    \"name\": \"yosugi\"\n  },\n  \"plugins\": [\n    {\n      \"name\": \"zundamon\",\n      \"source\": \"./\",\n      \"description\": \"ずんだもんキャラクターモードで開発をサポート\",\n      \"version\": \"1.0.0\",\n      \"author\": {\n        \"name\": \"yosugi\"\n      },\n      \"homepage\": \"https://github.com/yosugi/cc-zundamon-plugins\",\n      \"repository\": \"https://github.com/yosugi/cc-zundamon-plugins\",\n      \"license\": \"MIT\"\n    }\n  ]\n}\n",
        ".claude-plugin/plugin.json": "{\n  \"name\": \"zundamon\",\n  \"version\": \"1.0.0\",\n  \"description\": \"ずんだもんキャラクターモードで開発をサポート\"\n}\n",
        "README.md": "# zundamon-plugin\n\nずんだもんキャラクターモードで開発をサポートする Claude Code プラグイン。\n\n## インストール\n\n```bash\n/plugin marketplace add yosugi/cc-zundamon-plugins\n/plugin install zundamon@cc-zundamon-plugins\n```\n\n## 使い方\n\nClaude Code で以下のコマンドを実行：\n\n```\n/zundamon\n```\n\nすると、ずんだもんがあなたの開発をサポートしてくれます。\n\n## ずんだもんの特徴\n\n- 一人称は「ボク」\n- 語尾は「〜なのだ」「〜のだ」\n- どんなエラーにもめげない前向きな性格\n- ずんだ餅が大好き\n\n## 会話例\n\n```\nあなた: このコードにバグがあるんだけど...\n\nずんだもん: あわわ、エラーなのだ！でも大丈夫、ボクがついてるのだ！\n一緒に直すのだ！エラーは成長のチャンスなのだ！\n```\n\n## 使用技術\n\nずんだもんのキャラクター定義には [IntentScript](https://github.com/yosugi/intent-script) を使用しています。\n\nIntentScriptは、AIに「何をしたいか」という意図を明確に伝えるためのYAML形式の言語です。\nプログラミング知識がなくても使え、LLMによる解釈を前提とした設計になっています。\n\n詳しくは以下の記事をご覧ください\n- [IntentScript - 意図を書くための新しい言語](https://zenn.dev/yosugi/articles/intent-script-introduce)\n\n## ライセンス\n\nMIT\n\n---\n\n※ 本プラグインは、ずんだもんを題材にした非公式の二次創作です。\n公式プロジェクトや原作者とは関係ありません。\n\n"
      },
      "plugins": [
        {
          "name": "zundamon",
          "source": "./",
          "description": "ずんだもんキャラクターモードで開発をサポート",
          "version": "1.0.0",
          "author": {
            "name": "yosugi"
          },
          "homepage": "https://github.com/yosugi/cc-zundamon-plugins",
          "repository": "https://github.com/yosugi/cc-zundamon-plugins",
          "license": "MIT",
          "categories": [],
          "install_commands": [
            "/plugin marketplace add yosugi/cc-zundamon-plugins",
            "/plugin install zundamon@cc-zundamon-plugins"
          ]
        }
      ]
    }
  ]
}